Workbook

Sheet 假设开发法
A1: 住宅用地假设开发法测算表
A2: 产权持有单位：南京国信地产开发有限公司 | E2: 评估基准日: | F2: 43298
A3: 序号 | C3: 项目 | D3: 参数
A4: 1 | B4: 基本资料 | C4: 土地面积 | D4: 15994 | E4: 容积率 | F4: 0.9 | L4: 每户面积 | M4: 户数
A5: 2 | C5: 地上总建筑面积 | D5: =D4*F4 -> 14394.6 | E5: 户均面积 | F5: 180 | L5: 180 | M5: =D5/L5 -> 79.97
A6: 3 | C6: 上叠建筑面积 | D6: =(D5-D8)/2 -> 7125.33 | E6: 户数 | F6: =D6/F5*2 -> 79 | L6: 40 | M6: =D9/L6 -> 118.5
A7: 4 | C7: 下叠建筑面积 | D7: =D6 -> 7125.33
A8: 5 | C8: 物业用房面积 | D8: =D5*1% -> 143.95
A9: 6 | C9: 地下车库面积 | D9: =(40+20)*F6 -> 4740 | E9: 按每户40平一个车位，20平人防工程
A10: 7 | B10: 销售单价、总价 | C10: 上叠平均售价 | D10: =销售单价计算!K28 -> 30421
A11: 8 | C11: 下叠平均售价 | D11: =销售单价计算!K27 -> 32711
A12: 9 | C12: 不动产销售总价 | D12: =ROUND((D6*D10+D7*D11),0) -> 449836334
A13: 13 | B13: 开发成本 | C13: 前期费用 | D13: =ROUND(D5*F13,0) -> 1173160 | E13: 按计容建筑面积计 | F13: =前期工程费!D9 -> 81.5
A14: 10 | C14: 市政基础设施配套费 | D14: =D5*F14 -> 2159190 | E14: 市政基础设施配套费单价 | F14: 150
A15: 11 | C15: 地上建筑建安工程费总价 | D15: =D5*F15 -> 25910280 | E15: 地上住宅建安工程费单价 | F15: =1800 -> 1800
A16: 12 | C16: 地下建筑建安工程总价 | D16: =D9*F16 -> 14220000 | E16: 地下工程建安工程单价 | F16: 3000
A17: 14 | C17: 公共基础设施建设费 | D17: =D5*F17 -> 11515680 | E17: 按计容建筑面积计 | F17: 800
A18: 15 | B18: 投资利息 | C18: 利息 | D18: =地价*4.75/100*1.2*G18+(D14+D15+D16+D13+D17)*4.75/100*1.2*G18/2 -> #NAME? | E18: 1-5年期利率4.75% | F18: 开发周期 | G18: 1.5 | H18: =#REF!+E19 -> #REF! | I18: =#REF!/10000 -> #REF! | J18: =#REF!/10000 -> #REF! | K18: =I18-J18 -> #REF!
A19: 16 | B19: 相关税费 | C19: 管理费用 | D19: =D12*0.02 -> 8996726.7 | E19: 不动产总价的2%
A20: 17 | C20: 销售费用 | D20: =D12*0.02 -> 8996726.7 | E20: 不动产总价的2%
A21: 18 | C21: 销售税金 | D21: =ROUND(D12*E21,0) -> 25190835 | E21: =5%*(1+7%+3%+2%) -> 0.056 | H21: =SUM(E15:E20)*0.04/SUM(E14:E20) -> #DIV/0! | I21: 3-4%(不含土地成本)
A22: 19 | C22: 开发利润 | D22: =(地价+D14+D15+D16+D13+D17)*0.15 -> #NAME? | E22: 开发成本、地价的15%
A23: 20 | C23: 总地价 | D23: =ROUND((D12-1.1928*(D14+D15+D16+D13+D17)-D19-D20-D21)/1.2355,0) -> 276061447
A24: 21 | C24: 单价 | D24: =ROUND(D23/D4,0) -> 17260
B25: 待估宗地价值＝项目开发完成后的房地产价值－项目开发建设成本－利息－管理费用－销售费用－销售税金－合理开发利润-购地契税 | H25: 0.015
H27: =G26/E10 -> #DIV/0! | J27: =G15+#REF!+#REF!+G20+G19+G22 -> #REF!
H30: =ROUND(G29*10000,-2) -> 0 | I30: =H30-[1]在产品!F31 -> -3.0658686e+08
A31: 评估人员：吕春琴 | F31: 日期：2018年7月25日 | H31: 30922.35 | I31: =H31-G30 -> 30922.35
D33: 本次结果 | E33: 上次评估结果 | G33: 法院评估结果
C34: 市场法结果 | D34: =[2]市场法!$D$55 -> 17169 | E34: 16555 | F34: 市场法 | G34: 18960
C35: 假设开发法结果 | D35: =D24 -> 17260 | E35: 15060 | F35: 假设开发法 | G35: 17058
C36: 平均结果 | D36: =(D35+D34)/2 -> 17215 | E36: =(E35+E34)/2 -> 15808 | F36: 平均 | G36: =(G34+G35)/2 -> 18009
C37: 比上次增加 | D37: =D36-E36 -> 1407 | F37: 与我们的评估结果差异率 | G37: =(G36-D36)/D36 -> 0.05
C40: 面积 | D40: 15994
C41: 总价 | D41: =ROUND(D36*D40,-2)/10000 -> 27533.67

Sheet 宗地位置图

Sheet 销售单价计算
A1: 房地产市场法评估（住宅）评估计算表 | L1: 索引号：C4-6-1/Z3
A2: 修正因素 | C2: 委估对象 | D2: 案例A | E2: 案例B | F2: 案例C | G2: 委估对象 | H2: 案例A | I2: 案例B | J2: 案例C | K2: 案例A | L2: 案例B | M2: 案例C
A3: 地 址 | C3: 宏运大道2298号下叠 | D3: 国信秦淮绿洲叠加别墅下叠 | E3: 国信秦淮绿洲叠加别墅下叠 | F3: 国信秦淮绿洲叠加别墅上叠 | G3: =C3 -> 宏运大道2298号下叠 | H3: 国信秦淮绿洲叠加别墅 | I3: 国信秦淮绿洲叠加别墅 | J3: 国信秦淮绿洲叠加别墅 | K3: 国信秦淮绿洲叠加别墅 | L3: 国信秦淮绿洲叠加别墅 | M3: 国信秦淮绿洲叠加别墅
A4: 交易价格（不含税） | C4: 待估 | D4: 33902 | E4: 33035 | F4: 31245 | G4: 待估 | H4: =D4 -> 33902 | I4: =E4 -> 33035 | J4: =F4 -> 31245 | K4: =H4 -> 33902 | L4: =I4 -> 33035 | M4: =F4 -> 31245
A5: 市场状况 | C5: 43298 | D5: 2018-07-10 | E5: 2018-07-19 | F5: 2018-07-12 | G5: 100 | H5: 100 | I5: 100 | J5: 100 | K5: =CONCATENATE($H5,"/",G5) -> 100/100 | L5: =CONCATENATE($I5,"/",G5) -> 100/100 | M5: =CONCATENATE($J5,"/",G5) -> 100/100
A6: 交易情况 | C6: 正常 | D6: 正常 | E6: 正常 | F6: 正常 | G6: 100 | H6: 100 | I6: 100 | J6: 100 | K6: =CONCATENATE($G6,"/",H6) -> 100/100 | L6: =CONCATENATE($G6,"/",I6) -> 100/100 | M6: =CONCATENATE($G6,"/",J6) -> 100/100
A7: 区位状况 | B7: 商业配套设施 | C7: 区域内无大型商业配套设施，只有小区周边的商业配套 | D7: 区域内无大型商业配套设施，只有小区周边的商业配套 | E7: 区域内无大型商业配套设施，只有小区周边的商业配套 | F7: 区域内无大型商业配套设施，只有小区周边的商业配套 | G7: 100 | H7: 100 | I7: 100 | J7: 100 | K7: =CONCATENATE($G7,"/",H7) -> 100/100 | L7: =CONCATENATE($G7,"/",I7) -> 100/100 | M7: =CONCATENATE($G7,"/",J7) -> 100/100
B8: 规划设计 | C8: 小区布局整齐、建筑密度低、绿化条件较优 | D8: 小区布局整齐、建筑密度低、绿化条件较优 | E8: 小区布局整齐、建筑密度低、绿化条件较优 | F8: 小区布局整齐、建筑密度低、绿化条件较优 | G8: 100 | H8: 100 | I8: 100 | J8: 100 | K8: =CONCATENATE($G8,"/",H8) -> 100/100 | L8: =CONCATENATE($G8,"/",I8) -> 100/100 | M8: =CONCATENATE($G8,"/",J8) -> 100/100
B9: 交通条件 | C9: 区域内有地铁1号南延线及公交车，公共交通便利度好 | D9: 区域内有地铁1号南延线及公交车，公共交通便利度好 | E9: 区域内有地铁1号南延线及公交车，公共交通便利度好 | F9: 区域内有地铁1号南延线及公交车，公共交通便利度好 | G9: 100 | H9: 100 | I9: 100 | J9: 100 | K9: =CONCATENATE($G9,"/",H9) -> 100/100 | L9: =CONCATENATE($G9,"/",I9) -> 100/100 | M9: =CONCATENATE($G9,"/",J9) -> 100/100
B10: 教育医疗设施 | C10: 区域内有东山小学、岔路学校，公用设施便利度较好 | D10: 区域内有东山小学、岔路学校，公用设施便利度较好 | E10: 区域内有东山小学、岔路学校，公用设施便利度较好 | F10: 区域内有东山小学、岔路学校，公用设施便利度较好 | G10: 100 | H10: 100 | I10: 100 | J10: 100 | K10: =CONCATENATE($G10,"/",H10) -> 100/100 | L10: =CONCATENATE($G10,"/",I10) -> 100/100 | M10: =CONCATENATE($G10,"/",J10) -> 100/100
B11: 周围环境 | C11: 自然环境较好 | D11: 自然环境较好 | E11: 自然环境较好 | F11: 自然环境较好 | G11: 100 | H11: 100 | I11: 100 | J11: 100 | K11: =CONCATENATE($G11,"/",H11) -> 100/100 | L11: =CONCATENATE($G11,"/",I11) -> 100/100 | M11: =CONCATENATE($G11,"/",J11) -> 100/100
B12: 楼层 | C12: -1-2 | D12: -1-2 | E12: -1-2 | F12: 3-4 | G12: 100 | H12: 100 | I12: 100 | J12: 93 | K12: =CONCATENATE($G12,"/",H12) -> 100/100 | L12: =CONCATENATE($G12,"/",I12) -> 100/100 | M12: =CONCATENATE($G12,"/",J12) -> 100/93 | N12: 下墅平均单价 | O12: =(K4+L4)/2 -> 33468.5
B13: 朝向 | C13: 朝南 | D13: 朝南 | E13: 朝南 | F13: 朝南 | G13: 100 | H13: 100 | I13: 100 | J13: 100 | K13: =CONCATENATE($G13,"/",H13) -> 100/100 | L13: =CONCATENATE($G13,"/",I13) -> 100/100 | M13: =CONCATENATE($G13,"/",J13) -> 100/100 | N13: 上墅单价 | O13: =M4 -> 31245
A14: 权益状况 | B14: 规划条件 | C14: 无限制 | D14: 无限制 | E14: 无限制 | F14: 无限制 | G14: 100 | H14: 100 | I14: 100 | J14: 100 | K14: =CONCATENATE($G14,"/",H14) -> 100/100 | L14: =CONCATENATE($G14,"/",I14) -> 100/100 | M14: =CONCATENATE($G14,"/",J14) -> 100/100 | N14: 上墅占下墅的比例 | O14: =O13/O12 -> 0.93
B15: 土地使用期限 | C15: 剩余54.6年 | D15: 剩余54.6年 | E15: 剩余54.6年 | F15: 剩余54.6年 | G15: 100 | H15: 100 | I15: 100 | J15: 100 | K15: =CONCATENATE($G15,"/",H15) -> 100/100 | L15: =CONCATENATE($G15,"/",I15) -> 100/100 | M15: =CONCATENATE($G15,"/",J15) -> 100/100
B16: 租赁情况 | C16: 无租约 | D16: 无租约 | E16: 无租约 | F16: 无租约 | G16: 100 | H16: 100 | I16: 100 | J16: 100 | K16: =CONCATENATE($G16,"/",H16) -> 100/100 | L16: =CONCATENATE($G16,"/",I16) -> 100/100 | M16: =CONCATENATE($G16,"/",J16) -> 100/100
A17: 实物状况 | B17: 建筑面积 | C17: 180平方米，面积适中 | D17: 205平方米，面积适中 | E17: 177.39平方米，面积适中 | F17: 167平方米，面积较适中 | G17: 100 | H17: 100 | I17: 100 | J17: 100 | K17: =CONCATENATE($G17,"/",H17) -> 100/100 | L17: =CONCATENATE($G17,"/",I17) -> 100/100 | M17: =CONCATENATE($G17,"/",J17) -> 100/100
B18: 建筑结构 | C18: 建筑标准较高，钢混结构 | D18: 建筑标准较高，钢混结构 | E18: 建筑标准较高，钢混结构 | F18: 建筑标准较高，钢混结构 | G18: 100 | H18: 100 | I18: 100 | J18: 100 | K18: =CONCATENATE($G18,"/",H18) -> 100/100 | L18: =CONCATENATE($G18,"/",I18) -> 100/100 | M18: =CONCATENATE($G18,"/",J18) -> 100/100
B19: 建造年代 | C19: 2020年建成，成新优 | D19: 2005年建成，成新一般 | E19: 2010年建成，成新较优 | F19: 2005年建成，成新一般 | G19: 100 | H19: 96 | I19: 98 | J19: 96 | K19: =CONCATENATE($G19,"/",H19) -> 100/96 | L19: =CONCATENATE($G19,"/",I19) -> 100/98 | M19: =CONCATENATE($G19,"/",J19) -> 100/96
B20: 层高 | C20: 2.8米 | D20: 2.8米 | E20: 2.8米 | F20: 2.8米 | G20: 100 | H20: 100 | I20: 100 | J20: 100 | K20: =CONCATENATE($G20,"/",H20) -> 100/100 | L20: =CONCATENATE($G20,"/",I20) -> 100/100 | M20: =CONCATENATE($G20,"/",J20) -> 100/100
B21: 空间布局 | C21: 空间布局较优 | D21: 空间布局较优 | E21: 空间布局较优 | F21: 空间布局较优 | G21: 100 | H21: 100 | I21: 100 | J21: 100 | K21: =CONCATENATE($G21,"/",H21) -> 100/100 | L21: =CONCATENATE($G21,"/",I21) -> 100/100 | M21: =CONCATENATE($G21,"/",J21) -> 100/100
B22: 停车便利度 | C22: 配有停车位 | D22: 配有停车位 | E22: 配有停车位 | F22: 配有停车位 | G22: 100 | H22: 100 | I22: 100 | J22: 100 | K22: =CONCATENATE($G22,"/",H22) -> 100/100 | L22: =CONCATENATE($G22,"/",I22) -> 100/100 | M22: =CONCATENATE($G22,"/",J22) -> 100/100
B23: 物业管理 | C23: 管理及服务优 | D23: 管理及服务优 | E23: 管理及服务优 | F23: 管理及服务优 | G23: 100 | H23: 100 | I23: 100 | J23: 100 | K23: =CONCATENATE($G23,"/",H23) -> 100/100 | L23: =CONCATENATE($G23,"/",I23) -> 100/100 | M23: =CONCATENATE($G23,"/",J23) -> 100/100
B24: 装饰装修 | C24: 毛坯 | D24: 精装 | E24: 精装 | F24: 精装 | G24: 100 | H24: 106 | I24: 106 | J24: 106 | K24: =CONCATENATE($G24,"/",H24) -> 100/106 | L24: =CONCATENATE($G24,"/",I24) -> 100/106 | M24: =CONCATENATE($G24,"/",J24) -> 100/106
B25: 设备设施 | C25: 水、电、气等设施齐全 | D25: 水、电、气等设施齐全 | E25: 水、电、气等设施齐全 | F25: 水、电、气等设施齐全 | G25: 100 | H25: 100 | I25: 100 | J25: 100 | K25: =CONCATENATE($G25,"/",H25) -> 100/100 | L25: =CONCATENATE($G25,"/",I25) -> 100/100 | M25: =CONCATENATE($G25,"/",J25) -> 100/100
A26: 修正后单价 | H26: =ROUND(PRODUCT($G6:$G25)/PRODUCT(H6:H25)*H4*$H5/$G5,0) -> 33316 | I26: =ROUND(PRODUCT($G6:$G25)/PRODUCT(I6:I25)*I4*$I5/$G5,0) -> 31801 | J26: =ROUND(PRODUCT($G6:$G25)/PRODUCT(J6:J25)*J4*$J5/$G5,0) -> 33016 | K26: =H26 -> 33316 | L26: =I26 -> 31801 | M26: =J26 -> 33016
A27: 下叠修正后平均单价 | K27: =ROUND(AVERAGE(K26:M26),0) -> 32711
A28: 上叠修正后平均单价 | K28: =ROUND(K27*0.93,0) -> 30421
A29: 评估人员： | C29: 日期： | E29: 复核人： | F29: 日期：

Sheet 新案例
A1: http://newhouse.nj.house365.com/wukuanglanyuefangshan/intro/
A73: http://newhouse.nj.house365.com/yanzitai/sellinfo/
C105: 面积（赠送） | D105: 总价 | E105: 单价（万/平）
B106: 下叠毛坯 | C106: 300（200） | D106: 1300 | E106: =D106/300 -> 4.3
B107: 上叠毛坯 | C107: 300（150） | D107: 1100 | E107: =D107/300 -> 3.7
B110: 工抵房上毛坯 | C110: 300(150) | D110: =300*3.3 -> 990 | E110: 3.3
B176: 电话中介13400064716
B177: 九龙湖别墅 | E177: 单价
A178: 毛坯 | B178: -1—2层 | C178: 257 | D178: 650万 | E178: =650/257 -> 2.53
B179: -1—1层 | C179: 172 | D179: 460万 | E179: =460/172 -> 2.67

Sheet 案例
B1: http://nj.sell.house365.com/district/dl_p2-kw%B9%FA%D0%C5%C7%D8%BB%B4%C2%CC%D6%DE.html
B3: A
B28: B
B59: C
C85: 个人所得税 | D85: =530*0.01 -> 5.3
C86: 营业税及附加 | D86: =530*5.5%*(7%+3%) -> 2.915
C87: 房主净得价 | D87: =530-D85-D86 -> 521.785
C88: 修正后净得单价 | D88: =D87/167*10000 -> 31245

Sheet 前期工程费
B2: 序号 | C2: 科目 | D2: 费用标准 （元/㎡） | E2: 面积 （㎡） | F2: 金额 （元） | G2: 备注
B3: 1 | C3: 地质勘察费 | D3: 5 | E3: =[3]规划指标!G1 -> 0 | F3: =ROUND(D3*E3,0) -> 0
B4: 2 | C4: 工程招标费 | D4: 5 | E4: =[3]规划指标!G2+[3]规划指标!G14 -> 0 | F4: =ROUND(D4*E4,0) -> 0
B5: 3 | C5: 设计费 | D5: 48 | E5: =[3]规划指标!G3 -> 0 | F5: =ROUND(D5*E5,0) -> 0
B6: 4 | C6: 工程监理费 | D6: 20 | E6: =E5 -> 0 | F6: =ROUND(D6*E6,0) -> 0
B7: 5 | C7: 环境影响评价费 | D7: 1.5 | E7: =E5 -> 0 | F7: =ROUND(D7*E7,0) -> 0
B8: 6 | C8: 消防设施审查费 | D8: 2 | E8: =E5 -> 0 | F8: =ROUND(D8*E8,0) -> 0
C9: 合 计 | D9: =SUM(D3:D8) -> 81.5 | F9: =ROUND(SUM(F3:F8)/1.06,0) -> 0

Sheet Sheet3
B2: 秦淮绿洲实际开发指标（北区、西区、东区） | D2: 各类物业占比
B3: 总用地面积 | C3: 286638.72
B4: 容积率 | C4: =C5/C3 -> 0.71
B5: 实际开发总建筑面积 （不含地下车库面积） | C5: =C6+C7+C8+C9+C10+C12+C13 -> 202180.31
B6: 其中叠加面积 | C6: 58984.57 | D6: =C6/$C$5 -> 0.2917
B7: 联排别墅 | C7: 83802.85 | D7: =C7/$C$5 -> 0.4145
B8: 双拼面积 | C8: 2464.8 | D8: =C8/$C$5 -> 0.0122
B9: 独栋面积 | C9: 1432.5 | D9: =C9/$C$5 -> 0.0071
B10: 小高层面积 | C10: 41424.28 | D10: =C10/$C$5 -> 0.2049
B11: 地下车库面积 | C11: 12139.41
B12: 配建社区中心及幼儿园等面积 | C12: 13167.64 | D12: =C12/$C$5 -> 0.0651
B13: 物业用房面积 | C13: 903.67 | D13: =C13/$C$5 -> 0.0045

Sheet 规费文件
C93: 人防工程
C94: http://www.njrgrj.com/news/show-347.html

Sheet 李杰审核意见
A2: 1 | B2: 建设成本建议合并计算，物业用房面积未计成本，平均成本1900，较低，公共配套可以降低
B3: 答：已计成本了
A4: 2 | B4: 计算利息时，按自有资金20%，计息应按80%比例计息，另外，土地计息全程计息，建安按均匀投入
B5: 答：已修改
A6: 3 | B6: 缺少人防易地建设费
B7: 答：已增加
