Workbook
Name _2003_6_25: [1]ITEM!#REF!
Name _2003_6_25: [1]ITEM!#REF!
Name _2003_6_25: [1]ITEM!#REF!
Name _2003_6_25: [1]ITEM!#REF!
Name _2003_6_25: [1]ITEM!#REF!
Name _2003_6_25: [1]ITEM!#REF!
Name _BSP2: #REF!
Name _BSP2: #REF!
Name _BSP2: #REF!
Name _BSP2: #REF!
Name _BSP2: #REF!
Name _BSP2: #REF!
Name _BSP2: #REF!
Name _pgz101: #REF!
Name _pgz101: #REF!
Name _pgz101: #REF!
Name _pgz101: #REF!
Name _pgz101: #REF!
Name _pgz101: #REF!
Name _pgz101: #REF!
Name _pgz102: #REF!
Name _pgz102: #REF!
Name _pgz102: #REF!
Name _pgz102: #REF!
Name _pgz102: #REF!
Name _pgz102: #REF!
Name _pgz102: #REF!
Name _pgz103: #REF!
Name _pgz103: #REF!
Name _pgz103: #REF!
Name _pgz103: #REF!
Name _pgz103: #REF!
Name _pgz103: #REF!
Name _pgz103: #REF!
Name _pgz104: #REF!
Name _pgz104: #REF!
Name _pgz104: #REF!
Name _pgz104: #REF!
Name _pgz104: #REF!
Name _pgz104: #REF!
Name _pgz104: #REF!
Name _pgz105: #REF!
Name _pgz105: #REF!
Name _pgz105: #REF!
Name _pgz105: #REF!
Name _pgz105: #REF!
Name _pgz105: #REF!
Name _pgz105: #REF!
Name _pgz106: #REF!
Name _pgz106: #REF!
Name _pgz106: #REF!
Name _pgz106: #REF!
Name _pgz106: #REF!
Name _pgz106: #REF!
Name _pgz106: #REF!
Name _pgz511: #REF!
Name _pgz511: #REF!
Name _pgz511: #REF!
Name _pgz511: #REF!
Name _pgz511: #REF!

Sheet 记事
C2: 应用前提
C3: 1、稳定期增长率假设为零，如考虑永续增长，终值需另外用价值驱动因素模型计算。
C4: 2、未考虑预测期内被评估企业依靠收购所创造的收入增长。
C5: 3、FCFE模型只适用评估基准日及未来预测期间无付息负债的情形。
C6: 建模的规则
C7: 表中数字 | D7: 蓝字黄底表示手动录入数据
C8: 表中数字 | D8: 红字表示在该单元格中的公式左右不一样，或强调关注。
D9: 同一年的数据在不同表中均在同一列中，方便查找错误。
D10: 不要隐藏行和列，采用数据中的创建组和取消组合处理，易于查找数据。
D11: 单元格中的公式不要直接写入数据，数据由表外单元格链入。
D12: 工作底稿完成后无关数据全部删除，只保留有关数据。
C14: 密码0528
C15: V5.0修改记录
C16: 1、“1报表”营运能力分析财务指标非整年进行年化处理。
C17: 2、表“7折旧”、“8摊销”、“9溢余现金”、“10营运”进行拆分，表“7折旧”和“8摊销”“+”后隐藏的是自动计算公式，一般无需改动。
C18: 限制用途现金位置进行了移动；“9溢余现金”、“10营运”，增加了历史数据分析，反映趋势变化。
C19: 3、表“预测财报”布局调整：增加完成资产负债表、利润表剩余项目，后面报表自动计算得出财务指标，用于分析历史与未来趋势。
C20: 预测资产负债表可以合理分析企业未来的借款金额。
C21: 4、表“9财务费用”末端行增加(由预测资产负债表计算得出)新增借款，反映企业未来是否有资金缺口，需要融多少资金。
C22: 5、表“13FCFF”修改折现率计算方法——迭代计算。
C24: V5.1修改记录
C25: 1、表“7折旧”行42即“期末设备类账面净值”公式汇总错误，已修改。该行数据不影响估值，但影响“预测财报”数据。

Sheet 步骤
E1: 索引号：SY1
B2: 企业价值评估现金流量折现法(DCF)计算及步骤复核表
B3: ='1报表'!B12 -> 被评估单位：YLSJ公司 | D3: 评估基准日 | E3: ='1报表'!E5 -> 43281
B4: 评估人员 | D4: 现场工作日期
B5: 复核人 | D5: 复核日期
B6: 操作步骤与要求 | D6: 是 | E6: 不适用
B7: 一、前期工作
B8: 1.取得被评估企业前3~5年和本期审计报告、会计报表、科目明细表，以及相关收入、成本、费用等统计资料
B9: 2.取得企业资产、财务、经营状况资料，着重了解经营活动涉及的范围，收入、收益结构，资产配置情况，在此基础上区分企业经营活动和经营活动之外的其他活动涉及相关资产、负债、损益等。布置企业填报资产基础法申报表、收益预测申报表，并在资产基础法的申报表上标识经营性资产（负债）与非经营性资产（负债）。以上资料由企业盖章或签字确认。
B10: 二、统计、调整
B11: 3.根据评估业务的具体情况，在分析企业各科目明细的基础上，分析和调整被评估企业（1）财务报表编制基础；（2）非经常性收入和支出；（3）非经营性资产、负债和溢余资产及其相关的收入和支出。如涉及可比企业同理处理。
B12: 4.区分经营活动与其他活动，并统计、分析： a\营业收入；b\营业成本(材料、燃料动力、人工、制造费用)；c\税金及附加；d\折旧及摊销、固定及无形资产、长期待摊；e\销售、管理费用；f\资产减值损失、公允价值变动收益；g\营业外收支；h\财务费用
B13: 5.区分经营活动和其他活动，编制利润调整表
B14: 6.计算经营最低保有现金，测算溢余现金
B15: 7.区分经营活动和其他活动编制资产负债调整表
B16: 8.根据调整后的资产负债表、利润表，分析历史财务指标。
B17: 9.正确识别被评估企业所属行业，审慎选择参考上市公司，并统计相关财务指标
B18: 三、分析、预测
... B40: 金融资产、未并表的长期股权投资、投资性房地产以及溢余及非经营资产、负债等相关活动。

Sheet 1报表
B2: 输入信息
B3: 被评估单位： | E3: YLSJ公司
B4: 评估对象： | E4: 股东全部权益价值
B5: 评估基准日： | E5: 43281
B6: 短期预测(期)： | E6: 6
B7: 预测期间： | C7: =E5+1 -> 43282 | D7: To | E7: =DATE(YEAR(E5)+E6-1,12,31) -> 45291
B10: 资产负债表
B11: =B5&TEXT(E5,"YYYY/M/D") -> 评估基准日：2018/6/30
B12: =B3&E3 -> 被评估单位：YLSJ公司 | E12: 单位：万元
B13: 科目 | C13: =EDATE(D13,-12) -> 42735 | D13: =DATE(YEAR(E13)-1,12,31) -> 43100 | E13: =E5 -> 43281
B14: 流动资产：
B15: 货币资金 | C15: 606.91602 | D15: 422.55445 | E15: 125.24516
B16: 以公允价值计量且其变动计入当期损益的金融资产 | C16: 744.71178 | D16: 42.244674 | E16: 143.964
B17: 衍生金融资产
B18: 应收票据及应收账款 | C18: 915.13378 | D18: 747.61612 | E18: 479.66661
B19: 预付款项
A20: 保留 | B20: 应收利息
A21: 保留 | B21: 应收股利
B22: 其他应收款 | C22: 186.2834 | D22: 217.9241 | E22: 950.31863
B23: 存货
A24: 新准则 | B24: 合同资产
B25: 持有待售资产
B26: 一年内到期的非流动资产
B27: 其他流动资产 | C27: 0.575 | D27: 0.575 | E27: 0.575
B28: 流动资产合计 | C28: =SUM(C15:C27) -> 2453.62 | D28: =SUM(D15:D27) -> 1430.9143 | E28: =SUM(E15:E27) -> 1699.7694
B29: 非流动资产：
B30: 可供出售金融资产 | C30: 1.332422 | D30: 1.332422 | E30: 1.332422
B31: 持有至到期投资
A32: 新准则 | B32: 债权投资
A33: 新准则 | B33: 其他债权投资
B34: 长期应收款
B35: 长期股权投资 | C35: 3.465172 | D35: 3.465172 | E35: 3.465172
A36: 新准则 | B36: 其他权益工具投资
A37: 新准则 | B37: 其他非流动金融资产
B38: 投资性房地产
B39: 固定资产 | C39: 108.53785 | D39: 111.62056 | E39: 94.661335
B40: 在建工程
B41: 生产性生物资产
B42: 油气资产
B43: 无形资产 | C43: 0.477818 | D43: 9.480241 | E43: 5.916019
B44: 开发支出
B45: 商誉
B46: 长期待摊费用
B47: 递延所得税资产
B48: 其他非流动资产
B49: 非流动资产合计 | C49: =SUM(C30:C48) -> 113.81326 | D49: =SUM(D30:D48) -> 125.89839 | E49: =SUM(E30:E48) -> 105.37495
B50: 资产总计 | C50: =C28+C49 -> 2567.4332 | D50: =D28+D49 -> 1556.8127 | E50: =E28+E49 -> 1805.1443
B51: 流动负债：
B52: 短期借款
B53: 以公允价值计量且其变动计入当期损益的金融负债
B54: 衍生金融负债
B55: 应付票据及应付账款 | E55: 297.39516
B56: 预收款项 | C56: 124.37 | D56: 78 | E56: 99.1537
A57: 新准则 | B57: 合同负债
B58: 应付职工薪酬 | D58: -0.188809
B59: 应交税费 | C59: 100.54686 | D59: 28.32304 | E59: 2.22638
A60: 保留 | B60: 应付利息
A61: 保留 | B61: 应付股利 | E61: 656.42426
B62: 其他应付款 | C62: 512.49286 | D62: 612.62296 | E62: 211.60836
B63: 持有待售负债
B64: 一年内到期的非流动负债
B65: 其他流动负债
B66: 流动负债合计 | C66: =SUM(C52:C65) -> 737.40972 | D66: =SUM(D52:D65) -> 718.75719 | E66: =SUM(E52:E65) -> 1266.8079
B67: 非流动负债：
B68: 长期借款
B69: 应付债券
B70: 长期应付款 | C70: 31.161043 | D70: 31.278408 | E70: 31.315556
A71: 合并 | B71: 长期应付职工薪酬
B72: 预计负债
B73: 递延收益
B74: 递延所得税负债
B75: 其他非流动负债
B76: 非流动负债合计 | C76: =SUM(C68:C75) -> 31.161043 | D76: =SUM(D68:D75) -> 31.278408 | E76: =SUM(E68:E75) -> 31.315556
B77: 负债合计 | C77: =C66+C76 -> 768.57076 | D77: =D66+D76 -> 750.0356 | E77: =E66+E76 -> 1298.1234
B78: 所有者权益：
B79: 实收资本 | C79: 305 | D79: 305 | E79: 305
B80: 其他权益工具
B81: 资本公积 | C81: 1.296156 | D81: 1.296156 | E81: 1.296156
B82: 减：库存股
B83: 其他综合收益
B84: 盈余公积 | C84: 174.93031 | D84: 174.93031 | E84: 174.93031
A85: 合并 | B85: 一般风险准备
B86: 未分配利润 | C86: 1317.636 | D86: 325.55068 | E86: 25.794464
B87: 归属于母公司所有者权益合计 | C87: =SUM(C79:C81)-C82+SUM(C83:C86) -> 1798.8625 | D87: =SUM(D79:D81)-D82+SUM(D83:D86) -> 806.77714 | E87: =SUM(E79:E81)-E82+SUM(E83:E86) -> 507.02093
B88: 少数股东权益
B89: 所有者权益合计 | C89: =C87+C88 -> 1798.8625 | D89: =D87+D88 -> 806.77714 | E89: =E87+E88 -> 507.02093
B90: 负债和所有者权益总计 | C90: =C77+C89 -> 2567.4332 | D90: =D77+D89 -> 1556.8127 | E90: =E77+E89 -> 1805.1443
B91: 检查核对 | C91: =C50-C90 -> 0 | D91: =D50-D90 -> 0 | E91: =E50-E90 -> 0
B92: 报表是否平衡？ | C92: =IF(ROUND(C91,0)=0,"OK","需要检查") -> OK | D92: =IF(ROUND(D91,0)=0,"OK","需要检查") -> OK | E92: =IF(ROUND(E91,0)=0,"OK","需要检查") -> OK
B93: 利润表
B94: =B11 -> 评估基准日：2018/6/30 | D94: 基准年已经营月数 | E94: =MONTH(E13) -> 6
B95: =B12 -> 被评估单位：YLSJ公司 | E95: 单位：万元
B96: 科目 | C96: =YEAR(C13)&"年" -> 2016年 | D96: =YEAR(D13)&"年" -> 2017年 | E96: =YEAR(E13)&"年1-"&MONTH(E13) -> 2018年1-6
B97: 一、营业收入 | C97: 6309.9996 | D97: 6454.082 | E97: 2068.9888
B98: 减：营业成本 | C98: 5325.209 | D98: 5874.6686 | E98: 2248.3124
B99: 税金及附加 | C99: 32.988746 | D99: 28.542702 | E99: 19.638479
B100: 销售费用
B101: 管理费用 | C101: 668.47256 | D101: 615.9856 | E101: 268.92924
B102: 研发费用
B103: 财务费用 | C103: -33.89954 | D103: -11.184311 | E103: -1.012909
...

Sheet 2报表调整
B2: 资产负债调整表 | J2: 非经营性资产和负债分析表
B3: ='1报表'!B11 -> 评估基准日：2018/6/30 | K3: 根据资产负债核实表填写
B4: ='1报表'!B12 -> 被评估单位：YLSJ公司 | H4: 单位：万元
B5: 科目 | C5: ='1报表'!E13 -> 43281 | N5: 单位：万元
C6: 账面值 | D6: 重分类 | E6: 其中：非经营性资产、负债 | F6: 溢余资产 | G6: 经营性资产及负债账面值 | H6: 调整原因 | J6: 项目 | K6: ='1报表'!C13 -> 42735 | L6: ='1报表'!D13 -> 43100 | M6: ='1报表'!E13 -> 43281 | N6: 评估值
B7: 流动资产： | J7: 非经营性资产
B8: 货币资金 | C8: ='1报表'!E15 -> 125.24516 | D8: =C8 -> 125.24516 | F8: ='9溢余现金'!E25 -> 0 | G8: =D8-(E8+F8) -> 125.24516 | J8: 货币资金
B9: 交易性金融资产 | C9: ='1报表'!E16 -> 143.964 | D9: =C9 -> 143.964 | E9: 143.964 | G9: =D9-(E9+F9) -> 0 | H9: 非经常性损益 | J9: 交易性金融资产 | K9: ='1报表'!C16 -> 744.71178 | L9: ='1报表'!D16 -> 42.244674 | M9: =E9 -> 143.964 | N9: =M9 -> 143.964
B10: 衍生金融资产 | C10: ='1报表'!E17 -> 0 | D10: =C10 -> 0 | G10: =D10-(E10+F10) -> 0 | J10: 衍生金融资产 | K10: ='1报表'!C17 -> 0 | L10: ='1报表'!D17 -> 0 | M10: =E10 -> 0 | N10: =M10 -> 0
B11: 应收票据及应收账款 | C11: ='1报表'!E18 -> 479.66661 | D11: =C11 -> 479.66661 | G11: =D11-(E11+F11) -> 479.66661 | J11: 非经营性应收票据及应收账款 | M11: =E11 -> 0 | N11: =M11 -> 0
B12: 预付款项 | C12: ='1报表'!E19 -> 0 | D12: =C12 -> 0 | G12: =D12-(E12+F12) -> 0 | J12: 非经营性预付款项 | M12: =E12 -> 0 | N12: 0
B13: 应收利息 | C13: ='1报表'!E20 -> 0 | D13: =C13 -> 0 | G13: =D13-(E13+F13) -> 0 | J13: 应收利息 | K13: ='1报表'!C20 -> 0 | L13: ='1报表'!D20 -> 0 | M13: =E13 -> 0 | N13: =M13 -> 0
B14: 应收股利 | C14: ='1报表'!E21 -> 0 | D14: =C14 -> 0 | G14: =D14-(E14+F14) -> 0 | J14: 应收股利 | K14: ='1报表'!C21 -> 0 | L14: ='1报表'!D21 -> 0 | M14: =E14 -> 0 | N14: =M14 -> 0
B15: 其他应收款 | C15: ='1报表'!E22 -> 950.31863 | D15: =C15 -> 950.31863 | E15: 759.29843 | G15: =D15-(E15+F15) -> 191.0202 | H15: 退休股东费用和调整应收回的自然人股东分红 | J15: 非经营性其他应收款 | K15: 62.159376 | L15: 22.875 | M15: =E15 -> 759.29843 | N15: =M15 -> 759.29843 | O15: 退休股东费用和调整应收回的自然人股东分红
B16: 存货 | C16: ='1报表'!E23 -> 0 | D16: =C16 -> 0 | G16: =D16-(E16+F16) -> 0 | J16: 非经营、报废的存货 | M16: =E16 -> 0 | N16: =M16 -> 0
B17: 合同资产 | C17: ='1报表'!E24 -> 0 | D17: =C17 -> 0 | G17: =D17-(E17+F17) -> 0 | J17: 非经营性合同资产 | M17: =E17 -> 0 | N17: =M17 -> 0
B18: 持有待售资产 | C18: ='1报表'!E25 -> 0 | D18: =C18 -> 0 | G18: =D18-(E18+F18) -> 0 | J18: 持有待售资产 | K18: ='1报表'!C25 -> 0 | L18: ='1报表'!D25 -> 0 | M18: =E18 -> 0 | N18: =M18 -> 0
B19: 一年内到期的非流动资产 | C19: ='1报表'!E26 -> 0 | D19: =C19 -> 0 | G19: =D19-(E19+F19) -> 0 | J19: 非经营性一年内到期的非流动资产 | M19: =E19 -> 0 | N19: =M19 -> 0
B20: 其他流动资产 | C20: ='1报表'!E27 -> 0.575 | D20: =C20 -> 0.575 | E20: 0.575 | G20: =D20-(E20+F20) -> 0 | H20: 应收的预计无法收回的设计费 | J20: 非经营性其他流动资产 | K20: 0.575 | L20: 0.575 | M20: =E20 -> 0.575 | N20: 0 | O20: 应收的预计无法收回的设计费
B21: 流动资产合计 | C21: =SUM(C8:C20) -> 1699.7694 | D21: =SUM(D8:D20) -> 1699.7694 | E21: =SUM(E8:E20) -> 903.83743 | F21: =SUM(F8:F20) -> 0 | G21: =SUM(G8:G20) -> 795.93197 | J21: 非经营性流动资产小计 | K21: =SUM(K9:K20) -> 807.44615 | L21: =SUM(L9:L20) -> 65.694674 | M21: =SUM(M9:M20) -> 903.83743 | N21: =SUM(N9:N20) -> 903.26243
B22: 非流动资产：
B23: 可供出售金融资产 | C23: ='1报表'!E30 -> 1.332422 | D23: =C23 -> 1.332422 | E23: 1.332422 | G23: =D23-(E23+F23) -> 0 | H23: 电力基金，非经营性资产 | J23: 可供出售金融资产 | K23: ='1报表'!C30 -> 1.332422 | L23: ='1报表'!D30 -> 1.332422 | M23: =E23 -> 1.332422 | N23: =M23 -> 1.332422 | O23: 电力基金
B24: 持有至到期投资 | C24: ='1报表'!E31 -> 0 | D24: =C24 -> 0 | G24: =D24-(E24+F24) -> 0 | J24: 持有至到期投资 | K24: ='1报表'!C31 -> 0 | L24: ='1报表'!D31 -> 0 | M24: =E24 -> 0
B25: 债权投资 | C25: ='1报表'!E32 -> 0 | D25: =C25 -> 0 | G25: =D25-(E25+F25) -> 0 | J25: 债权投资 | K25: ='1报表'!C32 -> 0 | L25: ='1报表'!D32 -> 0 | M25: =E25 -> 0
B26: 其他债权投资 | C26: ='1报表'!E33 -> 0 | D26: =C26 -> 0 | G26: =D26-(E26+F26) -> 0 | J26: 其他债权投资 | K26: ='1报表'!C33 -> 0 | L26: ='1报表'!D33 -> 0 | M26: =E26 -> 0
B27: 长期应收款 | C27: ='1报表'!E34 -> 0 | D27: =C27 -> 0 | G27: =D27-(E27+F27) -> 0 | J27: 非经营性长期应收款 | M27: =E27 -> 0
B28: 长期股权投资 | C28: ='1报表'!E35 -> 3.465172 | D28: =C28 -> 3.465172 | E28: 3.465172 | G28: =D28-(E28+F28) -> 0 | H28: xx开发有限公司,作为非经营性资产单独评估 | J28: 长期股权投资 | K28: ='1报表'!C35 -> 3.465172 | L28: ='1报表'!D35 -> 3.465172 | M28: =E28 -> 3.465172 | N28: 0 | O28: xx园林开发有限公司，已破产，无资产可收回
B29: 其他权益工具投资 | C29: ='1报表'!E36 -> 0 | D29: =C29 -> 0 | G29: =D29-(E29+F29) -> 0 | J29: 其他权益工具投资 | K29: ='1报表'!C36 -> 0 | L29: ='1报表'!D36 -> 0 | M29: =E29 -> 0
B30: 其他非流动金融资产 | C30: ='1报表'!E37 -> 0 | D30: =C30 -> 0 | G30: =D30-(E30+F30) -> 0 | J30: 其他非流动金融资产 | K30: ='1报表'!C37 -> 0 | L30: ='1报表'!D37 -> 0 | M30: =E30 -> 0
B31: 投资性房地产 | C31: ='1报表'!E38 -> 0 | D31: =C31 -> 0 | G31: =D31-(E31+F31) -> 0 | J31: 投资性房地产 | K31: ='1报表'!C38 -> 0 | L31: ='1报表'!D38 -> 0 | M31: =E31 -> 0
B32: 固定资产 | C32: ='1报表'!E39 -> 94.661335 | D32: =C32 -> 94.661335 | G32: =D32-(E32+F32) -> 94.661335 | J32: 非经营性固定资产 | M32: =E32 -> 0
B33: 在建工程 | C33: ='1报表'!E40 -> 0 | D33: =C33 -> 0 | G33: =D33-(E33+F33) -> 0 | J33: 非经营性在建工程 | M33: =E33 -> 0
B34: 生产性生物资产 | C34: ='1报表'!E41 -> 0 | D34: =C34 -> 0 | G34: =D34-(E34+F34) -> 0 | J34: 非经营性生产性生物资产 | M34: =E34 -> 0
B35: 油气资产 | C35: ='1报表'!E42 -> 0 | D35: =C35 -> 0 | G35: =D35-(E35+F35) -> 0 | J35: 非经营性油气资产 | M35: =E35 -> 0
B36: 无形资产 | C36: ='1报表'!E43 -> 5.916019 | D36: =C36 -> 5.916019 | G36: =D36-(E36+F36) -> 5.916019 | J36: 非经营性无形资产 | M36: =E36 -> 0
B37: 开发支出 | C37: ='1报表'!E44 -> 0 | D37: =C37 -> 0 | G37: =D37-(E37+F37) -> 0 | J37: 非经营性开发支出 | M37: =E37 -> 0
B38: 商誉 | C38: ='1报表'!E45 -> 0 | D38: =C38 -> 0 | G38: =D38-(E38+F38) -> 0 | J38: 商誉
B39: 长期待摊费用 | C39: ='1报表'!E46 -> 0 | D39: =C39 -> 0 | G39: =D39-(E39+F39) -> 0 | J39: 非经营性长期待摊费用 | M39: =E39 -> 0
B40: 递延所得税资产 | C40: ='1报表'!E47 -> 0 | D40: =C40 -> 0 | G40: =D40-(E40+F40) -> 0 | J40: 递延所得税资产 | M40: =E40 -> 0
B41: 其他非流动资产 | C41: ='1报表'!E48 -> 0 | D41: =C41 -> 0 | G41: =D41-(E41+F41) -> 0 | J41: 非经营性其他非流动资产 | M41: =E41 -> 0
B42: 非流动资产合计 | C42: =SUM(C23:C41) -> 105.37495 | D42: =SUM(D23:D41) -> 105.37495 | E42: =SUM(E23:E41) -> 4.797594 | F42: =SUM(F23:F41) -> 0 | G42: =SUM(G23:G41) -> 100.57735 | J42: 非经营性非流动资产小计 | K42: =SUM(K23:K41) -> 4.797594 | L42: =SUM(L23:L41) -> 4.797594 | M42: =SUM(M23:M41) -> 4.797594 | N42: =SUM(N23:N41) -> 1.332422
B43: 资产总计 | C43: =C21+C42 -> 1805.1443 | D43: =D21+D42 -> 1805.1443 | E43: =E21+E42 -> 908.63502 | F43: =F21+F42 -> 0 | G43: =G21+G42 -> 896.50932 | J43: 非经营性资产合计 | K43: =K21+K42 -> 812.24375 | L43: =L21+L42 -> 70.492268 | M43: =M21+M42 -> 908.63502 | N43: =N21+N42 -> 904.59485
B44: 流动负债： | J44: 非经营性负债 | K44: =K6 -> 42735 | L44: =L6 -> 43100 | M44: =M6 -> 43281 | N44: =N6 -> 评估值
B45: 短期借款 | C45: ='1报表'!E52 -> 0 | D45: =C45 -> 0 | G45: =D45-(E45+F45) -> 0 | J45: 短期借款
B46: 交易性金融负债 | C46: ='1报表'!E53 -> 0 | D46: =C46 -> 0 | G46: =D46-(E46+F46) -> 0 | J46: 交易性金融负债 | K46: ='1报表'!C53 -> 0 | L46: ='1报表'!D53 -> 0 | M46: =E46 -> 0 | N46: =M46 -> 0
B47: 衍生金融负债 | C47: ='1报表'!E54 -> 0 | D47: =C47 -> 0 | G47: =D47-(E47+F47) -> 0 | J47: 衍生金融负债 | K47: ='1报表'!C54 -> 0 | L47: ='1报表'!D54 -> 0 | M47: =E47 -> 0 | N47: =M47 -> 0
B48: 应付票据及应付账款 | C48: ='1报表'!E55 -> 297.39516 | D48: =C48 -> 297.39516 | G48: =D48-(E48+F48) -> 297.39516 | J48: 非经营性应付票据及应付账款 | M48: =E48 -> 0 | N48: =M48 -> 0
B49: 预收款项 | C49: ='1报表'!E56 -> 99.1537 | D49: =C49 -> 99.1537 | G49: =D49-(E49+F49) -> 99.1537 | J49: 非经营性预收款项 | M49: =E49 -> 0 | N49: =M49 -> 0
B50: 合同负债 | C50: ='1报表'!E57 -> 0 | D50: =C50 -> 0 | G50: =D50-(E50+F50) -> 0 | J50: 非经营性合同负债 | M50: =E50 -> 0 | N50: =M50 -> 0
B51: 应付职工薪酬 | C51: ='1报表'!E58 -> 0 | D51: =C51 -> 0 | G51: =D51-(E51+F51) -> 0 | J51: 非经营性应付职工薪酬 | M51: =E51 -> 0 | N51: =M51 -> 0
B52: 应交税费 | C52: ='1报表'!E59 -> 2.22638 | D52: =C52 -> 2.22638 | G52: =D52-(E52+F52) -> 2.22638 | J52: 应交税费
B53: 应付利息 | C53: ='1报表'!E60 -> 0 | D53: =C53 -> 0 | G53: =D53-(E53+F53) -> 0 | J53: 应付利息 | K53: ='1报表'!C60 -> 0 | L53: ='1报表'!D60 -> 0 | M53: =E53 -> 0 | N53: =M53 -> 0
B54: 应付股利 | C54: ='1报表'!E61 -> 656.42426 | D54: =C54 -> 656.42426 | E54: 656.42426 | G54: =D54-(E54+F54) -> 0 | H54: 非经营性负债 | J54: 应付股利 | K54: ='1报表'!C61 -> 0 | L54: ='1报表'!D61 -> 0 | M54: =E54 -> 656.42426 | N54: =M54 -> 656.42426
B55: 其他应付款 | C55: ='1报表'!E62 -> 211.60836 | D55: =C55 -> 211.60836 | E55: 0.377956 | G55: =D55-(E55+F55) -> 211.23041 | H55: 改制费用 | J55: 非经营性其他应付款 | K55: 13.110856 | L55: 45.288056 | M55: =E55 -> 0.377956 | N55: =M55 -> 0.377956 | O55: 改制费用
B56: 持有待售负债 | C56: ='1报表'!E63 -> 0 | D56: =C56 -> 0 | G56: =D56-(E56+F56) -> 0 | J56: 持有待售负债 | K56: ='1报表'!C63 -> 0 | L56: ='1报表'!D63 -> 0 | M56: =E56 -> 0 | N56: =M56 -> 0
B57: 一年内到期的非流动负债 | C57: ='1报表'!E64 -> 0 | D57: =C57 -> 0 | G57: =D57-(E57+F57) -> 0 | J57: 一年内到期的非流动负债
B58: 其他流动负债 | C58: ='1报表'!E65 -> 0 | D58: =C58 -> 0 | G58: =D58-(E58+F58) -> 0 | J58: 非经营性其他流动负债 | M58: =E58 -> 0 | N58: =M58 -> 0
B59: 流动负债合计 | C59: =SUM(C45:C58) -> 1266.8079 | D59: =SUM(D45:D58) -> 1266.8079 | E59: =SUM(E45:E58) -> 656.80221 | F59: =SUM(F45:F58) -> 0 | G59: =SUM(G45:G58) -> 610.00565 | J59: 非经营性流动负债小计 | K59: =SUM(K46:K58) -> 13.110856 | L59: =SUM(L46:L58) -> 45.288056 | M59: =SUM(M46:M58) -> 656.80221 | N59: =SUM(N46:N58) -> 656.80221
B60: 非流动负债：
B61: 长期借款 | C61: ='1报表'!E68 -> 0 | D61: =C61 -> 0 | G61: =D61-(E61+F61) -> 0 | J61: 长期借款
B62: 应付债券 | C62: ='1报表'!E69 -> 0 | D62: =C62 -> 0 | G62: =D62-(E62+F62) -> 0 | J62: 应付债券
B63: 长期应付款 | C63: ='1报表'!E70 -> 31.315556 | D63: =C63 -> 31.315556 | E63: 31.315556 | G63: =D63-(E63+F63) -> 0 | H63: 职工房款和职工住房维修基金 | J63: 非经营性长期应付款 | K63: 31.161043 | L63: 31.278408 | M63: =E63 -> 31.315556 | N63: =M63 -> 31.315556 | O63: 职工房款和职工住房维修基金
B64: 长期应付职工薪酬 | C64: ='1报表'!E71 -> 0 | D64: =C64 -> 0 | G64: =D64-(E64+F64) -> 0 | J64: 非经营性长期应付职工薪酬 | M64: =E64 -> 0
B65: 预计负债 | C65: ='1报表'!E72 -> 0 | D65: =C65 -> 0 | G65: =D65-(E65+F65) -> 0 | J65: 非经营性预计负债 | M65: =E65 -> 0
B66: 递延收益 | C66: ='1报表'!E73 -> 0 | D66: =C66 -> 0 | G66: =D66-(E66+F66) -> 0 | J66: 非经营性递延收益 | M66: =E66 -> 0
B67: 递延所得税负债 | C67: ='1报表'!E74 -> 0 | D67: =C67 -> 0 | G67: =D67-(E67+F67) -> 0 | J67: 递延所得税负债 | M67: =E67 -> 0
B68: 其他非流动负债 | C68: ='1报表'!E75 -> 0 | D68: =C68 -> 0 | G68: =D68-(E68+F68) -> 0 | J68: 非经营性其他非流动负债 | M68: =E68 -> 0
B69: 非流动负债合计 | C69: =SUM(C61:C68) -> 31.315556 | D69: =SUM(D61:D68) -> 31.315556 | E69: =SUM(E61:E68) -> 31.315556 | F69: =SUM(F61:F68) -> 0 | G69: =SUM(G61:G68) -> 0 | J69: 非经营性非流动负债小计 | K69: =SUM(K63:K68) -> 31.161043 | L69: =SUM(L63:L68) -> 31.278408 | M69: =SUM(M63:M68) -> 31.315556 | N69: =SUM(N63:N68) -> 31.315556
B70: 负债合计 | C70: =C59+C69 -> 1298.1234 | D70: =D59+D69 -> 1298.1234 | E70: =E59+E69 -> 688.11777 | F70: =F59+F69 -> 0 | G70: =G59+G69 -> 610.00565 | J70: 非经营性负债合计 | K70: =K59+K69 -> 44.271899 | L70: =L59+L69 -> 76.566464 | M70: =M59+M69 -> 688.11777 | N70: =N59+N69 -> 688.11777
B71: 所有者权益：
B72: 实收资本 | C72: ='1报表'!E79 -> 305 | D72: =C72 -> 305
B73: 其他权益工具 | C73: ='1报表'!E80 -> 0 | D73: =C73 -> 0
B74: 资本公积 | C74: ='1报表'!E81 -> 1.296156 | D74: =C74 -> 1.296156
B75: 减：库存股 | C75: ='1报表'!E82 -> 0 | D75: =C75 -> 0
B76: 其他综合收益 | C76: ='1报表'!E83 -> 0 | D76: =C76 -> 0
B77: 盈余公积 | C77: ='1报表'!E84 -> 174.93031 | D77: =C77 -> 174.93031
B78: 一般风险准备 | C78: ='1报表'!E85 -> 0 | D78: =C78 -> 0
B79: 未分配利润 | C79: ='1报表'!E86 -> 25.794464 | D79: =C79 -> 25.794464
B80: 归属于母公司所有者权益合计 | C80: =SUM(C72:C74)-C75+SUM(C76:C79) -> 507.02093 | D80: =SUM(D72:D74)-D75+SUM(D76:D79) -> 507.02093 | E80: =E82-E81 -> 220.51726 | F80: =F43-F70 -> 0 | G80: =D80-(E80+F80) -> 286.50368
B81: 少数股东权益 | C81: ='1报表'!E88 -> 0 | D81: =C81 -> 0 | G81: =D81-(E81+F81) -> 0
B82: 所有者权益合计 | C82: =C80+C81 -> 507.02093 | D82: =D80+D81 -> 507.02093 | E82: =E43-E70 -> 220.51726 | F82: =F43-F70 -> 0 | G82: =D82-(E82+F82) -> 286.50368
B83: 负债和所有者权益总计 | C83: =C70+C82 -> 1805.1443 | D83: =D70+D82 -> 1805.1443 | G83: =G70+G82 -> 896.50932
B84: 检查核对 | C84: =C43-C83 -> 0 | D84: =D43-D83 -> 0 | G84: =G43-G83 -> 0
B85: 平衡检查？ | C85: =IF(ROUND(C84,0)=0,"OK","需要检查") -> OK | D85: =IF(ROUND(D84,0)=0,"OK","需要检查") -> OK | G85: =IF(ROUND(G84,0)=0,"OK","需要检查") -> OK

Sheet 3收入
B1: 营业收入预测表
B2: ='1报表'!B11 -> 评估基准日：2018/6/30
B3: ='1报表'!B12 -> 被评估单位：YLSJ公司 | K3: 单位：万元
B4: 年度 | C4: ='1报表'!C96 -> 2016年 | D4: ='1报表'!D96 -> 2017年 | E4: ='1报表'!E96 -> 2018年1-6 | F4: =YEAR('1报表'!E5)&"年" -> 2018年 | G4: =LEFT(F4,4)+1&"年" -> 2019年 | H4: =LEFT(G4,4)+1&"年" -> 2020年 | I4: =LEFT(H4,4)+1&"年" -> 2021年 | J4: =LEFT(I4,4)+1&"年" -> 2022年 | K4: =LEFT(J4,4)+1&"年" -> 2023年
B5: 数据汇总 | C5: ='1报表'!C97 -> 6309.9996 | D5: ='1报表'!D97 -> 6454.082 | E5: ='1报表'!E97 -> 2068.9888 | F5: 4500 | G5: =F5*1.1 -> 4950 | H5: =G5*1.08 -> 5346 | I5: =H5*1.05 -> 5613.3 | J5: =I5*1.03 -> 5781.699 | K5: =J5 -> 5781.699
B6: 增长率 | D6: =IF(C5,D5/C5-1,"na") -> 0.022833987 | E6: na | F6: =IF(D5,F5/D5-1,"na") -> -0.30276684 | G6: =IF(F5,G5/F5-1,"na") -> 0.1 | H6: =IF(G5,H5/G5-1,"na") -> 0.08 | I6: =IF(H5,I5/H5-1,"na") -> 0.05 | J6: =IF(I5,J5/I5-1,"na") -> 0.03 | K6: =IF(J5,K5/J5-1,"na") -> 0
B9: 具体预测见“收益法预测操作手册”

Sheet 4成本
B1: 营业成本预测表
B2: ='1报表'!B11 -> 评估基准日：2018/6/30
B3: ='1报表'!B12 -> 被评估单位：YLSJ公司 | K3: 单位：万元
B4: 年度 | C4: ='3收入'!C4 -> 2016年 | D4: ='3收入'!D4 -> 2017年 | E4: ='3收入'!E4 -> 2018年1-6 | F4: ='3收入'!F4 -> 2018年 | G4: ='3收入'!G4 -> 2019年 | H4: ='3收入'!H4 -> 2020年 | I4: ='3收入'!I4 -> 2021年 | J4: ='3收入'!J4 -> 2022年 | K4: ='3收入'!K4 -> 2023年
B5: 数据汇总 | C5: ='1报表'!C98 -> 5325.209 | D5: ='1报表'!D98 -> 5874.6686 | E5: ='1报表'!E98 -> 2248.3124 | F5: =F84 -> 3958.79 | G5: =G84 -> 4362.54 | H5: =H84 -> 4708.1747 | I5: =I84 -> 4917.871 | J5: =J84 -> 5074.1781 | K5: =K84 -> 5081.3281
B6: 营业收入 | C6: ='3收入'!C5 -> 6309.9996 | D6: ='3收入'!D5 -> 6454.082 | E6: ='3收入'!E5 -> 2068.9888 | F6: ='3收入'!F5 -> 4500 | G6: ='3收入'!G5 -> 4950 | H6: ='3收入'!H5 -> 5346 | I6: ='3收入'!I5 -> 5613.3 | J6: ='3收入'!J5 -> 5781.699 | K6: ='3收入'!K5 -> 5781.699
B7: 毛利率 | C7: =IF(C6,(C6-C5)/C6,"na") -> 0.15606824 | D7: =IF(D6,(D6-D5)/D6,"na") -> 0.089774725 | E7: =IF(E6,(E6-E5)/E6,"na") -> -0.08667207 | F7: =IF(F6,(F6-F5)/F6,"na") -> 0.12026889 | G7: =IF(G6,(G6-G5)/G6,"na") -> 0.11867879 | H7: =IF(H6,(H6-H5)/H6,"na") -> 0.11930888 | I7: =IF(I6,(I6-I5)/I6,"na") -> 0.12388951 | J7: =IF(J6,(J6-J5)/J6,"na") -> 0.12237248 | K7: =IF(K6,(K6-K5)/K6,"na") -> 0.12113582
B8: 营业成本预测（生产型企业）（方式一）
B9: 项目1 | C9: =C4 -> 2016年 | D9: =D4 -> 2017年 | E9: =E4 -> 2018年1-6 | F9: =F4 -> 2018年 | G9: =G4 -> 2019年 | H9: =H4 -> 2020年 | I9: =I4 -> 2021年 | J9: =J4 -> 2022年 | K9: =K4 -> 2023年 | M9: 按科目进行分析
B10: 原材料 | M10: 评估实务中还应当对原材料的变化趋势作一说明，公司消化原材料价格变化的经营措施。
B11: 占收入比 | C11: =IF(C6,C10/C6,"na") -> 0 | D11: =IF(D6,D10/D6,"na") -> 0 | E11: =IF(E6,E10/E6,"na") -> 0 | M11: 员工人数是否会随着收入增长而增加，消化人工成本的措施。
B12: =B10 -> 原材料 | C12: =C10 -> 0 | D12: =D10 -> 0 | E12: =E10 -> 0 | F12: =IF(F10,F10,F11*F6) -> 0 | G12: =IF(G10,G10,G11*G6) -> 0 | H12: =IF(H10,H10,H11*H6) -> 0 | I12: =IF(I10,I10,I11*I6) -> 0 | J12: =IF(J10,J10,J11*J6) -> 0 | K12: =IF(K10,K10,K11*K6) -> 0 | M12: （要有具体的纸质底稿支撑）
B13: 占收入比 | F13: =IF(F6,F12/F6,"na") -> 0 | G13: =IF(G6,G12/G6,"na") -> 0 | H13: =IF(H6,H12/H6,"na") -> 0 | I13: =IF(I6,I12/I6,"na") -> 0 | J13: =IF(J6,J12/J6,"na") -> 0 | K13: =IF(K6,K12/K6,"na") -> 0
B15: 项目2 | C15: =C4 -> 2016年 | D15: =D4 -> 2017年 | E15: =E4 -> 2018年1-6 | F15: =F4 -> 2018年 | G15: =G4 -> 2019年 | H15: =H4 -> 2020年 | I15: =I4 -> 2021年 | J15: =J4 -> 2022年 | K15: =K4 -> 2023年
B16: 燃料及动力
B17: 占收入比 | C17: =IF(C6,C16/C6,"na") -> 0 | D17: =IF(D6,D16/D6,"na") -> 0 | E17: =IF(E6,E16/E6,"na") -> 0
B18: =B16 -> 燃料及动力 | C18: =C16 -> 0 | D18: =D16 -> 0 | E18: =E16 -> 0 | F18: =IF(F16,F16,F17*F6) -> 0 | G18: =IF(G16,G16,G17*G6) -> 0 | H18: =IF(H16,H16,H17*H6) -> 0 | I18: =IF(I16,I16,I17*I6) -> 0 | J18: =IF(J16,J16,J17*J6) -> 0 | K18: =IF(K16,K16,K17*K6) -> 0
B19: 占收入比 | F19: =IF(F6,F18/F6,"na") -> 0 | G19: =IF(G6,G18/G6,"na") -> 0 | H19: =IF(H6,H18/H6,"na") -> 0 | I19: =IF(I6,I18/I6,"na") -> 0 | J19: =IF(J6,J18/J6,"na") -> 0 | K19: =IF(K6,K18/K6,"na") -> 0
B21: 项目3 | C21: =C4 -> 2016年 | D21: =D4 -> 2017年 | E21: =E4 -> 2018年1-6 | F21: =F4 -> 2018年 | G21: =G4 -> 2019年 | H21: =H4 -> 2020年 | I21: =I4 -> 2021年 | J21: =J4 -> 2022年 | K21: =K4 -> 2023年
B22: 生产人员工资及附加
B23: 占收入比 | C23: =IF(C6,C22/C6,"na") -> 0 | D23: =IF(D6,D22/D6,"na") -> 0 | E23: =IF(E6,E22/E6,"na") -> 0 | G23: =F23 -> 0 | H23: =G23 -> 0 | I23: =H23 -> 0 | J23: =I23 -> 0 | K23: =J23 -> 0
B24: =B22 -> 生产人员工资及附加 | C24: =C22 -> 0 | D24: =D22 -> 0 | E24: =E22 -> 0 | F24: =IF(F22,F22,F23*F6) -> 0 | G24: =IF(G22,G22,G23*G6) -> 0 | H24: =IF(H22,H22,H23*H6) -> 0 | I24: =IF(I22,I22,I23*I6) -> 0 | J24: =IF(J22,J22,J23*J6) -> 0 | K24: =IF(K22,K22,K23*K6) -> 0
B25: 占收入比 | F25: =IF(F6,F24/F6,"na") -> 0 | G25: =IF(G6,G24/G6,"na") -> 0 | H25: =IF(H6,H24/H6,"na") -> 0 | I25: =IF(I6,I24/I6,"na") -> 0 | J25: =IF(J6,J24/J6,"na") -> 0 | K25: =IF(K6,K24/K6,"na") -> 0
B27: 项目4 | C27: =C4 -> 2016年 | D27: =D4 -> 2017年 | E27: =E4 -> 2018年1-6 | F27: =F4 -> 2018年 | G27: =G4 -> 2019年 | H27: =H4 -> 2020年 | I27: =I4 -> 2021年 | J27: =J4 -> 2022年 | K27: =K4 -> 2023年
B28: 折旧（及摊销） | F28: ='7折旧'!F5 -> 43.79 | G28: ='7折旧'!G5 -> 56.04 | H28: ='7折旧'!H5 -> 57.154732 | I28: ='7折旧'!I5 -> 34.3 | J28: ='7折旧'!J5 -> 44.1 | K28: ='7折旧'!K5 -> 51.25
B29: 占收入比 | C29: =IF(C6,C28/C6,"na") -> 0 | D29: =IF(D6,D28/D6,"na") -> 0 | E29: =IF(E6,E28/E6,"na") -> 0 | F29: =IF(F6,F28/F6,"na") -> 0.0097311111 | G29: =IF(G6,G28/G6,"na") -> 0.011321212 | H29: =IF(H6,H28/H6,"na") -> 0.010691121 | I29: =IF(I6,I28/I6,"na") -> 0.0061104876 | J29: =IF(J6,J28/J6,"na") -> 0.0076275157 | K29: =IF(K6,K28/K6,"na") -> 0.0088641764
B31: 项目5 | C31: =C4 -> 2016年 | D31: =D4 -> 2017年 | E31: =E4 -> 2018年1-6 | F31: =F4 -> 2018年 | G31: =G4 -> 2019年 | H31: =H4 -> 2020年 | I31: =I4 -> 2021年 | J31: =J4 -> 2022年 | K31: =K4 -> 2023年
B32: 其他
B33: 占收入比 | C33: =IF(C6,C32/C6,"na") -> 0 | D33: =IF(D6,D32/D6,"na") -> 0 | E33: =IF(E6,E32/E6,"na") -> 0
B34: =B32 -> 其他 | C34: =C32 -> 0 | D34: =D32 -> 0 | E34: =E32 -> 0 | F34: =IF(F32,F32,F33*F6) -> 0 | G34: =IF(G32,G32,G33*G6) -> 0 | H34: =IF(H32,H32,H33*H6) -> 0 | I34: =IF(I32,I32,I33*I6) -> 0 | J34: =IF(J32,J32,J33*J6) -> 0 | K34: =IF(K32,K32,K33*K6) -> 0
B35: 占收入比 | F35: =IF(F6,F34/F6,"na") -> 0 | G35: =IF(G6,G34/G6,"na") -> 0 | H35: =IF(H6,H34/H6,"na") -> 0 | I35: =IF(I6,I34/I6,"na") -> 0 | J35: =IF(J6,J34/J6,"na") -> 0 | K35: =IF(K6,K34/K6,"na") -> 0
B37: 项目（汇总） | C37: =C4 -> 2016年 | D37: =D4 -> 2017年 | E37: =E4 -> 2018年1-6 | F37: =F4 -> 2018年 | G37: =G4 -> 2019年 | H37: =H4 -> 2020年 | I37: =I4 -> 2021年 | J37: =J4 -> 2022年 | K37: =K4 -> 2023年
B38: 营业成本 | C38: =C12+C18+C24+C28+C34 -> 0 | D38: =D12+D18+D24+D28+D34 -> 0 | E38: =E12+E18+E24+E28+E34 -> 0 | F38: =F12+F18+F24+F28+F34 -> 43.79 | G38: =G12+G18+G24+G28+G34 -> 56.04 | H38: =H12+H18+H24+H28+H34 -> 57.154732 | I38: =I12+I18+I24+I28+I34 -> 34.3 | J38: =J12+J18+J24+J28+J34 -> 44.1 | K38: =K12+K18+K24+K28+K34 -> 51.25
B39: 占收入比 | C39: =IF(C6,C38/C6,"na") -> 0 | D39: =IF(D6,D38/D6,"na") -> 0 | E39: =IF(E6,E38/E6,"na") -> 0 | F39: =IF(F6,F38/F6,"na") -> 0.0097311111 | G39: =IF(G6,G38/G6,"na") -> 0.011321212 | H39: =IF(H6,H38/H6,"na") -> 0.010691121 | I39: =IF(I6,I38/I6,"na") -> 0.0061104876 | J39: =IF(J6,J38/J6,"na") -> 0.0076275157 | K39: =IF(K6,K38/K6,"na") -> 0.0088641764
B40: 毛利率 | C40: =IF(C6,1-C39,"na") -> 1 | D40: =IF(D6,1-D39,"na") -> 1 | E40: =IF(E6,1-E39,"na") -> 1 | F40: =IF(F6,1-F39,"na") -> 0.99026889 | G40: =IF(G6,1-G39,"na") -> 0.98867879 | H40: =IF(H6,1-H39,"na") -> 0.98930888 | I40: =IF(I6,1-I39,"na") -> 0.99388951 | J40: =IF(J6,1-J39,"na") -> 0.99237248 | K40: =IF(K6,1-K39,"na") -> 0.99113582
B42: 按产品/项目毛利率分析（方式二） | E42: 需具体分析毛利率变动原因，以及提高或降低措施，而不是仅仅列张汇总表（要有具体的纸质底稿支撑）
B43: 毛利率 | C43: =C4 -> 2016年 | D43: =D4 -> 2017年 | E43: =E4 -> 2018年1-6 | F43: =F4 -> 2018年 | G43: =G4 -> 2019年 | H43: =H4 -> 2020年 | I43: =I4 -> 2021年 | J43: =J4 -> 2022年 | K43: =K4 -> 2023年
B44: 产品a
B45: 产品b
B46: 产品c
B47: 综合毛利率 | C47: =IF(C6,(C6-C5)/C6,"na") -> 0.15606824 | D47: =IF(D6,(D6-D5)/D6,"na") -> 0.089774725 | E47: =IF(E6,(E6-E5)/E6,"na") -> -0.08667207 | F47: =IF(F6,(F6-F5)/F6,"na") -> 0.12026889 | G47: =IF(G6,(G6-G5)/G6,"na") -> 0.11867879 | H47: =IF(H6,(H6-H5)/H6,"na") -> 0.11930888 | I47: =IF(I6,(I6-I5)/I6,"na") -> 0.12388951 | J47: =IF(J6,(J6-J5)/J6,"na") -> 0.12237248 | K47: =IF(K6,(K6-K5)/K6,"na") -> 0.12113582
B49: 可比公司对比分析（可选）
B50: 毛利率 | C50: =C4 -> 2016年 | D50: =D4 -> 2017年 | E50: =E4 -> 2018年1-6 | F50: 平均值
B51: xx公司 | F51: =IF(ISERROR(AVERAGE(C51:E51)),0,AVERAGE(C51:E51)) -> 0
F52: =IF(ISERROR(AVERAGE(C52:E52)),0,AVERAGE(C52:E52)) -> 0
F53: =IF(ISERROR(AVERAGE(C53:E53)),0,AVERAGE(C53:E53)) -> 0
F54: =IF(ISERROR(AVERAGE(C54:E54)),0,AVERAGE(C54:E54)) -> 0
F55: =IF(ISERROR(AVERAGE(C55:E55)),0,AVERAGE(C55:E55)) -> 0
F56: =IF(ISERROR(AVERAGE(C56:E56)),0,AVERAGE(C56:E56)) -> 0
B57: 平均值 | C57: =IF(ISERROR(AVERAGE(C51:C56)),0,AVERAGE(C51:C56)) -> 0 | D57: =IF(ISERROR(AVERAGE(D51:D56)),0,AVERAGE(D51:D56)) -> 0 | E57: =IF(ISERROR(AVERAGE(E51:E56)),0,AVERAGE(E51:E56)) -> 0
B58: 中位数 | C58: =IF(ISERROR(MEDIAN(C51:C56)),0,MEDIAN(C51:C56)) -> 0 | D58: =IF(ISERROR(MEDIAN(D51:D56)),0,MEDIAN(D51:D56)) -> 0 | E58: =IF(ISERROR(MEDIAN(E51:E56)),0,MEDIAN(E51:E56)) -> 0
B59: 示例
B60: 成本分析
B61: 项目1 | C61: =C4 -> 2016年 | D61: =D4 -> 2017年 | E61: =E4 -> 2018年1-6 | F61: =F4 -> 2018年 | G61: =G4 -> 2019年 | H61: =H4 -> 2020年 | I61: =I4 -> 2021年 | J61: =J4 -> 2022年 | K61: =K4 -> 2023年
B62: 应付成本及其他 | C62: 2496.387 | D62: 2524.4998 | E62: 582.51966
B63: 占收入比 | C63: =IF(C6,C62/C6,"na") -> 0.39562396 | D63: =IF(D6,D62/D6,"na") -> 0.39114778 | E63: =IF(E6,E62/E6,"na") -> 0.281548 | F63: 0.39 | G63: =F63 -> 0.39 | H63: =G63 -> 0.39 | I63: =H63 -> 0.39 | J63: =I63 -> 0.39 | K63: =J63 -> 0.39
B64: 应付成本及其他 | C64: =C62 -> 2496.387 | D64: =D62 -> 2524.4998 | E64: =E62 -> 582.51966 | F64: =IF(F62,F62,F63*F6) -> 1755 | G64: =IF(G62,G62,G63*G6) -> 1930.5 | H64: =IF(H62,H62,H63*H6) -> 2084.94 | I64: =IF(I62,I62,I63*I6) -> 2189.187 | J64: =IF(J62,J62,J63*J6) -> 2254.8626 | K64: =IF(K62,K62,K63*K6) -> 2254.8626
B65: 占收入比 | F65: =IF(F6,F64/F6,"na") -> 0.39 | G65: =IF(G6,G64/G6,"na") -> 0.39 | H65: =IF(H6,H64/H6,"na") -> 0.39 | I65: =IF(I6,I64/I6,"na") -> 0.39 | J65: =IF(J6,J64/J6,"na") -> 0.39 | K65: =IF(K6,K64/K6,"na") -> 0.39
B67: 项目2 | C67: =C4 -> 2016年 | D67: =D4 -> 2017年 | E67: =E4 -> 2018年1-6 | F67: =F4 -> 2018年 | G67: =G4 -> 2019年 | H67: =H4 -> 2020年 | I67: =I4 -> 2021年 | J67: =J4 -> 2022年 | K67: =K4 -> 2023年
B68: 办公差旅费用 | C68: 627.70474 | D68: 647.62261 | E68: 195.6247
B69: 占收入比 | C69: =IF(C6,C68/C6,"na") -> 0.099477779 | D69: =IF(D6,D68/D6,"na") -> 0.1003431 | E69: =IF(E6,E68/E6,"na") -> 0.094550872 | F69: 0.1 | G69: =F69 -> 0.1 | H69: =G69 -> 0.1 | I69: =H69 -> 0.1 | J69: =I69 -> 0.1 | K69: =J69 -> 0.1
B70: 办公差旅费用 | C70: =C68 -> 627.70474 | D70: =D68 -> 647.62261 | E70: =E68 -> 195.6247 | F70: =IF(F68,F68,F69*F6) -> 450 | G70: =IF(G68,G68,G69*G6) -> 495 | H70: =IF(H68,H68,H69*H6) -> 534.6 | I70: =IF(I68,I68,I69*I6) -> 561.33 | J70: =IF(J68,J68,J69*J6) -> 578.1699 | K70: =IF(K68,K68,K69*K6) -> 578.1699
B71: 占收入比 | F71: =IF(F6,F70/F6,"na") -> 0.1 | G71: =IF(G6,G70/G6,"na") -> 0.1 | H71: =IF(H6,H70/H6,"na") -> 0.1 | I71: =IF(I6,I70/I6,"na") -> 0.1 | J71: =IF(J6,J70/J6,"na") -> 0.1 | K71: =IF(K6,K70/K6,"na") -> 0.1
B73: 项目3 | C73: =C67 -> 2016年 | D73: =D67 -> 2017年 | E73: =E67 -> 2018年1-6 | F73: =F67 -> 2018年 | G73: =G67 -> 2019年 | H73: =H67 -> 2020年 | I73: =I67 -> 2021年 | J73: =J67 -> 2022年 | K73: =K67 -> 2023年
B74: 生产人员工资及附加 | C74: 2154.657 | D74: 2653.2073 | E74: 1450.9406
B75: 占收入比 | C75: =IF(C6,C74/C6,"na") -> 0.34146707 | D75: =IF(D6,D74/D6,"na") -> 0.4110898 | E75: =IF(E6,E74/E6,"na") -> 0.70128006 | F75: 0.38 | G75: =F75 -> 0.38 | H75: =G75 -> 0.38 | I75: =H75 -> 0.38 | J75: =I75 -> 0.38 | K75: =J75 -> 0.38
B76: 生产人员工资及附加 | C76: =C74 -> 2154.657 | D76: =D74 -> 2653.2073 | E76: =E74 -> 1450.9406 | F76: =IF(F74,F74,F75*F6) -> 1710 | G76: =IF(G74,G74,G75*G6) -> 1881 | H76: =IF(H74,H74,H75*H6) -> 2031.48 | I76: =IF(I74,I74,I75*I6) -> 2133.054 | J76: =IF(J74,J74,J75*J6) -> 2197.0456 | K76: =IF(K74,K74,K75*K6) -> 2197.0456
B77: 占收入比 | F77: =IF(F6,F76/F6,"na") -> 0.38 | G77: =IF(G6,G76/G6,"na") -> 0.38 | H77: =IF(H6,H76/H6,"na") -> 0.38 | I77: =IF(I6,I76/I6,"na") -> 0.38 | J77: =IF(J6,J76/J6,"na") -> 0.38 | K77: =IF(K6,K76/K6,"na") -> 0.38
B79: 项目4 | C79: =C73 -> 2016年 | D79: =D73 -> 2017年 | E79: =E73 -> 2018年1-6 | F79: =F73 -> 2018年 | G79: =G73 -> 2019年 | H79: =H73 -> 2020年 | I79: =I73 -> 2021年 | J79: =J73 -> 2022年 | K79: =K73 -> 2023年
B80: 折旧（及摊销） | C80: 46.460209 | D80: 49.338851 | E80: 19.225383 | F80: ='7折旧'!F5 -> 43.79 | G80: ='7折旧'!G5 -> 56.04 | H80: ='7折旧'!H5 -> 57.154732 | I80: ='7折旧'!I5 -> 34.3 | J80: ='7折旧'!J5 -> 44.1 | K80: ='7折旧'!K5 -> 51.25
B81: 占收入比 | C81: =IF(C6,C80/C6,"na") -> 0.0073629496 | D81: =IF(D6,D80/D6,"na") -> 0.0076445962 | E81: =IF(E6,E80/E6,"na") -> 0.0092921638 | F81: =IF(F6,F80/F6,"na") -> 0.0097311111 | G81: =IF(G6,G80/G6,"na") -> 0.011321212 | H81: =IF(H6,H80/H6,"na") -> 0.010691121 | I81: =IF(I6,I80/I6,"na") -> 0.0061104876 | J81: =IF(J6,J80/J6,"na") -> 0.0076275157 | K81: =IF(K6,K80/K6,"na") -> 0.0088641764
B83: 项目（汇总） | C83: =C79 -> 2016年 | D83: =D79 -> 2017年 | E83: =E79 -> 2018年1-6 | F83: =F79 -> 2018年 | G83: =G79 -> 2019年 | H83: =H79 -> 2020年 | I83: =I79 -> 2021年 | J83: =J79 -> 2022年 | K83: =K79 -> 2023年
B84: 营业成本 | C84: =C64+C70+C76+C80 -> 5325.209 | D84: =D64+D70+D76+D80 -> 5874.6686 | E84: =E64+E70+E76+E80 -> 2248.3103 | F84: =F64+F70+F76+F80 -> 3958.79 | G84: =G64+G70+G76+G80 -> 4362.54 | H84: =H64+H70+H76+H80 -> 4708.1747 | I84: =I64+I70+I76+I80 -> 4917.871 | J84: =J64+J70+J76+J80 -> 5074.1781 | K84: =K64+K70+K76+K80 -> 5081.3281
B85: 占收入比 | C85: =IF(C6,C84/C6,"na") -> 0.84393176 | D85: =IF(D6,D84/D6,"na") -> 0.91022528 | E85: =IF(E6,E84/E6,"na") -> 1.0866711 | F85: =IF(F6,F84/F6,"na") -> 0.87973111 | G85: =IF(G6,G84/G6,"na") -> 0.88132121 | H85: =IF(H6,H84/H6,"na") -> 0.88069112 | I85: =IF(I6,I84/I6,"na") -> 0.87611049 | J85: =IF(J6,J84/J6,"na") -> 0.87762752 | K85: =IF(K6,K84/K6,"na") -> 0.87886418
B86: 毛利率 | C86: =IF(C6,1-C85,"na") -> 0.15606824 | D86: =IF(D6,1-D85,"na") -> 0.089774725 | E86: =IF(E6,1-E85,"na") -> -0.086671091 | F86: =IF(F6,1-F85,"na") -> 0.12026889 | G86: =IF(G6,1-G85,"na") -> 0.11867879 | H86: =IF(H6,1-H85,"na") -> 0.11930888 | I86: =IF(I6,1-I85,"na") -> 0.12388951 | J86: =IF(J6,1-J85,"na") -> 0.12237248 | K86: =IF(K6,1-K85,"na") -> 0.12113582

Sheet 5税金
B1: 税金及附加预测表
B2: ='1报表'!B11 -> 评估基准日：2018/6/30
B3: ='1报表'!B12 -> 被评估单位：YLSJ公司 | K3: 单位：万元
B4: 年度 | C4: ='3收入'!C4 -> 2016年 | D4: ='3收入'!D4 -> 2017年 | E4: ='3收入'!E4 -> 2018年1-6 | F4: ='3收入'!F4 -> 2018年 | G4: ='3收入'!G4 -> 2019年 | H4: ='3收入'!H4 -> 2020年 | I4: ='3收入'!I4 -> 2021年 | J4: ='3收入'!J4 -> 2022年 | K4: ='3收入'!K4 -> 2023年
B5: 数据汇总 | C5: ='1报表'!C99 -> 32.988746 | D5: ='1报表'!D99 -> 28.542702 | E5: ='1报表'!E99 -> 19.638479 | F5: =F13 -> 22.5 | G5: =G13 -> 24.75 | H5: =H13 -> 26.73 | I5: =I13 -> 28.0665 | J5: =J13 -> 28.908495 | K5: =K13 -> 28.908495
B6: 营业收入 | C6: ='3收入'!C5 -> 6309.9996 | D6: ='3收入'!D5 -> 6454.082 | E6: ='3收入'!E5 -> 2068.9888 | F6: ='3收入'!F5 -> 4500 | G6: ='3收入'!G5 -> 4950 | H6: ='3收入'!H5 -> 5346 | I6: ='3收入'!I5 -> 5613.3 | J6: ='3收入'!J5 -> 5781.699 | K6: ='3收入'!K5 -> 5781.699
B7: 占收入比 | C7: =IF(C6,C5/C6,"na") -> 0.0052280108 | D7: =IF(D6,D5/D6,"na") -> 0.0044224263 | E7: =IF(E6,E5/E6,"na") -> 0.0094918246 | F7: =IF(F6,F5/F6,"na") -> 0.005 | G7: =IF(G6,G5/G6,"na") -> 0.005 | H7: =IF(H6,H5/H6,"na") -> 0.005 | I7: =IF(I6,I5/I6,"na") -> 0.005 | J7: =IF(J6,J5/J6,"na") -> 0.005 | K7: =IF(K6,K5/K6,"na") -> 0.005
B8: 按收入占比分析（方式一） | D8: 实务中如果历史数据比较平稳，可采用下例简化处理。
C9: =C4 -> 2016年 | D9: =D4 -> 2017年 | E9: =E4 -> 2018年1-6 | F9: =F4 -> 2018年 | G9: =G4 -> 2019年 | H9: =H4 -> 2020年 | I9: =I4 -> 2021年 | J9: =J4 -> 2022年 | K9: =K4 -> 2023年
B10: 营业收入 | C10: =C6 -> 6309.9996 | D10: =D6 -> 6454.082 | E10: =E6 -> 2068.9888 | F10: =F6 -> 4500 | G10: =G6 -> 4950 | H10: =H6 -> 5346 | I10: =I6 -> 5613.3 | J10: =J6 -> 5781.699 | K10: =K6 -> 5781.699
B11: 税金及附加 | C11: =C5 -> 32.988746 | D11: =D5 -> 28.542702
B12: 占收入比 | C12: =IF(C10,C11/C10,"na") -> 0.0052280108 | D12: =IF(D10,D11/D10,"na") -> 0.0044224263 | E12: =IF(E10,E11/E10,"na") -> 0 | F12: 0.005 | G12: =F12 -> 0.005 | H12: =G12 -> 0.005 | I12: =H12 -> 0.005 | J12: =I12 -> 0.005 | K12: =J12 -> 0.005
B13: 税金及附加 | F13: =IF(F11,F11,F12*F10) -> 22.5 | G13: =IF(G11,G11,G12*G10) -> 24.75 | H13: =IF(H11,H11,H12*H10) -> 26.73 | I13: =IF(I11,I11,I12*I10) -> 28.0665 | J13: =IF(J11,J11,J12*J10) -> 28.908495 | K13: =IF(K11,K11,K12*K10) -> 28.908495
B14: 占收入比 | F14: =IF(F10,F13/F10,"na") -> 0.005 | G14: =IF(G10,G13/G10,"na") -> 0.005 | H14: =IF(H10,H13/H10,"na") -> 0.005 | I14: =IF(I10,I13/I10,"na") -> 0.005 | J14: =IF(J10,J13/J10,"na") -> 0.005 | K14: =IF(K10,K13/K10,"na") -> 0.005
B16: 分项目进行分析（方式二） | D16: 实务中如果企业产品不单一，每种产品或服务适用的税率不同，以及金额较大，应分项目评估。示例如下
B17: 项目 | C17: =C4 -> 2016年 | D17: =D4 -> 2017年 | E17: =E4 -> 2018年1-6 | F17: =F4 -> 2018年 | G17: =G4 -> 2019年 | H17: =H4 -> 2020年 | I17: =I4 -> 2021年 | J17: =J4 -> 2022年 | K17: =K4 -> 2023年 | L17: 税率 | M17: 计税公式 | N17: 计税依据的主要内容
B18: 增值税销项 | L18: 0.16
B19: 增值税进项 | L19: 0.16 | N19: 注意资本性支出中设备的增值税要加上
B20: 应缴增值税 | C20: =C18-C19 -> 0 | D20: =D18-D19 -> 0 | E20: =E18-E19 -> 0 | F20: =F18-F19 -> 0 | G20: =G18-G19 -> 0 | H20: =H18-H19 -> 0 | I20: =I18-I19 -> 0 | J20: =J18-J19 -> 0 | K20: =K18-K19 -> 0 | M20: (1)-(2)
B21: 应缴营业税 | N21: 营改增后，该项无。
B22: 应缴流转税合计 | C22: =C20+C21 -> 0 | D22: =D20+D21 -> 0 | E22: =E20+E21 -> 0 | F22: =IF(F20+F21<0,0,F20+F21) -> 0 | G22: =IF(G20+G21<0,0,G20+G21) -> 0 | H22: =IF(H20+H21<0,0,H20+H21) -> 0 | I22: =IF(I20+I21<0,0,I20+I21) -> 0 | J22: =IF(J20+J21<0,0,J20+J21) -> 0 | K22: =IF(K20+K21<0,0,K20+K21) -> 0 | M22: (3)+(4)
B23: 消费税
B24: 城市维护建设税 | F24: =F48*$L$24 -> 0 | G24: =G48*$L$24 -> 0 | H24: =H48*$L$24 -> 0 | I24: =I48*$L$24 -> 0 | J24: =J48*$L$24 -> 0 | K24: =K48*$L$24 -> 0 | L24: 0.07 | M24: 应交流转税项
B25: 资源税
B26: 教育费附加 | F26: =F48*$L$26 -> 0 | G26: =G48*$L$26 -> 0 | H26: =H48*$L$26 -> 0 | I26: =I48*$L$26 -> 0 | J26: =J48*$L$26 -> 0 | K26: =K48*$L$26 -> 0 | L26: 0.05 | M26: 应交流转税项
B27: 房产税
B28: 土地使用税
B29: 车船使用税
B30: 印花税 | L30: 0.0003 | N30: 特殊行业要具实考虑
B31: 其他
B32: 合计 | C32: =C21+SUM(C23:C31) -> 0 | D32: =D21+SUM(D23:D31) -> 0 | E32: =E21+SUM(E23:E31) -> 0 | F32: =F21+SUM(F23:F31) -> 0 | G32: =G21+SUM(G23:G31) -> 0 | H32: =H21+SUM(H23:H31) -> 0 | I32: =I21+SUM(I23:I31) -> 0 | J32: =J21+SUM(J23:J31) -> 0 | K32: =K21+SUM(K23:K31) -> 0
B33: 占收入比 | F33: =IF(F6,F32/F6,"na") -> 0 | G33: =IF(G6,G32/G6,"na") -> 0 | H33: =IF(H6,H32/H6,"na") -> 0 | I33: =IF(I6,I32/I6,"na") -> 0 | J33: =IF(J6,J32/J6,"na") -> 0 | K33: =IF(K6,K32/K6,"na") -> 0
B35: 实务中如果企业产品不单一，每种产品或服务适用的增值税率不同，以及金额较大，应分项目评估。示例如下
B36: 增值税计算 | F36: =F4 -> 2018年 | G36: =G4 -> 2019年 | H36: =H4 -> 2020年 | I36: =I4 -> 2021年 | J36: =J4 -> 2022年 | K36: =K4 -> 2023年
B37: 增值税销项税
B39: 原辅材料进项税
B40: 运输费
B41: 水电费
B42: 其他科目转入进项税
B43: 购买设备进项税
B44: 购买土地进项税
B45: 购买无形资产进项税
B46: 未抵扣进项税
B47: 增值税进项税合计 | F47: =SUM(F39:F46) -> 0 | G47: =SUM(G39:G46) -> 0 | H47: =SUM(H39:H46) -> 0 | I47: =SUM(I39:I46) -> 0 | J47: =SUM(J39:J46) -> 0 | K47: =SUM(K39:K46) -> 0
B48: 应交增值税 | F48: =F37-F47 -> 0 | G48: =G37-G47 -> 0 | H48: =H37-H47 -> 0 | I48: =I37-I47 -> 0 | J48: =J37-J47 -> 0 | K48: =K37-K47 -> 0

Sheet 6销管
B1: 销售费用、管理费用、研发费用预测表
B2: ='1报表'!B11 -> 评估基准日：2018/6/30
B3: ='1报表'!B12 -> 被评估单位：YLSJ公司 | K3: 单位：万元
B4: 数据汇总 | C4: ='3收入'!C4 -> 2016年 | D4: ='3收入'!D4 -> 2017年 | E4: ='3收入'!E4 -> 2018年1-6 | F4: ='3收入'!F4 -> 2018年 | G4: ='3收入'!G4 -> 2019年 | H4: ='3收入'!H4 -> 2020年 | I4: ='3收入'!I4 -> 2021年 | J4: ='3收入'!J4 -> 2022年 | K4: ='3收入'!K4 -> 2023年
B5: 销售费用 | C5: ='1报表'!C100 -> 0 | D5: ='1报表'!D100 -> 0 | E5: ='1报表'!E100 -> 0 | F5: =F41 -> 0 | G5: =G41 -> 0 | H5: =H41 -> 0 | I5: =I41 -> 0 | J5: =J41 -> 0 | K5: =K41 -> 0
B6: 管理费用 | C6: ='1报表'!C101 -> 668.47256 | D6: ='1报表'!D101 -> 615.9856 | E6: ='1报表'!E101 -> 268.92924 | F6: =F75 -> 475.43751 | G6: =G75 -> 512.95 | H6: =H75 -> 554.946 | I6: =I75 -> 583.4433 | J6: =J75 -> 599.9516 | K6: =K75 -> 599.9516
B7: 研发费用 | C7: ='1报表'!C102 -> 0 | D7: ='1报表'!D102 -> 0 | E7: ='1报表'!E102 -> 0 | F7: =F82 -> 0 | G7: =G82 -> 0 | H7: =H82 -> 0 | I7: =I82 -> 0 | J7: =J82 -> 0 | K7: =K82 -> 0
B8: 销售、管理、研发费用 | C8: =SUM(C5:C7) -> 668.47256 | D8: =SUM(D5:D7) -> 615.9856 | E8: =SUM(E5:E7) -> 268.92924 | F8: =SUM(F5:F7) -> 475.43751 | G8: =SUM(G5:G7) -> 512.95 | H8: =SUM(H5:H7) -> 554.946 | I8: =SUM(I5:I7) -> 583.4433 | J8: =SUM(J5:J7) -> 599.9516 | K8: =SUM(K5:K7) -> 599.9516
B9: 营业收入 | C9: ='3收入'!C5 -> 6309.9996 | D9: ='3收入'!D5 -> 6454.082 | E9: ='3收入'!E5 -> 2068.9888 | F9: ='3收入'!F5 -> 4500 | G9: ='3收入'!G5 -> 4950 | H9: ='3收入'!H5 -> 5346 | I9: ='3收入'!I5 -> 5613.3 | J9: ='3收入'!J5 -> 5781.699 | K9: ='3收入'!K5 -> 5781.699
B10: SGA/Sale | C10: =IF(C9,C8/C9,"na") -> 0.10593861 | D10: =IF(D9,D8/D9,"na") -> 0.095441241 | E10: =IF(E9,E8/E9,"na") -> 0.129981 | F10: =IF(F9,F8/F9,"na") -> 0.10565278 | G10: =IF(G9,G8/G9,"na") -> 0.10362626 | H10: =IF(H9,H8/H9,"na") -> 0.10380584 | I10: =IF(I9,I8/I9,"na") -> 0.10393945 | J10: =IF(J9,J8/J9,"na") -> 0.10376735 | K10: =IF(K9,K8/K9,"na") -> 0.10376735
B11: 销售费用分析（点行"+" 号展开） | E11: 科目内容只是示例，根据具体项目改动！ | I11: 金额大、变动大的科目要具体分析
B12: 销售费用 | C12: =C4 -> 2016年 | D12: =D4 -> 2017年 | E12: =E4 -> 2018年1-6 | F12: =F4 -> 2018年 | G12: =G4 -> 2019年 | H12: =H4 -> 2020年 | I12: =I4 -> 2021年 | J12: =J4 -> 2022年 | K12: =K4 -> 2023年
B13: 差旅费
B14: 招待费
B15: 运输费
B16: 广告/宣传费
B17: 商检/报关费
B18: 检定费/检测费
B19: 工资
B20: 社保费
B21: 其他
B23: 合计 | C23: =SUM(C13:C22) -> 0 | D23: =SUM(D13:D22) -> 0 | E23: =SUM(E13:E22) -> 0 | F23: =SUM(F13:F22) -> 0 | G23: =SUM(G13:G22) -> 0 | H23: =SUM(H13:H22) -> 0 | I23: =SUM(I13:I22) -> 0 | J23: =SUM(J13:J22) -> 0 | K23: =SUM(K13:K22) -> 0
B24: 检查核对 | C24: =C23-C5 -> 0 | D24: =D23-D5 -> 0 | E24: =E23-E5 -> 0
B25: 与报表一致? | C25: =IF(ROUND(C24,0)=0,"OK","需要检查") -> OK | D25: =IF(ROUND(D24,0)=0,"OK","需要检查") -> OK | E25: =IF(ROUND(E24,0)=0,"OK","需要检查") -> OK
B26: 占收入比例 | E26: =C12&"-"&E12 -> 2016年-2018年1-6 | F26: 相关系数 | G26: 平均值 | H26: 评估取值
B27: =B13 -> 差旅费 | C27: =IF(C13,C13/C$9,"") | D27: =IF(D13,D13/D$9,"") | E27: =IF(E13,E13/E$9,"") | F27: =IF(COUNT(C27:E27)>2,CORREL(C$9:E$9,C13:E13),"") | G27: =AVERAGE(C27:E27) -> #DIV/0!
B28: =B14 -> 招待费 | C28: =IF(C14,C14/C$9,"") | D28: =IF(D14,D14/D$9,"") | E28: =IF(E14,E14/E$9,"") | F28: =IF(COUNT(C28:E28)>2,CORREL(C$9:E$9,C14:E14),"") | G28: =AVERAGE(C28:E28) -> #DIV/0!
B29: =B15 -> 运输费 | C29: =IF(C15,C15/C$9,"") | D29: =IF(D15,D15/D$9,"") | E29: =IF(E15,E15/E$9,"") | F29: =IF(COUNT(C29:E29)>2,CORREL(C$9:E$9,C15:E15),"") | G29: =AVERAGE(C29:E29) -> #DIV/0!
B30: =B16 -> 广告/宣传费 | C30: =IF(C16,C16/C$9,"") | D30: =IF(D16,D16/D$9,"") | E30: =IF(E16,E16/E$9,"") | F30: =IF(COUNT(C30:E30)>2,CORREL(C$9:E$9,C16:E16),"") | G30: =AVERAGE(C30:E30) -> #DIV/0!
B31: =B17 -> 商检/报关费 | C31: =IF(C17,C17/C$9,"") | D31: =IF(D17,D17/D$9,"") | E31: =IF(E17,E17/E$9,"") | F31: =IF(COUNT(C31:E31)>2,CORREL(C$9:E$9,C17:E17),"") | G31: =AVERAGE(C31:E31) -> #DIV/0!
B32: =B18 -> 检定费/检测费 | C32: =IF(C18,C18/C$9,"") | D32: =IF(D18,D18/D$9,"") | E32: =IF(E18,E18/E$9,"") | F32: =IF(COUNT(C32:E32)>2,CORREL(C$9:E$9,C18:E18),"") | G32: =AVERAGE(C32:E32) -> #DIV/0!
B33: =B19 -> 工资 | C33: =IF(C19,C19/C$9,"") | D33: =IF(D19,D19/D$9,"") | E33: =IF(E19,E19/E$9,"") | F33: =IF(COUNT(C33:E33)>2,CORREL(C$9:E$9,C19:E19),"") | G33: =AVERAGE(C33:E33) -> #DIV/0!
B34: =B20 -> 社保费 | C34: =IF(C20,C20/C$9,"") | D34: =IF(D20,D20/D$9,"") | E34: =IF(E20,E20/E$9,"") | F34: =IF(COUNT(C34:E34)>2,CORREL(C$9:E$9,C20:E20),"") | G34: =AVERAGE(C34:E34) -> #DIV/0!
B35: =B21 -> 其他 | C35: =IF(C21,C21/C$9,"") | D35: =IF(D21,D21/D$9,"") | E35: =IF(E21,E21/E$9,"") | F35: =IF(COUNT(C35:E35)>2,CORREL(C$9:E$9,C21:E21),"") | G35: =AVERAGE(C35:E35) -> #DIV/0!
B37: 销售费用分析
B38: 项目 | C38: =C4 -> 2016年 | D38: =D4 -> 2017年 | E38: =E4 -> 2018年1-6 | F38: =F4 -> 2018年 | G38: =G4 -> 2019年 | H38: =H4 -> 2020年 | I38: =I4 -> 2021年 | J38: =J4 -> 2022年 | K38: =K4 -> 2023年
B39: 销售费用 | C39: =C23 -> 0 | D39: =D23 -> 0 | E39: =E23 -> 0 | F39: =F23 -> 0 | G39: =G23 -> 0 | H39: =H23 -> 0 | I39: =I23 -> 0 | J39: =J23 -> 0 | K39: =K23 -> 0
B40: 占收入比 | C40: =IF(C9,C39/C9,"na") -> 0 | D40: =IF(D9,D39/D9,"na") -> 0 | E40: =IF(E9,E39/E9,"na") -> 0
B41: 销售费用 | F41: =IF(F39,F39,F40*F9) -> 0 | G41: =IF(G39,G39,G40*G9) -> 0 | H41: =IF(H39,H39,H40*H9) -> 0 | I41: =IF(I39,I39,I40*I9) -> 0 | J41: =IF(J39,J39,J40*J9) -> 0 | K41: =IF(K39,K39,K40*K9) -> 0
B42: 占收入比 | F42: =IF(F9,F41/F9,"na") -> 0 | G42: =IF(G9,G41/G9,"na") -> 0 | H42: =IF(H9,H41/H9,"na") -> 0 | I42: =IF(I9,I41/I9,"na") -> 0 | J42: =IF(J9,J41/J9,"na") -> 0 | K42: =IF(K9,K41/K9,"na") -> 0
B44: 管理费用分析（点行 "+" 号展开） | E44: 科目内容只是示例，根据具体项目改动！ | I44: 金额大、变动大的科目要分析
B45: 管理费用 | C45: =C4 -> 2016年 | D45: =D4 -> 2017年 | E45: =E4 -> 2018年1-6 | F45: =F4 -> 2018年 | G45: =G4 -> 2019年 | H45: =H4 -> 2020年 | I45: =I4 -> 2021年 | J45: =J4 -> 2022年 | K45: =K4 -> 2023年
B46: 工资及福利 | C46: 460.42472 | D46: 415.05823 | E46: 207.57171 | F46: =F9*$H$58 -> 315 | G46: =G9*$H$58 -> 346.5 | H46: =H9*$H$58 -> 374.22 | I46: =I9*$H$58 -> 392.931 | J46: =J9*$H$58 -> 404.71893 | K46: =K9*$H$58 -> 404.71893
B47: 办公差旅费用 | C47: 164.76053 | D47: 161.0297 | E47: 53.753487 | F47: =F9*$H$59 -> 121.5 | G47: =G9*$H$59 -> 133.65 | H47: =H9*$H$59 -> 144.342 | I47: =I9*$H$59 -> 151.5591 | J47: =J9*$H$59 -> 156.10587 | K47: =K9*$H$59 -> 156.10587
B48: 无形资产摊销 | C48: 2.895436 | D48: 8.042885 | E48: 4.521487 | F48: ='8摊销'!F6 -> 10.937506 | G48: ='8摊销'!G6 -> 3 | H48: ='8摊销'!H6 -> 5 | I48: ='8摊销'!I6 -> 6.5 | J48: ='8摊销'!J6 -> 6 | K48: ='8摊销'!K6 -> 6
B49: 办公房改造 | C49: 12.8232 | D49: 15.2804 | E49: 0 | F49: 10 | G49: =F49 -> 10 | H49: =G49 -> 10 | I49: =H49 -> 10 | J49: =I49 -> 10 | K49: =J49 -> 10 | L49: 预计固定支出 | M49: 13-16年办公房改造平均支出 | O49: =AVERAGE(C49:D49) -> 14.0518
B50: 其他 | C50: 27.568673 | D50: 16.574382 | E50: 3.082551 | F50: =F9*$H$62 -> 18 | G50: =G9*$H$62 -> 19.8 | H50: =H9*$H$62 -> 21.384 | I50: =I9*$H$62 -> 22.4532 | J50: =J9*$H$62 -> 23.126796 | K50: =K9*$H$62 -> 23.126796
B54: 合计 | C54: =SUM(C46:C53) -> 668.47256 | D54: =SUM(D46:D53) -> 615.9856 | E54: =SUM(E46:E53) -> 268.92924 | F54: =SUM(F46:F53) -> 475.43751 | G54: =SUM(G46:G53) -> 512.95 | H54: =SUM(H46:H53) -> 554.946 | I54: =SUM(I46:I53) -> 583.4433 | J54: =SUM(J46:J53) -> 599.9516 | K54: =SUM(K46:K53) -> 599.9516
B55: 检查核对 | C55: =C54-C6 -> 0 | D55: =D54-D6 -> 0 | E55: =E54-E6 -> 0
B56: 与报表一致? | C56: =IF(ROUND(C55,0)=0,"OK","需要检查") -> OK | D56: =IF(ROUND(D55,0)=0,"OK","需要检查") -> OK | E56: =IF(ROUND(E55,0)=0,"OK","需要检查") -> OK
B57: 占收入比例 | E57: =C45&"-"&E45 -> 2016年-2018年1-6 | F57: 相关系数 | G57: 平均值 | H57: 评估取值
B58: =B46 -> 工资及福利 | C58: =IF(C46,C46/C$9,"") -> 0.072967473 | D58: =IF(D46,D46/D$9,"") -> 0.064309414 | E58: =IF(E46,E46/E$9,"") -> 0.1003252 | F58: =IF(COUNT(C58:E58)>2,CORREL(C$9:E$9,C46:E46),"") -> 0.98046455 | G58: =AVERAGE(C58:E58) -> 0.079200695 | H58: 0.07
B59: =B47 -> 办公差旅费用 | C59: =IF(C47,C47/C$9,"") -> 0.026111021 | D59: =IF(D47,D47/D$9,"") -> 0.024950055 | E59: =IF(E47,E47/E$9,"") -> 0.025980559 | F59: =IF(COUNT(C59:E59)>2,CORREL(C$9:E$9,C47:E47),"") -> 0.99828834 | G59: =AVERAGE(C59:E59) -> 0.025680545 | H59: 0.027
B60: =B48 -> 无形资产摊销 | C60: =IF(C48,C48/C$9,"") -> 0.00045886469 | D60: =IF(D48,D48/D$9,"") -> 0.0012461703 | E60: =IF(E48,E48/E$9,"") -> 0.0021853608 | F60: =IF(COUNT(C60:E60)>2,CORREL(C$9:E$9,C48:E48),"") -> 0.23613927 | G60: =AVERAGE(C60:E60) -> 0.0012967986
B61: =B49 -> 办公房改造 | C61: =IF(C49,C49/C$9,"") -> 0.002032203 | D61: =IF(D49,D49/D$9,"") -> 0.0023675559 | E61: =IF(E49,E49/E$9,"") | F61: =IF(COUNT(C61:E61)>2,CORREL(C$9:E$9,C49:E49),"") | G61: =AVERAGE(C61:E61) -> 0.0021998794 | I61: 少于3个数据，无意义
B62: =B50 -> 其他 | C62: =IF(C50,C50/C$9,"") -> 0.0043690451 | D62: =IF(D50,D50/D$9,"") -> 0.0025680464 | E62: =IF(E50,E50/E$9,"") -> 0.0014898829 | F62: =IF(COUNT(C62:E62)>2,CORREL(C$9:E$9,C50:E50),"") -> 0.88058526 | G62: =AVERAGE(C62:E62) -> 0.0028089915 | H62: 0.004
B64: 增长比例 | G64: 平均值 | H64: 评估取值
B65: =B46 -> 工资及福利 | D65: =IF(C46,D46/C46-1,"") -> -0.098531835 | G65: =AVERAGE(C65:D65) -> -0.098531835
B66: =B47 -> 办公差旅费用 | D66: =IF(C47,D47/C47-1,"") -> -0.022643955 | E66: =IF(D17,E17/D17-1,"") | G66: =AVERAGE(C66:D66) -> -0.022643955
B67: =B48 -> 无形资产摊销 | D67: =IF(C48,D48/C48-1,"") -> 1.7777803 | E67: =IF(D18,E18/D18-1,"") | G67: =AVERAGE(C67:D67) -> 1.7777803
B68: =B49 -> 办公房改造 | D68: =IF(C49,D49/C49-1,"") -> 0.19162144 | E68: =IF(D19,E19/D19-1,"") | G68: =AVERAGE(C68:D68) -> 0.19162144
B69: =B50 -> 其他 | D69: =IF(C50,D50/C50-1,"") -> -0.39879653 | E69: =IF(D20,E20/D20-1,"") | G69: =AVERAGE(C69:D69) -> -0.39879653
B71: 管理费用分析
B72: 项目 | C72: =C4 -> 2016年 | D72: =D4 -> 2017年 | E72: =E4 -> 2018年1-6 | F72: =F4 -> 2018年 | G72: =G4 -> 2019年 | H72: =H4 -> 2020年 | I72: =I4 -> 2021年 | J72: =J4 -> 2022年 | K72: =K4 -> 2023年
B73: 管理费用 | C73: =C54 -> 668.47256 | D73: =D54 -> 615.9856 | E73: =E54 -> 268.92924 | F73: =F54 -> 475.43751 | G73: =G54 -> 512.95 | H73: =H54 -> 554.946 | I73: =I54 -> 583.4433 | J73: =J54 -> 599.9516 | K73: =K54 -> 599.9516
B74: 占收入比 | C74: =IF(C9,C73/C9,"na") -> 0.10593861 | D74: =IF(D9,D73/D9,"na") -> 0.095441241 | E74: =IF(E9,E73/E9,"na") -> 0.129981
B75: 管理费用 | F75: =IF(F73,F73,F74*F9) -> 475.43751 | G75: =IF(G73,G73,G74*G9) -> 512.95 | H75: =IF(H73,H73,H74*H9) -> 554.946 | I75: =IF(I73,I73,I74*I9) -> 583.4433 | J75: =IF(J73,J73,J74*J9) -> 599.9516 | K75: =IF(K73,K73,K74*K9) -> 599.9516
B76: 占收入比 | F76: =IF(F9,F75/F9,"na") -> 0.10565278 | G76: =IF(G9,G75/G9,"na") -> 0.10362626 | H76: =IF(H9,H75/H9,"na") -> 0.10380584 | I76: =IF(I9,I75/I9,"na") -> 0.10393945 | J76: =IF(J9,J75/J9,"na") -> 0.10376735 | K76: =IF(K9,K75/K9,"na") -> 0.10376735
B78: 研发费用分析（点行 "+" 号展开）
B79: 项目 | C79: =C88 -> 0 | D79: =D88 -> 0 | E79: =E88 -> 0 | F79: =F88 -> 0 | G79: =G88 -> 0 | H79: =H88 -> 0 | I79: =I88 -> 0 | J79: =J88 -> 0 | K79: =K88 -> 0
B80: 研发费用
B81: 占收入比 | C81: =IF(C80,C80/C9,"na") -> na | D81: =IF(D80,D80/D9,"na") -> na | E81: =IF(E80,E80/E9,"na") -> na | G81: =F81 -> 0 | H81: =G81 -> 0 | I81: =H81 -> 0 | J81: =I81 -> 0 | K81: =J81 -> 0
B82: 研发费用 | F82: =IF(F80,F80,F81*F9) -> 0 | G82: =IF(G80,G80,G81*G9) -> 0 | H82: =IF(H80,H80,H81*H9) -> 0 | I82: =IF(I80,I80,I81*I9) -> 0 | J82: =IF(J80,J80,J81*J9) -> 0 | K82: =IF(K80,K80,K81*K9) -> 0
B83: 占收入比 | F83: =IF(F9,F82/F9,"na") -> 0 | G83: =IF(G9,G82/G9,"na") -> 0 | H83: =IF(H9,H82/H9,"na") -> 0 | I83: =IF(I9,I82/I9,"na") -> 0 | J83: =IF(J9,J82/J9,"na") -> 0 | K83: =IF(K9,K82/K9,"na") -> 0
B85: 尽可能取得明细分项，同上分析。
B88: 可比公司对比分析（可选）
C89: =C4 -> 2016年 | D89: =D4 -> 2017年 | E89: =E4 -> 2018年1-6 | F89: =F105 -> 平均值
B90: 销售费用率 | C90: =C102 -> 0 | D90: =D102 -> 0 | E90: =E102 -> 0 | F90: =IF(ISERROR(AVERAGE(C90:E90)),0,AVERAGE(C90:E90)) -> 0
B91: 管理费用率 | C91: =C112 -> 0 | D91: =D112 -> 0 | E91: =E112 -> 0 | F91: =IF(ISERROR(AVERAGE(C91:E91)),0,AVERAGE(C91:E91)) -> 0
B92: 研发费用率 | C92: =C122 -> 0 | D92: =D122 -> 0 | E92: =E122 -> 0 | F92: =IF(ISERROR(AVERAGE(C92:E92)),0,AVERAGE(C92:E92)) -> 0
B93: 三费合计 | C93: =SUM(C90:C91) -> 0 | D93: =SUM(D90:D91) -> 0 | E93: =SUM(E90:E91) -> 0 | F93: =IF(ISERROR(AVERAGE(C93:E93)),0,AVERAGE(C93:E93)) -> 0
B95: 销售费用率 | C95: =C4 -> 2016年 | D95: =D4 -> 2017年 | E95: =E4 -> 2018年1-6 | F95: 平均值
B96: xx公司 | F96: =IF(ISERROR(AVERAGE(C96:E96)),0,AVERAGE(C96:E96)) -> 0
F97: =IF(ISERROR(AVERAGE(C97:E97)),0,AVERAGE(C97:E97)) -> 0
F98: =IF(ISERROR(AVERAGE(C98:E98)),0,AVERAGE(C98:E98)) -> 0
F99: =IF(ISERROR(AVERAGE(C99:E99)),0,AVERAGE(C99:E99)) -> 0
F100: =IF(ISERROR(AVERAGE(C100:E100)),0,AVERAGE(C100:E100)) -> 0
F101: =IF(ISERROR(AVERAGE(C101:E101)),0,AVERAGE(C101:E101)) -> 0
B102: 平均值 | C102: =IF(ISERROR(AVERAGE(C96:C101)),0,AVERAGE(C96:C101)) -> 0 | D102: =IF(ISERROR(AVERAGE(D96:D101)),0,AVERAGE(D96:D101)) -> 0 | E102: =IF(ISERROR(AVERAGE(E96:E101)),0,AVERAGE(E96:E101)) -> 0
B103: 中位数 | C103: =IF(ISERROR(MEDIAN(C96:C101)),0,MEDIAN(C96:C101)) -> 0 | D103: =IF(ISERROR(MEDIAN(D96:D101)),0,MEDIAN(D96:D101)) -> 0 | E103: =IF(ISERROR(MEDIAN(E96:E101)),0,MEDIAN(E96:E101)) -> 0
B105: 管理费用率 | C105: =C95 -> 2016年 | D105: =D95 -> 2017年 | E105: =E95 -> 2018年1-6 | F105: 平均值
B106: =B96 -> xx公司 | F106: =IF(ISERROR(AVERAGE(C106:E106)),0,AVERAGE(C106:E106)) -> 0
B107: =B97 -> 0 | F107: =IF(ISERROR(AVERAGE(C107:E107)),0,AVERAGE(C107:E107)) -> 0
B108: =B98 -> 0 | F108: =IF(ISERROR(AVERAGE(C108:E108)),0,AVERAGE(C108:E108)) -> 0
B109: =B99 -> 0 | F109: =IF(ISERROR(AVERAGE(C109:E109)),0,AVERAGE(C109:E109)) -> 0
B110: =B100 -> 0 | F110: =IF(ISERROR(AVERAGE(C110:E110)),0,AVERAGE(C110:E110)) -> 0
B111: =B101 -> 0 | F111: =IF(ISERROR(AVERAGE(C111:E111)),0,AVERAGE(C111:E111)) -> 0
B112: 平均值 | C112: =IF(ISERROR(AVERAGE(C106:C111)),0,AVERAGE(C106:C111)) -> 0 | D112: =IF(ISERROR(AVERAGE(D106:D111)),0,AVERAGE(D106:D111)) -> 0 | E112: =IF(ISERROR(AVERAGE(E106:E111)),0,AVERAGE(E106:E111)) -> 0
B113: 中位数 | C113: =IF(ISERROR(MEDIAN(C106:C111)),0,MEDIAN(C106:C111)) -> 0 | D113: =IF(ISERROR(MEDIAN(D106:D111)),0,MEDIAN(D106:D111)) -> 0 | E113: =IF(ISERROR(MEDIAN(E106:E111)),0,MEDIAN(E106:E111)) -> 0
B115: 研发费用率 | C115: =C105 -> 2016年 | D115: =D105 -> 2017年 | E115: =E105 -> 2018年1-6 | F115: 平均值
...

Sheet 7折旧
B1: 固定资产支出与折旧预测表
B2: ='1报表'!B11 -> 评估基准日：2018/6/30 | L2: 该工作表已保护！
B3: ='1报表'!B12 -> 被评估单位：YLSJ公司 | E3: =12-MONTH('1报表'!E5) -> 6 | F3: =F4&"剩余折摊月数" -> 2018年剩余折摊月数 | K3: 单位：万元
B4: 项目 | C4: =D4&"占比" -> 2018年1-6占比 | D4: ='3收入'!E4 -> 2018年1-6 | E4: =F4&(RIGHT(D4,1)+1)&"-12" -> 2018年7-12 | F4: ='3收入'!F4 -> 2018年 | G4: ='3收入'!G4 -> 2019年 | H4: ='3收入'!H4 -> 2020年 | I4: ='3收入'!I4 -> 2021年 | J4: ='3收入'!J4 -> 2022年 | K4: ='3收入'!K4 -> 2023年 | L4: 评估取值
B5: 生产成本中的折旧 | C5: =IF(D5,D5/D$9,"") -> 1 | D5: 20.67 | F5: =F$9*$L5 -> 43.79 | G5: =G$9*$L5 -> 56.04 | H5: =H$9*$L5 -> 57.154732 | I5: =I$9*$L5 -> 34.3 | J5: =J$9*$L5 -> 44.1 | K5: =K$9*$L5 -> 51.25 | L5: 1
B6: 销售费用中的折旧 | C6: =IF(D6,D6/D$9,"") | F6: =F$9*$L6 -> 0 | G6: =G$9*$L6 -> 0 | H6: =H$9*$L6 -> 0 | I6: =I$9*$L6 -> 0 | J6: =J$9*$L6 -> 0 | K6: =K$9*$L6 -> 0
B7: 管理费用中的折旧 | C7: =IF(D7,D7/D$9,"") | F7: =F$9*$L7 -> 0 | G7: =G$9*$L7 -> 0 | H7: =H$9*$L7 -> 0 | I7: =I$9*$L7 -> 0 | J7: =J$9*$L7 -> 0 | K7: =K$9*$L7 -> 0
B8: 研发费用中的折旧 | C8: =IF(D8,D8/D$9,"") | F8: =F$9*$L8 -> 0 | G8: =G$9*$L8 -> 0 | H8: =H$9*$L8 -> 0 | I8: =I$9*$L8 -> 0 | J8: =J$9*$L8 -> 0 | K8: =K$9*$L8 -> 0
B9: 固定资产折旧额 | C9: =SUM(C5:C8) -> 1 | D9: =SUM(D5:D8) -> 20.67 | E9: =E28+E43 -> 23.12 | F9: =D9+E9 -> 43.79 | G9: =G28+G43 -> 56.04 | H9: =H28+H43 -> 57.154732 | I9: =I28+I43 -> 34.3 | J9: =J28+J43 -> 44.1 | K9: =K28+K43 -> 51.25 | L9: =SUM(L5:L8) -> 1
B10: 固定资产支出 | E10: =E26+SUM(E37:E39) -> 49 | G10: =G26+SUM(G37:G39) -> 49 | H10: =H26+SUM(H37:H39) -> 49 | I10: =I26+SUM(I37:I39) -> 49 | J10: =J26+SUM(J37:J39) -> 49 | K10: =K26+SUM(K37:K39) -> 47
B11: 未转固资产的处理
B12: 科目 | D12: =D4 -> 2018年1-6 | E12: =E4 -> 2018年7-12 | F12: =F4 -> 2018年 | G12: =G4 -> 2019年 | H12: =H4 -> 2020年 | I12: =I4 -> 2021年 | J12: =J4 -> 2022年 | K12: =K4 -> 2023年 | L12: 折旧年限
B13: 未转固建筑物的账面值
B14: 年度转固金额
B15: 未转固设备的账面值
B16: 年度转固金额-机器
B17: 年度转固金额-车辆
B18: 年度转固金额-电子设备
B20: 房屋建筑物
B21: 数据汇总 | C21: 折旧率 | D21: =D4 -> 2018年1-6 | E21: =E4 -> 2018年7-12 | F21: =F4 -> 2018年 | G21: =G4 -> 2019年 | H21: =H4 -> 2020年 | I21: =I4 -> 2021年 | J21: =J4 -> 2022年 | K21: =K4 -> 2023年 | L21: 折旧年限
B22: 基准日已提足折旧建筑类账面原值
B23: 基准日未提足折旧建筑类账面原值
B24: 基准日建筑类账面净值
B25: 存量建筑类折旧额 | E25: =IF(D24>D23*C25/12*E3,D23*C25/12*E3,D24) -> 0 | G25: =IF((D24-E25)>D23*C25,D23*C25,D24-E25) -> 0 | H25: =IF(($D24-$E25-SUM($G25:G25))>$G25,$G25,$D24-$E25-SUM($G25:G25)) -> 0 | I25: =IF(($D24-$E25-SUM($G25:H25))>$G25,$G25,$D24-$E25-SUM($G25:H25)) -> 0 | J25: =IF(($D24-$E25-SUM($G25:I25))>$G25,$G25,$D24-$E25-SUM($G25:I25)) -> 0 | K25: =IF(($D24-$E25-SUM($G25:J25))>$G25,$G25,$D24-$E25-SUM($G25:J25)) -> 0
B26: 新增建筑物投入原值
B27: 新增建筑类折旧额 | E27: =IF($L13,E14/$L13/12*E3,0)+IF($L27,E26/$L27/12*E3,0) -> 0 | G27: =IF($L13,($E14+SUM($G14:G14))/$L13,0)+IF($L27,($E26+SUM($G26:G26))/$L27,0) -> 0 | H27: =IF($L13,($E14+SUM($G14:H14))/$L13,0)+IF($L27,($E26+SUM($G26:H26))/$L27,0) -> 0 | I27: =IF($L13,($E14+SUM($G14:I14))/$L13,0)+IF($L27,($E26+SUM($G26:I26))/$L27,0) -> 0 | J27: =IF($L13,($E14+SUM($G14:J14))/$L13,0)+IF($L27,($E26+SUM($G26:J26))/$L27,0) -> 0 | K27: =IF($L13,($E14+SUM($G14:K14))/$L13,0)+IF($L27,($E26+SUM($G26:K26))/$L27,0) -> 0
B28: 建筑类折旧额小计 | E28: =E25+E27 -> 0 | G28: =G25+G27 -> 0 | H28: =H25+H27 -> 0 | I28: =I25+I27 -> 0 | J28: =J25+J27 -> 0 | K28: =K25+K27 -> 0
B29: 期末建筑物类账面净值 | E29: =D24+E14+E26-E28 -> 0 | F29: =E29 -> 0 | G29: =F29+G14+G26-G28 -> 0 | H29: =G29+H14+H26-H28 -> 0 | I29: =H29+I14+I26-I28 -> 0 | J29: =I29+J14+J26-J28 -> 0 | K29: =J29+K14+K26-K28 -> 0
B31: 设备
B32: 项目 | C32: 折旧率 | D32: =D4 -> 2018年1-6 | E32: =E4 -> 2018年7-12 | F32: =F4 -> 2018年 | G32: =G4 -> 2019年 | H32: =H4 -> 2020年 | I32: =I4 -> 2021年 | J32: =J4 -> 2022年 | K32: =K4 -> 2023年 | L32: 折旧年限
B33: 基准日已提足折旧设备类账面原值 | D33: 0
B34: 基准日未提足折旧设备类账面原值 | D34: 451.86
B35: 基准日账面净值 | D35: 94.664732
B36: 存量设备类折旧额 | C36: 0.091488514 | E36: =IF(D35>D34*C36/12*E3,D34*C36/12*E3,D35) -> 20.67 | G36: =IF((D35-E36)>D34*C36,D34*C36,D35-E36) -> 41.34 | H36: =IF(($D35-$E36-SUM($G36:G36))>$G36,$G36,$D35-$E36-SUM($G36:G36)) -> 32.654732 | I36: =IF(($D35-$E36-SUM($G36:H36))>$G36,$G36,$D35-$E36-SUM($G36:H36)) -> 0 | J36: =IF(($D35-$E36-SUM($G36:I36))>$G36,$G36,$D35-$E36-SUM($G36:I36)) -> 0 | K36: =IF(($D35-$E36-SUM($G36:J36))>$G36,$G36,$D35-$E36-SUM($G36:J36)) -> 0
B37: 新增机器投入原值
B38: 新增车辆投入原值 | E38: 14 | G38: 14 | H38: 14 | I38: 14 | J38: 14 | K38: 12 | L38: 5
B39: 新增电子设备投入原值 | E39: 35 | G39: 35 | H39: 35 | I39: 35 | J39: 35 | K39: 35 | L39: 5
B40: 新增机器折旧额 | E40: =E55 -> 0 | G40: =G55 -> 0 | H40: =H55 -> 0 | I40: =I55 -> 0 | J40: =J55 -> 0 | K40: =K55 -> 0
B41: 新增车辆折旧额 | E41: =E64 -> 0.7 | G41: =G64 -> 4.2 | H41: =H64 -> 7 | I41: =I64 -> 9.8 | J41: =J64 -> 12.6 | K41: =K64 -> 14.5
B42: 新增电子设备折旧额 | E42: =E73 -> 1.75 | G42: =G73 -> 10.5 | H42: =H73 -> 17.5 | I42: =I73 -> 24.5 | J42: =J73 -> 31.5 | K42: =K73 -> 36.75
B43: 设备类折旧额小计 | E43: =E36+SUM(E40:E42) -> 23.12 | G43: =G36+SUM(G40:G42) -> 56.04 | H43: =H36+SUM(H40:H42) -> 57.154732 | I43: =I36+SUM(I40:I42) -> 34.3 | J43: =J36+SUM(J40:J42) -> 44.1 | K43: =K36+SUM(K40:K42) -> 51.25
B44: 期末设备类账面净值 | E44: =D35+SUM(E16:E18)+SUM(E37:E39)-E43 -> 120.54473 | F44: =E44 -> 120.54473 | G44: =F44+SUM(G16:G18)+SUM(G37:G39)-G43 -> 113.50473 | H44: =G44+SUM(H16:H18)+SUM(H37:H39)-H43 -> 105.35 | I44: =H44+SUM(I16:I18)+SUM(I37:I39)-I43 -> 120.05 | J44: =I44+SUM(J16:J18)+SUM(J37:J39)-J43 -> 124.95 | K44: =J44+SUM(K16:K18)+SUM(K37:K39)-K43 -> 120.7
B45: 基准日数据与资产负债表检查核对
B46: 固定资产 | D46: =IF(ROUND(D24+D35-'2报表调整'!G32,-1),"数据不一致","OK") -> OK
B47: 在建工程 | D47: =IF(ROUND(D13+D15+'8摊销'!D13-'2报表调整'!G33,-1),"数据不一致","OK") -> OK
B48: 年度 | C48: 机器折旧额自动计算过程 | E48: =E4 -> 2018年7-12 | F48: =F4 -> 2018年 | G48: =G4 -> 2019年 | H48: =H4 -> 2020年 | I48: =I4 -> 2021年 | J48: =J4 -> 2022年 | K48: =K4 -> 2023年
B49: =E48 -> 2018年7-12 | E49: =IF(L37,(E16+E37)/L37/12*E3/2,0) -> 0 | G49: =IF(E49,IF((E16+E37-E49)>(E16+E37)/L37,(E16+E37)/L37,E16+E37-E49),0) -> 0 | H49: =IF(($E16+$E37-$E49-SUM($G49:G49))>$G49,$G49,$E16+$E37-$E49-SUM($G49:G49)) -> 0 | I49: =IF(($E16+$E37-$E49-SUM($G49:H49))>$G49,$G49,$E16+$E37-$E49-SUM($G49:H49)) -> 0 | J49: =IF(($E16+$E37-$E49-SUM($G49:I49))>$G49,$G49,$E16+$E37-$E49-SUM($G49:I49)) -> 0 | K49: =IF(($E16+$E37-$E49-SUM($G49:J49))>$G49,$G49,$E16+$E37-$E49-SUM($G49:J49)) -> 0
B50: =G48 -> 2019年 | G50: =IF(L37,(G16+G37)/L37/2,0) -> 0 | H50: =IF(L37,(G16+G37)/L37,0) -> 0 | I50: =IF(($G16+$G37-SUM($G50:H50))>$H50,$H50,$G16+$G37-SUM($G50:H50)) -> 0 | J50: =IF(($G16+$G37-SUM($G50:I50))>$H50,$H50,$G16+$G37-SUM($G50:I50)) -> 0 | K50: =IF(($G16+$G37-SUM($G50:J50))>$H50,$H50,$G16+$G37-SUM($G50:J50)) -> 0
B51: =H48 -> 2020年 | H51: =IF(L37,(H16+H37)/L37/2,0) -> 0 | I51: =IF(L37,(H16+H37)/L37,0) -> 0 | J51: =IF(($H16+$H37-SUM($H51:I51))>$I51,$I51,$H16+$H37-SUM($H51:I51)) -> 0 | K51: =IF(($H16+$H37-SUM($H51:J51))>$I51,$I51,$H16+$H37-SUM($H51:J51)) -> 0
B52: =I48 -> 2021年 | I52: =IF(L37,(I16+I37)/L37/2,0) -> 0 | J52: =IF(L37,(I16+I37)/L37,0) -> 0 | K52: =IF(($I16+$I37-SUM($I52:J52))>$J52,$J52,$I16+$I37-SUM($I52:J52)) -> 0
B53: =J48 -> 2022年 | J53: =IF(L37,(J16+J37)/L37/2,0) -> 0 | K53: =IF(L37,(J16+J37)/L37,0) -> 0
B54: =K48 -> 2023年 | K54: =IF(L37,(K16+K37)/L37/2,0) -> 0
B55: 合计 | E55: =SUM(E49:E54) -> 0 | G55: =SUM(G49:G54) -> 0 | H55: =SUM(H49:H54) -> 0 | I55: =SUM(I49:I54) -> 0 | J55: =SUM(J49:J54) -> 0 | K55: =SUM(K49:K54) -> 0
B57: 年度 | C57: 车辆折旧额自动计算过程 | E57: =E48 -> 2018年7-12 | F57: =F48 -> 2018年 | G57: =G48 -> 2019年 | H57: =H48 -> 2020年 | I57: =I48 -> 2021年 | J57: =J48 -> 2022年 | K57: =K48 -> 2023年
B58: =E57 -> 2018年7-12 | E58: =IF(L38,(E17+E38)/L38/12*E3/2,0) -> 0.7 | G58: =IF(L38,IF((E17+E38-E58)>(E17+E38)/L38,(E17+E38)/L38,E17+E38-E58),0) -> 2.8 | H58: =IF(($E17+$E38-$E58-SUM($G58:G58))>$G58,$G58,$E17+$E38-$E58-SUM($G58:G58)) -> 2.8 | I58: =IF(($E17+$E38-$E58-SUM($G58:H58))>$G58,$G58,$E17+$E38-$E58-SUM($G58:H58)) -> 2.8 | J58: =IF(($E17+$E38-$E58-SUM($G58:I58))>$G58,$G58,$E17+$E38-$E58-SUM($G58:I58)) -> 2.8 | K58: =IF(($E17+$E38-$E58-SUM($G58:J58))>$G58,$G58,$E17+$E38-$E58-SUM($G58:J58)) -> 2.1
B59: =G57 -> 2019年 | G59: =IF(L38,(G17+G38)/L38/2,0) -> 1.4 | H59: =IF(L38,(G17+G38)/L38,0) -> 2.8 | I59: =IF(($G17+$G38-SUM($G59:H59))>$H59,$H59,$G17+$G38-SUM($G59:H59)) -> 2.8 | J59: =IF(($G17+$G38-SUM($G59:I59))>$H59,$H59,$G17+$G38-SUM($G59:I59)) -> 2.8 | K59: =IF(($G17+$G38-SUM($G59:J59))>$H59,$H59,$G17+$G38-SUM($G59:J59)) -> 2.8
B60: =H57 -> 2020年 | H60: =IF(L38,(H17+H38)/L38/2,0) -> 1.4 | I60: =IF(L38,(H17+H38)/L38,0) -> 2.8 | J60: =IF(($H17+$H38-SUM($H60:I60))>$I60,$I60,$H17+$H38-SUM($H60:I60)) -> 2.8 | K60: =IF(($H17+$H38-SUM($H60:J60))>$I60,$I60,$H17+$H38-SUM($H60:J60)) -> 2.8
B61: =I57 -> 2021年 | I61: =IF(L38,(I17+I38)/L38/2,0) -> 1.4 | J61: =IF(L38,(I17+I38)/L38,0) -> 2.8 | K61: =IF(($I17+$I38-SUM($I61:J61))>$J61,$J61,$I17+$I38-SUM($I61:J61)) -> 2.8
B62: =J57 -> 2022年 | J62: =IF(L38,(J17+J38)/L38/2,0) -> 1.4 | K62: =IF(L38,(J17+J38)/L38,0) -> 2.8
B63: =K57 -> 2023年 | K63: =IF(L38,(K17+K38)/L38/2,0) -> 1.2
B64: 合计 | E64: =SUM(E58:E63) -> 0.7 | G64: =SUM(G58:G63) -> 4.2 | H64: =SUM(H58:H63) -> 7 | I64: =SUM(I58:I63) -> 9.8 | J64: =SUM(J58:J63) -> 12.6 | K64: =SUM(K58:K63) -> 14.5
B66: 年度 | C66: 电子设备折旧额自动计算过程 | E66: =E48 -> 2018年7-12 | F66: =F48 -> 2018年 | G66: =G48 -> 2019年 | H66: =H48 -> 2020年 | I66: =I48 -> 2021年 | J66: =J48 -> 2022年 | K66: =K48 -> 2023年
B67: =E66 -> 2018年7-12 | E67: =IF(L39,(E18+E39)/L39/12*E3/2,0) -> 1.75 | G67: =IF(L39,IF((E18+E39-E67)>(E18+E39)/L39,(E18+E39)/L39,E18+E39-E67),0) -> 7 | H67: =IF(($E18+$E39-$E67-SUM($G67:G67))>$G67,$G67,$E18+$E39-$E67-SUM($G67:G67)) -> 7 | I67: =IF(($E18+$E39-$E67-SUM($G67:H67))>$G67,$G67,$E18+$E39-$E67-SUM($G67:H67)) -> 7 | J67: =IF(($E18+$E39-$E67-SUM($G67:I67))>$G67,$G67,$E18+$E39-$E67-SUM($G67:I67)) -> 7 | K67: =IF(($E18+$E39-$E67-SUM($G67:J67))>$G67,$G67,$E18+$E39-$E67-SUM($G67:J67)) -> 5.25
B68: =G66 -> 2019年 | G68: =IF(L39,(G18+G39)/L39/2,0) -> 3.5 | H68: =IF(L39,(G18+G39)/L39,0) -> 7 | I68: =IF(($G18+$G39-SUM($G68:H68))>$H68,$H68,$G18+$G39-SUM($G68:H68)) -> 7 | J68: =IF(($G18+$G39-SUM($G68:I68))>$H68,$H68,$G18+$G39-SUM($G68:I68)) -> 7 | K68: =IF(($G18+$G39-SUM($G68:J68))>$H68,$H68,$G18+$G39-SUM($G68:J68)) -> 7
B69: =H66 -> 2020年 | H69: =IF(L39,(H18+H39)/L39/2,0) -> 3.5 | I69: =IF(L39,(H18+H39)/L39,0) -> 7 | J69: =IF(($H18+$H39-SUM($H69:I69))>$I69,$I69,$H18+$H39-SUM($H69:I69)) -> 7 | K69: =IF(($H18+$H39-SUM($H69:J69))>$I69,$I69,$H18+$H39-SUM($H69:J69)) -> 7
B70: =I66 -> 2021年 | I70: =IF(L39,(I18+I39)/L39/2,0) -> 3.5 | J70: =IF(L39,(I18+I39)/L39,0) -> 7 | K70: =IF(($I18+$I39-SUM($I70:J70))>$J70,$J70,$I18+$I39-SUM($I70:J70)) -> 7
B71: =J66 -> 2022年 | J71: =IF(L39,(J18+J39)/L39/2,0) -> 3.5 | K71: =IF(L39,(J18+J39)/L39,0) -> 7
B72: =K66 -> 2023年 | K72: =IF(L39,(K18+K39)/L39/2,0) -> 3.5
B73: 合计 | E73: =SUM(E67:E72) -> 1.75 | G73: =SUM(G67:G72) -> 10.5 | H73: =SUM(H67:H72) -> 17.5 | I73: =SUM(I67:I72) -> 24.5 | J73: =SUM(J67:J72) -> 31.5 | K73: =SUM(K67:K72) -> 36.75
B75: 固定资产投入分析
C76: 建筑类 | D76: 设备类
B77: =E4&"账面净值" -> 2018年7-12账面净值 | C77: =D24 -> 0 | D77: =D35 -> 94.664732
B78: =E4&"资产负债表中已计入" -> 2018年7-12资产负债表中已计入 | C78: =D13 -> 0 | D78: =D15 -> 0
B79: =F4&"尚需要再投入" -> 2018年尚需要再投入 | C79: =E26 -> 0 | D79: =SUM(E37:E39) -> 49
B80: 小计 | C80: =SUM(C77:C79) -> 0 | D80: =SUM(D77:D79) -> 143.66473

Sheet 8摊销
B1: 长摊和无形资产支出与摊销预测表
B2: ='1报表'!B11 -> 评估基准日：2018/6/30 | M2: 该工作表已保护！
B3: ='1报表'!B12 -> 被评估单位：YLSJ公司 | E3: ='7折旧'!E3 -> 6 | F3: ='7折旧'!F3 -> 2018年剩余折摊月数 | K3: 单位：万元
B4: 数据汇总 | D4: ='3收入'!E4 -> 2018年1-6 | E4: =F4&(RIGHT(D4,1)+1)&"-12" -> 2018年7-12 | F4: ='3收入'!F4 -> 2018年 | G4: ='3收入'!G4 -> 2019年 | H4: ='3收入'!H4 -> 2020年 | I4: ='3收入'!I4 -> 2021年 | J4: ='3收入'!J4 -> 2022年 | K4: ='3收入'!K4 -> 2023年
B5: 长期待摊费用摊销 | D5: =D52 -> 0 | E5: =E52 -> 0 | F5: =D5+E5 -> 0 | G5: =G52 -> 0 | H5: =H52 -> 0 | I5: =I52 -> 0 | J5: =J52 -> 0 | K5: =K52 -> 0
B6: 无形资产摊销 | D6: =D25+D34 -> 4.521487 | E6: =E25+E34 -> 6.416019 | F6: =D6+E6 -> 10.937506 | G6: =G25+G34 -> 3 | H6: =H25+H34 -> 5 | I6: =I25+I34 -> 6.5 | J6: =J25+J34 -> 6 | K6: =K25+K34 -> 6
B7: 摊销合计 | E7: =SUM(E5:E6) -> 6.416019 | F7: =SUM(F5:F6) -> 10.937506 | G7: =SUM(G5:G6) -> 3 | H7: =SUM(H5:H6) -> 5 | I7: =SUM(I5:I6) -> 6.5 | J7: =SUM(J5:J6) -> 6 | K7: =SUM(K5:K6) -> 6
B8: 长摊资产支出 | E8: =E50 -> 0 | G8: =G50 -> 0 | H8: =H50 -> 0 | I8: =I50 -> 0 | J8: =J50 -> 0 | K8: =K50 -> 0
B9: 无形资产支出 | E9: =E23+E32 -> 6 | G9: =G23+G32 -> 6 | H9: =H23+H32 -> 6 | I9: =I23+I32 -> 6 | J9: =J23+J32 -> 6 | K9: =K23+K32 -> 6
B10: 长摊和无形资产支出 | E10: =SUM(E8:E9) -> 6 | G10: =SUM(G8:G9) -> 6 | H10: =SUM(H8:H9) -> 6 | I10: =SUM(I8:I9) -> 6 | J10: =SUM(J8:J9) -> 6 | K10: =SUM(K8:K9) -> 6
B11: 未资本化无形资产的处理
B12: 科目 | C12: 摊销年限 | D12: =D4 -> 2018年1-6 | E12: =E4 -> 2018年7-12 | F12: =F4 -> 2018年 | G12: =G4 -> 2019年 | H12: =H4 -> 2020年 | I12: =I4 -> 2021年 | J12: =J4 -> 2022年 | K12: =K4 -> 2023年
B13: 未资本化的土地
B14: 年度资本化金额
B15: 未资本化的无形资产 | D15: ='2报表调整'!G37 -> 0
B16: 年度资本化金额
B18: 土地使用权
B19: 项目 | C19: 摊销年限 | D19: =D4 -> 2018年1-6 | E19: =E4 -> 2018年7-12 | F19: =F4 -> 2018年 | G19: =G4 -> 2019年 | H19: =H4 -> 2020年 | I19: =I4 -> 2021年 | J19: =J4 -> 2022年 | K19: =K4 -> 2023年
B20: 基准日土地账面原值
B21: 基准日土地账面净值
B22: 存量土地摊销额 | E22: =IF(C22,IF(D21>D20/C22/12*E3,D20/C22/12*E3,D21),0) -> 0 | G22: =IF(C22,IF((D21-E22)>D20/C22,D20/C22,D21-E22),0) -> 0 | H22: =IF(($D21-$E22-SUM($G22:G22))>$G22,$G22,$D21-$E22-SUM($G22:G22)) -> 0 | I22: =IF(($D21-$E22-SUM($G22:H22))>$G22,$G22,$D21-$E22-SUM($G22:H22)) -> 0 | J22: =IF(($D21-$E22-SUM($G22:I22))>$G22,$G22,$D21-$E22-SUM($G22:I22)) -> 0 | K22: =IF(($D21-$E22-SUM($G22:J22))>$G22,$G22,$D21-$E22-SUM($G22:J22)) -> 0
B23: 新增土地投入原值
B24: 新增土地摊销额 | E24: =IF($C13,E14/$C13/12*E3,0)+IF($C24,E23/$C24/12*E3,0) -> 0 | G24: =IF($C13,($E14+SUM($G14:G14))/$C13,0)+IF($C24,($E23+SUM($G23:G23))/$C24,0) -> 0 | H24: =IF($C13,($E14+SUM($G14:H14))/$C13,0)+IF($C24,($E23+SUM($G23:H23))/$C24,0) -> 0 | I24: =IF($C13,($E14+SUM($G14:I14))/$C13,0)+IF($C24,($E23+SUM($G23:I23))/$C24,0) -> 0 | J24: =IF($C13,($E14+SUM($G14:J14))/$C13,0)+IF($C24,($E23+SUM($G23:J23))/$C24,0) -> 0 | K24: =IF($C13,($E14+SUM($G14:K14))/$C13,0)+IF($C24,($E23+SUM($G23:K23))/$C24,0) -> 0
B25: 土地摊销额小计 | D25: =D22+D24 -> 0 | E25: =E22+E24 -> 0 | F25: =D25+E25 -> 0 | G25: =G22+G24 -> 0 | H25: =H22+H24 -> 0 | I25: =I22+I24 -> 0 | J25: =J22+J24 -> 0 | K25: =K22+K24 -> 0
B26: 土地使用权账面净值 | E26: =D21+E14+E23-E25 -> 0 | F26: =E26 -> 0 | G26: =F26+G14+G23-G25 -> 0 | H26: =G26+H14+H23-H25 -> 0 | I26: =H26+I14+I23-I25 -> 0 | J26: =I26+J14+J23-J25 -> 0 | K26: =J26+K14+K23-K25 -> 0
B27: 其他无形资产
B28: 项目 | C28: 摊销年限 | D28: =D19 -> 2018年1-6 | E28: =E19 -> 2018年7-12 | F28: =F19 -> 2018年 | G28: =G19 -> 2019年 | H28: =H19 -> 2020年 | I28: =I19 -> 2021年 | J28: =J19 -> 2022年 | K28: =K19 -> 2023年
B29: 基准日其他无形资产账面原值 | D29: 125.66642
B30: 基准日其他无形资产账面净值 | D30: 5.916019
B31: 存量其他无形资产摊销额 | C31: 3 | D31: 4.521487 | E31: =IF(C31,IF(D30>D29/C31/12*E3,D29/C31/12*E3,D30),0) -> 5.916019 | G31: =IF(C31,IF((D30-E31)>D29/C31,D29/C31,D30-E31),0) -> 0 | H31: =IF(($D30-$E31-SUM($G31:G31))>$G31,$G31,$D30-$E31-SUM($G31:G31)) -> 0 | I31: =IF(($D30-$E31-SUM($G31:H31))>$G31,$G31,$D30-$E31-SUM($G31:H31)) -> 0 | J31: =IF(($D30-$E31-SUM($G31:I31))>$G31,$G31,$D30-$E31-SUM($G31:I31)) -> 0 | K31: =IF(($D30-$E31-SUM($G31:J31))>$G31,$G31,$D30-$E31-SUM($G31:J31)) -> 0
B32: 新增技术类无形资产投入原值 | C32: 3 | E32: 6 | G32: 6 | H32: 6 | I32: 6 | J32: 6 | K32: 6
B33: 新增无形资产摊销额 | E33: =E44 -> 0.5 | G33: =G44 -> 3 | H33: =H44 -> 5 | I33: =I44 -> 6.5 | J33: =J44 -> 6 | K33: =K44 -> 6
B34: 无形资产摊销额小计 | D34: =D31+D33 -> 4.521487 | E34: =E31+E33 -> 6.416019 | G34: =G31+G33 -> 3 | H34: =H31+H33 -> 5 | I34: =I31+I33 -> 6.5 | J34: =J31+J33 -> 6 | K34: =K31+K33 -> 6
B35: 其他无形资产账面净值 | E35: =D30+E16+E32-E33 -> 11.416019 | F35: =E35 -> 11.416019 | G35: =F35+G16+G32-G33 -> 14.416019 | H35: =G35+H16+H32-H33 -> 15.416019 | I35: =H35+I16+I32-I33 -> 14.916019 | J35: =I35+J16+J32-J33 -> 14.916019 | K35: =J35+K16+K32-K33 -> 14.916019
B37: 年度 | E37: =E28 -> 2018年7-12 | F37: =F28 -> 2018年 | G37: =G28 -> 2019年 | H37: =H28 -> 2020年 | I37: =I28 -> 2021年 | J37: =J28 -> 2022年 | K37: =K28 -> 2023年
B38: =E37 -> 2018年7-12 | E38: =IF(C32,(E16+E32)/C32/12*E3/2,0) -> 0.5 | G38: =IF(C32,IF((E16+E32-E38)>(E16+E32)/C32,(E16+E32)/C32,E16+E32-E38),0) -> 2 | H38: =IF(($E16+$E32-$E38-SUM($G38:G38))>$G38,$G38,$E16+$E32-$E38-SUM($G38:G38)) -> 2 | I38: =IF(($E16+$E32-$E38-SUM($G38:H38))>$G38,$G38,$E16+$E32-$E38-SUM($G38:H38)) -> 1.5 | J38: =IF(($E16+$E32-$E38-SUM($G38:I38))>$G38,$G38,$E16+$E32-$E38-SUM($G38:I38)) -> 0 | K38: =IF(($E16+$E32-$E38-SUM($G38:J38))>$G38,$G38,$E16+$E32-$E38-SUM($G38:J38)) -> 0
B39: =G37 -> 2019年 | C39: 技术无形资产摊销额自动计算过程 | G39: =IF(C32,(G16+G32)/C32/2,0) -> 1 | H39: =IF(C32,(G16+G32)/C32,0) -> 2 | I39: =IF(($G16+$G32-SUM($G39:H39))>$H39,$H39,$G16+$G32-SUM($G39:H39)) -> 2 | J39: =IF(($G16+$G32-SUM($G39:I39))>$H39,$H39,$G16+$G32-SUM($G39:I39)) -> 1 | K39: =IF(($G16+$G32-SUM($G39:J39))>$H39,$H39,$G16+$G32-SUM($G39:J39)) -> 0
B40: =H37 -> 2020年 | H40: =IF(C32,(H16+H32)/C32/2,0) -> 1 | I40: =IF(C32,(H16+H32)/C32,0) -> 2 | J40: =IF(($H16+$H32-SUM($H40:I40))>$I40,$I40,$H16+$H32-SUM($H40:I40)) -> 2 | K40: =IF(($H16+$H32-SUM($H40:J40))>$I40,$I40,$H16+$H32-SUM($H40:J40)) -> 1
B41: =I37 -> 2021年 | I41: =IF(C32,(I16+I32)/C32/2,0) -> 1 | J41: =IF(C32,(I16+I32)/C32,0) -> 2 | K41: =IF(($I16+$I32-SUM($I41:J41))>$J41,$J41,$I16+$I32-SUM($I41:J41)) -> 2
B42: =J37 -> 2022年 | J42: =IF(C32,(J16+J32)/C32/2,0) -> 1 | K42: =IF(C32,(J16+J32)/C32,0) -> 2
B43: =K37 -> 2023年 | K43: =IF(C32,(K16+K32)/C32/2,0) -> 1
B44: 合计 | E44: =SUM(E38:E43) -> 0.5 | G44: =SUM(G38:G43) -> 3 | H44: =SUM(H38:H43) -> 5 | I44: =SUM(I38:I43) -> 6.5 | J44: =SUM(J38:J43) -> 6 | K44: =SUM(K38:K43) -> 6
B45: 长期待摊费用
B46: 项目 | C46: 摊销年限 | D46: =D4 -> 2018年1-6 | E46: =E4 -> 2018年7-12 | F46: =F4 -> 2018年 | G46: =G4 -> 2019年 | H46: =H4 -> 2020年 | I46: =I4 -> 2021年 | J46: =J4 -> 2022年 | K46: =K4 -> 2023年
B47: 基准日长摊费用原值
B48: 基准日长摊费用净值 | D48: ='2报表调整'!G39 -> 0
B49: 存量长期费用摊销额 | E49: =IF(C49,IF(D48>D47/C49/12*E3,D47/C49/12*E3,D48),0) -> 0 | G49: =IF(C49,IF((D48-E49)>D47/C49,D47/C49,D48-E49),0) -> 0 | H49: =IF(($D48-$E49-SUM($G49:G49))>$G49,$G49,$D48-$E49-SUM($G49:G49)) -> 0 | I49: =IF(($D48-$E49-SUM($G49:H49))>$G49,$G49,$D48-$E49-SUM($G49:H49)) -> 0 | J49: =IF(($D48-$E49-SUM($G49:I49))>$G49,$G49,$D48-$E49-SUM($G49:I49)) -> 0 | K49: =IF(($D48-$E49-SUM($G49:J49))>$G49,$G49,$D48-$E49-SUM($G49:J49)) -> 0
B50: 新增长摊资产投入原值
B51: 新增长摊费用摊销额 | E51: =E62 -> 0 | G51: =G62 -> 0 | H51: =H62 -> 0 | I51: =I62 -> 0 | J51: =J62 -> 0 | K51: =K62 -> 0
B52: 长期费用摊销额小计 | D52: =D49+D51 -> 0 | E52: =E49+E51 -> 0 | G52: =G49+G51 -> 0 | H52: =H49+H51 -> 0 | I52: =I49+I51 -> 0 | J52: =J49+J51 -> 0 | K52: =K49+K51 -> 0
B53: 长期待摊费用账面净值 | E53: =D48+E50-E52 -> 0 | F53: =E53 -> 0 | G53: =F53+G50-G52 -> 0 | H53: =G53+H50-H52 -> 0 | I53: =H53+I50-I52 -> 0 | J53: =I53+J50-J52 -> 0 | K53: =J53+K50-K52 -> 0
B55: 年度 | E55: =E46 -> 2018年7-12 | F55: =F46 -> 2018年 | G55: =G46 -> 2019年 | H55: =H46 -> 2020年 | I55: =I46 -> 2021年 | J55: =J46 -> 2022年 | K55: =K46 -> 2023年
B56: =E55 -> 2018年7-12 | E56: =IF(C50,E50/C50/12*E3,0) -> 0 | G56: =IF(C50,IF((E50-E56)>E50/C50,E50/C50,E50-E56),0) -> 0 | H56: =IF(($E50-$E56-SUM($G56:G56))>$G56,$G56,$E50-$E56-SUM($G56:G56)) -> 0 | I56: =IF(($E50-$E56-SUM($G56:H56))>$G56,$G56,$E50-$E56-SUM($G56:H56)) -> 0 | J56: =IF(($E50-$E56-SUM($G56:I56))>$G56,$G56,$E50-$E56-SUM($G56:I56)) -> 0 | K56: =IF(($E50-$E56-SUM($G56:J56))>$G56,$G56,$E50-$E56-SUM($G56:J56)) -> 0
B57: =G55 -> 2019年 | C57: 长摊资产摊销额自动计算过程 | G57: =IF(C50,G50/C50,0) -> 0 | H57: =IF(($G50-SUM($G57:G57))>$G57,$G57,$G50-SUM($G57:G57)) -> 0 | I57: =IF(($G50-SUM($G57:H57))>$G57,$G57,$G50-SUM($G57:H57)) -> 0 | J57: =IF(($G50-SUM($G57:I57))>$G57,$G57,$G50-SUM($G57:I57)) -> 0 | K57: =IF(($G50-SUM($G57:J57))>$G57,$G57,$G50-SUM($G57:J57)) -> 0
B58: =H55 -> 2020年 | H58: =IF(C50,H50/C50,0) -> 0 | I58: =IF(($H50-SUM($H58:H58))>$H58,$H58,$H50-SUM($H58:H58)) -> 0 | J58: =IF(($H50-SUM($H58:I58))>$H58,$H58,$H50-SUM($H58:I58)) -> 0 | K58: =IF(($H50-SUM($H58:J58))>$H58,$H58,$H50-SUM($H58:J58)) -> 0
B59: =I55 -> 2021年 | I59: =IF(C50,I50/C50,0) -> 0 | J59: =IF(($I50-SUM($I59:I59))>$I59,$I59,$I50-SUM($I59:I59)) -> 0 | K59: =IF(($I50-SUM($I59:J59))>$I59,$I59,$I50-SUM($I59:J59)) -> 0
B60: =J55 -> 2022年 | J60: =IF(C50,J50/C50,0) -> 0 | K60: =IF(($J50-SUM($J60:J60))>$J60,$J60,$J50-SUM($J60:J60)) -> 0
B61: =K55 -> 2023年 | K61: =IF(C50,K50/C50,0) -> 0
B62: 合计 | E62: =SUM(E56:E61) -> 0 | G62: =SUM(G56:G61) -> 0 | H62: =SUM(H56:H61) -> 0 | I62: =SUM(I56:I61) -> 0 | J62: =SUM(J56:J61) -> 0 | K62: =SUM(K56:K61) -> 0
B64: 基准日数据与资产负债表检查核对
B65: 在建工程 | D65: =IF(ROUND(D13+'7折旧'!D13+'7折旧'!D15-'2报表调整'!G33,-1),"数据不一致","OK") -> OK
B66: 无形资产 | D66: =IF(ROUND(D21+D30-'2报表调整'!G36,-1),"数据不一致","OK") -> OK
B67: 开发支出 | D67: =IF(D15-'2报表调整'!G37,"数据不一致","OK") -> OK
B68: 长期待摊费用 | D68: =IF(D48-'2报表调整'!G39,"数据不一致","OK") -> OK

Sheet 9溢余现金
B1: 经营最低保有现金分析表
B2: ='1报表'!B11 -> 评估基准日：2018/6/30
B3: ='1报表'!B12 -> 被评估单位：YLSJ公司 | K3: 单位：万元
B4: 项目 | C4: ='3收入'!C4 -> 2016年 | D4: ='3收入'!D4 -> 2017年 | E4: ='3收入'!E4 -> 2018年1-6 | F4: ='3收入'!F4 -> 2018年 | G4: ='3收入'!G4 -> 2019年 | H4: ='3收入'!H4 -> 2020年 | I4: ='3收入'!I4 -> 2021年 | J4: ='3收入'!J4 -> 2022年 | K4: ='3收入'!K4 -> 2023年
B5: 生产成本的人工费用 | C5: ='4成本'!C70+'4成本'!C76 -> 2782.3618 | D5: ='4成本'!D70+'4成本'!D76 -> 3300.8299 | E5: ='4成本'!E70+'4成本'!E76 -> 1646.5653 | F5: ='4成本'!F70+'4成本'!F76 -> 2160 | G5: ='4成本'!G70+'4成本'!G76 -> 2376 | H5: ='4成本'!H70+'4成本'!H76 -> 2566.08 | I5: ='4成本'!I70+'4成本'!I76 -> 2694.384 | J5: ='4成本'!J70+'4成本'!J76 -> 2775.2155 | K5: ='4成本'!K70+'4成本'!K76 -> 2775.2155 | L5: 还要加上办公差旅费用
B6: 营业税金及附加 | C6: ='5税金'!C5 -> 32.988746 | D6: ='5税金'!D5 -> 28.542702 | E6: ='5税金'!E5 -> 19.638479 | F6: ='5税金'!F5 -> 22.5 | G6: ='5税金'!G5 -> 24.75 | H6: ='5税金'!H5 -> 26.73 | I6: ='5税金'!I5 -> 28.0665 | J6: ='5税金'!J5 -> 28.908495 | K6: ='5税金'!K5 -> 28.908495
B7: 销售费用 | C7: ='6销管'!C5 -> 0 | D7: ='6销管'!D5 -> 0 | E7: ='6销管'!E5 -> 0 | F7: ='6销管'!F5 -> 0 | G7: ='6销管'!G5 -> 0 | H7: ='6销管'!H5 -> 0 | I7: ='6销管'!I5 -> 0 | J7: ='6销管'!J5 -> 0 | K7: ='6销管'!K5 -> 0
B8: 管理费用 | C8: ='6销管'!C6 -> 668.47256 | D8: ='6销管'!D6 -> 615.9856 | E8: ='6销管'!E6 -> 268.92924 | F8: ='6销管'!F6 -> 475.43751 | G8: ='6销管'!G6 -> 512.95 | H8: ='6销管'!H6 -> 554.946 | I8: ='6销管'!I6 -> 583.4433 | J8: ='6销管'!J6 -> 599.9516 | K8: ='6销管'!K6 -> 599.9516
B9: 研发费用 | C9: ='6销管'!C7 -> 0 | D9: ='6销管'!D7 -> 0 | E9: ='6销管'!E7 -> 0 | F9: ='6销管'!F7 -> 0 | G9: ='6销管'!G7 -> 0 | H9: ='6销管'!H7 -> 0 | I9: ='6销管'!I7 -> 0 | J9: ='6销管'!J7 -> 0 | K9: ='6销管'!K7 -> 0
B10: 财务费用中的利息支出 | C10: ='11财务费用'!C18 -> 0.473709 | D10: ='11财务费用'!D18 -> 0.956799 | E10: ='11财务费用'!E18 -> 0.0238 | F10: ='11财务费用'!F18 -> 0 | G10: ='11财务费用'!G18 -> 0 | H10: ='11财务费用'!H18 -> 0 | I10: ='11财务费用'!I18 -> 0 | J10: ='11财务费用'!J18 -> 0 | K10: ='11财务费用'!K18 -> 0
B11: 减：销售费用中折旧与摊销
B12: 减：管理费用中折旧与摊销 | C12: ='6销管'!C48 -> 2.895436 | D12: ='6销管'!D48 -> 8.042885 | E12: ='6销管'!E48 -> 4.521487 | F12: ='6销管'!F48 -> 10.937506 | G12: ='6销管'!G48 -> 3 | H12: ='6销管'!H48 -> 5 | I12: ='6销管'!I48 -> 6.5 | J12: ='6销管'!J48 -> 6 | K12: ='6销管'!K48 -> 6
B13: 减：研发费用中折旧与摊销
B14: 估计的付现成本合计 | C14: =SUM(C5:C10)-SUM(C11:C13) -> 3481.4014 | D14: =SUM(D5:D10)-SUM(D11:D13) -> 3938.2721 | E14: =SUM(E5:E10)-SUM(E11:E13) -> 1930.6353 | F14: =SUM(F5:F10)-SUM(F11:F13) -> 2647 | G14: =SUM(G5:G10)-SUM(G11:G13) -> 2910.7 | H14: =SUM(H5:H10)-SUM(H11:H13) -> 3142.756 | I14: =SUM(I5:I10)-SUM(I11:I13) -> 3299.3938 | J14: =SUM(J5:J10)-SUM(J11:J13) -> 3398.0756 | K14: =SUM(K5:K10)-SUM(K11:K13) -> 3398.0756
B15: 月数 | C15: 12 | D15: 12 | E15: =MONTH('1报表'!E5) -> 6 | F15: 12 | G15: 12 | H15: 12 | I15: 12 | J15: 12 | K15: 12
B16: 月均付现成本 | C16: =C14/C15 -> 290.11678 | D16: =D14/D15 -> 328.18934 | E16: =E14/E15 -> 321.77255 | F16: =F14/F15 -> 220.58333 | G16: =G14/G15 -> 242.55833 | H16: =H14/H15 -> 261.89633 | I16: =I14/I15 -> 274.94948 | J16: =J14/J15 -> 283.17297 | K16: =K14/K15 -> 283.17297
B17: 保有现金系数(月） | C17: =D17 -> 1 | D17: =E17 -> 1 | E17: 1 | F17: =E17 -> 1 | G17: =F17 -> 1 | H17: =G17 -> 1 | I17: =H17 -> 1 | J17: =I17 -> 1 | K17: =J17 -> 1 | L17: 一般取1，取其他数据应结合行业特点说明
B18: 限制用途现金 | C18: 31.161043 | D18: 31.278408 | E18: 31.315556 | F18: =E18 -> 31.315556 | G18: =F18 -> 31.315556 | H18: =G18 -> 31.315556 | I18: =H18 -> 31.315556 | J18: =I18 -> 31.315556 | K18: =J18 -> 31.315556 | L18: 职工房款和职工住房维修基金
B19: 经营最低保有现金测算 | C19: =MIN(C16*C17,C23)+C18 -> 321.27782 | D19: =MIN(D16*D17,D23)+D18 -> 359.46775 | E19: =MIN(E16*E17,E23)+E18 -> 156.56072 | F19: =F16*F17+F18 -> 251.89889 | G19: =G16*G17+G18 -> 273.87389 | H19: =H16*H17+H18 -> 293.21189 | I19: =I16*I17+I18 -> 306.26504 | J19: =J16*J17+J18 -> 314.48852 | K19: =K16*K17+K18 -> 314.48852
B20: 经营必备现金/收入（检查） | C20: =C19/'3收入'!C5 -> 0.050915665 | D20: =D19/'3收入'!D5 -> 0.055696186 | E20: =E19/'3收入'!E5 -> 0.07567016 | F20: =F19/'3收入'!F5 -> 0.055977531 | G20: =G19/'3收入'!G5 -> 0.055328058 | H20: =H19/'3收入'!H5 -> 0.054846968 | I20: =I19/'3收入'!I5 -> 0.054560604 | J20: =J19/'3收入'!J5 -> 0.05439379 | K20: =K19/'3收入'!K5 -> 0.05439379
B21: 评估基准日溢余现金分析表
B22: 项目 | E22: =E4 -> 2018年1-6
B23: 资产负债表中的货币资金 | E23: ='2报表调整'!D8 -> 125.24516
B24: 其中：经营最低保有现金 | E24: =E19 -> 156.56072
B25: 溢余现金 | E25: =MAX(E23-E24,0) -> 0

Sheet 10营运
B1: 营运资金预测表
B2: ='1报表'!B11 -> 评估基准日：2018/6/30
B3: ='1报表'!B12 -> 被评估单位：YLSJ公司 | E3: =MONTH('1报表'!E5) -> 6 | F3: 基准年已经营月数 | K3: 单位：万元
B4: 项目 | C4: ='3收入'!C4 -> 2016年 | D4: ='3收入'!D4 -> 2017年 | E4: ='3收入'!E4 -> 2018年1-6 | F4: ='3收入'!F4 -> 2018年 | G4: ='3收入'!G4 -> 2019年 | H4: ='3收入'!H4 -> 2020年 | I4: ='3收入'!I4 -> 2021年 | J4: ='3收入'!J4 -> 2022年 | K4: ='3收入'!K4 -> 2023年 | L4: 全部为经营性资产负债；不含非经营！
B5: 经营最低保有现金 | C5: ='9溢余现金'!C19 -> 321.27782 | D5: ='9溢余现金'!D19 -> 359.46775 | E5: ='9溢余现金'!E19 -> 156.56072 | F5: ='9溢余现金'!F19 -> 251.89889 | G5: ='9溢余现金'!G19 -> 273.87389 | H5: ='9溢余现金'!H19 -> 293.21189 | I5: ='9溢余现金'!I19 -> 306.26504 | J5: ='9溢余现金'!J19 -> 314.48852 | K5: ='9溢余现金'!K19 -> 314.48852 | L5: 当企业不稳定时，不能用周转天数预测！采用绝对额进行预测！
B6: 应收票据及应收账款计算行 | C6: ='1报表'!C18-'2报表调整'!K11 -> 915.13378 | D6: ='1报表'!D18-'2报表调整'!L11 -> 747.61612 | E6: ='2报表调整'!G11 -> 479.66661
B7: 周转天数 | C7: =IF(C41,360*C6/C41,0) -> 52.210489 | D7: =IF(D41,360*D6/D41,0) -> 41.70102 | E7: =IF(E41,360*E6*E3/E41/12,0) -> 41.730525 | F7: 42 | G7: =F7 -> 42 | H7: =G7 -> 42 | I7: =H7 -> 42 | J7: =I7 -> 42 | K7: =J7 -> 42
B8: 应收票据及应收账款 | C8: =C6 -> 915.13378 | D8: =D6 -> 747.61612 | E8: =E6 -> 479.66661 | F8: =IF(F6,F6,F41*F7/360) -> 525 | G8: =IF(G6,G6,G41*G7/360) -> 577.5 | H8: =IF(H6,H6,H41*H7/360) -> 623.7 | I8: =IF(I6,I6,I41*I7/360) -> 654.885 | J8: =IF(J6,J6,J41*J7/360) -> 674.53155 | K8: =IF(K6,K6,K41*K7/360) -> 674.53155
B9: 预付款项计算行 | C9: ='1报表'!C19-'2报表调整'!K12 -> 0 | D9: ='1报表'!D19-'2报表调整'!L12 -> 0 | E9: ='2报表调整'!G12 -> 0
B10: 周转天数 | C10: =IF(C42,360*C9/C42,0) -> 0 | D10: =IF(D42,360*D9/D42,0) -> 0 | E10: =IF(E42,360*E9*E3/E42/12,0) -> 0 | G10: =F10 -> 0 | H10: =G10 -> 0 | I10: =H10 -> 0 | J10: =I10 -> 0 | K10: =J10 -> 0
B11: 预付款项 | C11: =C9 -> 0 | D11: =D9 -> 0 | E11: =E9 -> 0 | F11: =IF(F9,F9,F42*F10/360) -> 0 | G11: =IF(G9,G9,G42*G10/360) -> 0 | H11: =IF(H9,H9,H42*H10/360) -> 0 | I11: =IF(I9,I9,I42*I10/360) -> 0 | J11: =IF(J9,J9,J42*J10/360) -> 0 | K11: =IF(K9,K9,K42*K10/360) -> 0
B12: 其他应收款计算行 | C12: ='1报表'!C22-'2报表调整'!K15 -> 124.12402 | D12: ='1报表'!D22-'2报表调整'!L15 -> 195.0491 | E12: ='2报表调整'!G15 -> 191.0202
B13: 周转天数 | C13: =IF(C41,360*C12/C41,0) -> 7.0815613 | D13: =IF(D41,360*D12/D41,0) -> 10.879576 | E13: =IF(E41,360*E12*E3/E41/12,0) -> 16.61857 | F13: 15 | G13: =F13 -> 15 | H13: =G13 -> 15 | I13: =H13 -> 15 | J13: =I13 -> 15 | K13: =J13 -> 15
B14: 其他应收款 | C14: =C12 -> 124.12402 | D14: =D12 -> 195.0491 | E14: =E12 -> 191.0202 | F14: =IF(F12,F12,F41*F13/360) -> 187.5 | G14: =IF(G12,G12,G41*G13/360) -> 206.25 | H14: =IF(H12,H12,H41*H13/360) -> 222.75 | I14: =IF(I12,I12,I41*I13/360) -> 233.8875 | J14: =IF(J12,J12,J41*J13/360) -> 240.90413 | K14: =IF(K12,K12,K41*K13/360) -> 240.90413
B15: 存货计算行 | C15: ='1报表'!C23-'2报表调整'!K16 -> 0 | D15: ='1报表'!D23-'2报表调整'!L16 -> 0 | E15: ='2报表调整'!G16 -> 0
B16: 周转天数 | C16: =IF(C42,360*C15/C42,0) -> 0 | D16: =IF(D42,360*D15/D42,0) -> 0 | E16: =IF(E42,360*E15*E3/E42/12,0) -> 0 | G16: =F16 -> 0 | H16: =G16 -> 0 | I16: =H16 -> 0 | J16: =I16 -> 0 | K16: =J16 -> 0
B17: 存货 | C17: =C15 -> 0 | D17: =D15 -> 0 | E17: =E15 -> 0 | F17: =IF(F15,F15,F42*F16/360) -> 0 | G17: =IF(G15,G15,G42*G16/360) -> 0 | H17: =IF(H15,H15,H42*H16/360) -> 0 | I17: =IF(I15,I15,I42*I16/360) -> 0 | J17: =IF(J15,J15,J42*J16/360) -> 0 | K17: =IF(K15,K15,K42*K16/360) -> 0
B18: 合同资产 | C18: ='1报表'!C24-'2报表调整'!K17 -> 0 | D18: ='1报表'!D24-'2报表调整'!L17 -> 0 | E18: ='2报表调整'!G17 -> 0
B19: 一年内到期的非流动资产 | C19: ='1报表'!C26-'2报表调整'!K19 -> 0 | D19: ='1报表'!D26-'2报表调整'!L19 -> 0 | E19: ='2报表调整'!G19 -> 0
B20: 其他流动资产 | C20: ='1报表'!C27-'2报表调整'!K20 -> 0 | D20: ='1报表'!D27-'2报表调整'!L20 -> 0 | E20: ='2报表调整'!G20 -> 0
B21: 流动资产合计 | C21: =C5+C8+C11+C14+C17+C18+C19+C20 -> 1360.5356 | D21: =D5+D8+D11+D14+D17+D18+D19+D20 -> 1302.133 | E21: =E5+E8+E11+E14+E17+E18+E19+E20 -> 827.24752 | F21: =F5+F8+F11+F14+F17+F18+F19+F20 -> 964.39889 | G21: =G5+G8+G11+G14+G17+G18+G19+G20 -> 1057.6239 | H21: =H5+H8+H11+H14+H17+H18+H19+H20 -> 1139.6619 | I21: =I5+I8+I11+I14+I17+I18+I19+I20 -> 1195.0375 | J21: =J5+J8+J11+J14+J17+J18+J19+J20 -> 1229.9242 | K21: =K5+K8+K11+K14+K17+K18+K19+K20 -> 1229.9242
B23: 应付票据及应付款项计算行 | C23: ='1报表'!C55-'2报表调整'!K48 -> 0 | D23: ='1报表'!D55-'2报表调整'!L48 -> 0 | E23: ='2报表调整'!G48 -> 297.39516
B24: 周转天数 | C24: =IF(C42,360*C23/C42,0) -> 0 | D24: =IF(D42,360*D23/D42,0) -> 0 | E24: =IF(E42,360*E23*E3/E42/12,0) -> 23.809471 | F24: 20 | G24: =F24 -> 20 | H24: =G24 -> 20 | I24: =H24 -> 20 | J24: =I24 -> 20 | K24: =J24 -> 20
B25: 应付票据及应付账款 | C25: =C23 -> 0 | D25: =D23 -> 0 | E25: =E23 -> 297.39516 | F25: =IF(F23,F23,F42*F24/360) -> 219.93278 | G25: =IF(G23,G23,G42*G24/360) -> 242.36333 | H25: =IF(H23,H23,H42*H24/360) -> 261.56526 | I25: =IF(I23,I23,I42*I24/360) -> 273.21506 | J25: =IF(J23,J23,J42*J24/360) -> 281.89879 | K25: =IF(K23,K23,K42*K24/360) -> 282.29601
B26: 预收款项计算行 | C26: ='1报表'!C56-'2报表调整'!K49 -> 124.37 | D26: ='1报表'!D56-'2报表调整'!L49 -> 78 | E26: ='2报表调整'!G49 -> 99.1537
B27: 周转天数 | C27: =IF(C41,360*C26/C41,0) -> 7.0955948 | D27: =IF(D41,360*D26/D41,0) -> 4.3507349 | E27: =IF(E41,360*E26*E3/E41/12,0) -> 8.6262747 | F27: 6 | G27: =F27 -> 6 | H27: =G27 -> 6 | I27: =H27 -> 6 | J27: =I27 -> 6 | K27: =J27 -> 6
B28: 预收款项 | C28: =C26 -> 124.37 | D28: =D26 -> 78 | E28: =E26 -> 99.1537 | F28: =IF(F26,F26,F41*F27/360) -> 75 | G28: =IF(G26,G26,G41*G27/360) -> 82.5 | H28: =IF(H26,H26,H41*H27/360) -> 89.1 | I28: =IF(I26,I26,I41*I27/360) -> 93.555 | J28: =IF(J26,J26,J41*J27/360) -> 96.36165 | K28: =IF(K26,K26,K41*K27/360) -> 96.36165
B29: 合同负债 | C29: ='1报表'!C57-'2报表调整'!K50 -> 0 | D29: ='1报表'!D57-'2报表调整'!L50 -> 0 | E29: ='2报表调整'!G50 -> 0
B30: 应付职工薪酬 | C30: ='1报表'!C58-'2报表调整'!K51 -> 0 | D30: ='1报表'!D58-'2报表调整'!L51 -> -0.188809 | E30: ='2报表调整'!G51 -> 0
B31: 应交税费 | C31: ='1报表'!C59 -> 100.54686 | D31: ='1报表'!D59 -> 28.32304 | E31: ='2报表调整'!G52 -> 2.22638
B32: 其他应付款计算行 | C32: ='1报表'!C62-'2报表调整'!K55 -> 499.382 | D32: ='1报表'!D62-'2报表调整'!L55 -> 567.3349 | E32: ='2报表调整'!G55 -> 211.23041
B33: 占成本比例 | C33: =IF(C42,C32/C42,0) -> 0.093776977 | D33: =IF(D42,D32/D42,0) -> 0.09657309 | E33: =IF(E42,E32*E3/E42/12,0) -> 0.046975325 | F33: 0.1 | G33: =F33 -> 0.1 | H33: =G33 -> 0.1 | I33: =H33 -> 0.1 | J33: =I33 -> 0.1 | K33: =J33 -> 0.1
B34: 其他应付款 | C34: =C32 -> 499.382 | D34: =D32 -> 567.3349 | E34: =E32 -> 211.23041 | F34: =IF(F32,F32,F42*F33) -> 395.879 | G34: =IF(G32,G32,G42*G33) -> 436.254 | H34: =IF(H32,H32,H42*H33) -> 470.81747 | I34: =IF(I32,I32,I42*I33) -> 491.7871 | J34: =IF(J32,J32,J42*J33) -> 507.41781 | K34: =IF(K32,K32,K42*K33) -> 508.13281
B35: 其他流动负债计算行 | C35: ='1报表'!C65-'2报表调整'!K58 -> 0 | D35: ='1报表'!D65-'2报表调整'!L58 -> 0 | E35: ='2报表调整'!G58 -> 0
B36: 占成本比例 | C36: =IF(C42,C35/C42,0) -> 0 | D36: =IF(D42,D35/D42,0) -> 0 | E36: =IF(E42,E35*E3/E42/12,0) -> 0
B37: 其他流动负债 | C37: =C35 -> 0 | D37: =D35 -> 0 | E37: =E35 -> 0 | F37: =IF(F35,F35,F42*F36) -> 0 | G37: =IF(G35,G35,G42*G36) -> 0 | H37: =IF(H35,H35,H42*H36) -> 0 | I37: =IF(I35,I35,I42*I36) -> 0 | J37: =IF(J35,J35,J42*J36) -> 0 | K37: =IF(K35,K35,K42*K36) -> 0
B38: 流动负债合计 | C38: =C25+C28+C29+C30+C31+C34+C37 -> 724.29886 | D38: =D25+D28+D29+D30+D31+D34+D37 -> 673.46913 | E38: =E25+E28+E29+E30+E31+E34+E37 -> 610.00565 | F38: =F25+F28+F29+F30+F31+F34+F37 -> 690.81178 | G38: =G25+G28+G29+G30+G31+G34+G37 -> 761.11733 | H38: =H25+H28+H29+H30+H31+H34+H37 -> 821.48274 | I38: =I25+I28+I29+I30+I31+I34+I37 -> 858.55716 | J38: =J25+J28+J29+J30+J31+J34+J37 -> 885.67825 | K38: =K25+K28+K29+K30+K31+K34+K37 -> 886.79047
B39: 营运资金 | C39: =C21-C38 -> 636.23677 | D39: =D21-D38 -> 628.66384 | E39: =E21-E38 -> 217.24188 | F39: =F21-F38 -> 273.58711 | G39: =G21-G38 -> 296.50656 | H39: =H21-H38 -> 318.17915 | I39: =I21-I38 -> 336.48038 | J39: =J21-J38 -> 344.24595 | K39: =K21-K38 -> 343.13373
B40: 营运资金增加额 | F40: =F39-E39 -> 56.345235 | G40: =G39-F39 -> 22.919444 | H40: =H39-G39 -> 21.672597 | I40: =I39-H39 -> 18.301231 | J40: =J39-I39 -> 7.7655671 | K40: =K39-J39 -> -1.1122222
B41: 营业收入 | C41: ='3收入'!C5 -> 6309.9996 | D41: ='3收入'!D5 -> 6454.082 | E41: ='3收入'!E5 -> 2068.9888 | F41: ='3收入'!F5 -> 4500 | G41: ='3收入'!G5 -> 4950 | H41: ='3收入'!H5 -> 5346 | I41: ='3收入'!I5 -> 5613.3 | J41: ='3收入'!J5 -> 5781.699 | K41: ='3收入'!K5 -> 5781.699
B42: 营业成本 | C42: ='4成本'!C5 -> 5325.209 | D42: ='4成本'!D5 -> 5874.6686 | E42: ='4成本'!E5 -> 2248.3124 | F42: ='4成本'!F5 -> 3958.79 | G42: ='4成本'!G5 -> 4362.54 | H42: ='4成本'!H5 -> 4708.1747 | I42: ='4成本'!I5 -> 4917.871 | J42: ='4成本'!J5 -> 5074.1781 | K42: ='4成本'!K5 -> 5081.3281
B43: 营运资金占收入比 | C43: =C39/C41 -> 0.10082992 | D43: =D39/D41 -> 0.097405617 | E43: =E39/E41 -> 0.10499906 | F43: =F39/F41 -> 0.060797136 | G43: =G39/G41 -> 0.059900314 | H43: =H39/H41 -> 0.059517238 | I43: =I39/I41 -> 0.059943417 | J43: =J39/J41 -> 0.059540621 | K43: =K39/K41 -> 0.059348252
D44: 如果将历史年度的非经营剔除后，营运资金占比就更清晰反映出趋势。

Sheet 11财务费用
B1: 财务费用预测表
B2: ='1报表'!B11 -> 评估基准日：2018/6/30
B3: ='1报表'!B12 -> 被评估单位：YLSJ公司 | E3: ='7折旧'!F3 -> 2018年剩余折摊月数 | F3: ='7折旧'!E3 -> 6 | K3: 单位：万元
B4: 汇总数据 | C4: 利息率% | D4: 借款起讫日期 | E4: ='3收入'!E4 -> 2018年1-6 | F4: ='7折旧'!E4 -> 2018年7-12 | G4: ='3收入'!G4 -> 2019年 | H4: ='3收入'!H4 -> 2020年 | I4: ='3收入'!I4 -> 2021年 | J4: ='3收入'!J4 -> 2022年 | K4: ='3收入'!K4 -> 2023年
B5: 短期借款
B6: 一年内到期的非流动负债
B7: 长期借款
B8: 新增借款 | C8: 0.054 | L8: 该行迭代计算得出
B9: 应付债券
B10: 付息负债合计 | E10: =SUM(E5:E9) -> 0 | F10: =SUM(F5:F9) -> 0 | G10: =SUM(G5:G9) -> 0 | H10: =SUM(H5:H9) -> 0 | I10: =SUM(I5:I9) -> 0 | J10: =SUM(J5:J9) -> 0 | K10: =SUM(K5:K9) -> 0
B11: 财务费用测算
B12: 利息支出 | C12: ='3收入'!C4 -> 2016年 | D12: ='3收入'!D4 -> 2017年 | E12: =E4 -> 2018年1-6 | F12: =F4 -> 2018年7-12 | G12: =G4 -> 2019年 | H12: =H4 -> 2020年 | I12: =I4 -> 2021年 | J12: =J4 -> 2022年 | K12: =K4 -> 2023年
B13: 短期借款 | F13: =$C5*E5/12*$F$3 -> 0 | G13: =$C5*F5 -> 0 | H13: =$C5*G5 -> 0 | I13: =$C5*H5 -> 0 | J13: =$C5*I5 -> 0 | K13: =$C5*J5 -> 0 | L13: 采用上年数计算，可根据具体发生情况填列
B14: 一年内到期的非流动负债 | F14: =$C6*E6/12*$F$3 -> 0 | G14: =$C6*F6 -> 0 | H14: =$C6*G6 -> 0 | I14: =$C6*H6 -> 0 | J14: =$C6*I6 -> 0 | K14: =$C6*J6 -> 0
B15: 长期借款 | F15: =$C7*E7/12*$F$3 -> 0 | G15: =$C7*F7 -> 0 | H15: =$C7*G7 -> 0 | I15: =$C7*H7 -> 0 | J15: =$C7*I7 -> 0 | K15: =$C7*J7 -> 0
B16: 新增借款 | F16: =$C8*E8/12*$F$3 -> 0 | G16: =$C8*F8 -> 0 | H16: =$C8*G8 -> 0 | I16: =$C8*H8 -> 0 | J16: =$C8*I8 -> 0 | K16: =$C8*J8 -> 0
B17: 应付债券 | F17: =$C9*E9/12*$F$3 -> 0 | G17: =$C9*F9 -> 0 | H17: =$C9*G9 -> 0 | I17: =$C9*H9 -> 0 | J17: =$C9*I9 -> 0 | K17: =$C9*J9 -> 0
B18: 利息支出小计 | C18: ='1报表'!C104 -> 0.473709 | D18: ='1报表'!D104 -> 0.956799 | E18: ='1报表'!E104 -> 0.0238 | F18: =SUM(F13:F17) -> 0 | G18: =SUM(G13:G17) -> 0 | H18: =SUM(H13:H17) -> 0 | I18: =SUM(I13:I17) -> 0 | J18: =SUM(J13:J17) -> 0 | K18: =SUM(K13:K17) -> 0
B19: 利息收入 | C19: ='1报表'!C105 -> 34.373249 | D19: ='1报表'!D105 -> 12.14111 | E19: ='1报表'!E105 -> 1.036709
B20: 汇兑损益及手续费等 | C20: =C21-C18+C19 -> 0 | D20: =D21-D18+D19 -> 0 | E20: =E21-E18+E19 -> 0 | L20: 预测期只考虑手续费，不考虑汇兑损益
B21: 财务费用合计 | C21: ='1报表'!C103 -> -33.89954 | D21: ='1报表'!D103 -> -11.184311 | E21: ='1报表'!E103 -> -1.012909 | F21: =SUM(F18:F20) -> 0 | G21: =SUM(G18:G20) -> 0 | H21: =SUM(H18:H20) -> 0 | I21: =SUM(I18:I20) -> 0 | J21: =SUM(J18:J20) -> 0 | K21: =SUM(K18:K20) -> 0
B23: 新增借款(由预测资产负债表计算得出) | D23: 无“预测财报”表删除 | F23: =预测财报!F83 -> 0 | G23: =预测财报!G83 -> 0 | H23: =预测财报!H83 -> 0 | I23: =预测财报!I83 -> 0 | J23: =预测财报!J83 -> 0 | K23: =预测财报!K83 -> 0 | L23: 企业未来是否有资金缺口，需要融多少资金，
B24: 是否相等？ | F24: =F8-F23 -> 0 | G24: =G8-G23 -> 0 | H24: =H8-H23 -> 0 | I24: =I8-I23 -> 0 | J24: =J8-J23 -> 0 | L24: 只有通过预测资产负债表计算才能得出。
B27: 借款明细核实如下

Sheet 12收益表
B1: 收益预测表
B2: ='1报表'!B11 -> 评估基准日：2018/6/30
B3: ='1报表'!B12 -> 被评估单位：YLSJ公司 | K3: 单位：万元
B4: 利润表（经营性） | C4: ='3收入'!C4 -> 2016年 | D4: ='3收入'!D4 -> 2017年 | E4: ='3收入'!E4 -> 2018年1-6 | F4: ='3收入'!F4 -> 2018年 | G4: ='3收入'!G4 -> 2019年 | H4: ='3收入'!H4 -> 2020年 | I4: ='3收入'!I4 -> 2021年 | J4: ='3收入'!J4 -> 2022年 | K4: ='3收入'!K4 -> 2023年
B5: 一、营业收入 | C5: ='3收入'!C5 -> 6309.9996 | D5: ='3收入'!D5 -> 6454.082 | E5: ='3收入'!E5 -> 2068.9888 | F5: ='3收入'!F5 -> 4500 | G5: ='3收入'!G5 -> 4950 | H5: ='3收入'!H5 -> 5346 | I5: ='3收入'!I5 -> 5613.3 | J5: ='3收入'!J5 -> 5781.699 | K5: ='3收入'!K5 -> 5781.699
B6: 减:营业成本 | C6: ='4成本'!C5 -> 5325.209 | D6: ='4成本'!D5 -> 5874.6686 | E6: ='4成本'!E5 -> 2248.3124 | F6: ='4成本'!F5 -> 3958.79 | G6: ='4成本'!G5 -> 4362.54 | H6: ='4成本'!H5 -> 4708.1747 | I6: ='4成本'!I5 -> 4917.871 | J6: ='4成本'!J5 -> 5074.1781 | K6: ='4成本'!K5 -> 5081.3281
B7: 减:税金及附加 | C7: ='5税金'!C5 -> 32.988746 | D7: ='5税金'!D5 -> 28.542702 | E7: ='5税金'!E5 -> 19.638479 | F7: ='5税金'!F5 -> 22.5 | G7: ='5税金'!G5 -> 24.75 | H7: ='5税金'!H5 -> 26.73 | I7: ='5税金'!I5 -> 28.0665 | J7: ='5税金'!J5 -> 28.908495 | K7: ='5税金'!K5 -> 28.908495
B8: 减:销售费用 | C8: ='6销管'!C5 -> 0 | D8: ='6销管'!D5 -> 0 | E8: ='6销管'!E5 -> 0 | F8: ='6销管'!F5 -> 0 | G8: ='6销管'!G5 -> 0 | H8: ='6销管'!H5 -> 0 | I8: ='6销管'!I5 -> 0 | J8: ='6销管'!J5 -> 0 | K8: ='6销管'!K5 -> 0
B9: 减:管理费用 | C9: ='6销管'!C6 -> 668.47256 | D9: ='6销管'!D6 -> 615.9856 | E9: ='6销管'!E6 -> 268.92924 | F9: ='6销管'!F6 -> 475.43751 | G9: ='6销管'!G6 -> 512.95 | H9: ='6销管'!H6 -> 554.946 | I9: ='6销管'!I6 -> 583.4433 | J9: ='6销管'!J6 -> 599.9516 | K9: ='6销管'!K6 -> 599.9516
B10: 减:研发费用 | C10: ='6销管'!C7 -> 0 | D10: ='6销管'!D7 -> 0 | E10: ='6销管'!E7 -> 0 | F10: ='6销管'!F7 -> 0 | G10: ='6销管'!G7 -> 0 | H10: ='6销管'!H7 -> 0 | I10: ='6销管'!I7 -> 0 | J10: ='6销管'!J7 -> 0 | K10: ='6销管'!K7 -> 0
B11: 减:财务费用 | C11: ='11财务费用'!C21 -> -33.89954 | D11: ='11财务费用'!D21 -> -11.184311 | E11: ='11财务费用'!E21 -> -1.012909 | F11: ='11财务费用'!F21+E11 -> -1.012909 | G11: ='11财务费用'!G21 -> 0 | H11: ='11财务费用'!H21 -> 0 | I11: ='11财务费用'!I21 -> 0 | J11: ='11财务费用'!J21 -> 0 | K11: ='11财务费用'!K21 -> 0
B12: 二、营业利润 | C12: =C5-SUM(C6:C11) -> 317.22878 | D12: =D5-SUM(D6:D11) -> -53.930552 | E12: =E5-SUM(E6:E11) -> -466.87835 | F12: =F5-SUM(F6:F11) -> 44.285403 | G12: =G5-SUM(G6:G11) -> 49.76 | H12: =H5-SUM(H6:H11) -> 56.149268 | I12: =I5-SUM(I6:I11) -> 83.9192 | J12: =J5-SUM(J6:J11) -> 78.660776 | K12: =K5-SUM(K6:K11) -> 71.510776
B13: 三、利润总额 | C13: =C12 -> 317.22878 | D13: =D12 -> -53.930552 | E13: =E12 -> -466.87835 | F13: =F12 -> 44.285403 | G13: =G12 -> 49.76 | H13: =H12 -> 56.149268 | I13: =I12 -> 83.9192 | J13: =J12 -> 78.660776 | K13: =K12 -> 71.510776
B14: 减：弥补以前年度亏损 | F14: =-D13 -> 53.930552 | G14: =F14-F13 -> 9.645149
B15: 减：研发费用加计扣除
B16: 减：其他纳税调减额
B17: 加：其他纳税调增额
B18: 应纳税所得额 | F18: =F13-F14-F15-F16+F17 -> -9.645149 | G18: =G13-G14-G15-G16+G17 -> 40.114851 | H18: =H13-H14-H15-H16+H17 -> 56.149268 | I18: =I13-I14-I15-I16+I17 -> 83.9192 | J18: =J13-J14-J15-J16+J17 -> 78.660776 | K18: =K13-K14-K15-K16+K17 -> 71.510776
B19: 所得税税率 | F19: 0.25 | G19: 0.25 | H19: 0.25 | I19: 0.25 | J19: 0.25 | K19: 0.25
B20: 减:所得税费用 | F20: =IF(F18<0,0,F18*F19) -> 0 | G20: =IF(G18<0,0,G18*G19) -> 10.028713 | H20: =IF(H18<0,0,H18*H19) -> 14.037317 | I20: =IF(I18<0,0,I18*I19) -> 20.9798 | J20: =IF(J18<0,0,J18*J19) -> 19.665194 | K20: =IF(K18<0,0,K18*K19) -> 17.877694
B21: 四、净利润 | F21: =F13-F20 -> 44.285403 | G21: =G13-G20 -> 39.731287 | H21: =H13-H20 -> 42.111951 | I21: =I13-I20 -> 62.9394 | J21: =J13-J20 -> 58.995582 | K21: =K13-K20 -> 53.633082
B22: 减:少数股东损益
B23: 五、归母净利润 | F23: =F21-F22 -> 44.285403 | G23: =G21-G22 -> 39.731287 | H23: =H21-H22 -> 42.111951 | I23: =I21-I22 -> 62.9394 | J23: =J21-J22 -> 58.995582 | K23: =K21-K22 -> 53.633082
B26: 补充预测利润表用数据，无“预测财报”表删除下列数据！
B27: 三、利润总额 | C27: =C13 -> 317.22878 | D27: =D13 -> -53.930552 | E27: =E13 -> -466.87835
B28: 减：弥补以前年度亏损
B29: 减：研发费用加计扣除
B30: 减：其他纳税调减额
B31: 加：其他纳税调增额
B32: 应纳税所得额 | C32: =C27-C28-C29-C30+C31 -> 317.22878 | D32: =D27-D28-D29-D30+D31 -> -53.930552 | E32: =E27-E28-E29-E30+E31 -> -466.87835
B33: 所得税税率 | C33: 0.25 | D33: 0.25 | E33: 0.25
B34: 减:所得税费用 | C34: =IF(C32<0,0,C32*C33) -> 79.307194 | D34: =IF(D32<0,0,D32*D33) -> 0 | E34: =IF(E32<0,0,E32*E33) -> 0

Sheet 13FCFF
B1: 企业自由现金流量测算表
B2: ='1报表'!B11 -> 评估基准日：2018/6/30
B3: ='1报表'!B12 -> 被评估单位：YLSJ公司 | L3: 单位：万元
B4: 项目 | F4: ='7折旧'!E4 -> 2018年7-12 | G4: ='3收入'!G4 -> 2019年 | H4: ='3收入'!H4 -> 2020年 | I4: ='3收入'!I4 -> 2021年 | J4: ='3收入'!J4 -> 2022年 | K4: ='3收入'!K4 -> 2023年 | L4: 永续期
B5: 一、营业收入 | F5: ='12收益表'!F5-'12收益表'!E5 -> 2431.0112 | G5: ='12收益表'!G5 -> 4950 | H5: =预测财报!H20 -> 5346 | I5: =预测财报!I20 -> 5613.3 | J5: =预测财报!J20 -> 5781.699 | K5: =预测财报!K20 -> 5781.699 | L5: =K5 -> 5781.699
B6: 减：营业成本 | F6: ='12收益表'!F6-'12收益表'!E6 -> 1710.4776 | G6: ='12收益表'!G6 -> 4362.54 | H6: ='12收益表'!H6 -> 4708.1747 | I6: ='12收益表'!I6 -> 4917.871 | J6: ='12收益表'!J6 -> 5074.1781 | K6: ='12收益表'!K6 -> 5081.3281 | L6: =K6 -> 5081.3281
B7: 减：税金及附加 | F7: ='12收益表'!F7-'12收益表'!E7 -> 2.861521 | G7: ='12收益表'!G7 -> 24.75 | H7: ='12收益表'!H7 -> 26.73 | I7: ='12收益表'!I7 -> 28.0665 | J7: ='12收益表'!J7 -> 28.908495 | K7: ='12收益表'!K7 -> 28.908495 | L7: =K7 -> 28.908495
B8: 减：销售费用 | F8: ='12收益表'!F8-'12收益表'!E8 -> 0 | G8: ='12收益表'!G8 -> 0 | H8: ='12收益表'!H8 -> 0 | I8: ='12收益表'!I8 -> 0 | J8: ='12收益表'!J8 -> 0 | K8: ='12收益表'!K8 -> 0 | L8: =K8 -> 0
B9: 减：管理费用 | F9: ='12收益表'!F9-'12收益表'!E9 -> 206.50827 | G9: ='12收益表'!G9 -> 512.95 | H9: ='12收益表'!H9 -> 554.946 | I9: ='12收益表'!I9 -> 583.4433 | J9: ='12收益表'!J9 -> 599.9516 | K9: ='12收益表'!K9 -> 599.9516 | L9: =K9 -> 599.9516
B10: 减：研发费用 | F10: ='12收益表'!F10-'12收益表'!E10 -> 0 | G10: ='12收益表'!G10 -> 0 | H10: ='12收益表'!H10 -> 0 | I10: ='12收益表'!I10 -> 0 | J10: ='12收益表'!J10 -> 0 | K10: ='12收益表'!K10 -> 0 | L10: =K10 -> 0
B11: 减：财务费用 | F11: ='12收益表'!F11-'12收益表'!E11 -> 0 | G11: ='12收益表'!G11 -> 0 | H11: ='12收益表'!H11 -> 0 | I11: ='12收益表'!I11 -> 0 | J11: ='12收益表'!J11 -> 0 | K11: ='12收益表'!K11 -> 0 | L11: =IF('11财务费用'!K10,SUMPRODUCT('11财务费用'!C5:C9,'11财务费用'!K5:K9)+'11财务费用'!K20,0) -> 0
B12: 二、营业利润 | F12: =F5-SUM(F6:F11) -> 511.16375 | G12: =G5-SUM(G6:G11) -> 49.76 | H12: =H5-SUM(H6:H11) -> 56.149268 | I12: =I5-SUM(I6:I11) -> 83.9192 | J12: =J5-SUM(J6:J11) -> 78.660776 | K12: =K5-SUM(K6:K11) -> 71.510776 | L12: =L5-SUM(L6:L11) -> 71.510776
B13: 三、利润总额 | F13: =F12 -> 511.16375 | G13: =G12 -> 49.76 | H13: =H12 -> 56.149268 | I13: =I12 -> 83.9192 | J13: =J12 -> 78.660776 | K13: =K12 -> 71.510776 | L13: =L12 -> 71.510776
B14: 减：所得税费用 | F14: ='12收益表'!F20-'12收益表'!E20 -> 0 | G14: ='12收益表'!G20 -> 10.028713 | H14: ='12收益表'!H20 -> 14.037317 | I14: ='12收益表'!I20 -> 20.9798 | J14: ='12收益表'!J20 -> 19.665194 | K14: ='12收益表'!K20 -> 17.877694 | L14: =L13*L32 -> 17.877694
B15: 四、净利润 | F15: =F13-F14 -> 511.16375 | G15: =G13-G14 -> 39.731287 | H15: =H13-H14 -> 42.111951 | I15: =I13-I14 -> 62.9394 | J15: =J13-J14 -> 58.995582 | K15: =K13-K14 -> 53.633082 | L15: =L13-L14 -> 53.633082
B16: 加：扣税后利息费用 | F16: =(1-F32)*'11财务费用'!F18 -> 0 | G16: =(1-G32)*'11财务费用'!G18 -> 0 | H16: =(1-H32)*'11财务费用'!H18 -> 0 | I16: =(1-I32)*'11财务费用'!I18 -> 0 | J16: =(1-J32)*'11财务费用'!J18 -> 0 | K16: =(1-K32)*'11财务费用'!K18 -> 0 | L16: =(1-L32)*SUMPRODUCT('11财务费用'!C5:C9,'11财务费用'!K5:K9) -> 0
B17: 加：折旧与摊销 | F17: ='7折旧'!E9+'8摊销'!E7 -> 29.536019 | G17: ='7折旧'!G9+'8摊销'!G7 -> 59.04 | H17: ='7折旧'!H9+'8摊销'!H7 -> 62.154732 | I17: ='7折旧'!I9+'8摊销'!I7 -> 40.8 | J17: ='7折旧'!J9+'8摊销'!J7 -> 50.1 | K17: ='7折旧'!K9+'8摊销'!K7 -> 57.25 | L17: =K17 -> 57.25
B18: 减：资本性支出 | F18: ='7折旧'!E10+'8摊销'!E10 -> 55 | G18: ='7折旧'!G10+'8摊销'!G10 -> 55 | H18: ='7折旧'!H10+'8摊销'!H10 -> 55 | I18: ='7折旧'!I10+'8摊销'!I10 -> 55 | J18: ='7折旧'!J10+'8摊销'!J10 -> 55 | K18: ='7折旧'!K10+'8摊销'!K10 -> 53 | L18: =L17 -> 57.25
B19: 减：净营运资金变动 | F19: ='10营运'!F40 -> 56.345235 | G19: ='10营运'!G40 -> 22.919444 | H19: ='10营运'!H40 -> 21.672597 | I19: ='10营运'!I40 -> 18.301231 | J19: ='10营运'!J40 -> 7.7655671 | K19: ='10营运'!K40 -> -1.1122222 | L19: 0
B20: 五、企业自由现金流量 | F20: =F15+F16+F17-F18-F19 -> 429.35454 | G20: =G15+G16+G17-G18-G19 -> 20.851843 | H20: =H15+H16+H17-H18-H19 -> 27.594086 | I20: =I15+I16+I17-I18-I19 -> 30.438169 | J20: =J15+J16+J17-J18-J19 -> 46.330015 | K20: =K15+K16+K17-K18-K19 -> 58.995304 | L20: =L15+L16+L17-L18-L19 -> 53.633082
B21: 折现期 | F21: =1-MONTH('1报表'!E5)/12 -> 0.5 | G21: =1+F21 -> 1.5 | H21: =1+G21 -> 2.5 | I21: =1+H21 -> 3.5 | J21: =1+I21 -> 4.5 | K21: =1+J21 -> 5.5
B22: 折现率 | F22: =F48 -> 0.12703038 | G22: =F22 -> 0.12703038 | H22: =G22 -> 0.12703038 | I22: =H22 -> 0.12703038 | J22: =I22 -> 0.12703038 | K22: =J22 -> 0.12703038 | L22: =K22 -> 0.12703038
B23: 折现系数 | F23: =1/(1+F22)^F21 -> 0.94195941 | G23: =F23/(1+G22) -> 0.83578884 | H23: =G23/(1+H22) -> 0.74158501 | I23: =H23/(1+I22) -> 0.65799913 | J23: =I23/(1+J22) -> 0.58383442 | K23: =J23/(1+K22) -> 0.518029 | L23: =K23/L22 -> 4.077993
B24: (计算WACC1)折现值 | F24: =F20*F23 -> 404.43455 | G24: =G20*G23 -> 17.427737 | H24: =H20*H23 -> 20.46336 | I24: =I20*I23 -> 20.028289 | J24: =J20*J23 -> 27.049057 | K24: =K20*K23 -> 30.561279 | L24: =L20*L23 -> 218.71533
B25: 迭代后折现率 | F25: =F48 -> 0.12703038 | G25: =I48 -> 0.12703038 | H25: =I48 -> 0.12703038 | I25: =I48 -> 0.12703038 | J25: =L48 -> 0.12703038 | K25: =L48 -> 0.12703038 | L25: =L48 -> 0.12703038 | M25: 无付息负债，无需迭代计算！
B26: 迭代后折现系数 | F26: =1/(1+F25)^F21 -> 0.94195941 | G26: =F26/(1+G25) -> 0.83578884 | H26: =G26/(1+H25) -> 0.74158501 | I26: =H26/(1+I25) -> 0.65799913 | J26: =I26/(1+J25) -> 0.58383442 | K26: =J26/(1+K25) -> 0.518029 | L26: =K26/L25 -> 4.077993
B27: 最终评估折现值 | F27: =F20*F26 -> 404.43455 | G27: =G20*G26 -> 17.427737 | H27: =H20*H26 -> 20.46336 | I27: =I20*I26 -> 20.028289 | J27: =J20*J26 -> 27.049057 | K27: =K20*K26 -> 30.561279 | L27: =L20*L26 -> 218.71533
B28: 六、企业自由现金流现值合计 | F28: =SUM(F27:L27) -> 738.6796
B29: 经营性资产价值 | F29: =F28*J29 -> 738.6796 | H29: 是否选择年中折现？ | J29: =IF(K29="年末",1,(1+F22)^0.5) -> 1 | K29: 年末 | L29: 调整系数 | M29: 本公式为单一折现率使用的年中折现调整系数，多折现率的公式尚未导出。
B31: 项目 | F31: =F4 -> 2018年7-12 | G31: =G4 -> 2019年 | H31: =H4 -> 2020年 | I31: =I4 -> 2021年 | J31: =J4 -> 2022年 | K31: =K4 -> 2023年 | L31: =L4 -> 永续期
B32: 企业所得税率T | F32: ='12收益表'!F19 -> 0.25 | G32: ='12收益表'!G19 -> 0.25 | H32: ='12收益表'!H19 -> 0.25 | I32: ='12收益表'!I19 -> 0.25 | J32: ='12收益表'!J19 -> 0.25 | K32: ='12收益表'!K19 -> 0.25 | L32: =K32 -> 0.25
B33: WACC1测算（2018年） | I33: WACC2测算（2019-2021年） | L33: WACC3测算（2022年及以后）
B34: 付息债务D | F34: ='11财务费用'!E10 -> 0
B35: 企业所得税率T | F35: =F32 -> 0.25 | I35: =G32 -> 0.25 | L35: =J32 -> 0.25
B36: 无风险报酬率Rf | F36: 0.0397 | I36: =F36 -> 0.0397 | L36: =I36 -> 0.0397
B37: 市场风险溢价MRP | F37: 0.0739 | I37: =F37 -> 0.0739 | L37: =I37 -> 0.0739
B38: 个别风险调整系数Q | F38: 0.0279 | I38: =F38 -> 0.0279 | L38: =I38 -> 0.0279
B39: 行业βU | F39: 0.8042 | I39: =F39 -> 0.8042 | L39: =I39 -> 0.8042
B40: 债务成本Kd | F40: 0.054 | I40: =F40 -> 0.054 | L40: =I40 -> 0.054
B41: βL=βu[1+(1-T)D/E] | F41: =F39*(1+(1-F35)*F44) -> 0.8042 | I41: =I39*(1+(1-I35)*I44) -> 0.8042 | L41: =L39*(1+(1-L35)*L44) -> 0.8042
B42: 权益成本Ke＝Rf＋βL×MRP＋Q | F42: =F36+F41*F37+F38 -> 0.12703038 | I42: =I36+I41*I37+I38 -> 0.12703038 | L42: =L36+L41*L37+L38 -> 0.12703038
B44: D/E | F44: 0 | G44: =F34/(SUM(F27:L27)-F34) -> 0 | H44: =F44-G44 -> 0 | I44: 0 | J44: =F34/(SUM(F27:L27)-F34) -> 0 | K44: =I44-J44 -> 0 | L44: 0 | M44: =F34/(SUM(F27:L27)-F34) -> 0 | N44: =L44-M44 -> 0
B45: We=E/(D+E) | F45: =G45 -> 1 | G45: =1/(F44+1) -> 1 | H45: =F45-G45 -> 0 | I45: =J45 -> 1 | J45: =1/(I44+1) -> 1 | K45: =I45-J45 -> 0 | L45: =M45 -> 1 | M45: =1/(L44+1) -> 1 | N45: =L45-M45 -> 0
B46: Wd=D/(D+E) | F46: =G46 -> 0 | G46: =1-F45 -> 0 | H46: =F46-G46 -> 0 | I46: =J46 -> 0 | J46: =1-I45 -> 0 | K46: =I46-J46 -> 0 | L46: =M46 -> 0 | M46: =1-L45 -> 0 | N46: =L46-M46 -> 0
B48: WACC=Ke×We+(1-T)Kd×Wd | F48: =F42*F45+(1-F35)*F40*F46 -> 0.12703038 | I48: =I42*I45+(1-I35)*I40*I46 -> 0.12703038 | L48: =L42*L45+(1-L35)*L40*L46 -> 0.12703038
B51: 股东权益价值测算表
B52: 项目 | F52: 评估值 | G52: 备注
B53: 经营性资产价值 | F53: =F29 -> 738.6796
B54: 加：溢余资产评估值 | F54: ='2报表调整'!F80 -> 0
B55: 加：非经营性资产评估值 | F55: ='2报表调整'!N43 -> 904.59485
B56: 减：非经营性负债评估值 | F56: ='2报表调整'!N70 -> 688.11777
B57: 企业整体资产价值 | F57: =F53+F54+F55-F56 -> 955.15669
B58: 减：付息负债价值 | F58: ='11财务费用'!E10 -> 0
B59: 减：股票期权
B60: 减：可转换债券
B61: 减：少数股东权益
B62: 股东全部权益价值 | F62: =F57-SUM(F58:F61) -> 955.15669 | I62: ='14FCFE'!F46 -> 955.15669 | J62: =F62-I62 -> 0 | K62: FCFF和FCFE两种口径计算值相同
B63: 股东全部权益价值（取整） | F63: =ROUND(F62,-1) -> 960
B64: 控制权对评估对象价值的影响 | G64: 未考虑
B65: 流动性对评估对象价值的影响 | G65: 未考虑
B66: 本次评估股权比例
B67: 部分股权评估值 | F67: =F63*F66 -> 0

Sheet 14FCFE
B1: 股权自由现金流量测算表
B2: ='1报表'!B11 -> 评估基准日：2018/6/30
B3: ='1报表'!B12 -> 被评估单位：YLSJ公司 | L3: 单位：万元
B4: 项目 | F4: ='7折旧'!E4 -> 2018年7-12 | G4: ='3收入'!G4 -> 2019年 | H4: ='3收入'!H4 -> 2020年 | I4: ='3收入'!I4 -> 2021年 | J4: ='3收入'!J4 -> 2022年 | K4: ='3收入'!K4 -> 2023年 | L4: 永续期
B5: 一、营业收入 | F5: ='12收益表'!F5-'12收益表'!E5 -> 2431.0112 | G5: ='12收益表'!G5 -> 4950 | H5: ='12收益表'!H5 -> 5346 | I5: ='12收益表'!I5 -> 5613.3 | J5: ='12收益表'!J5 -> 5781.699 | K5: ='12收益表'!K5 -> 5781.699 | L5: =K5 -> 5781.699
B6: 减：营业成本 | F6: ='12收益表'!F6-'12收益表'!E6 -> 1710.4776 | G6: ='12收益表'!G6 -> 4362.54 | H6: ='12收益表'!H6 -> 4708.1747 | I6: ='12收益表'!I6 -> 4917.871 | J6: ='12收益表'!J6 -> 5074.1781 | K6: ='12收益表'!K6 -> 5081.3281 | L6: =K6 -> 5081.3281
B7: 减：税金及附加 | F7: ='12收益表'!F7-'12收益表'!E7 -> 2.861521 | G7: ='12收益表'!G7 -> 24.75 | H7: ='12收益表'!H7 -> 26.73 | I7: ='12收益表'!I7 -> 28.0665 | J7: ='12收益表'!J7 -> 28.908495 | K7: ='12收益表'!K7 -> 28.908495 | L7: =K7 -> 28.908495
B8: 减：销售费用 | F8: ='12收益表'!F8-'12收益表'!E8 -> 0 | G8: ='12收益表'!G8 -> 0 | H8: ='12收益表'!H8 -> 0 | I8: ='12收益表'!I8 -> 0 | J8: ='12收益表'!J8 -> 0 | K8: ='12收益表'!K8 -> 0 | L8: =K8 -> 0
B9: 减：管理费用 | F9: ='12收益表'!F9-'12收益表'!E9 -> 206.50827 | G9: ='12收益表'!G9 -> 512.95 | H9: ='12收益表'!H9 -> 554.946 | I9: ='12收益表'!I9 -> 583.4433 | J9: ='12收益表'!J9 -> 599.9516 | K9: ='12收益表'!K9 -> 599.9516 | L9: =K9 -> 599.9516
B10: 减：研发费用 | F10: ='12收益表'!F10-'12收益表'!E10 -> 0 | G10: ='12收益表'!G10 -> 0 | H10: ='12收益表'!H10 -> 0 | I10: ='12收益表'!I10 -> 0 | J10: ='12收益表'!J10 -> 0 | K10: ='12收益表'!K10 -> 0 | L10: =K10 -> 0
B11: 减：财务费用 | F11: =IF('11财务费用'!E10,"模型不适用",'11财务费用'!F21) -> 0 | G11: =IF('11财务费用'!F10,"模型不适用",'11财务费用'!G21) -> 0 | H11: =IF('11财务费用'!G10,"模型不适用",'11财务费用'!H21) -> 0 | I11: =IF('11财务费用'!H10,"模型不适用",'11财务费用'!I21) -> 0 | J11: =IF('11财务费用'!I10,"模型不适用",'11财务费用'!J21) -> 0 | K11: =IF('11财务费用'!J10,"模型不适用",'11财务费用'!K21) -> 0 | L11: =IF('11财务费用'!K10,"模型不适用",'11财务费用'!L21) -> 0
B12: 二、营业利润 | F12: =F5-SUM(F6:F11) -> 511.16375 | G12: =G5-SUM(G6:G11) -> 49.76 | H12: =H5-SUM(H6:H11) -> 56.149268 | I12: =I5-SUM(I6:I11) -> 83.9192 | J12: =J5-SUM(J6:J11) -> 78.660776 | K12: =K5-SUM(K6:K11) -> 71.510776 | L12: =L5-SUM(L6:L11) -> 71.510776
B13: 三、利润总额 | F13: =F12 -> 511.16375 | G13: =G12 -> 49.76 | H13: =H12 -> 56.149268 | I13: =I12 -> 83.9192 | J13: =J12 -> 78.660776 | K13: =K12 -> 71.510776 | L13: =L12 -> 71.510776
B14: 减:所得税费用 | F14: ='12收益表'!F20-'12收益表'!E20 -> 0 | G14: ='12收益表'!G20 -> 10.028713 | H14: ='12收益表'!H20 -> 14.037317 | I14: ='12收益表'!I20 -> 20.9798 | J14: ='12收益表'!J20 -> 19.665194 | K14: ='12收益表'!K20 -> 17.877694 | L14: =L13*'12收益表'!K19 -> 17.877694
B15: 四、净利润 | F15: =F13-F14 -> 511.16375 | G15: =G13-G14 -> 39.731287 | H15: =H13-H14 -> 42.111951 | I15: =I13-I14 -> 62.9394 | J15: =J13-J14 -> 58.995582 | K15: =K13-K14 -> 53.633082 | L15: =L13-L14 -> 53.633082
B16: 加：折旧与摊销 | F16: ='7折旧'!E9+'8摊销'!E7 -> 29.536019 | G16: ='7折旧'!G9+'8摊销'!G7 -> 59.04 | H16: ='7折旧'!H9+'8摊销'!H7 -> 62.154732 | I16: ='7折旧'!I9+'8摊销'!I7 -> 40.8 | J16: ='7折旧'!J9+'8摊销'!J7 -> 50.1 | K16: ='7折旧'!K9+'8摊销'!K7 -> 57.25 | L16: =K16 -> 57.25
B17: 减：资本性支出 | F17: ='7折旧'!E10+'8摊销'!E10 -> 55 | G17: ='7折旧'!G10+'8摊销'!G10 -> 55 | H17: ='7折旧'!H10+'8摊销'!H10 -> 55 | I17: ='7折旧'!I10+'8摊销'!I10 -> 55 | J17: ='7折旧'!J10+'8摊销'!J10 -> 55 | K17: ='7折旧'!K10+'8摊销'!K10 -> 53 | L17: =L16 -> 57.25
B18: 减：净营运资金变动 | F18: ='10营运'!F40 -> 56.345235 | G18: ='10营运'!G40 -> 22.919444 | H18: ='10营运'!H40 -> 21.672597 | I18: ='10营运'!I40 -> 18.301231 | J18: ='10营运'!J40 -> 7.7655671 | K18: ='10营运'!K40 -> -1.1122222 | L18: 0
B19: 加：付息债务的增加 | F19: =IF('11财务费用'!E10,"模型不适用",0) -> 0 | G19: =IF('11财务费用'!F10,"模型不适用",0) -> 0 | H19: =IF('11财务费用'!G10,"模型不适用",0) -> 0 | I19: =IF('11财务费用'!H10,"模型不适用",0) -> 0 | J19: =IF('11财务费用'!I10,"模型不适用",0) -> 0 | K19: =IF('11财务费用'!J10,"模型不适用",0) -> 0 | L19: 0
B20: 股权自由现金流 (FCFE) | F20: =F15+F16-F17-F18+F19 -> 429.35454 | G20: =G15+G16-G17-G18+G19 -> 20.851843 | H20: =H15+H16-H17-H18+H19 -> 27.594086 | I20: =I15+I16-I17-I18+I19 -> 30.438169 | J20: =J15+J16-J17-J18+J19 -> 46.330015 | K20: =K15+K16-K17-K18+K19 -> 58.995304 | L20: =L15+L16-L17-L18+L19 -> 53.633082
B21: 折现期 | F21: =1-MONTH('1报表'!E5)/12 -> 0.5 | G21: =1+F21 -> 1.5 | H21: =1+G21 -> 2.5 | I21: =1+H21 -> 3.5 | J21: =1+I21 -> 4.5 | K21: =1+J21 -> 5.5
B22: 折现率 | F22: =F33 -> 0.12703038 | G22: =F22 -> 0.12703038 | H22: =G22 -> 0.12703038 | I22: =H22 -> 0.12703038 | J22: =I22 -> 0.12703038 | K22: =J22 -> 0.12703038 | L22: =K22 -> 0.12703038
B23: 折现系数 | F23: =1/(1+F22)^F21 -> 0.94195941 | G23: =F23/(1+G22) -> 0.83578884 | H23: =G23/(1+H22) -> 0.74158501 | I23: =H23/(1+I22) -> 0.65799913 | J23: =I23/(1+J22) -> 0.58383442 | K23: =J23/(1+K22) -> 0.518029 | L23: =K23/L22 -> 4.077993
B24: 股权自由现金流现值 | F24: =F20*F23 -> 404.43455 | G24: =G20*G23 -> 17.427737 | H24: =H20*H23 -> 20.46336 | I24: =I20*I23 -> 20.028289 | J24: =J20*J23 -> 27.049057 | K24: =K20*K23 -> 30.561279 | L24: =L20*L23 -> 218.71533
B25: 六、股权自由现金流现值合计 | F25: =SUM(F24:L24) -> 738.6796
B27: 折现率计算表
B28: 项目 | F28: 取值
B29: 无风险报酬率（Rf） | F29: 0.0397
B30: MRP（市场风险溢价）=Rm-Rf | F30: 0.0739
B31: βL（=βU） | F31: 0.8042
B32: Q | F32: 0.0279
B33: 权益成本Ke | F33: =F29+F31*F30+F32 -> 0.12703038
B34: 永续期不考虑增长
B36: 股东权益价值测算表
B37: 项目 | F37: 评估值 | G37: 备注
B38: 股权自由现金流现值 | F38: =F25 -> 738.6796
B39: 加：溢余资产评估值 | F39: ='2报表调整'!F80 -> 0
B40: 加：非经营性资产评估值 | F40: ='2报表调整'!N43 -> 904.59485
B41: 减：非经营性负债评估值 | F41: ='2报表调整'!N70 -> 688.11777
B42: 股东全部权益价值E1 | F42: =F38+F39+F40-F41 -> 955.15669
B43: 减：股票期权
B44: 减：可转换债券
B45: 减：少数股东权益
B46: 股东全部权益价值E2 | F46: =F42-SUM(F43:F45) -> 955.15669
B47: 股东全部权益价值（取整） | F47: =ROUND(F46,-1) -> 960
B48: 控制权对评估对象价值的影响 | G48: 未考虑
B49: 流动性对评估对象价值的影响 | G49: 未考虑
B50: 本次评估股权比例
B51: 部分股权评估值 | F51: =F47*F50 -> 0
B53: 应用前提
B54: 该FCFE模型只适用评估基准日及未来预测期间无付息负债的情形。

Sheet 预测财报
B1: 经营性资产财务报表预测表（检查用）
B2: ='1报表'!B11 -> 评估基准日：2018/6/30
B3: ='1报表'!B12 -> 被评估单位：YLSJ公司 | K3: 单位：万元
B4: 完成资产负债表剩余项目 | C4: ='1报表'!C13 -> 42735 | D4: ='1报表'!D13 -> 43100 | E4: ='1报表'!E13 -> 43281 | F4: =DATE(YEAR(E4),12,31) -> 43465 | G4: =EDATE(F4,12) -> 43830 | H4: =EDATE(G4,12) -> 44196 | I4: =EDATE(H4,12) -> 44561 | J4: =EDATE(I4,12) -> 44926 | K4: =EDATE(J4,12) -> 45291
B5: 长期应收款 | C5: ='1报表'!C34-'2报表调整'!K27 -> 0 | D5: ='1报表'!D34-'2报表调整'!L27 -> 0 | E5: ='2报表调整'!G27 -> 0
B6: 其他非流动资产 | C6: ='1报表'!C48-'2报表调整'!K41 -> 0 | D6: ='1报表'!D48-'2报表调整'!L41 -> 0 | E6: ='2报表调整'!G41 -> 0
B7: 长期应付款 | C7: ='1报表'!C70-'2报表调整'!K63 -> 0 | D7: ='1报表'!D70-'2报表调整'!L63 -> 0 | E7: ='2报表调整'!G63 -> 0
B8: 长期应付职工薪酬 | C8: ='1报表'!C71-'2报表调整'!K64 -> 0 | D8: ='1报表'!D71-'2报表调整'!L64 -> 0 | E8: ='2报表调整'!G64 -> 0
B9: 预计负债 | C9: ='1报表'!C72-'2报表调整'!K65 -> 0 | D9: ='1报表'!D72-'2报表调整'!L65 -> 0 | E9: ='2报表调整'!G65 -> 0
B10: 递延收益 | C10: ='1报表'!C73-'2报表调整'!K66 -> 0 | D10: ='1报表'!D73-'2报表调整'!L66 -> 0 | E10: ='2报表调整'!G66 -> 0
B11: 其他非流动负债 | C11: ='1报表'!C75-'2报表调整'!K68 -> 0 | D11: ='1报表'!D75-'2报表调整'!L68 -> 0 | E11: ='2报表调整'!G68 -> 0
B12: 少数股东所在公司派发股利的比例 | F12: 0.5 | G12: =F12 -> 0.5 | H12: =G12 -> 0.5 | I12: =H12 -> 0.5 | J12: =I12 -> 0.5 | K12: =J12 -> 0.5
B13: 补充投入资本计算表剩余历史数据
B14: 加：收购无形资产的累计摊销额
B15: 加：累计减值的商誉
B16: 完成利润表剩余项目
B17: 新增借款利率 | F17: ='11财务费用'!C8 -> 0.054
B19: 利润表（经营性） | C19: ='3收入'!C4 -> 2016年 | D19: ='3收入'!D4 -> 2017年 | E19: ='3收入'!E4 -> 2018年1-6 | F19: ='3收入'!F4 -> 2018年 | G19: ='3收入'!G4 -> 2019年 | H19: ='3收入'!H4 -> 2020年 | I19: ='3收入'!I4 -> 2021年 | J19: ='3收入'!J4 -> 2022年 | K19: ='3收入'!K4 -> 2023年
B20: 一、营业收入 | C20: ='3收入'!C5 -> 6309.9996 | D20: ='3收入'!D5 -> 6454.082 | E20: ='3收入'!E5 -> 2068.9888 | F20: ='3收入'!F5 -> 4500 | G20: ='3收入'!G5 -> 4950 | H20: ='3收入'!H5 -> 5346 | I20: ='3收入'!I5 -> 5613.3 | J20: ='3收入'!J5 -> 5781.699 | K20: ='3收入'!K5 -> 5781.699
B21: 减:营业成本 | C21: ='4成本'!C5 -> 5325.209 | D21: ='4成本'!D5 -> 5874.6686 | E21: ='4成本'!E5 -> 2248.3124 | F21: ='4成本'!F5 -> 3958.79 | G21: ='4成本'!G5 -> 4362.54 | H21: ='4成本'!H5 -> 4708.1747 | I21: ='4成本'!I5 -> 4917.871 | J21: ='4成本'!J5 -> 5074.1781 | K21: ='4成本'!K5 -> 5081.3281
B22: 减:税金及附加 | C22: ='5税金'!C5 -> 32.988746 | D22: ='5税金'!D5 -> 28.542702 | E22: ='5税金'!E5 -> 19.638479 | F22: ='5税金'!F5 -> 22.5 | G22: ='5税金'!G5 -> 24.75 | H22: ='5税金'!H5 -> 26.73 | I22: ='5税金'!I5 -> 28.0665 | J22: ='5税金'!J5 -> 28.908495 | K22: ='5税金'!K5 -> 28.908495
B23: 减:销售费用 | C23: ='6销管'!C5 -> 0 | D23: ='6销管'!D5 -> 0 | E23: ='6销管'!E5 -> 0 | F23: ='6销管'!F5 -> 0 | G23: ='6销管'!G5 -> 0 | H23: ='6销管'!H5 -> 0 | I23: ='6销管'!I5 -> 0 | J23: ='6销管'!J5 -> 0 | K23: ='6销管'!K5 -> 0
B24: 减:管理费用 | C24: ='6销管'!C6 -> 668.47256 | D24: ='6销管'!D6 -> 615.9856 | E24: ='6销管'!E6 -> 268.92924 | F24: ='6销管'!F6 -> 475.43751 | G24: ='6销管'!G6 -> 512.95 | H24: ='6销管'!H6 -> 554.946 | I24: ='6销管'!I6 -> 583.4433 | J24: ='6销管'!J6 -> 599.9516 | K24: ='6销管'!K6 -> 599.9516
B25: 减:研发费用 | C25: ='6销管'!C7 -> 0 | D25: ='6销管'!D7 -> 0 | E25: ='6销管'!E7 -> 0 | F25: ='6销管'!F7 -> 0 | G25: ='6销管'!G7 -> 0 | H25: ='6销管'!H7 -> 0 | I25: ='6销管'!I7 -> 0 | J25: ='6销管'!J7 -> 0 | K25: ='6销管'!K7 -> 0
B26: 减:手续费和汇兑损益等 | C26: ='1报表'!C103-C28+C29 -> 0 | D26: ='1报表'!D103-D28+D29 -> 0 | E26: ='1报表'!E103-E28+E29 -> 0 | F26: ='11财务费用'!F20 -> 0 | G26: ='11财务费用'!G20 -> 0 | H26: ='11财务费用'!H20 -> 0 | I26: ='11财务费用'!I20 -> 0 | J26: ='11财务费用'!J20 -> 0 | K26: ='11财务费用'!K20 -> 0
B27: 减:利息支出(新增借款) | G27: =$F$17*F83 -> 0 | H27: =$F$17*G83 -> 0 | I27: =$F$17*H83 -> 0 | J27: =$F$17*I83 -> 0 | K27: =$F$17*J83 -> 0
B28: 减:利息支出(原有债务) | C28: ='11财务费用'!C18 -> 0.473709 | D28: ='11财务费用'!D18 -> 0.956799 | E28: ='11财务费用'!E18 -> 0.0238 | F28: ='11财务费用'!F18+E28 -> 0.0238 | G28: ='11财务费用'!G18 -> 0 | H28: ='11财务费用'!H18 -> 0 | I28: ='11财务费用'!I18 -> 0 | J28: ='11财务费用'!J18 -> 0 | K28: ='11财务费用'!K18 -> 0
B29: 加:利息收入(保有、溢余现金) | C29: ='11财务费用'!C19 -> 34.373249 | D29: ='11财务费用'!D19 -> 12.14111 | E29: ='11财务费用'!E19 -> 1.036709
B30: 二、营业利润 | C30: =C20-SUM(C21:C28)+C29 -> 317.22878 | D30: =D20-SUM(D21:D28)+D29 -> -53.930552 | E30: =E20-SUM(E21:E28)+E29 -> -466.87835 | F30: =F20-SUM(F21:F28)+F29 -> 43.248694 | G30: =G20-SUM(G21:G28)+G29 -> 49.76 | H30: =H20-SUM(H21:H28)+H29 -> 56.149268 | I30: =I20-SUM(I21:I28)+I29 -> 83.9192 | J30: =J20-SUM(J21:J28)+J29 -> 78.660776 | K30: =K20-SUM(K21:K28)+K29 -> 71.510776
B31: 三、利润总额 | C31: =C30 -> 317.22878 | D31: =D30 -> -53.930552 | E31: =E30 -> -466.87835 | F31: =F30 -> 43.248694 | G31: =G30 -> 49.76 | H31: =H30 -> 56.149268 | I31: =I30 -> 83.9192 | J31: =J30 -> 78.660776 | K31: =K30 -> 71.510776
B32: 减:所得税费用 | C32: ='12收益表'!C34 -> 79.307194 | D32: ='12收益表'!D34 -> 0 | E32: ='12收益表'!E34 -> 0 | F32: ='12收益表'!F20 -> 0 | G32: ='12收益表'!G20 -> 10.028713 | H32: ='12收益表'!H20 -> 14.037317 | I32: ='12收益表'!I20 -> 20.9798 | J32: ='12收益表'!J20 -> 19.665194 | K32: ='12收益表'!K20 -> 17.877694
B33: 四、净利润 | C33: =C31-C32 -> 237.92158 | D33: =D31-D32 -> -53.930552 | E33: =E31-E32 -> -466.87835 | F33: =F31-F32 -> 43.248694 | G33: =G31-G32 -> 39.731287 | H33: =H31-H32 -> 42.111951 | I33: =I31-I32 -> 62.9394 | J33: =J31-J32 -> 58.995582 | K33: =K31-K32 -> 53.633082
B34: 减:少数股东损益 | C34: ='1报表'!C122 -> 0 | D34: ='1报表'!D122 -> 0 | E34: ='1报表'!E122 -> 0 | F34: ='12收益表'!F22 -> 0 | G34: ='12收益表'!G22 -> 0 | H34: ='12收益表'!H22 -> 0 | I34: ='12收益表'!I22 -> 0 | J34: ='12收益表'!J22 -> 0 | K34: ='12收益表'!K22 -> 0
B35: 五、归母净利润 | C35: =C33-C34 -> 237.92158 | D35: =D33-D34 -> -53.930552 | E35: =E33-E34 -> -466.87835 | F35: =F33-F34 -> 43.248694 | G35: =G33-G34 -> 39.731287 | H35: =H33-H34 -> 42.111951 | I35: =I33-I34 -> 62.9394 | J35: =J33-J34 -> 58.995582 | K35: =K33-K34 -> 53.633082
B36: 股利支付 | G36: =F41 -> 450.55217 | H36: =G41 -> 471.40401 | I36: =H41 -> 498.9981 | J36: =I41 -> 529.43627 | K36: =J41 -> 575.76628
B37: 扣除股利支付后净利润 | F37: =F35-F36 -> 43.248694 | G37: =G35-G36 -> -410.82088 | H37: =H35-H36 -> -429.29206 | I37: =I35-I36 -> -436.0587 | J37: =J35-J36 -> -470.44069 | K37: =K35-K36 -> -522.1332
B39: 资产负债表（经营性） | C39: =C4 -> 42735 | D39: =D4 -> 43100 | E39: =E4 -> 43281 | F39: =F4 -> 43465 | G39: =G4 -> 43830 | H39: =H4 -> 44196 | I39: =I4 -> 44561 | J39: =J4 -> 44926 | K39: =K4 -> 45291
B40: 流动资产
B41: 盈余现金 | C41: =MAX('1报表'!C15-'10营运'!C5,0) -> 285.63819 | D41: =MAX('1报表'!D15-'10营运'!D5,0) -> 63.086704 | E41: =MAX('1报表'!E15-'10营运'!E5,0) -> 0 | F41: =MAX(F100,0) -> 450.55217 | G41: =MAX(G100,0) -> 471.40401 | H41: =MAX(H100,0) -> 498.9981 | I41: =MAX(I100,0) -> 529.43627 | J41: =MAX(J100,0) -> 575.76628 | K41: =MAX(K100,0) -> 634.76159
B42: 经营最低保有现金 | C42: =MIN('1报表'!C15,'10营运'!C5) -> 321.27782 | D42: =MIN('1报表'!D15,'10营运'!D5) -> 359.46775 | E42: =MIN('1报表'!E15,'10营运'!E5) -> 125.24516 | F42: ='10营运'!F5 -> 251.89889 | G42: ='10营运'!G5 -> 273.87389 | H42: ='10营运'!H5 -> 293.21189 | I42: ='10营运'!I5 -> 306.26504 | J42: ='10营运'!J5 -> 314.48852 | K42: ='10营运'!K5 -> 314.48852
B43: 应收票据及应收账款 | C43: ='10营运'!C8 -> 915.13378 | D43: ='10营运'!D8 -> 747.61612 | E43: ='10营运'!E8 -> 479.66661 | F43: ='10营运'!F8 -> 525 | G43: ='10营运'!G8 -> 577.5 | H43: ='10营运'!H8 -> 623.7 | I43: ='10营运'!I8 -> 654.885 | J43: ='10营运'!J8 -> 674.53155 | K43: ='10营运'!K8 -> 674.53155
B44: 预付款项 | C44: ='10营运'!C11 -> 0 | D44: ='10营运'!D11 -> 0 | E44: ='10营运'!E11 -> 0 | F44: ='10营运'!F11 -> 0 | G44: ='10营运'!G11 -> 0 | H44: ='10营运'!H11 -> 0 | I44: ='10营运'!I11 -> 0 | J44: ='10营运'!J11 -> 0 | K44: ='10营运'!K11 -> 0
B45: 其他应收款 | C45: ='10营运'!C14 -> 124.12402 | D45: ='10营运'!D14 -> 195.0491 | E45: ='10营运'!E14 -> 191.0202 | F45: ='10营运'!F14 -> 187.5 | G45: ='10营运'!G14 -> 206.25 | H45: ='10营运'!H14 -> 222.75 | I45: ='10营运'!I14 -> 233.8875 | J45: ='10营运'!J14 -> 240.90413 | K45: ='10营运'!K14 -> 240.90413
B46: 存货 | C46: ='10营运'!C17 -> 0 | D46: ='10营运'!D17 -> 0 | E46: ='10营运'!E17 -> 0 | F46: ='10营运'!F17 -> 0 | G46: ='10营运'!G17 -> 0 | H46: ='10营运'!H17 -> 0 | I46: ='10营运'!I17 -> 0 | J46: ='10营运'!J17 -> 0 | K46: ='10营运'!K17 -> 0
B47: 合同资产 | C47: ='10营运'!C18 -> 0 | D47: ='10营运'!D18 -> 0 | E47: ='10营运'!E18 -> 0 | F47: ='10营运'!F18 -> 0 | G47: ='10营运'!G18 -> 0 | H47: ='10营运'!H18 -> 0 | I47: ='10营运'!I18 -> 0 | J47: ='10营运'!J18 -> 0 | K47: ='10营运'!K18 -> 0
B48: 一年内到期的非流动资产 | C48: ='10营运'!C19 -> 0 | D48: ='10营运'!D19 -> 0 | E48: ='10营运'!E19 -> 0 | F48: ='10营运'!F19 -> 0 | G48: ='10营运'!G19 -> 0 | H48: ='10营运'!H19 -> 0 | I48: ='10营运'!I19 -> 0 | J48: ='10营运'!J19 -> 0 | K48: ='10营运'!K19 -> 0
B49: 其他流动资产 | C49: ='10营运'!C20 -> 0 | D49: ='10营运'!D20 -> 0 | E49: ='10营运'!E20 -> 0 | F49: ='10营运'!F20 -> 0 | G49: ='10营运'!G20 -> 0 | H49: ='10营运'!H20 -> 0 | I49: ='10营运'!I20 -> 0 | J49: ='10营运'!J20 -> 0 | K49: ='10营运'!K20 -> 0
B50: 流动资产合计 | C50: =SUM(C41:C49) -> 1646.1738 | D50: =SUM(D41:D49) -> 1365.2197 | E50: =SUM(E41:E49) -> 795.93197 | F50: =SUM(F41:F49) -> 1414.9511 | G50: =SUM(G41:G49) -> 1529.0279 | H50: =SUM(H41:H49) -> 1638.66 | I50: =SUM(I41:I49) -> 1724.4738 | J50: =SUM(J41:J49) -> 1805.6905 | K50: =SUM(K41:K49) -> 1864.6858
B51: 非流动资产
B52: 长期应收款 | C52: =C5 -> 0 | D52: =D5 -> 0 | E52: =E5 -> 0 | F52: =F5 -> 0 | G52: =G5 -> 0 | H52: =H5 -> 0 | I52: =I5 -> 0 | J52: =J5 -> 0 | K52: =K5 -> 0
B53: 固定资产 | C53: ='1报表'!C39-'2报表调整'!K32 -> 108.53785 | D53: ='1报表'!D39-'2报表调整'!L32 -> 111.62056 | E53: ='2报表调整'!G32 -> 94.661335 | F53: ='7折旧'!F29+'7折旧'!F44 -> 120.54473 | G53: ='7折旧'!G29+'7折旧'!G44 -> 113.50473 | H53: ='7折旧'!H29+'7折旧'!H44 -> 105.35 | I53: ='7折旧'!I29+'7折旧'!I44 -> 120.05 | J53: ='7折旧'!J29+'7折旧'!J44 -> 124.95 | K53: ='7折旧'!K29+'7折旧'!K44 -> 120.7
B54: 在建工程 | C54: ='1报表'!C40-'2报表调整'!K33 -> 0 | D54: ='1报表'!D40-'2报表调整'!L33 -> 0 | E54: ='2报表调整'!G33 -> 0
B55: 生产性生物资产 | C55: ='1报表'!C41-'2报表调整'!K34 -> 0 | D55: ='1报表'!D41-'2报表调整'!L34 -> 0 | E55: ='2报表调整'!G34 -> 0
B56: 油气资产 | C56: ='1报表'!C42-'2报表调整'!K35 -> 0 | D56: ='1报表'!D42-'2报表调整'!L35 -> 0 | E56: ='2报表调整'!G35 -> 0
B57: 无形资产 | C57: ='1报表'!C43-'2报表调整'!K36 -> 0.477818 | D57: ='1报表'!D43-'2报表调整'!L36 -> 9.480241 | E57: ='2报表调整'!G36 -> 5.916019 | F57: ='8摊销'!F26+'8摊销'!F35 -> 11.416019 | G57: ='8摊销'!G26+'8摊销'!G35 -> 14.416019 | H57: ='8摊销'!H26+'8摊销'!H35 -> 15.416019 | I57: ='8摊销'!I26+'8摊销'!I35 -> 14.916019 | J57: ='8摊销'!J26+'8摊销'!J35 -> 14.916019 | K57: ='8摊销'!K26+'8摊销'!K35 -> 14.916019
B58: 开发支出 | C58: ='1报表'!C44-'2报表调整'!K37 -> 0 | D58: ='1报表'!D44-'2报表调整'!L37 -> 0 | E58: ='2报表调整'!G37 -> 0
B59: 商誉 | C59: ='1报表'!C45 -> 0 | D59: ='1报表'!D45 -> 0 | E59: ='2报表调整'!G38 -> 0 | F59: =E59 -> 0 | G59: =F59 -> 0 | H59: =G59 -> 0 | I59: =H59 -> 0 | J59: =I59 -> 0 | K59: =J59 -> 0
B60: 长期待摊费用 | C60: ='1报表'!C46-'2报表调整'!K39 -> 0 | D60: ='1报表'!D46-'2报表调整'!L39 -> 0 | E60: ='2报表调整'!G39 -> 0 | F60: ='8摊销'!F53 -> 0 | G60: ='8摊销'!G53 -> 0 | H60: ='8摊销'!H53 -> 0 | I60: ='8摊销'!I53 -> 0 | J60: ='8摊销'!J53 -> 0 | K60: ='8摊销'!K53 -> 0
B61: 递延所得税资产 | C61: ='1报表'!C47-'2报表调整'!K40 -> 0 | D61: ='1报表'!D47-'2报表调整'!L40 -> 0 | E61: ='2报表调整'!G40 -> 0 | F61: =E61 -> 0 | G61: =F61 -> 0 | H61: =G61 -> 0 | I61: =H61 -> 0 | J61: =I61 -> 0 | K61: =J61 -> 0
B62: 其他非流动资产 | C62: =C6 -> 0 | D62: =D6 -> 0 | E62: =E6 -> 0 | F62: =F6 -> 0 | G62: =G6 -> 0 | H62: =H6 -> 0 | I62: =I6 -> 0 | J62: =J6 -> 0 | K62: =K6 -> 0
B63: 非流动资产合计 | C63: =SUM(C52:C62) -> 109.01567 | D63: =SUM(D52:D62) -> 121.1008 | E63: =SUM(E52:E62) -> 100.57735 | F63: =SUM(F52:F62) -> 131.96075 | G63: =SUM(G52:G62) -> 127.92075 | H63: =SUM(H52:H62) -> 120.76602 | I63: =SUM(I52:I62) -> 134.96602 | J63: =SUM(J52:J62) -> 139.86602 | K63: =SUM(K52:K62) -> 135.61602
B64: 资产总计 | C64: =C50+C63 -> 1755.1895 | D64: =D50+D63 -> 1486.3205 | E64: =E50+E63 -> 896.50932 | F64: =F50+F63 -> 1546.9118 | G64: =G50+G63 -> 1656.9487 | H64: =H50+H63 -> 1759.426 | I64: =I50+I63 -> 1859.4398 | J64: =J50+J63 -> 1945.5565 | K64: =K50+K63 -> 2000.3018
B65: 非付息流动负债
B66: 应付票据及应付款项 | C66: ='10营运'!C25 -> 0 | D66: ='10营运'!D25 -> 0 | E66: ='10营运'!E25 -> 297.39516 | F66: ='10营运'!F25 -> 219.93278 | G66: ='10营运'!G25 -> 242.36333 | H66: ='10营运'!H25 -> 261.56526 | I66: ='10营运'!I25 -> 273.21506 | J66: ='10营运'!J25 -> 281.89879 | K66: ='10营运'!K25 -> 282.29601
B67: 预收款项 | C67: ='10营运'!C28 -> 124.37 | D67: ='10营运'!D28 -> 78 | E67: ='10营运'!E28 -> 99.1537 | F67: ='10营运'!F28 -> 75 | G67: ='10营运'!G28 -> 82.5 | H67: ='10营运'!H28 -> 89.1 | I67: ='10营运'!I28 -> 93.555 | J67: ='10营运'!J28 -> 96.36165 | K67: ='10营运'!K28 -> 96.36165
B68: 合同负债 | C68: ='10营运'!C29 -> 0 | D68: ='10营运'!D29 -> 0 | E68: ='10营运'!E29 -> 0 | F68: ='10营运'!F29 -> 0 | G68: ='10营运'!G29 -> 0 | H68: ='10营运'!H29 -> 0 | I68: ='10营运'!I29 -> 0 | J68: ='10营运'!J29 -> 0 | K68: ='10营运'!K29 -> 0
B69: 应付职工薪酬 | C69: ='10营运'!C30 -> 0 | D69: ='10营运'!D30 -> -0.188809 | E69: ='10营运'!E30 -> 0 | F69: ='10营运'!F30 -> 0 | G69: ='10营运'!G30 -> 0 | H69: ='10营运'!H30 -> 0 | I69: ='10营运'!I30 -> 0 | J69: ='10营运'!J30 -> 0 | K69: ='10营运'!K30 -> 0
B70: 应交税费 | C70: ='10营运'!C31 -> 100.54686 | D70: ='10营运'!D31 -> 28.32304 | E70: ='10营运'!E31 -> 2.22638 | F70: ='10营运'!F31 -> 0 | G70: ='10营运'!G31 -> 0 | H70: ='10营运'!H31 -> 0 | I70: ='10营运'!I31 -> 0 | J70: ='10营运'!J31 -> 0 | K70: ='10营运'!K31 -> 0
B71: 其他应付款 | C71: ='10营运'!C34 -> 499.382 | D71: ='10营运'!D34 -> 567.3349 | E71: ='10营运'!E34 -> 211.23041 | F71: ='10营运'!F34 -> 395.879 | G71: ='10营运'!G34 -> 436.254 | H71: ='10营运'!H34 -> 470.81747 | I71: ='10营运'!I34 -> 491.7871 | J71: ='10营运'!J34 -> 507.41781 | K71: ='10营运'!K34 -> 508.13281
B72: 其他流动负债 | C72: ='10营运'!C37 -> 0 | D72: ='10营运'!D37 -> 0 | E72: ='10营运'!E37 -> 0 | F72: ='10营运'!F37 -> 0 | G72: ='10营运'!G37 -> 0 | H72: ='10营运'!H37 -> 0 | I72: ='10营运'!I37 -> 0 | J72: ='10营运'!J37 -> 0 | K72: ='10营运'!K37 -> 0
B73: 非付息流动负债合计 | C73: =SUM(C66:C72) -> 724.29886 | D73: =SUM(D66:D72) -> 673.46913 | E73: =SUM(E66:E72) -> 610.00565 | F73: =SUM(F66:F72) -> 690.81178 | G73: =SUM(G66:G72) -> 761.11733 | H73: =SUM(H66:H72) -> 821.48274 | I73: =SUM(I66:I72) -> 858.55716 | J73: =SUM(J66:J72) -> 885.67825 | K73: =SUM(K66:K72) -> 886.79047
B74: 非付息非流动负债
B75: 长期应付款 | C75: =C7 -> 0 | D75: =D7 -> 0 | E75: =E7 -> 0 | F75: =F7 -> 0 | G75: =G7 -> 0 | H75: =H7 -> 0 | I75: =I7 -> 0 | J75: =J7 -> 0 | K75: =K7 -> 0
B76: 长期应付职工薪酬 | C76: =C8 -> 0 | D76: =D8 -> 0 | E76: =E8 -> 0 | F76: =F8 -> 0 | G76: =G8 -> 0 | H76: =H8 -> 0 | I76: =I8 -> 0 | J76: =J8 -> 0 | K76: =K8 -> 0
B77: 预计负债 | C77: =C9 -> 0 | D77: =D9 -> 0 | E77: =E9 -> 0 | F77: =F9 -> 0 | G77: =G9 -> 0 | H77: =H9 -> 0 | I77: =I9 -> 0 | J77: =J9 -> 0 | K77: =K9 -> 0
B78: 递延收益 | C78: =C10 -> 0 | D78: =D10 -> 0 | E78: =E10 -> 0 | F78: =F10 -> 0 | G78: =G10 -> 0 | H78: =H10 -> 0 | I78: =I10 -> 0 | J78: =J10 -> 0 | K78: =K10 -> 0
B79: 递延所得税负债 | C79: ='1报表'!C74-'2报表调整'!K67 -> 0 | D79: ='1报表'!D74-'2报表调整'!L67 -> 0 | E79: ='2报表调整'!G67 -> 0 | F79: =E79 -> 0 | G79: =F79 -> 0 | H79: =G79 -> 0 | I79: =H79 -> 0 | J79: =I79 -> 0 | K79: =J79 -> 0
B80: 其他非流动负债 | C80: =C11 -> 0 | D80: =D11 -> 0 | E80: =E11 -> 0 | F80: =F11 -> 0 | G80: =G11 -> 0 | H80: =H11 -> 0 | I80: =I11 -> 0 | J80: =J11 -> 0 | K80: =K11 -> 0
B81: 非付息非流动负债合计 | C81: =SUM(C75:C80) -> 0 | D81: =SUM(D75:D80) -> 0 | E81: =SUM(E75:E80) -> 0 | F81: =SUM(F75:F80) -> 0 | G81: =SUM(G75:G80) -> 0 | H81: =SUM(H75:H80) -> 0 | I81: =SUM(I75:I80) -> 0 | J81: =SUM(J75:J80) -> 0 | K81: =SUM(K75:K80) -> 0
B82: 付息负债
B83: 新增借款 | F83: =-MIN(F100,0) -> 0 | G83: =-MIN(G100,0) -> 0 | H83: =-MIN(H100,0) -> 0 | I83: =-MIN(I100,0) -> 0 | J83: =-MIN(J100,0) -> 0 | K83: =-MIN(K100,0) -> 0
B84: 短期借款 | C84: ='1报表'!C52 -> 0 | D84: ='1报表'!D52 -> 0 | E84: ='1报表'!E52 -> 0 | F84: ='11财务费用'!F5 -> 0 | G84: ='11财务费用'!G5 -> 0 | H84: ='11财务费用'!H5 -> 0 | I84: ='11财务费用'!I5 -> 0 | J84: ='11财务费用'!J5 -> 0 | K84: ='11财务费用'!K5 -> 0
B85: 一年内到期的非流动负债 | C85: ='1报表'!C64 -> 0 | D85: ='1报表'!D64 -> 0 | E85: ='1报表'!E64 -> 0 | F85: ='11财务费用'!F6 -> 0 | G85: ='11财务费用'!G6 -> 0 | H85: ='11财务费用'!H6 -> 0 | I85: ='11财务费用'!I6 -> 0 | J85: ='11财务费用'!J6 -> 0 | K85: ='11财务费用'!K6 -> 0
B86: 长期借款 | C86: ='1报表'!C68 -> 0 | D86: ='1报表'!D68 -> 0 | E86: ='1报表'!E68 -> 0 | F86: ='11财务费用'!F7 -> 0 | G86: ='11财务费用'!G7 -> 0 | H86: ='11财务费用'!H7 -> 0 | I86: ='11财务费用'!I7 -> 0 | J86: ='11财务费用'!J7 -> 0 | K86: ='11财务费用'!K7 -> 0
B87: 应付债券 | C87: ='1报表'!C69 -> 0 | D87: ='1报表'!D69 -> 0 | E87: ='1报表'!E69 -> 0 | F87: ='11财务费用'!F9 -> 0 | G87: ='11财务费用'!G9 -> 0 | H87: ='11财务费用'!H9 -> 0 | I87: ='11财务费用'!I9 -> 0 | J87: ='11财务费用'!J9 -> 0 | K87: ='11财务费用'!K9 -> 0
B88: 付息负债合计 | C88: =SUM(C83:C87) -> 0 | D88: =SUM(D83:D87) -> 0 | E88: =SUM(E83:E87) -> 0 | F88: =SUM(F83:F87) -> 0 | G88: =SUM(G83:G87) -> 0 | H88: =SUM(H83:H87) -> 0 | I88: =SUM(I83:I87) -> 0 | J88: =SUM(J83:J87) -> 0 | K88: =SUM(K83:K87) -> 0
B89: 负债合计 | C89: =C73+C81+C88 -> 724.29886 | D89: =D73+D81+D88 -> 673.46913 | E89: =E73+E81+E88 -> 610.00565 | F89: =F73+F81+F88 -> 690.81178 | G89: =G73+G81+G88 -> 761.11733 | H89: =H73+H81+H88 -> 821.48274 | I89: =I73+I81+I88 -> 858.55716 | J89: =J73+J81+J88 -> 885.67825 | K89: =K73+K81+K88 -> 886.79047
B90: 所有者权益
B91: 归母权益 | C91: ='1报表'!C87-'2报表调整'!K43+'2报表调整'!K70 -> 1030.8906 | D91: ='1报表'!D87-'2报表调整'!L43+'2报表调整'!L70 -> 812.85134 | E91: ='2报表调整'!G80 -> 286.50368 | F91: =D91+F35+F12*F34 -> 856.10003 | G91: =F91+G35+G12*G34 -> 895.83132 | H91: =G91+H35+H12*H34 -> 937.94327 | I91: =H91+I35+I12*I34 -> 1000.8827 | J91: =I91+J35+J12*J34 -> 1059.8783 | K91: =J91+K35+K12*K34 -> 1113.5113
B92: 少数股东权益 | C92: ='1报表'!C88 -> 0 | D92: ='1报表'!D88 -> 0 | E92: ='1报表'!E88 -> 0 | F92: =D92+(1-F12)*F34 -> 0 | G92: =F92+(1-G12)*G34 -> 0 | H92: =G92+(1-H12)*H34 -> 0 | I92: =H92+(1-I12)*I34 -> 0 | J92: =I92+(1-J12)*J34 -> 0 | K92: =J92+(1-K12)*K34 -> 0
B93: 所有者权益合计 | C93: =C91+C92 -> 1030.8906 | D93: =D91+D92 -> 812.85134 | E93: =E91+E92 -> 286.50368 | F93: =F91+F92 -> 856.10003 | G93: =G91+G92 -> 895.83132 | H93: =H91+H92 -> 937.94327 | I93: =I91+I92 -> 1000.8827 | J93: =J91+J92 -> 1059.8783 | K93: =K91+K92 -> 1113.5113
B94: 负债和所有者权益总计 | C94: =C89+C93 -> 1755.1895 | D94: =D89+D93 -> 1486.3205 | E94: =E89+E93 -> 896.50932 | F94: =F89+F93 -> 1546.9118 | G94: =G89+G93 -> 1656.9487 | H94: =H89+H93 -> 1759.426 | I94: =I89+I93 -> 1859.4398 | J94: =J89+J93 -> 1945.5565 | K94: =K89+K93 -> 2000.3018
B95: 检查核对 | C95: =C64-C94 -> 0 | D95: =D64-D94 -> 0 | E95: =E64-E94 -> 0 | F95: =F64-F94 -> 0 | G95: =G64-G94 -> 0 | H95: =H64-H94 -> 0 | I95: =I64-I94 -> 0 | J95: =J64-J94 -> 0 | K95: =K64-K94 -> 0
B96: 报表是否平衡？ | C96: =IF(ROUND(C95,0),"需要检查","OK") -> OK | D96: =IF(ROUND(D95,0),"需要检查","OK") -> OK | E96: =IF(ROUND(E95,0),"需要检查","OK") -> OK | F96: =IF(ROUND(F95,0),"需要检查","OK") -> OK | G96: =IF(ROUND(G95,0),"需要检查","OK") -> OK | H96: =IF(ROUND(H95,0),"需要检查","OK") -> OK | I96: =IF(ROUND(I95,0),"需要检查","OK") -> OK | J96: =IF(ROUND(J95,0),"需要检查","OK") -> OK | K96: =IF(ROUND(K95,0),"需要检查","OK") -> OK
B97: 报表调平自动计算公式
B98: 扣除溢余现金的资产 | F98: =SUM(F42:F49)+F63 -> 1096.3596 | G98: =SUM(G42:G49)+G63 -> 1185.5446 | H98: =SUM(H42:H49)+H63 -> 1260.4279 | I98: =SUM(I42:I49)+I63 -> 1330.0036 | J98: =SUM(J42:J49)+J63 -> 1369.7902 | K98: =SUM(K42:K49)+K63 -> 1365.5402
B99: 扣除新增借款的负债与权益 | F99: =F73+F81+SUM(F84:F87)+F93 -> 1546.9118 | G99: =G73+G81+SUM(G84:G87)+G93 -> 1656.9487 | H99: =H73+H81+SUM(H84:H87)+H93 -> 1759.426 | I99: =I73+I81+SUM(I84:I87)+I93 -> 1859.4398 | J99: =J73+J81+SUM(J84:J87)+J93 -> 1945.5565 | K99: =K73+K81+SUM(K84:K87)+K93 -> 2000.3018
B100: 溢余现金（新增借款） | F100: =IF(ISERROR(F99-F98),0,F99-F98) -> 450.55217 | G100: =IF(ISERROR(G99-G98),0,G99-G98) -> 471.40401 | H100: =IF(ISERROR(H99-H98),0,H99-H98) -> 498.9981 | I100: =IF(ISERROR(I99-I98),0,I99-I98) -> 529.43627 | J100: =IF(ISERROR(J99-J98),0,J99-J98) -> 575.76628 | K100: =IF(ISERROR(K99-K98),0,K99-K98) -> 634.76159
B102: 经营性投入资本的计算 | K102: 单位：万元
B103: 科目 | C103: =C19 -> 2016年 | D103: =D19 -> 2017年 | E103: =E19 -> 2018年1-6 | F103: =F19 -> 2018年 | G103: =G19 -> 2019年 | H103: =H19 -> 2020年 | I103: =I19 -> 2021年 | J103: =J19 -> 2022年 | K103: =K19 -> 2023年
...
