Workbook
Name _2003_6_25: [1]ITEM!#REF!
Name _2003_6_25: [1]ITEM!#REF!
Name _2003_6_25: [1]ITEM!#REF!
Name _2003_6_25: [1]ITEM!#REF!
Name _2003_6_25: [1]ITEM!#REF!
Name _BSP2: #REF!
Name _BSP2: #REF!
Name _BSP2: #REF!
Name _BSP2: #REF!
Name _BSP2: #REF!
Name _BSP2: #REF!
Name _pgz101: #REF!
Name _pgz101: #REF!
Name _pgz101: #REF!
Name _pgz101: #REF!
Name _pgz101: #REF!
Name _pgz101: #REF!
Name _pgz102: #REF!
Name _pgz102: #REF!
Name _pgz102: #REF!
Name _pgz102: #REF!
Name _pgz102: #REF!
Name _pgz102: #REF!
Name _pgz103: #REF!
Name _pgz103: #REF!
Name _pgz103: #REF!
Name _pgz103: #REF!
Name _pgz103: #REF!
Name _pgz103: #REF!
Name _pgz104: #REF!
Name _pgz104: #REF!
Name _pgz104: #REF!
Name _pgz104: #REF!
Name _pgz104: #REF!
Name _pgz104: #REF!
Name _pgz105: #REF!
Name _pgz105: #REF!
Name _pgz105: #REF!
Name _pgz105: #REF!
Name _pgz105: #REF!
Name _pgz105: #REF!
Name _pgz106: #REF!
Name _pgz106: #REF!
Name _pgz106: #REF!
Name _pgz106: #REF!
Name _pgz106: #REF!
Name _pgz106: #REF!
Name _pgz511: #REF!
Name _pgz511: #REF!
Name _pgz511: #REF!
Name _pgz511: #REF!
Name _pgz511: #REF!
Name _pgz511: #REF!
Name _pgz512: #REF!
Name _pgz512: #REF!
Name _pgz512: #REF!
Name _pgz512: #REF!
Name _pgz512: #REF!
Name _pgz512: #REF!
Name _pgz513: #REF!

Sheet 记事
C2: 应用前提
C3: 1、稳定期增长率假设为零，如考虑永续增长，终值需另外用价值驱动因素模型计算。
C4: 2、未考虑预测期内被评估企业依靠收购所创造的收入增长。
C5: 3、FCFE模型只适用评估基准日及未来预测期间无付息负债的情形。
C6: 建模的规则
C7: 表中数字 | D7: 蓝字黄底表示手动录入数据
C8: 表中数字 | D8: 红字表示在该单元格中的公式左右不一样，或强调关注。
D9: 同一年的数据在不同表中均在同一列中，方便查找错误。
D10: 不要隐藏行和列，采用数据中的创建组和取消组合处理，易于查找数据。
D11: 单元格中的公式不要直接写入数据，数据由表外单元格链入。
D12: 工作底稿完成后无关数据全部删除，只保留有关数据。
C14: 密码0528
C15: V5.0修改记录
C17: 1、表“7折旧”、“8摊销”、“9溢余现金”、“10营运”进行拆分，表“7折旧”和“8摊销”“+”后隐藏的是自动计算公式，一般无需改动。
C18: 限制用途现金位置进行了移动；“9溢余现金”、“10营运”，增加了历史数据分析，反映趋势变化。
C19: 2、表“预测财报”布局调整：增加完成资产负债表、利润表剩余项目，后面报表自动计算得出财务指标，用于分析历史与未来趋势。
C20: 预测资产负债表可以合理分析企业未来的借款金额。
C21: 3、表“9财务费用”末端行增加(由预测资产负债表计算得出)新增借款，反映企业未来是否有资金缺口，需要融多少资金。
C22: 4、表“13FCFF”修改折现率计算方法——迭代计算。
C24: V5.1修改记录
C25: 1、表“7折旧”行42即“期末设备类账面净值”公式汇总错误，已修改。该行数据不影响估值，但影响“预测财报”数据。

Sheet 步骤
E1: 索引号：SY1
B2: 企业价值评估现金流量折现法(DCF)计算及步骤复核表
B3: ='1报表'!B12 -> 被评估单位：JSBD公司 | D3: 评估基准日 | E3: ='1报表'!E5 -> 43100
B4: 评估人员 | D4: 现场工作日期
B5: 复核人 | D5: 复核日期
B6: 操作步骤与要求 | D6: 是 | E6: 不适用
B7: 一、前期工作
B8: 1.取得被评估企业前3~5年和本期审计报告、会计报表、科目明细表，以及相关收入、成本、费用等统计资料
B9: 2.取得企业资产、财务、经营状况资料，着重了解经营活动涉及的范围，收入、收益结构，资产配置情况，在此基础上区分企业经营活动和经营活动之外的其他活动涉及相关资产、负债、损益等。布置企业填报资产基础法申报表、收益预测申报表，并在资产基础法的申报表上标识经营性资产（负债）与非经营性资产（负债）。以上资料由企业盖章或签字确认。
B10: 二、统计、调整
B11: 3.根据评估业务的具体情况，在分析企业各科目明细的基础上，分析和调整被评估企业（1）财务报表编制基础；（2）非经常性收入和支出；（3）非经营性资产、负债和溢余资产及其相关的收入和支出。如涉及可比企业同理处理。
B12: 4.区分经营活动与其他活动，并统计、分析： a\营业收入；b\营业成本(材料、燃料动力、人工、制造费用)；c\税金及附加；d\折旧及摊销、固定及无形资产、长期待摊；e\销售、管理费用；f\资产减值损失、公允价值变动收益；g\营业外收支；h\财务费用
B13: 5.区分经营活动和其他活动，编制利润调整表
B14: 6.计算经营最低保有现金，测算溢余现金
B15: 7.区分经营活动和其他活动编制资产负债调整表
B16: 8.根据调整后的资产负债表、利润表，分析历史财务指标。
B17: 9.正确识别被评估企业所属行业，审慎选择参考上市公司，并统计相关财务指标
B18: 三、分析、预测
... B40: 金融资产、未并表的长期股权投资、投资性房地产以及溢余及非经营资产、负债等相关活动。

Sheet 1报表
B2: 输入信息
B3: 被评估单位： | E3: JSBD公司
B4: 评估对象： | E4: 股东全部权益价值
B5: 评估基准日： | E5: 43100
B6: 短期预测(期)： | E6: 5
B7: 预测期间： | C7: =E5+1 -> 43101 | D7: To | E7: =EDATE(E5,E6*12) -> 44926
B10: 资产负债表
B11: =B5&TEXT(E5,"YYYY/M/D") -> 评估基准日：2017/12/31
B12: =B3&E3 -> 被评估单位：JSBD公司 | E12: 单位：万元
B13: 科目 | C13: =EDATE(D13,-12) -> 42369 | D13: =EDATE(E13,-12) -> 42735 | E13: =E5 -> 43100
B14: 流动资产：
B15: 货币资金 | C15: 107.23511 | D15: 232.26688 | E15: 276.81451
B16: 以公允价值计量且其变动计入当期损益的金融资产
B17: 衍生金融资产
B18: 应收票据及应收账款 | C18: =9+2168.895942 -> 2177.8959 | D18: =97.73602+2520.404145 -> 2618.1402 | E18: =293.613289+3142.781439 -> 3436.3947
B19: 预付款项 | C19: 163.1034 | D19: 99.846675 | E19: 52.493946
A20: 保留 | B20: 应收利息
A21: 保留 | B21: 应收股利
B22: 其他应收款 | C22: 113.81446 | D22: 191.70885 | E22: 52.199492
B23: 存货 | C23: 879.74901 | D23: 1054.9352 | E23: 1331.2815
A24: 新准则 | B24: 合同资产
B25: 持有待售资产
B26: 一年内到期的非流动资产
B27: 其他流动资产 | C27: 34.793744 | D27: 21.197218 | E27: 162.85866
B28: 流动资产合计 | C28: =SUM(C15:C27) -> 3476.5917 | D28: =SUM(D15:D27) -> 4218.095 | E28: =SUM(E15:E27) -> 5312.0429
B29: 非流动资产：
B30: 可供出售金融资产
B31: 持有至到期投资
A32: 新准则 | B32: 债权投资
A33: 新准则 | B33: 其他债权投资
B34: 长期应收款
B35: 长期股权投资
A36: 新准则 | B36: 其他权益工具投资
A37: 新准则 | B37: 其他非流动金融资产
B38: 投资性房地产
B39: 固定资产 | C39: 2374.1047 | D39: 2109.0141 | E39: 2328.7283
B40: 在建工程 | E40: 201.28205
B41: 生产性生物资产
B42: 油气资产
B43: 无形资产 | C43: 317.96748 | D43: 306.03733 | E43: 459.60841
B44: 开发支出
B45: 商誉
B46: 长期待摊费用
B47: 递延所得税资产 | C47: 77.510453 | D47: 88.215967 | E47: 101.06477
B48: 其他非流动资产 | C48: 28.32889 | D48: 294.362 | E48: 191.69743
B49: 非流动资产合计 | C49: =SUM(C30:C48) -> 2797.9116 | D49: =SUM(D30:D48) -> 2797.6294 | E49: =SUM(E30:E48) -> 3282.381
B50: 资产总计 | C50: =C28+C49 -> 6274.5032 | D50: =D28+D49 -> 7015.7244 | E50: =E28+E49 -> 8594.4239
B51: 流动负债：
B52: 短期借款 | C52: 900 | D52: 1100 | E52: 1000
B53: 以公允价值计量且其变动计入当期损益的金融负债
B54: 衍生金融负债
B55: 应付票据及应付账款 | C55: 417.61032 | D55: 1037.928 | E55: 1346.0374
B56: 预收款项 | C56: 131.76532 | D56: 195.99939 | E56: 351.09636
A57: 新准则 | B57: 合同负债
B58: 应付职工薪酬 | C58: 132.57767 | D58: 163.35175 | E58: 345.76284
B59: 应交税费 | C59: 104.3759 | D59: 117.08402 | E59: 225.302
A60: 保留 | B60: 应付利息 | E60: 1.510417
A61: 保留 | B61: 应付股利
B62: 其他应付款 | C62: 1493.8281 | D62: 1824.9313 | E62: 1487.8203
B63: 持有待售负债
B64: 一年内到期的非流动负债 | C64: 1150
B65: 其他流动负债
B66: 流动负债合计 | C66: =SUM(C52:C65) -> 4330.1573 | D66: =SUM(D52:D65) -> 4439.2944 | E66: =SUM(E52:E65) -> 4757.5293
B67: 非流动负债：
B68: 长期借款
B69: 应付债券
B70: 长期应付款
A71: 合并 | B71: 长期应付职工薪酬
B72: 预计负债
B73: 递延收益
B74: 递延所得税负债
B75: 其他非流动负债
B76: 非流动负债合计 | C76: =SUM(C68:C75) -> 0 | D76: =SUM(D68:D75) -> 0 | E76: =SUM(E68:E75) -> 0
B77: 负债合计 | C77: =C66+C76 -> 4330.1573 | D77: =D66+D76 -> 4439.2944 | E77: =E66+E76 -> 4757.5293
B78: 所有者权益：
B79: 实收资本 | C79: 1320 | D79: 1320 | E79: 1320
B80: 其他权益工具
B81: 资本公积 | C81: 204.62 | D81: 204.62 | E81: 1235.9069
B82: 减：库存股
B83: 其他综合收益
B84: 盈余公积 | C84: 137.00097 | D84: 199.6863 | E84: 128.28416
A85: 合并 | B85: 一般风险准备
B86: 未分配利润 | C86: 282.72496 | D86: 852.12363 | E86: 1152.7036
B87: 归属于母公司所有者权益合计 | C87: =SUM(C79:C81)-C82+SUM(C83:C86) -> 1944.3459 | D87: =SUM(D79:D81)-D82+SUM(D83:D86) -> 2576.4299 | E87: =SUM(E79:E81)-E82+SUM(E83:E86) -> 3836.8946
B88: 少数股东权益
B89: 所有者权益合计 | C89: =C87+C88 -> 1944.3459 | D89: =D87+D88 -> 2576.4299 | E89: =E87+E88 -> 3836.8946
B90: 负债和所有者权益总计 | C90: =C77+C89 -> 6274.5032 | D90: =D77+D89 -> 7015.7244 | E90: =E77+E89 -> 8594.4239
B91: 检查核对 | C91: =C50-C90 -> 0 | D91: =D50-D90 -> 0 | E91: =E50-E90 -> 0
B92: 报表是否平衡？ | C92: =IF(ROUND(C91,0)=0,"OK","需要检查") -> OK | D92: =IF(ROUND(D91,0)=0,"OK","需要检查") -> OK | E92: =IF(ROUND(E91,0)=0,"OK","需要检查") -> OK
B93: 利润表
B94: =B11 -> 评估基准日：2017/12/31
B95: =B12 -> 被评估单位：JSBD公司 | E95: 单位：万元
B96: 科目 | C96: =YEAR(C13)&"年" -> 2015年 | D96: =YEAR(D13)&"年" -> 2016年 | E96: =YEAR(E13)&"年" -> 2017年
B97: 一、营业收入 | C97: 5647.5609 | D97: 7304.7745 | E97: 9615.5763
B98: 减：营业成本 | C98: 3450.9962 | D98: 4625.6862 | E98: 5762.986
B99: 税金及附加 | C99: 53.873421 | D99: 81.416231 | E99: 113.39456
B100: 销售费用 | C100: 481.4591 | D100: 588.55087 | E100: 750.19684
B101: 管理费用 | C101: 694.30698 | D101: 710.43654 | E101: 1052.4467
B102: 研发费用 | C102: 384.83578 | D102: 369.90657 | E102: 435.369
B103: 财务费用 | C103: 131.45509 | D103: 111.81699 | E103: 100.04826
...

Sheet 2报表调整
B2: 资产负债调整表 | J2: 非经营性资产和负债分析表
B3: ='1报表'!B11 -> 评估基准日：2017/12/31 | K3: 根据资产负债核实表填写
B4: ='1报表'!B12 -> 被评估单位：JSBD公司 | H4: 单位：万元
B5: 科目 | C5: ='1报表'!E13 -> 43100 | N5: 单位：万元
C6: 账面值 | D6: 重分类 | E6: 其中：非经营性资产、负债 | F6: 溢余资产 | G6: 经营性资产及负债账面值 | H6: 调整原因 | J6: 项目 | K6: ='1报表'!C13 -> 42369 | L6: ='1报表'!D13 -> 42735 | M6: ='1报表'!E13 -> 43100 | N6: 评估值
B7: 流动资产： | J7: 非经营性资产
B8: 货币资金 | C8: ='1报表'!E15 -> 276.81451 | D8: =C8 -> 276.81451 | F8: ='9溢余现金'!E25 -> 37.453128 | G8: =D8-(E8+F8) -> 239.36138 | J8: 货币资金
B9: 交易性金融资产 | C9: ='1报表'!E16 -> 0 | D9: =C9 -> 0 | G9: =D9-(E9+F9) -> 0 | J9: 交易性金融资产 | K9: ='1报表'!C16 -> 0 | L9: ='1报表'!D16 -> 0 | M9: =E9 -> 0 | N9: =M9 -> 0
B10: 衍生金融资产 | C10: ='1报表'!E17 -> 0 | D10: =C10 -> 0 | G10: =D10-(E10+F10) -> 0 | J10: 衍生金融资产 | K10: ='1报表'!C17 -> 0 | L10: ='1报表'!D17 -> 0 | M10: =E10 -> 0 | N10: =M10 -> 0
B11: 应收票据及应收账款 | C11: ='1报表'!E18 -> 3436.3947 | D11: =C11 -> 3436.3947 | G11: =D11-(E11+F11) -> 3436.3947 | J11: 非经营性应收票据及应收账款 | M11: =E11 -> 0 | N11: =M11 -> 0
B12: 预付款项 | C12: ='1报表'!E19 -> 52.493946 | D12: =C12 -> 52.493946 | E12: 8.943124 | G12: =D12-(E12+F12) -> 43.550822 | H12: 费用性质无票挂账款项 | J12: 非经营性预付款项 | M12: =E12 -> 8.943124 | N12: 0
B13: 应收利息 | C13: ='1报表'!E20 -> 0 | D13: =C13 -> 0 | G13: =D13-(E13+F13) -> 0 | J13: 应收利息 | K13: ='1报表'!C20 -> 0 | L13: ='1报表'!D20 -> 0 | M13: =E13 -> 0 | N13: =M13 -> 0
B14: 应收股利 | C14: ='1报表'!E21 -> 0 | D14: =C14 -> 0 | G14: =D14-(E14+F14) -> 0 | J14: 应收股利 | K14: ='1报表'!C21 -> 0 | L14: ='1报表'!D21 -> 0 | M14: =E14 -> 0 | N14: =M14 -> 0
B15: 其他应收款 | C15: ='1报表'!E22 -> 52.199492 | D15: =C15 -> 52.199492 | E15: 29.88 | G15: =D15-(E15+F15) -> 22.319492 | J15: 非经营性其他应收款 | M15: =E15 -> 29.88 | N15: =D95 -> 5.880218
B16: 存货 | C16: ='1报表'!E23 -> 1331.2815 | D16: =C16 -> 1331.2815 | G16: =D16-(E16+F16) -> 1331.2815 | J16: 非经营、报废的存货 | M16: =E16 -> 0 | N16: =M16 -> 0
B17: 合同资产 | C17: ='1报表'!E24 -> 0 | D17: =C17 -> 0 | G17: =D17-(E17+F17) -> 0 | J17: 非经营性合同资产 | M17: =E17 -> 0 | N17: =M17 -> 0
B18: 持有待售资产 | C18: ='1报表'!E25 -> 0 | D18: =C18 -> 0 | G18: =D18-(E18+F18) -> 0 | J18: 持有待售资产 | K18: ='1报表'!C25 -> 0 | L18: ='1报表'!D25 -> 0 | M18: =E18 -> 0 | N18: =M18 -> 0
B19: 一年内到期的非流动资产 | C19: ='1报表'!E26 -> 0 | D19: =C19 -> 0 | G19: =D19-(E19+F19) -> 0 | J19: 非经营性一年内到期的非流动资产 | M19: =E19 -> 0 | N19: =M19 -> 0
B20: 其他流动资产 | C20: ='1报表'!E27 -> 162.85866 | D20: =C20 -> 162.85866 | E20: 77.8 | G20: =D20-(E20+F20) -> 85.05866 | H20: 理财产品 | J20: 非经营性其他流动资产 | M20: =E20 -> 77.8 | N20: =M20 -> 77.8
B21: 流动资产合计 | C21: =SUM(C8:C20) -> 5312.0429 | D21: =SUM(D8:D20) -> 5312.0429 | E21: =SUM(E8:E20) -> 116.62312 | F21: =SUM(F8:F20) -> 37.453128 | G21: =SUM(G8:G20) -> 5157.9666 | J21: 非经营性流动资产小计 | K21: =SUM(K9:K20) -> 0 | L21: =SUM(L9:L20) -> 0 | M21: =SUM(M9:M20) -> 116.62312 | N21: =SUM(N9:N20) -> 83.680218
B22: 非流动资产：
B23: 可供出售金融资产 | C23: ='1报表'!E30 -> 0 | D23: =C23 -> 0 | G23: =D23-(E23+F23) -> 0 | J23: 可供出售金融资产 | K23: ='1报表'!C30 -> 0 | L23: ='1报表'!D30 -> 0 | M23: =E23 -> 0
B24: 持有至到期投资 | C24: ='1报表'!E31 -> 0 | D24: =C24 -> 0 | G24: =D24-(E24+F24) -> 0 | J24: 持有至到期投资 | K24: ='1报表'!C31 -> 0 | L24: ='1报表'!D31 -> 0 | M24: =E24 -> 0
B25: 债权投资 | C25: ='1报表'!E32 -> 0 | D25: =C25 -> 0 | G25: =D25-(E25+F25) -> 0 | J25: 债权投资 | K25: ='1报表'!C32 -> 0 | L25: ='1报表'!D32 -> 0 | M25: =E25 -> 0
B26: 其他债权投资 | C26: ='1报表'!E33 -> 0 | D26: =C26 -> 0 | G26: =D26-(E26+F26) -> 0 | J26: 其他债权投资 | K26: ='1报表'!C33 -> 0 | L26: ='1报表'!D33 -> 0 | M26: =E26 -> 0
B27: 长期应收款 | C27: ='1报表'!E34 -> 0 | D27: =C27 -> 0 | G27: =D27-(E27+F27) -> 0 | J27: 非经营性长期应收款 | M27: =E27 -> 0
B28: 长期股权投资 | C28: ='1报表'!E35 -> 0 | D28: =C28 -> 0 | G28: =D28-(E28+F28) -> 0 | J28: 长期股权投资 | K28: ='1报表'!C35 -> 0 | L28: ='1报表'!D35 -> 0 | M28: =E28 -> 0
B29: 其他权益工具投资 | C29: ='1报表'!E36 -> 0 | D29: =C29 -> 0 | G29: =D29-(E29+F29) -> 0 | J29: 其他权益工具投资 | K29: ='1报表'!C36 -> 0 | L29: ='1报表'!D36 -> 0 | M29: =E29 -> 0
B30: 其他非流动金融资产 | C30: ='1报表'!E37 -> 0 | D30: =C30 -> 0 | G30: =D30-(E30+F30) -> 0 | J30: 其他非流动金融资产 | K30: ='1报表'!C37 -> 0 | L30: ='1报表'!D37 -> 0 | M30: =E30 -> 0
B31: 投资性房地产 | C31: ='1报表'!E38 -> 0 | D31: =C31 -> 0 | G31: =D31-(E31+F31) -> 0 | J31: 投资性房地产 | K31: ='1报表'!C38 -> 0 | L31: ='1报表'!D38 -> 0 | M31: =E31 -> 0
B32: 固定资产 | C32: ='1报表'!E39 -> 2328.7283 | D32: =C32 -> 2328.7283 | G32: =D32-(E32+F32) -> 2328.7283 | J32: 非经营性固定资产 | M32: =E32 -> 0
B33: 在建工程 | C33: ='1报表'!E40 -> 201.28205 | D33: =C33+153.51675 -> 354.7988 | G33: =D33-(E33+F33) -> 354.7988 | J33: 非经营性在建工程 | M33: =E33 -> 0
B34: 生产性生物资产 | C34: ='1报表'!E41 -> 0 | D34: =C34 -> 0 | G34: =D34-(E34+F34) -> 0 | J34: 非经营性生产性生物资产 | M34: =E34 -> 0
B35: 油气资产 | C35: ='1报表'!E42 -> 0 | D35: =C35 -> 0 | G35: =D35-(E35+F35) -> 0 | J35: 非经营性油气资产 | M35: =E35 -> 0
B36: 无形资产 | C36: ='1报表'!E43 -> 459.60841 | D36: =C36 -> 459.60841 | G36: =D36-(E36+F36) -> 459.60841 | J36: 非经营性无形资产 | M36: =E36 -> 0
B37: 开发支出 | C37: ='1报表'!E44 -> 0 | D37: =C37 -> 0 | G37: =D37-(E37+F37) -> 0 | J37: 非经营性开发支出 | M37: =E37 -> 0
B38: 商誉 | C38: ='1报表'!E45 -> 0 | D38: =C38 -> 0 | G38: =D38-(E38+F38) -> 0 | J38: 商誉
B39: 长期待摊费用 | C39: ='1报表'!E46 -> 0 | D39: =C39 -> 0 | G39: =D39-(E39+F39) -> 0 | J39: 非经营性长期待摊费用 | M39: =E39 -> 0
B40: 递延所得税资产 | C40: ='1报表'!E47 -> 101.06477 | D40: =C40 -> 101.06477 | G40: =D40-(E40+F40) -> 101.06477 | J40: 递延所得税资产 | M40: =E40 -> 0
B41: 其他非流动资产 | C41: ='1报表'!E48 -> 191.69743 | D41: =C41-153.51675 -> 38.18068 | G41: =D41-(E41+F41) -> 38.18068 | H41: 设备款153.51675万元，重分类到在建工程 | J41: 非经营性其他非流动资产 | M41: =E41 -> 0
B42: 非流动资产合计 | C42: =SUM(C23:C41) -> 3282.381 | D42: =SUM(D23:D41) -> 3282.381 | E42: =SUM(E23:E41) -> 0 | F42: =SUM(F23:F41) -> 0 | G42: =SUM(G23:G41) -> 3282.381 | J42: 非经营性非流动资产小计 | K42: =SUM(K23:K41) -> 0 | L42: =SUM(L23:L41) -> 0 | M42: =SUM(M23:M41) -> 0 | N42: =SUM(N23:N41) -> 0
B43: 资产总计 | C43: =C21+C42 -> 8594.4239 | D43: =D21+D42 -> 8594.4239 | E43: =E21+E42 -> 116.62312 | F43: =F21+F42 -> 37.453128 | G43: =G21+G42 -> 8440.3476 | J43: 非经营性资产合计 | K43: =K21+K42 -> 0 | L43: =L21+L42 -> 0 | M43: =M21+M42 -> 116.62312 | N43: =N21+N42 -> 83.680218
B44: 流动负债： | J44: 非经营性负债 | K44: =K6 -> 42369 | L44: =L6 -> 42735 | M44: =M6 -> 43100 | N44: =N6 -> 评估值
B45: 短期借款 | C45: ='1报表'!E52 -> 1000 | D45: =C45 -> 1000 | G45: =D45-(E45+F45) -> 1000 | J45: 短期借款
B46: 交易性金融负债 | C46: ='1报表'!E53 -> 0 | D46: =C46 -> 0 | G46: =D46-(E46+F46) -> 0 | J46: 交易性金融负债 | K46: ='1报表'!C53 -> 0 | L46: ='1报表'!D53 -> 0 | M46: =E46 -> 0 | N46: =M46 -> 0
B47: 衍生金融负债 | C47: ='1报表'!E54 -> 0 | D47: =C47 -> 0 | G47: =D47-(E47+F47) -> 0 | J47: 衍生金融负债 | K47: ='1报表'!C54 -> 0 | L47: ='1报表'!D54 -> 0 | M47: =E47 -> 0 | N47: =M47 -> 0
B48: 应付票据及应付账款 | C48: ='1报表'!E55 -> 1346.0374 | D48: =C48-88.34 -> 1257.6974 | G48: =D48-(E48+F48) -> 1257.6974 | H48: 17年应付设备款88.34万元，重分类到其他应付款 | J48: 非经营性应付票据及应付账款 | M48: =E48 -> 0 | N48: =M48 -> 0
B49: 预收款项 | C49: ='1报表'!E56 -> 351.09636 | D49: =C49 -> 351.09636 | G49: =D49-(E49+F49) -> 351.09636 | J49: 非经营性预收款项 | M49: =E49 -> 0 | N49: =M49 -> 0
B50: 合同负债 | C50: ='1报表'!E57 -> 0 | D50: =C50 -> 0 | G50: =D50-(E50+F50) -> 0 | J50: 非经营性合同负债 | M50: =E50 -> 0 | N50: =M50 -> 0
B51: 应付职工薪酬 | C51: ='1报表'!E58 -> 345.76284 | D51: =C51 -> 345.76284 | G51: =D51-(E51+F51) -> 345.76284 | J51: 非经营性应付职工薪酬 | M51: =E51 -> 0 | N51: =M51 -> 0
B52: 应交税费 | C52: ='1报表'!E59 -> 225.302 | D52: =C52 -> 225.302 | G52: =D52-(E52+F52) -> 225.302 | J52: 应交税费
B53: 应付利息 | C53: ='1报表'!E60 -> 1.510417 | D53: =C53 -> 1.510417 | E53: 1.510417 | G53: =D53-(E53+F53) -> 0 | J53: 应付利息 | K53: ='1报表'!C60 -> 0 | L53: ='1报表'!D60 -> 0 | M53: =E53 -> 1.510417 | N53: =M53 -> 1.510417
B54: 应付股利 | C54: ='1报表'!E61 -> 0 | D54: =C54 -> 0 | G54: =D54-(E54+F54) -> 0 | J54: 应付股利 | K54: ='1报表'!C61 -> 0 | L54: ='1报表'!D61 -> 0 | M54: =E54 -> 0 | N54: =M54 -> 0
B55: 其他应付款 | C55: ='1报表'!E62 -> 1487.8203 | D55: =C55+88.34 -> 1576.1603 | E55: 1415.0058 | G55: =D55-(E55+F55) -> 161.15448 | J55: 非经营性其他应付款 | M55: =E55 -> 1415.0058 | N55: =D104 -> 1413.7342
B56: 持有待售负债 | C56: ='1报表'!E63 -> 0 | D56: =C56 -> 0 | G56: =D56-(E56+F56) -> 0 | J56: 持有待售负债 | K56: ='1报表'!C63 -> 0 | L56: ='1报表'!D63 -> 0 | M56: =E56 -> 0 | N56: =M56 -> 0
B57: 一年内到期的非流动负债 | C57: ='1报表'!E64 -> 0 | D57: =C57 -> 0 | G57: =D57-(E57+F57) -> 0 | J57: 一年内到期的非流动负债
B58: 其他流动负债 | C58: ='1报表'!E65 -> 0 | D58: =C58 -> 0 | G58: =D58-(E58+F58) -> 0 | J58: 非经营性其他流动负债 | M58: =E58 -> 0 | N58: =M58 -> 0
B59: 流动负债合计 | C59: =SUM(C45:C58) -> 4757.5293 | D59: =SUM(D45:D58) -> 4757.5293 | E59: =SUM(E45:E58) -> 1416.5162 | F59: =SUM(F45:F58) -> 0 | G59: =SUM(G45:G58) -> 3341.0131 | J59: 非经营性流动负债小计 | K59: =SUM(K46:K58) -> 0 | L59: =SUM(L46:L58) -> 0 | M59: =SUM(M46:M58) -> 1416.5162 | N59: =SUM(N46:N58) -> 1415.2446
B60: 非流动负债：
B61: 长期借款 | C61: ='1报表'!E68 -> 0 | D61: =C61 -> 0 | G61: =D61-(E61+F61) -> 0 | J61: 长期借款
B62: 应付债券 | C62: ='1报表'!E69 -> 0 | D62: =C62 -> 0 | G62: =D62-(E62+F62) -> 0 | J62: 应付债券
B63: 长期应付款 | C63: ='1报表'!E70 -> 0 | D63: =C63 -> 0 | G63: =D63-(E63+F63) -> 0 | J63: 非经营性长期应付款 | M63: =E63 -> 0
B64: 长期应付职工薪酬 | C64: ='1报表'!E71 -> 0 | D64: =C64 -> 0 | G64: =D64-(E64+F64) -> 0 | J64: 非经营性长期应付职工薪酬 | M64: =E64 -> 0
B65: 预计负债 | C65: ='1报表'!E72 -> 0 | D65: =C65 -> 0 | G65: =D65-(E65+F65) -> 0 | J65: 非经营性预计负债 | M65: =E65 -> 0
B66: 递延收益 | C66: ='1报表'!E73 -> 0 | D66: =C66 -> 0 | G66: =D66-(E66+F66) -> 0 | J66: 非经营性递延收益 | M66: =E66 -> 0
B67: 递延所得税负债 | C67: ='1报表'!E74 -> 0 | D67: =C67 -> 0 | G67: =D67-(E67+F67) -> 0 | J67: 递延所得税负债 | M67: =E67 -> 0
B68: 其他非流动负债 | C68: ='1报表'!E75 -> 0 | D68: =C68 -> 0 | G68: =D68-(E68+F68) -> 0 | J68: 非经营性其他非流动负债 | M68: =E68 -> 0
B69: 非流动负债合计 | C69: =SUM(C61:C68) -> 0 | D69: =SUM(D61:D68) -> 0 | E69: =SUM(E61:E68) -> 0 | F69: =SUM(F61:F68) -> 0 | G69: =SUM(G61:G68) -> 0 | J69: 非经营性非流动负债小计 | K69: =SUM(K63:K68) -> 0 | L69: =SUM(L63:L68) -> 0 | M69: =SUM(M63:M68) -> 0 | N69: =SUM(N63:N68) -> 0
B70: 负债合计 | C70: =C59+C69 -> 4757.5293 | D70: =D59+D69 -> 4757.5293 | E70: =E59+E69 -> 1416.5162 | F70: =F59+F69 -> 0 | G70: =G59+G69 -> 3341.0131 | J70: 非经营性负债合计 | K70: =K59+K69 -> 0 | L70: =L59+L69 -> 0 | M70: =M59+M69 -> 1416.5162 | N70: =N59+N69 -> 1415.2446
B71: 所有者权益：
B72: 实收资本 | C72: ='1报表'!E79 -> 1320 | D72: =C72 -> 1320
B73: 其他权益工具 | C73: ='1报表'!E80 -> 0 | D73: =C73 -> 0
B74: 资本公积 | C74: ='1报表'!E81 -> 1235.9069 | D74: =C74 -> 1235.9069
B75: 减：库存股 | C75: ='1报表'!E82 -> 0 | D75: =C75 -> 0
B76: 其他综合收益 | C76: ='1报表'!E83 -> 0 | D76: =C76 -> 0
B77: 盈余公积 | C77: ='1报表'!E84 -> 128.28416 | D77: =C77 -> 128.28416
B78: 一般风险准备 | C78: ='1报表'!E85 -> 0 | D78: =C78 -> 0
B79: 未分配利润 | C79: ='1报表'!E86 -> 1152.7036 | D79: =C79 -> 1152.7036
B80: 归属于母公司所有者权益合计 | C80: =SUM(C72:C74)-C75+SUM(C76:C79) -> 3836.8946 | D80: =SUM(D72:D74)-D75+SUM(D76:D79) -> 3836.8946 | E80: =E82-E81 -> -1299.8931 | F80: =F43-F70 -> 37.453128 | G80: =D80-(E80+F80) -> 5099.3346
B81: 少数股东权益 | C81: ='1报表'!E88 -> 0 | D81: =C81 -> 0 | G81: =D81-(E81+F81) -> 0
B82: 所有者权益合计 | C82: =C80+C81 -> 3836.8946 | D82: =D80+D81 -> 3836.8946 | E82: =E43-E70 -> -1299.8931 | F82: =F43-F70 -> 37.453128 | G82: =D82-(E82+F82) -> 5099.3346
B83: 负债和所有者权益总计 | C83: =C70+C82 -> 8594.4239 | D83: =D70+D82 -> 8594.4239 | G83: =G70+G82 -> 8440.3476
B84: 检查核对 | C84: =C43-C83 -> 0 | D84: =D43-D83 -> 0 | G84: =G43-G83 -> 0
B85: 平衡检查？ | C85: =IF(ROUND(C84,0)=0,"OK","需要检查") -> OK | D85: =IF(ROUND(D84,0)=0,"OK","需要检查") -> OK | G85: =IF(ROUND(G84,0)=0,"OK","需要检查") -> OK
B88: 预付款项 | C88: 账面值 | D88: 评估值
B89: 费用性质无票挂账款项 | C89: 8.943124 | D89: 0
B91: 其他应收款 | C91: 账面值 | D91: 评估值
B92: 北京xxx机械制造有限责任公司 | C92: 24 | D92: 0
B93: 世博宝得冷热科技江阴有限公司 | C93: 3 | D93: 3
B94: 员工暂借款 | C94: 2.880218 | D94: 2.880218
B95: 合计 | C95: =SUM(C92:C94) -> 29.880218 | D95: =SUM(D92:D94) -> 5.880218
B97: 其他应付款
B98: xl个人 | C98: 75.16938 | D98: 75.16938
B99: glq个人 | C99: 61.50222 | D99: 61.50222
B100: xx市财政局非税收入专户 | C100: 1.27156 | D100: 0
B101: xl个人 | C101: 666.46262 | D101: 666.46262
B102: xp个人 | C102: 520.6 | D102: 520.6
B103: glq个人 | C103: 90 | D103: 90
B104: 合计 | C104: =SUM(C98:C103) -> 1415.0058 | D104: =SUM(D98:D103) -> 1413.7342

Sheet 3收入
B1: 营业收入预测表
B2: ='1报表'!B11 -> 评估基准日：2017/12/31
B3: ='1报表'!B12 -> 被评估单位：JSBD公司 | J3: 单位：万元
B4: 年度 | C4: ='1报表'!C96 -> 2015年 | D4: ='1报表'!D96 -> 2016年 | E4: ='1报表'!E96 -> 2017年 | F4: =LEFT(E4,4)+1&"年" -> 2018年 | G4: =LEFT(F4,4)+1&"年" -> 2019年 | H4: =LEFT(G4,4)+1&"年" -> 2020年 | I4: =LEFT(H4,4)+1&"年" -> 2021年 | J4: =LEFT(I4,4)+1&"年" -> 2022年
B5: 数据汇总 | C5: ='1报表'!C97 -> 5647.5609 | D5: ='1报表'!D97 -> 7304.7745 | E5: ='1报表'!E97 -> 9615.5763 | F5: =F60 -> 11935.477 | G5: =G60 -> 14141.384 | H5: =H60 -> 15896.18 | I5: =I60 -> 16863.123 | J5: =J60 -> 17224.451
B6: 增长率 | D6: =IF(C5,D5/C5-1,"na") -> 0.29343883 | E6: =IF(D5,E5/D5-1,"na") -> 0.31634129 | F6: =IF(E5,F5/E5-1,"na") -> 0.24126489 | G6: =IF(F5,G5/F5-1,"na") -> 0.18481929 | H6: =IF(G5,H5/G5-1,"na") -> 0.12408942 | I6: =IF(H5,I5/H5-1,"na") -> 0.060828626 | J6: =IF(I5,J5/I5-1,"na") -> 0.021427138
B8: 项目 | D8: 2015年 | E8: 2016年 | F8: 2017年
B9: 内销 | C9: 可拆 | D9: 849.25232 | E9: 761.74943 | F9: 881.84195 | H9: 营业收入：主营业务收入、其他业务收入
C10: 钎焊 | D10: 3332.4019 | E10: 5230.7696 | F10: 7346.3833 | H10: 非经常性收入调整，形成新的增长率指标。
C11: 其他 | D11: 62.584148 | E11: 126.49229 | F11: 169.47457 | H11: 核实产能的天花板：重点预测期第一年（2018）
B12: 外销 | C12: 可拆 | D12: 189.80228 | E12: 103.84241 | F12: 188.39998 | H12: 后期收入的增长原因分析：
C13: 钎焊 | D13: 759.94412 | E13: 659.68712 | F13: 515.85933 | H13: 价格、产品结构调整→→组合价格的提高
C14: 其他 | D14: 288.58919 | E14: 163.05443 | F14: 294.8955 | H14: 增加资本性支出，提高产能→→原资本性支出不足，提高了支出金额→→ROIC
B15: 材料及板片 | D15: 164.98691 | E15: 259.17922 | F15: 218.72166 | H15: 行业增长率分析→→核实验证
B16: 合计 | D16: =SUM(D9:D15) -> 5647.5609 | E16: =SUM(E9:E15) -> 7304.7745 | F16: =SUM(F9:F15) -> 9615.5763
H17: 如果历史营业收入和成本中的其他收入和成本，未来预测收入成本中没有，则历史报表项需要调整。例如投资性房地产
B18: 按产品分类
B19: 收入分析 | C19: 2015年 | D19: 2016年 | E19: 2017年
B20: 可拆 | C20: =D9+D12 -> 1039.0546 | D20: =E9+E12 -> 865.59183 | E20: =F9+F12 -> 1070.2419
B21: 钎焊 | C21: =D10+D13 -> 4092.346 | D21: =E10+E13 -> 5890.4567 | E21: =F10+F13 -> 7862.2427
B22: 其他 | C22: =D11+D14 -> 351.17334 | D22: =E11+E14 -> 289.54672 | E22: =F11+F14 -> 464.37007
B23: 小计 | C23: =SUM(C20:C22) -> 5482.5739 | D23: =SUM(D20:D22) -> 7045.5953 | E23: =SUM(E20:E22) -> 9396.8547
B25: 产品增长率 | C25: 2015年 | D25: 2016年 | E25: 2017年
B26: 可拆 | D26: =D20/C20-1 -> -0.16694288 | E26: =E20/D20-1 -> 0.23642795
B27: 钎焊 | D27: =D21/C21-1 -> 0.43938385 | E27: =E21/D21-1 -> 0.33474245
B28: 其他 | D28: =D22/C22-1 -> -0.17548774 | E28: =E22/D22-1 -> 0.60378286
B29: 主要产品 | D29: =D23/C23-1 -> 0.28508897 | E29: =E23/D23-1 -> 0.33372047
B31: 产品结构占比 | C31: 2015年 | D31: 2016年 | E31: 2017年
B32: 可拆 | C32: =C20/C$23 -> 0.18951949 | D32: =D20/D$23 -> 0.12285574 | E32: =E20/E$23 -> 0.11389364 | F32: 产品结构下降，核实是否转型？比例继续下降？
B33: 钎焊 | C33: =C21/C$23 -> 0.74642787 | D33: =D21/D$23 -> 0.83604813 | E33: =E21/E$23 -> 0.83668876 | F33: 主要产品在增加，进一步核实驱动因素是组合单价、还是数量？
B34: 其他 | C34: =C22/C$23 -> 0.064052641 | D34: =D22/D$23 -> 0.041096133 | E34: =E22/E$23 -> 0.049417607
B36: 按销售分类
C37: 2015年 | D37: 2016年 | E37: 2017年
B38: 内销 | C38: =(SUM(D9:D11)+D15)/D16 -> 0.7807309 | D38: =(SUM(E9:E11)+E15)/E16 -> 0.87315365 | E38: =(SUM(F9:F11)+F15)/F16 -> 0.89608997 | F38: 主要市场在国内 | H38: 未来销售比例90:10
B39: 外销 | C39: =SUM(D12:D14)/D16 -> 0.2192691 | D39: =SUM(E12:E14)/E16 -> 0.12684635 | E39: =SUM(F12:F14)/F16 -> 0.10391003 | F39: 外销比例在下降 | H39: 外销费用不应大幅变动，即销售费用的外销费用
B41: 内外销影响的是销售毛利的多少，了解这个比例为确定毛利率水平和销售费用的变化。
B42: 采用一种分类方式预测，两种方式组合增加了预测难度
B43: 尽调结论
B44: 1、17年全年产能利用率约65%，产能瓶颈在烧结用炉子和检测设备，已订购相关设备，18年产能可以提高40%； | H44: =E57/0.65 -> 12095.758 | I44: 没超产能
B45: 2、目前的主要产品仍是钎焊换热器，18年销量的主要增长也在钎焊换热器；
B46: 3、计划订购一台3万吨液压机，主要用于生产可拆换热器，可拆换热器的销量19年开始大幅增加，预计销量增加额在2000万左右；
B47: 4、15~17年外销金额基本维持稳定，以后年度也保持在该水平；
B48: 5、由于大量国家环保政策、标准的出台，变热器的市场需求增加；
B49: 6、产品有明显的季节性，每年的5~11月为旺季。（这个不影响预测值）
B51: 收入分解 | D51: 自下而上 | F51: 自上而下，考虑竞争
B52: 销量？ | D52: 设备产能→→销量？ | F52: 市场容量→→市场占有率？
B53: 组合单价？ | F53: 销售单价的变化？
B55: 项目 | C55: 2015年 | D55: 2016年 | E55: 2017年 | F55: 2018年 | G55: 2019年 | H55: 2020年 | I55: 2021年 | J55: 2022年
B56: 可拆 | C56: =C20 -> 1039.0546 | D56: =D20 -> 865.59183 | E56: =E20 -> 1070.2419 | F56: =E56*(1+F68) -> 1093.01 | G56: =F56*(1+G68) -> 1110.3477 | H56: =G56*(1+H68) -> 1121.9517 | I56: =H56*(1+I68) -> 1127.6055 | J56: =I56*(1+J68) -> 1129.5505
B57: 钎焊 | C57: =C21 -> 4092.346 | D57: =D21 -> 5890.4567 | E57: =E21 -> 7862.2427 | F57: =E57*(1+F69) -> 10071.818 | G57: =F57*(1+G69) -> 12182.347 | H57: =G57*(1+H69) -> 13864.236 | I57: =H57*(1+I69) -> 14787.194 | J57: =I57*(1+J69) -> 15124.154
B58: 其他 | C58: =C22 -> 351.17334 | D58: =D22 -> 289.54672 | E58: =E22 -> 464.37007 | F58: =E58*(1+F70) -> 540.99141 | G58: =F58*(1+G70) -> 607.54888 | H58: =G58*(1+H70) -> 656.79486 | I58: =H58*(1+I70) -> 682.46564 | J58: =I58*(1+J70) -> 691.59618
B59: 材料及板片 | C59: =D15 -> 164.98691 | D59: =E15 -> 259.17922 | E59: =F15 -> 218.72166 | F59: =E59*(1+$L$59) -> 229.65774 | G59: =F59*(1+$L$59) -> 241.14063 | H59: =G59*(1+$L$59) -> 253.19766 | I59: =H59*(1+$L$59) -> 265.85754 | J59: =I59*(1+$L$59) -> 279.15042 | K59: 该项增长率 | L59: 0.05
B60: 收入合计 | C60: =SUM(C56:C59) -> 5647.5609 | D60: =SUM(D56:D59) -> 7304.7745 | E60: =SUM(E56:E59) -> 9615.5763 | F60: =SUM(F56:F59) -> 11935.477 | G60: =SUM(G56:G59) -> 14141.384 | H60: =SUM(H56:H59) -> 15896.18 | I60: =SUM(I56:I59) -> 16863.123 | J60: =SUM(J56:J59) -> 17224.451
B61: 与报表数是否相同？ | C61: =C60-C5 -> 0 | D61: =D60-D5 -> 0 | E61: =E60-E5 -> 0
B63: 两种预测的思路
B64: 1、 | C64: 每种产品的销量和价格的变化，用产能和市场占有率进行检查
B65: 2、 | C65: 每种产品销售增长率和结构占比预测，同样用产能和市场占有率进行检查 | I65: 可从可比公司的预期增长率上进行比较修正，或从规模上看可比公司的历史增长率变化
B66: 先粗估，然后根据后续信息再修正。 | L66: 行业分析
B67: 增长率 | C67: 2015年 | D67: 2016年 | E67: 2017年 | F67: 2018年 | G67: 2019年 | H67: 2020年 | I67: 2021年 | J67: 2022年 | L67: 2015年，我国换热器产业的市场规模为769亿元，同比增长8.92%。
B68: 可拆 | D68: =D26 -> -0.16694288 | E68: =E26 -> 0.23642795 | F68: =F$71*$G$82/F75 -> 0.021273779 | G68: =G$71*$G$82/G75 -> 0.015862279 | H68: =H$71*$G$82/H75 -> 0.010450779 | I68: =I$71*$G$82/I75 -> 0.0050392788 | J68: =J$71*$G$82/J75 -> 0.0017249432 | L68: 2015~2020年复合增长率 | O68: =(1500/769)^(1/5)-1 -> 0.14296514 | P68: 板式换热器 | Q68: =(420/192.25)^(1/5)-1 -> 0.16916711
B69: 钎焊 | D69: =D27 -> 0.43938385 | E69: =E27 -> 0.33474245 | F69: =F$71*$G$83/F76 -> 0.28103629 | G69: =G$71*$G$83/G76 -> 0.20954791 | H69: =H$71*$G$83/H76 -> 0.13805954 | I69: =I$71*$G$83/I76 -> 0.066571163 | J69: =J$71*$G$83/J76 -> 0.022787284 | L69: 2015~2020被评估企业复合增长率 | O69: =(H60/C60)^(1/5)-1 -> 0.22994692
B70: 其他 | D70: =D28 -> -0.17548774 | E70: =E28 -> 0.60378286 | F70: =F$71*$G$84/F77 -> 0.1650006 | G70: =G$71*$G$84/G77 -> 0.12302871 | H70: =H$71*$G$84/H77 -> 0.081056814 | I70: =I$71*$G$84/I77 -> 0.039084923 | J70: =J$71*$G$84/J77 -> 0.013378754 | L70: 2018~2022被评估企业复合增长率 | O70: =(J60/E60)^(1/5)-1 -> 0.12365765
B71: 产品收入 | D71: =D29 -> 0.28508897 | E71: =E29 -> 0.33372047 | F71: =AVERAGE(D71:E71)-($E$71-$J$71)/5 -> 0.24666063 | G71: =F71-($E$71-$J$71)/5 -> 0.18391653 | H71: =G71-($E$71-$J$71)/5 -> 0.12117244 | I71: =H71-($E$71-$J$71)/5 -> 0.058428344 | J71: 0.02 | L71: 可比上市公司分析
F73: 假设产品结构不变
B74: 结构占比 | C74: 2015年 | D74: 2016年 | E74: 2017年 | F74: 2018年 | G74: 2019年 | H74: 2020年 | I74: 2021年 | J74: 2022年 | L74: 2022年被评估企业预计市场占有率 | P74: =J60/10000/(420*1.169^2) -> 0.0030010075
B75: 可拆 | C75: =C32 -> 0.18951949 | D75: =D32 -> 0.12285574 | E75: =E32 -> 0.11389364 | F75: 0.11 | G75: =F75 -> 0.11 | H75: =G75 -> 0.11 | I75: =H75 -> 0.11 | J75: =I75 -> 0.11
B76: 钎焊 | C76: =C33 -> 0.74642787 | D76: =D33 -> 0.83604813 | E76: =E33 -> 0.83668876 | F76: 0.84 | G76: =F76 -> 0.84 | H76: =G76 -> 0.84 | I76: =H76 -> 0.84 | J76: =I76 -> 0.84
B77: 其他 | C77: =C34 -> 0.064052641 | D77: =D34 -> 0.041096133 | E77: =E34 -> 0.049417607 | F77: 0.05 | G77: =F77 -> 0.05 | H77: =G77 -> 0.05 | I77: =H77 -> 0.05 | J77: =I77 -> 0.05
B78: 产品收入 | C78: =SUM(C75:C77) -> 1 | D78: =SUM(D75:D77) -> 1 | E78: =SUM(E75:E77) -> 1 | F78: =SUM(F75:F77) -> 1 | G78: =SUM(G75:G77) -> 1 | H78: =SUM(H75:H77) -> 1 | I78: =SUM(I75:I77) -> 1 | J78: =SUM(J75:J77) -> 1
B81: 增长贡献率 | C81: 2015年 | D81: 2016年 | E81: 2017年 | F81: 平均值 | G81: 权重
B82: 可拆 | D82: =D68*D75 -> -0.020509892 | E82: =E68*E75 -> 0.026927639 | F82: =AVERAGE(D82:E82) -> 0.0032088737 | G82: =F82/F$85 -> 0.0094871877
B83: 钎焊 | D83: =D69*D76 -> 0.36734605 | E83: =E69*E76 -> 0.28007524 | F83: =AVERAGE(D83:E83) -> 0.32371064 | G83: =F83/F$85 -> 0.95706593
B84: 其他 | D84: =D70*D77 -> -0.0072118677 | E84: =E70*E77 -> 0.029837504 | F84: =AVERAGE(D84:E84) -> 0.011312818 | G84: =F84/F$85 -> 0.033446886
B85: 合计 | F85: =SUM(F82:F84) -> 0.33823234 | G85: =F85/F$85 -> 1

Sheet 4成本
B1: 营业成本预测表
B2: ='1报表'!B11 -> 评估基准日：2017/12/31
B3: ='1报表'!B12 -> 被评估单位：JSBD公司 | J3: 单位：万元
B4: 年度 | C4: ='3收入'!C4 -> 2015年 | D4: ='3收入'!D4 -> 2016年 | E4: ='3收入'!E4 -> 2017年 | F4: ='3收入'!F4 -> 2018年 | G4: ='3收入'!G4 -> 2019年 | H4: ='3收入'!H4 -> 2020年 | I4: ='3收入'!I4 -> 2021年 | J4: ='3收入'!J4 -> 2022年
B5: 数据汇总 | C5: ='1报表'!C98 -> 3450.9962 | D5: ='1报表'!D98 -> 4625.6862 | E5: ='1报表'!E98 -> 5762.986 | F5: =F106 -> 7161.2864 | G5: =G106 -> 8484.8303 | H5: =H106 -> 9537.7079 | I5: =I106 -> 10117.874 | J5: =J106 -> 10334.671
B6: 营业收入 | C6: ='3收入'!C5 -> 5647.5609 | D6: ='3收入'!D5 -> 7304.7745 | E6: ='3收入'!E5 -> 9615.5763 | F6: ='3收入'!F5 -> 11935.477 | G6: ='3收入'!G5 -> 14141.384 | H6: ='3收入'!H5 -> 15896.18 | I6: ='3收入'!I5 -> 16863.123 | J6: ='3收入'!J5 -> 17224.451
B7: 毛利率 | C7: =IF(C6,(C6-C5)/C6,"na") -> 0.38894042 | D7: =IF(D6,(D6-D5)/D6,"na") -> 0.36675852 | E7: =IF(E6,(E6-E5)/E6,"na") -> 0.40066141 | F7: =IF(F6,(F6-F5)/F6,"na") -> 0.4 | G7: =IF(G6,(G6-G5)/G6,"na") -> 0.4 | H7: =IF(H6,(H6-H5)/H6,"na") -> 0.4 | I7: =IF(I6,(I6-I5)/I6,"na") -> 0.4 | J7: =IF(J6,(J6-J5)/J6,"na") -> 0.4
B8: 营业成本预测（生产型企业）（方式一）
B9: 项目1 | C9: =C4 -> 2015年 | D9: =D4 -> 2016年 | E9: =E4 -> 2017年 | F9: =F4 -> 2018年 | G9: =G4 -> 2019年 | H9: =H4 -> 2020年 | I9: =I4 -> 2021年 | J9: =J4 -> 2022年 | L9: 按科目进行分析
B10: 原材料 | L10: 评估实务中还应当对原材料的变化趋势作一说明，公司消化原材料价格变化的经营措施。
B11: 占收入比 | C11: =IF(C6,C10/C6,"na") -> 0 | D11: =IF(D6,D10/D6,"na") -> 0 | E11: =IF(E6,E10/E6,"na") -> 0 | L11: 员工人数是否会随着收入增长而增加，消化人工成本的措施。
B12: =B10 -> 原材料 | C12: =C10 -> 0 | D12: =D10 -> 0 | E12: =E10 -> 0 | F12: =IF(F10,F10,F11*F6) -> 0 | G12: =IF(G10,G10,G11*G6) -> 0 | H12: =IF(H10,H10,H11*H6) -> 0 | I12: =IF(I10,I10,I11*I6) -> 0 | J12: =IF(J10,J10,J11*J6) -> 0 | L12: （要有具体的纸质底稿支撑）
B13: 占收入比 | F13: =IF(F6,F12/F6,"na") -> 0 | G13: =IF(G6,G12/G6,"na") -> 0 | H13: =IF(H6,H12/H6,"na") -> 0 | I13: =IF(I6,I12/I6,"na") -> 0 | J13: =IF(J6,J12/J6,"na") -> 0
B15: 项目2 | C15: =C4 -> 2015年 | D15: =D4 -> 2016年 | E15: =E4 -> 2017年 | F15: =F4 -> 2018年 | G15: =G4 -> 2019年 | H15: =H4 -> 2020年 | I15: =I4 -> 2021年 | J15: =J4 -> 2022年
B16: 燃料及动力
B17: 占收入比 | C17: =IF(C6,C16/C6,"na") -> 0 | D17: =IF(D6,D16/D6,"na") -> 0 | E17: =IF(E6,E16/E6,"na") -> 0
B18: =B16 -> 燃料及动力 | C18: =C16 -> 0 | D18: =D16 -> 0 | E18: =E16 -> 0 | F18: =IF(F16,F16,F17*F6) -> 0 | G18: =IF(G16,G16,G17*G6) -> 0 | H18: =IF(H16,H16,H17*H6) -> 0 | I18: =IF(I16,I16,I17*I6) -> 0 | J18: =IF(J16,J16,J17*J6) -> 0
B19: 占收入比 | F19: =IF(F6,F18/F6,"na") -> 0 | G19: =IF(G6,G18/G6,"na") -> 0 | H19: =IF(H6,H18/H6,"na") -> 0 | I19: =IF(I6,I18/I6,"na") -> 0 | J19: =IF(J6,J18/J6,"na") -> 0
B21: 项目3 | C21: =C4 -> 2015年 | D21: =D4 -> 2016年 | E21: =E4 -> 2017年 | F21: =F4 -> 2018年 | G21: =G4 -> 2019年 | H21: =H4 -> 2020年 | I21: =I4 -> 2021年 | J21: =J4 -> 2022年
B22: 生产人员工资及附加
B23: 占收入比 | C23: =IF(C6,C22/C6,"na") -> 0 | D23: =IF(D6,D22/D6,"na") -> 0 | E23: =IF(E6,E22/E6,"na") -> 0
B24: =B22 -> 生产人员工资及附加 | C24: =C22 -> 0 | D24: =D22 -> 0 | E24: =E22 -> 0 | F24: =IF(F22,F22,F23*F6) -> 0 | G24: =IF(G22,G22,G23*G6) -> 0 | H24: =IF(H22,H22,H23*H6) -> 0 | I24: =IF(I22,I22,I23*I6) -> 0 | J24: =IF(J22,J22,J23*J6) -> 0
B25: 占收入比 | F25: =IF(F6,F24/F6,"na") -> 0 | G25: =IF(G6,G24/G6,"na") -> 0 | H25: =IF(H6,H24/H6,"na") -> 0 | I25: =IF(I6,I24/I6,"na") -> 0 | J25: =IF(J6,J24/J6,"na") -> 0
B27: 项目4 | C27: =C4 -> 2015年 | D27: =D4 -> 2016年 | E27: =E4 -> 2017年 | F27: =F4 -> 2018年 | G27: =G4 -> 2019年 | H27: =H4 -> 2020年 | I27: =I4 -> 2021年 | J27: =J4 -> 2022年
B28: 折旧（及摊销） | F28: ='7折旧'!F5 -> 538.7712 | G28: ='7折旧'!G5 -> 572.2992 | H28: ='7折旧'!H5 -> 299.2771 | I28: ='7折旧'!I5 -> 147.18807 | J28: ='7折旧'!J5 -> 156.86807
B29: 占收入比 | C29: =IF(C6,C28/C6,"na") -> 0 | D29: =IF(D6,D28/D6,"na") -> 0 | E29: =IF(E6,E28/E6,"na") -> 0 | F29: =IF(F6,F28/F6,"na") -> 0.045140315 | G29: =IF(G6,G28/G6,"na") -> 0.040469816 | H29: =IF(H6,H28/H6,"na") -> 0.018826982 | I29: =IF(I6,I28/I6,"na") -> 0.0087283993 | J29: =IF(J6,J28/J6,"na") -> 0.0091072898
B31: 项目5 | C31: =C4 -> 2015年 | D31: =D4 -> 2016年 | E31: =E4 -> 2017年 | F31: =F4 -> 2018年 | G31: =G4 -> 2019年 | H31: =H4 -> 2020年 | I31: =I4 -> 2021年 | J31: =J4 -> 2022年
B32: 其他
B33: 占收入比 | C33: =IF(C6,C32/C6,"na") -> 0 | D33: =IF(D6,D32/D6,"na") -> 0 | E33: =IF(E6,E32/E6,"na") -> 0
B34: =B32 -> 其他 | C34: =C32 -> 0 | D34: =D32 -> 0 | E34: =E32 -> 0 | F34: =IF(F32,F32,F33*F6) -> 0 | G34: =IF(G32,G32,G33*G6) -> 0 | H34: =IF(H32,H32,H33*H6) -> 0 | I34: =IF(I32,I32,I33*I6) -> 0 | J34: =IF(J32,J32,J33*J6) -> 0
B35: 占收入比 | F35: =IF(F6,F34/F6,"na") -> 0 | G35: =IF(G6,G34/G6,"na") -> 0 | H35: =IF(H6,H34/H6,"na") -> 0 | I35: =IF(I6,I34/I6,"na") -> 0 | J35: =IF(J6,J34/J6,"na") -> 0
B37: 项目（汇总） | C37: =C4 -> 2015年 | D37: =D4 -> 2016年 | E37: =E4 -> 2017年 | F37: =F4 -> 2018年 | G37: =G4 -> 2019年 | H37: =H4 -> 2020年 | I37: =I4 -> 2021年 | J37: =J4 -> 2022年
B38: 营业成本 | C38: =C12+C18+C24+C28+C34 -> 0 | D38: =D12+D18+D24+D28+D34 -> 0 | E38: =E12+E18+E24+E28+E34 -> 0 | F38: =F12+F18+F24+F28+F34 -> 538.7712 | G38: =G12+G18+G24+G28+G34 -> 572.2992 | H38: =H12+H18+H24+H28+H34 -> 299.2771 | I38: =I12+I18+I24+I28+I34 -> 147.18807 | J38: =J12+J18+J24+J28+J34 -> 156.86807
B39: 占收入比 | C39: =IF(C6,C38/C6,"na") -> 0 | D39: =IF(D6,D38/D6,"na") -> 0 | E39: =IF(E6,E38/E6,"na") -> 0 | F39: =IF(F6,F38/F6,"na") -> 0.045140315 | G39: =IF(G6,G38/G6,"na") -> 0.040469816 | H39: =IF(H6,H38/H6,"na") -> 0.018826982 | I39: =IF(I6,I38/I6,"na") -> 0.0087283993 | J39: =IF(J6,J38/J6,"na") -> 0.0091072898
B40: 毛利率 | C40: =IF(C6,1-C39,"na") -> 1 | D40: =IF(D6,1-D39,"na") -> 1 | E40: =IF(E6,1-E39,"na") -> 1 | F40: =IF(F6,1-F39,"na") -> 0.95485969 | G40: =IF(G6,1-G39,"na") -> 0.95953018 | H40: =IF(H6,1-H39,"na") -> 0.98117302 | I40: =IF(I6,1-I39,"na") -> 0.9912716 | J40: =IF(J6,1-J39,"na") -> 0.99089271
B42: 按产品/项目毛利率分析（方式二） | F42: 需具体分析毛利率变动原因，以及提高或降低措施，而不是仅仅列张汇总表（要有具体的纸质底稿支撑）
B43: 毛利率 | C43: =C4 -> 2015年 | D43: =D4 -> 2016年 | E43: =E4 -> 2017年 | F43: =F4 -> 2018年 | G43: =G4 -> 2019年 | H43: =H4 -> 2020年 | I43: =I4 -> 2021年 | J43: =J4 -> 2022年
B44: 产品a
B45: 产品b
B46: 产品c
B47: 综合毛利率 | C47: =IF(C6,(C6-C5)/C6,"na") -> 0.38894042 | D47: =IF(D6,(D6-D5)/D6,"na") -> 0.36675852 | E47: =IF(E6,(E6-E5)/E6,"na") -> 0.40066141 | F47: =IF(F6,(F6-F5)/F6,"na") -> 0.4 | G47: =IF(G6,(G6-G5)/G6,"na") -> 0.4 | H47: =IF(H6,(H6-H5)/H6,"na") -> 0.4 | I47: =IF(I6,(I6-I5)/I6,"na") -> 0.4 | J47: =IF(J6,(J6-J5)/J6,"na") -> 0.4
B49: 可比公司对比分析（可选）
B50: 毛利率 | C50: =C4 -> 2015年 | D50: =D4 -> 2016年 | E50: =E4 -> 2017年 | F50: 平均值
B51: xx公司 | F51: =IF(ISERROR(AVERAGE(C51:E51)),0,AVERAGE(C51:E51)) -> 0
F52: =IF(ISERROR(AVERAGE(C52:E52)),0,AVERAGE(C52:E52)) -> 0
F53: =IF(ISERROR(AVERAGE(C53:E53)),0,AVERAGE(C53:E53)) -> 0
F54: =IF(ISERROR(AVERAGE(C54:E54)),0,AVERAGE(C54:E54)) -> 0
F55: =IF(ISERROR(AVERAGE(C55:E55)),0,AVERAGE(C55:E55)) -> 0
F56: =IF(ISERROR(AVERAGE(C56:E56)),0,AVERAGE(C56:E56)) -> 0
B57: 平均值 | C57: =IF(ISERROR(AVERAGE(C51:C56)),0,AVERAGE(C51:C56)) -> 0 | D57: =IF(ISERROR(AVERAGE(D51:D56)),0,AVERAGE(D51:D56)) -> 0 | E57: =IF(ISERROR(AVERAGE(E51:E56)),0,AVERAGE(E51:E56)) -> 0
B58: 中位数 | C58: =IF(ISERROR(MEDIAN(C51:C56)),0,MEDIAN(C51:C56)) -> 0 | D58: =IF(ISERROR(MEDIAN(D51:D56)),0,MEDIAN(D51:D56)) -> 0 | E58: =IF(ISERROR(MEDIAN(E51:E56)),0,MEDIAN(E51:E56)) -> 0
B59: 示例
B60: 成本分析
B61: 成本按产品大类进行分解分析，可先进行毛利率分析，再到成本。
B62: 成本 | H62: 收入 | K62: 毛利 | O62: 毛利率
B63: 项目 | D63: 2015年 | E63: 2016年 | F63: 2017年 | H63: 2015年 | I63: 2016年 | J63: 2017年 | K63: 2015年 | L63: 2016年 | M63: 2017年 | O63: 2015年 | P63: 2016年 | Q63: 2017年
B64: 内销 | C64: 可拆 | D64: 511.06564 | E64: 466.6351 | F64: 551.84515 | H64: ='3收入'!D9 -> 849.25232 | I64: ='3收入'!E9 -> 761.74943 | J64: ='3收入'!F9 -> 881.84195 | K64: =H64-D64 -> 338.18669 | L64: =I64-E64 -> 295.11433 | M64: =J64-F64 -> 329.99681 | O64: =K64/H64 -> 0.39821697 | P64: =L64/I64 -> 0.38741654 | Q64: =M64/J64 -> 0.37421309
C65: 钎焊 | D65: 2160.8728 | E65: 3354.2285 | F65: 4490.183 | H65: ='3收入'!D10 -> 3332.4019 | I65: ='3收入'!E10 -> 5230.7696 | J65: ='3收入'!F10 -> 7346.3833 | K65: =H65-D65 -> 1171.5291 | L65: =I65-E65 -> 1876.5411 | M65: =J65-F65 -> 2856.2003 | O65: =K65/H65 -> 0.35155698 | P65: =L65/I65 -> 0.35875048 | Q65: =M65/J65 -> 0.38878999
C66: 其他 | D66: 32.659751 | E66: 108.62106 | F66: 167.79878 | H66: ='3收入'!D11 -> 62.584148 | I66: ='3收入'!E11 -> 126.49229 | J66: ='3收入'!F11 -> 169.47457 | K66: =H66-D66 -> 29.924397 | L66: =I66-E66 -> 17.871225 | M66: =J66-F66 -> 1.6757873 | O66: =K66/H66 -> 0.47814659 | P66: =L66/I66 -> 0.14128312 | Q66: =M66/J66 -> 0.0098881346
B67: 外销 | C67: 可拆 | D67: 77.302258 | E67: 73.634992 | F67: 84.816582 | H67: ='3收入'!D12 -> 189.80228 | I67: ='3收入'!E12 -> 103.84241 | J67: ='3收入'!F12 -> 188.39998 | K67: =H67-D67 -> 112.50003 | L67: =I67-E67 -> 30.207416 | M67: =J67-F67 -> 103.5834 | O67: =K67/H67 -> 0.59272219 | P67: =L67/I67 -> 0.29089672 | Q67: =M67/J67 -> 0.54980579
C68: 钎焊 | D68: 461.86369 | E68: 412.53463 | F68: 246.15405 | H68: ='3收入'!D13 -> 759.94412 | I68: ='3收入'!E13 -> 659.68712 | J68: ='3收入'!F13 -> 515.85933 | K68: =H68-D68 -> 298.08043 | L68: =I68-E68 -> 247.15249 | M68: =J68-F68 -> 269.70528 | O68: =K68/H68 -> 0.39223993 | P68: =L68/I68 -> 0.37465108 | Q68: =M68/J68 -> 0.52282718
C69: 其他 | D69: 146.15818 | E69: 68.709656 | F69: 118.16651 | H69: ='3收入'!D14 -> 288.58919 | I69: ='3收入'!E14 -> 163.05443 | J69: ='3收入'!F14 -> 294.8955 | K69: =H69-D69 -> 142.43101 | L69: =I69-E69 -> 94.344779 | M69: =J69-F69 -> 176.72899 | O69: =K69/H69 -> 0.49354244 | P69: =L69/I69 -> 0.5786091 | Q69: =M69/J69 -> 0.59929361
B70: 材料及板片 | D70: 61.073904 | E70: 141.32228 | F70: 104.02186 | H70: ='3收入'!D15 -> 164.98691 | I70: ='3收入'!E15 -> 259.17922 | J70: ='3收入'!F15 -> 218.72166 | K70: =H70-D70 -> 103.91301 | L70: =I70-E70 -> 117.85695 | M70: =J70-F70 -> 114.69979 | O70: =K70/H70 -> 0.62982576 | P70: =L70/I70 -> 0.45473147 | Q70: =M70/J70 -> 0.52440986
B71: 合计 | D71: =SUM(D64:D70) -> 3450.9962 | E71: =SUM(E64:E70) -> 4625.6862 | F71: =SUM(F64:F70) -> 5762.986 | H71: =SUM(H64:H70) -> 5647.5609 | I71: =SUM(I64:I70) -> 7304.7745 | J71: =SUM(J64:J70) -> 9615.5763 | K71: =SUM(K64:K70) -> 2196.5647 | L71: =SUM(L64:L70) -> 2679.0883 | M71: =SUM(M64:M70) -> 3852.5903 | O71: =K71/H71 -> 0.38894042 | P71: =L71/I71 -> 0.36675852 | Q71: =M71/J71 -> 0.40066141
B73: 按产品分类 | G73: 收入 | K73: 毛利 | N73: 毛利率
B74: 成本分析 | C74: 2015年 | D74: 2016年 | E74: 2017年 | G74: 2015年 | H74: 2016年 | I74: 2017年 | K74: 2015年 | L74: 2016年 | M74: 2017年 | N74: 2015年 | O74: 2016年 | P74: 2017年
B75: 可拆 | C75: =D64+D67 -> 588.36789 | D75: =E64+E67 -> 540.27009 | E75: =F64+F67 -> 636.66173 | G75: =H64+H67 -> 1039.0546 | H75: =I64+I67 -> 865.59183 | I75: =J64+J67 -> 1070.2419 | K75: =G75-C75 -> 450.68671 | L75: =H75-D75 -> 325.32174 | M75: =I75-E75 -> 433.58021 | N75: =K75/G75 -> 0.4337469 | O75: =L75/H75 -> 0.37583735 | P75: =M75/I75 -> 0.40512354
B76: 钎焊 | C76: =D65+D68 -> 2622.7364 | D76: =E65+E68 -> 3766.7631 | E76: =F65+F68 -> 4736.3371 | G76: =H65+H68 -> 4092.346 | H76: =I65+I68 -> 5890.4567 | I76: =J65+J68 -> 7862.2427 | K76: =G76-C76 -> 1469.6096 | L76: =H76-D76 -> 2123.6936 | M76: =I76-E76 -> 3125.9056 | N76: =K76/G76 -> 0.35911176 | O76: =L76/H76 -> 0.36053123 | P76: =M76/I76 -> 0.39758447
B77: 其他 | C77: =D66+D69 -> 178.81793 | D77: =E66+E69 -> 177.33072 | E77: =F66+F69 -> 285.9653 | F77: 定制产品 | G77: =H66+H69 -> 351.17334 | H77: =I66+I69 -> 289.54672 | I77: =J66+J69 -> 464.37007 | K77: =G77-C77 -> 172.35541 | L77: =H77-D77 -> 112.216 | M77: =I77-E77 -> 178.40478 | N77: =K77/G77 -> 0.49079868 | O77: =L77/H77 -> 0.3875575 | P77: =M77/I77 -> 0.38418664
B78: 小计 | C78: =SUM(C75:C77) -> 3389.9223 | D78: =SUM(D75:D77) -> 4484.364 | E78: =SUM(E75:E77) -> 5658.9641 | G78: =SUM(G75:G77) -> 5482.5739 | H78: =SUM(H75:H77) -> 7045.5953 | I78: =SUM(I75:I77) -> 9396.8547 | K78: =SUM(K75:K77) -> 2092.6517 | L78: =SUM(L75:L77) -> 2561.2313 | M78: =SUM(M75:M77) -> 3737.8906 | N78: =K78/G78 -> 0.38169147 | O78: =L78/H78 -> 0.36352235 | P78: =M78/I78 -> 0.39778103
B79: 成本增长率 | G79: 收入增长率 | K79: 毛利增长率 | N79: 毛利率增长
B80: 产品增长率 | C80: 2015年 | D80: 2016年 | E80: 2017年 | G80: 2015年 | H80: 2016年 | I80: 2017年 | K80: 2015年 | L80: 2016年 | M80: 2017年 | N80: 2015年 | O80: 2016年 | P80: 2017年
B81: 可拆 | D81: =D75/C75-1 -> -0.081747836 | E81: =E75/D75-1 -> 0.1784138 | H81: =H75/G75-1 -> -0.16694288 | I81: =I75/H75-1 -> 0.23642795 | L81: =L75/K75-1 -> -0.27816434 | M81: =M75/L75-1 -> 0.33277354 | O81: =O75-N75 -> -0.057909547 | P81: =P75-O75 -> 0.029286194
B82: 钎焊 | D82: =D76/C76-1 -> 0.43619583 | E82: =E76/D76-1 -> 0.25740242 | H82: =H76/G76-1 -> 0.43938385 | I82: =I76/H76-1 -> 0.33474245 | J82: =I82-E82 -> 0.077340029 | L82: =L76/K76-1 -> 0.44507334 | M82: =M76/L76-1 -> 0.47191929 | O82: =O76-N76 -> 0.0014194708 | P82: =P76-O76 -> 0.037053241 | Q82: =M82-L82 -> 0.026845943
B83: 其他 | D83: =D77/C77-1 -> -0.0083168978 | E83: =E77/D77-1 -> 0.61261002 | H83: =H77/G77-1 -> -0.17548774 | I83: =I77/H77-1 -> 0.60378286 | L83: =L77/K77-1 -> -0.34892671 | M83: =M77/L77-1 -> 0.58983365 | O83: =O77-N77 -> -0.10324118 | P83: =P77-O77 -> -0.003370858
B84: 主要产品 | D84: =D78/C78-1 -> 0.32285156 | E84: =E78/D78-1 -> 0.26193239 | H84: =H78/G78-1 -> 0.28508897 | I84: =I78/H78-1 -> 0.33372047 | L84: =L78/K78-1 -> 0.2239167 | M84: =M78/L78-1 -> 0.45941153 | O84: =O78-N78 -> -0.018169118 | P84: =P78-O78 -> 0.034258685
B86: 产品结构占比 | C86: 2015年 | D86: 2016年 | E86: 2017年 | G86: 钎焊
B87: 可拆 | C87: =C75/C$78 -> 0.17356383 | D87: =D75/D$78 -> 0.12047864 | E87: =E75/E$78 -> 0.11250499 | F87: 1、 | G87: 2016年成本增长与收入、毛利增长基本持平，到2017年收入增长比成本高7.7百分点，毛利率提高3.7个百分点，
B88: 钎焊 | C88: =C76/C$78 -> 0.77368631 | D88: =D76/D$78 -> 0.83997713 | E88: =E76/E$78 -> 0.83696185 | G88: 直观的反映是组合价格的提高，需核实毛利率提高的驱动因素。
B89: 其他 | C89: =C77/C$78 -> 0.052749862 | D89: =D77/D$78 -> 0.03954423 | E89: =E77/E$78 -> 0.050533152 | G89: 可拆
F90: 2、 | G90: 2015~2017年毛利率在下降，
B91: 按销售分类 | G91: 2015-2016年公司生产不稳定，有股权纠纷等因素影响，2017年数据更有参考性
C92: 2015年 | D92: 2016年 | E92: 2017年 | G92: 其他
B93: 内销 | C93: =(SUM(D64:D66)+D70)/D71 -> 0.80141267 | D93: =(SUM(E64:E66)+E70)/E71 -> 0.8800439 | E93: =(SUM(F64:F66)+F70)/F71 -> 0.9220652 | F93: 3、 | G93: 定制产品，毛利率在下降
B94: 外销 | C94: =SUM(D67:D69)/D71 -> 0.19858733 | D94: =SUM(E67:E69)/E71 -> 0.1199561 | E94: =SUM(F67:F69)/F71 -> 0.077934797 | F94: 4、 | G94: 2017年全年产能利用率约65%，产能瓶颈在烧结用炉子和检测设备，已订购相关设备，18年产能可以提高40%；
G95: 这样即使销售价格下降，由于产能的提高，分摊固定费用，毛利率也可维持不变或略有上升。
C96: 2017年 | G96: 当然，也有可能竞争加剧，毛利率下降。
B97: 成本结构分析 | D97: 金额 | E97: 占比
C98: 直接材料 | D98: 4270.2525 | E98: =D98/D$101 -> 0.79946098 | F98: 这个数据用于计算进项税额， | I98: 需要核实境外销售的销项税额是否退税？
C99: 直接人工 | D99: 231.43623 | E99: =D99/D$101 -> 0.04332864 | F99: 原底稿中预测了生产人员薪酬，需要考虑如何将薪酬与毛利率的变化关联起来。
C100: 制造费用 | D100: 839.72581 | E100: =D100/D$101 -> 0.15721038 | F100: 制造费用与折旧相关，需要考虑如何将折旧与毛利率的变化关联起来。
C101: 合计 | D101: =SUM(D98:D100) -> 5341.4146 | E101: =D101/D$101 -> 1 | F101: 原底稿中的5341.41与2017年5762.99（总成本）不匹配，这是一个风险点。
E102: 假设未来毛利率水平保持不变
C103: =C4 -> 2015年 | D103: =D4 -> 2016年 | E103: =E4 -> 2017年 | F103: =F4 -> 2018年 | G103: =G4 -> 2019年 | H103: =H4 -> 2020年 | I103: =I4 -> 2021年 | J103: =J4 -> 2022年
B104: 营业收入 | C104: =C6 -> 5647.5609 | D104: =D6 -> 7304.7745 | E104: =E6 -> 9615.5763 | F104: =F6 -> 11935.477 | G104: =G6 -> 14141.384 | H104: =H6 -> 15896.18 | I104: =I6 -> 16863.123 | J104: =J6 -> 17224.451
B105: 毛利率 | C105: =(C104-C106)/C104 -> 0.38894042 | D105: =(D104-D106)/D104 -> 0.36675852 | E105: =(E104-E106)/E104 -> 0.40066141 | F105: 0.4 | G105: =F105 -> 0.4 | H105: =G105 -> 0.4 | I105: =H105 -> 0.4 | J105: =I105 -> 0.4
B106: 成本 | C106: =C5 -> 3450.9962 | D106: =D5 -> 4625.6862 | E106: =E5 -> 5762.986 | F106: =F104*(1-F105) -> 7161.2864 | G106: =G104*(1-G105) -> 8484.8303 | H106: =H104*(1-H105) -> 9537.7079 | I106: =I104*(1-I105) -> 10117.874 | J106: =J104*(1-J105) -> 10334.671

Sheet 5税金
B1: 税金及附加预测表
B2: ='1报表'!B11 -> 评估基准日：2017/12/31
B3: ='1报表'!B12 -> 被评估单位：JSBD公司 | J3: 单位：万元
B4: 年度 | C4: ='3收入'!C4 -> 2015年 | D4: ='3收入'!D4 -> 2016年 | E4: ='3收入'!E4 -> 2017年 | F4: ='3收入'!F4 -> 2018年 | G4: ='3收入'!G4 -> 2019年 | H4: ='3收入'!H4 -> 2020年 | I4: ='3收入'!I4 -> 2021年 | J4: ='3收入'!J4 -> 2022年
B5: 数据汇总 | C5: ='1报表'!C99 -> 53.873421 | D5: ='1报表'!D99 -> 81.416231 | E5: ='1报表'!E99 -> 113.39456 | F5: =F32 -> 107.26836 | G5: =G32 -> 127.21454 | H5: =H32 -> 142.79594 | I5: =I32 -> 152.48181 | J5: =J32 -> 155.38377
B6: 营业收入 | C6: ='3收入'!C5 -> 5647.5609 | D6: ='3收入'!D5 -> 7304.7745 | E6: ='3收入'!E5 -> 9615.5763 | F6: ='3收入'!F5 -> 11935.477 | G6: ='3收入'!G5 -> 14141.384 | H6: ='3收入'!H5 -> 15896.18 | I6: ='3收入'!I5 -> 16863.123 | J6: ='3收入'!J5 -> 17224.451
B7: 占收入比 | C7: =IF(C6,C5/C6,"na") -> 0.0095392369 | D7: =IF(D6,D5/D6,"na") -> 0.011145619 | E7: =IF(E6,E5/E6,"na") -> 0.011792799 | F7: =IF(F6,F5/F6,"na") -> 0.0089873536 | G7: =IF(G6,G5/G6,"na") -> 0.0089959049 | H7: =IF(H6,H5/H6,"na") -> 0.0089830352 | I7: =IF(I6,I5/I6,"na") -> 0.0090423234 | J7: =IF(J6,J5/J6,"na") -> 0.0090211158
B8: 按收入占比分析（方式一） | E8: 实务中如果历史数据比较平稳，可采用下例简化处理。
C9: =C4 -> 2015年 | D9: =D4 -> 2016年 | E9: =E4 -> 2017年 | F9: =F4 -> 2018年 | G9: =G4 -> 2019年 | H9: =H4 -> 2020年 | I9: =I4 -> 2021年 | J9: =J4 -> 2022年
B10: 营业收入 | C10: =C6 -> 5647.5609 | D10: =D6 -> 7304.7745 | E10: =E6 -> 9615.5763 | F10: =F6 -> 11935.477 | G10: =G6 -> 14141.384 | H10: =H6 -> 15896.18 | I10: =I6 -> 16863.123 | J10: =J6 -> 17224.451
B11: 税金及附加 | C11: =C5 -> 53.873421 | D11: =D5 -> 81.416231 | E11: =E5 -> 113.39456
B12: 占收入比 | C12: =IF(C10,C11/C10,"na") -> 0.0095392369 | D12: =IF(D10,D11/D10,"na") -> 0.011145619 | E12: =IF(E10,E11/E10,"na") -> 0.011792799
B13: 税金及附加 | F13: =IF(F11,F11,F12*F10) -> 0 | G13: =IF(G11,G11,G12*G10) -> 0 | H13: =IF(H11,H11,H12*H10) -> 0 | I13: =IF(I11,I11,I12*I10) -> 0 | J13: =IF(J11,J11,J12*J10) -> 0
B14: 占收入比 | F14: =IF(F10,F13/F10,"na") -> 0 | G14: =IF(G10,G13/G10,"na") -> 0 | H14: =IF(H10,H13/H10,"na") -> 0 | I14: =IF(I10,I13/I10,"na") -> 0 | J14: =IF(J10,J13/J10,"na") -> 0
B16: 分项目进行分析（方式二） | D16: 实务中如果企业产品不单一，每种产品或服务适用的税率不同，以及金额较大，应分项目评估。示例如下
B17: 项目 | C17: =C4 -> 2015年 | D17: =D4 -> 2016年 | E17: =E4 -> 2017年 | F17: =F4 -> 2018年 | G17: =G4 -> 2019年 | H17: =H4 -> 2020年 | I17: =I4 -> 2021年 | J17: =J4 -> 2022年 | K17: 税率 | L17: 计税公式 | M17: 计税依据的主要内容
B18: 增值税销项 | K18: 0.16
B19: 增值税进项 | K19: 0.16 | M19: 注意资本性支出中设备的增值税要加上
B20: 应缴增值税 | C20: =C18-C19 -> 0 | D20: =D18-D19 -> 0 | E20: =E18-E19 -> 0 | F20: =F18-F19 -> 0 | G20: =G18-G19 -> 0 | H20: =H18-H19 -> 0 | I20: =I18-I19 -> 0 | J20: =J18-J19 -> 0 | L20: (1)-(2)
B21: 应缴营业税 | M21: 营改增后，该项无。
B22: 应缴流转税合计 | C22: =C20+C21 -> 0 | D22: =D20+D21 -> 0 | E22: =E20+E21 -> 0 | F22: =IF(F20+F21<0,0,F20+F21) -> 0 | G22: =IF(G20+G21<0,0,G20+G21) -> 0 | H22: =IF(H20+H21<0,0,H20+H21) -> 0 | I22: =IF(I20+I21<0,0,I20+I21) -> 0 | J22: =IF(J20+J21<0,0,J20+J21) -> 0 | L22: (3)+(4)
B23: 消费税
B24: 城市维护建设税 | C24: 29.6243 | D24: 36.90478 | E24: 51.920506 | F24: =F48*$K$24 -> 46.785574 | G24: =G48*$K$24 -> 58.112024 | H24: =H48*$K$24 -> 66.955502 | I24: =I48*$K$24 -> 72.470218 | J24: =J48*$K$24 -> 74.112442 | K24: 0.07 | L24: 应交流转税项
B25: 资源税
B26: 教育费附加 | C26: 21.160215 | D26: 26.360555 | E26: 37.086081 | F26: =F48*$K$26 -> 33.418267 | G26: =G48*$K$26 -> 41.508588 | H26: =H48*$K$26 -> 47.825358 | I26: =I48*$K$26 -> 51.764442 | J26: =J48*$K$26 -> 52.937458 | K26: 0.05 | L26: 应交流转税项
B27: 房产税 | D27: 10.499706 | E27: 13.999608 | F27: 16.41 | G27: =F27 -> 16.41 | H27: =G27 -> 16.41 | I27: =H27 -> 16.41 | J27: =I27 -> 16.41 | N27: （土地原值+房屋原值）*0.7*1.2%
B28: 土地使用税 | D28: 5.83875 | E28: 7.785 | F28: 7.79 | G28: =F28 -> 7.79 | H28: =G28 -> 7.79 | I28: =H28 -> 7.79 | J28: =I28 -> 7.79 | N28: 土地面积*6元/平方米
B29: 车船使用税
B30: 印花税 | C30: 0.00975 | D30: 1.81244 | E30: 2.603364 | F30: ='3收入'!F5*0.8*0.03% -> 2.8645146 | G30: ='3收入'!G5*0.8*0.03% -> 3.3939321 | H30: ='3收入'!H5*0.8*0.03% -> 3.8150832 | I30: ='3收入'!I5*0.8*0.03% -> 4.0471494 | J30: ='3收入'!J5*0.8*0.03% -> 4.1338683 | K30: 0.0003 | M30: 特殊行业要具实考虑 | N30: 销售收入*0.8*0.03%
B31: 其他 | C31: 3.079156
B32: 合计 | C32: =C21+SUM(C23:C31) -> 53.873421 | D32: =D21+SUM(D23:D31) -> 81.416231 | E32: =E21+SUM(E23:E31) -> 113.39456 | F32: =F21+SUM(F23:F31) -> 107.26836 | G32: =G21+SUM(G23:G31) -> 127.21454 | H32: =H21+SUM(H23:H31) -> 142.79594 | I32: =I21+SUM(I23:I31) -> 152.48181 | J32: =J21+SUM(J23:J31) -> 155.38377
B33: 占收入比 | F33: =IF(F6,F32/F6,"na") -> 0.0089873536 | G33: =IF(G6,G32/G6,"na") -> 0.0089959049 | H33: =IF(H6,H32/H6,"na") -> 0.0089830352 | I33: =IF(I6,I32/I6,"na") -> 0.0090423234 | J33: =IF(J6,J32/J6,"na") -> 0.0090211158
B35: 实务中如果企业产品不单一，每种产品或服务适用的增值税率不同，以及金额较大，应分项目评估。示例如下
B36: 增值税计算 | F36: =F4 -> 2018年 | G36: =G4 -> 2019年 | H36: =H4 -> 2020年 | I36: =I4 -> 2021年 | J36: =J4 -> 2022年
B37: 增值税销项税 | F37: =F6*0.9*(0.25*17%+0.75*16%) -> 1745.5636 | G37: =G6*0.9*16% -> 2036.3593 | H37: =H6*0.9*16% -> 2289.0499 | I37: =I6*0.9*16% -> 2428.2897 | J37: =J6*0.9*16% -> 2480.321
B39: 直接材料进项税 | F39: ='4成本'!F5*0.8*(0.25*17%+0.75*16%) -> 930.96723 | G39: ='4成本'!G5*0.8*16% -> 1086.0583 | H39: ='4成本'!H5*0.8*16% -> 1220.8266 | I39: ='4成本'!I5*0.8*16% -> 1295.0878 | J39: ='4成本'!J5*0.8*16% -> 1322.8378
B40: 运输费 | F40: ='6销管'!F15*(0.25*11%+0.75*10%) -> 24.467729 | G40: ='6销管'!G15*10% -> 28.282768 | H40: ='6销管'!H15*10% -> 31.79236 | I40: ='6销管'!I15*10% -> 33.726245 | J40: ='6销管'!J15*10% -> 34.448902
B41: 水电费 | F41: =('6销管'!F59+'6销管'!F65)*(0.25*17%+0.75*16%) -> 3.2971756 | G41: =('6销管'!G59+'6销管'!G65)*16% -> 3.8464564 | H41: =('6销管'!H59+'6销管'!H65)*16% -> 4.3237609 | I41: =('6销管'!I59+'6销管'!I65)*16% -> 4.5867694 | J41: =('6销管'!J59+'6销管'!J65)*16% -> 4.6850507
B42: 其他科目转入进项税 | F42: 24.56268
B43: 购买设备进项税 | F43: 91.536404 | G43: 88 | H43: 72 | I43: 56 | J43: 56
B44: 购买土地进项税
B45: 购买无形资产进项税 | F45: 2.3669989 | G45: 0 | H45: 3.6 | I45: 3.6 | J45: 3.6
B46: 未抵扣进项税
B47: 增值税进项税合计 | F47: =SUM(F39:F46) -> 1077.1982 | G47: =SUM(G39:G46) -> 1206.1875 | H47: =SUM(H39:H46) -> 1332.5427 | I47: =SUM(I39:I46) -> 1393.0008 | J47: =SUM(J39:J46) -> 1421.5718
B48: 应交增值税 | F48: =F37-F47 -> 668.36534 | G48: =G37-G47 -> 830.17177 | H48: =H37-H47 -> 956.50717 | I48: =I37-I47 -> 1035.2888 | J48: =J37-J47 -> 1058.7492

Sheet 6销管
B1: 销售费用、管理费用、研发费用预测表
B2: ='1报表'!B11 -> 评估基准日：2017/12/31
B3: ='1报表'!B12 -> 被评估单位：JSBD公司 | J3: 单位：万元
B4: 数据汇总 | C4: ='3收入'!C4 -> 2015年 | D4: ='3收入'!D4 -> 2016年 | E4: ='3收入'!E4 -> 2017年 | F4: ='3收入'!F4 -> 2018年 | G4: ='3收入'!G4 -> 2019年 | H4: ='3收入'!H4 -> 2020年 | I4: ='3收入'!I4 -> 2021年 | J4: ='3收入'!J4 -> 2022年
B5: 销售费用 | C5: ='1报表'!C100 -> 481.4591 | D5: ='1报表'!D100 -> 588.55087 | E5: ='1报表'!E100 -> 750.19684 | F5: =F41 -> 950.06399 | G5: =G41 -> 1125.6541 | H5: =H41 -> 1265.3359 | I5: =I41 -> 1342.3046 | J5: =J41 -> 1371.0663
B6: 管理费用 | C6: ='1报表'!C101 -> 694.30698 | D6: ='1报表'!D101 -> 710.43654 | E6: ='1报表'!E101 -> 1052.4467 | F6: =F121 -> 1140.1681 | G6: =G121 -> 1284.8847 | H6: =H121 -> 1341.4961 | I6: =I121 -> 1376.4758 | J6: =J121 -> 1432.4397
B7: 研发费用 | C7: ='1报表'!C102 -> 384.83578 | D7: ='1报表'!D102 -> 369.90657 | E7: ='1报表'!E102 -> 435.369 | F7: =F128 -> 596.77387 | G7: =G128 -> 707.06919 | H7: =H128 -> 794.809 | I7: =I128 -> 843.15614 | J7: =J128 -> 861.22256
B8: 销售、管理、研发费用 | C8: =SUM(C5:C7) -> 1560.6019 | D8: =SUM(D5:D7) -> 1668.894 | E8: =SUM(E5:E7) -> 2238.0126 | F8: =SUM(F5:F7) -> 2687.0059 | G8: =SUM(G5:G7) -> 3117.608 | H8: =SUM(H5:H7) -> 3401.641 | I8: =SUM(I5:I7) -> 3561.9365 | J8: =SUM(J5:J7) -> 3664.7286
B9: 营业收入 | C9: ='3收入'!C5 -> 5647.5609 | D9: ='3收入'!D5 -> 7304.7745 | E9: ='3收入'!E5 -> 9615.5763 | F9: ='3收入'!F5 -> 11935.477 | G9: ='3收入'!G5 -> 14141.384 | H9: ='3收入'!H5 -> 15896.18 | I9: ='3收入'!I5 -> 16863.123 | J9: ='3收入'!J5 -> 17224.451
B10: SGA/Sale | C10: =IF(C9,C8/C9,"na") -> 0.27633201 | D10: =IF(D9,D8/D9,"na") -> 0.22846619 | E10: =IF(E9,E8/E9,"na") -> 0.23274867 | F10: =IF(F9,F8/F9,"na") -> 0.22512765 | G10: =IF(G9,G8/G9,"na") -> 0.2204599 | H10: =IF(H9,H8/H9,"na") -> 0.2139911 | I10: =IF(I9,I8/I9,"na") -> 0.21122639 | J10: =IF(J9,J8/J9,"na") -> 0.21276316
B11: 销售费用分析（点行"+" 号展开） | E11: 科目内容只是示例，根据具体项目改动！ | I11: 金额大、变动大的科目要分析
B12: 销售费用 | C12: =C4 -> 2015年 | D12: =D4 -> 2016年 | E12: =E4 -> 2017年 | F12: =F4 -> 2018年 | G12: =G4 -> 2019年 | H12: =H4 -> 2020年 | I12: =I4 -> 2021年 | J12: =J4 -> 2022年
B13: 差旅费 | C13: 82.784085 | D13: 54.068012 | E13: 73.787718 | F13: =F9*$H$27 -> 89.51608 | G13: =G9*$H$27 -> 106.06038 | H13: =H9*$H$27 -> 119.22135 | I13: =I9*$H$27 -> 126.47342 | J13: =J9*$H$27 -> 129.18338
B14: 招待费 | C14: 29.756603 | D14: 39.310676 | E14: 60.444225 | F14: =F9*$H$28 -> 66.838673 | G14: =G9*$H$28 -> 79.191749 | H14: =H9*$H$28 -> 89.018608 | I14: =I9*$H$28 -> 94.433487 | J14: =J9*$H$28 -> 96.456927
B15: 运输费 | C15: 97.206981 | D15: 162.27442 | E15: 196.42828 | F15: =F9*$H$29 -> 238.70955 | G15: =G9*$H$29 -> 282.82768 | H15: =H9*$H$29 -> 317.9236 | I15: =I9*$H$29 -> 337.26245 | J15: =J9*$H$29 -> 344.48902
B16: 广告/宣传费 | C16: 77.886603 | D16: 78.650505 | E16: 82.714493 | F16: =F9*$H$30 -> 132.4838 | G16: =G9*$H$30 -> 156.96936 | H16: =H9*$H$30 -> 176.4476 | I16: =I9*$H$30 -> 187.18066 | J16: =J9*$H$30 -> 191.19141
B17: 商检/报关费 | C17: 55.205293 | D17: 26.047723 | E17: 20.436228 | F17: =F9*$H$31 -> 25.064502 | G17: =G9*$H$31 -> 29.696906 | H17: =H9*$H$31 -> 33.381978 | I17: =I9*$H$31 -> 35.412558 | J17: =J9*$H$31 -> 36.171347
B18: 检定费/检测费 | C18: 28.890597 | D18: 46.584152 | E18: 97.208652 | F18: =F9*$H$32 -> 119.35477 | G18: =G9*$H$32 -> 141.41384 | H18: =H9*$H$32 -> 158.9618 | I18: =I9*$H$32 -> 168.63123 | J18: =J9*$H$32 -> 172.24451
B19: 工资 | C19: 86.94148 | D19: 159.93703 | E19: 191.96455 | F19: =F9*$H$33 -> 238.70955 | G19: =G9*$H$33 -> 282.82768 | H19: =H9*$H$33 -> 317.9236 | I19: =I9*$H$33 -> 337.26245 | J19: =J9*$H$33 -> 344.48902
B20: 社保费 | C20: 16.949916 | D20: 13.427223 | E20: 14.380442 | F20: =F9*$H$34 -> 25.064502 | G20: =G9*$H$34 -> 29.696906 | H20: =H9*$H$34 -> 33.381978 | I20: =I9*$H$34 -> 35.412558 | J20: =J9*$H$34 -> 36.171347
B21: 其他 | C21: 5.837541 | D21: 8.25112 | E21: 12.832256 | F21: =F9*$H$35 -> 14.322573 | G21: =G9*$H$35 -> 16.969661 | H21: =H9*$H$35 -> 19.075416 | I21: =I9*$H$35 -> 20.235747 | J21: =J9*$H$35 -> 20.669341
B23: 合计 | C23: =SUM(C13:C22) -> 481.4591 | D23: =SUM(D13:D22) -> 588.55087 | E23: =SUM(E13:E22) -> 750.19684 | F23: =SUM(F13:F22) -> 950.06399 | G23: =SUM(G13:G22) -> 1125.6541 | H23: =SUM(H13:H22) -> 1265.3359 | I23: =SUM(I13:I22) -> 1342.3046 | J23: =SUM(J13:J22) -> 1371.0663
B24: 检查核对 | C24: =C23-C5 -> 0 | D24: =D23-D5 -> 0 | E24: =E23-E5 -> 0
B25: 与报表一致? | C25: =IF(ROUND(C24,0)=0,"OK","需要检查") -> OK | D25: =IF(ROUND(D24,0)=0,"OK","需要检查") -> OK | E25: =IF(ROUND(E24,0)=0,"OK","需要检查") -> OK
B26: 占收入比例 | E26: =C12&"-"&E12 -> 2015年-2017年 | F26: 相关系数 | G26: 平均值 | H26: 评估取值
B27: =B13 -> 差旅费 | C27: =IF(C13,C13/C$9,"") -> 0.014658379 | D27: =IF(D13,D13/D$9,"") -> 0.0074017359 | E27: =IF(E13,E13/E$9,"") -> 0.0076737697 | F27: =IF(COUNT(C27:E27)>2,CORREL(C$9:E$9,C13:E13),"") -> -0.21475276 | G27: =AVERAGE(C27:E27) -> 0.0099112947 | H27: 0.0075
B28: =B14 -> 招待费 | C28: =IF(C14,C14/C$9,"") -> 0.00526893 | D28: =IF(D14,D14/D$9,"") -> 0.0053815044 | E28: =IF(E14,E14/E$9,"") -> 0.0062860741 | F28: =IF(COUNT(C28:E28)>2,CORREL(C$9:E$9,C14:E14),"") -> 0.99284575 | G28: =AVERAGE(C28:E28) -> 0.0056455028 | H28: 0.0056
B29: =B15 -> 运输费 | C29: =IF(C15,C15/C$9,"") -> 0.017212206 | D29: =IF(D15,D15/D$9,"") -> 0.022214843 | E29: =IF(E15,E15/E$9,"") -> 0.020428134 | F29: =IF(COUNT(C29:E29)>2,CORREL(C$9:E$9,C15:E15),"") -> 0.96302306 | G29: =AVERAGE(C29:E29) -> 0.019951728 | H29: 0.02
B30: =B16 -> 广告/宣传费 | C30: =IF(C16,C16/C$9,"") -> 0.013791193 | D30: =IF(D16,D16/D$9,"") -> 0.010767 | E30: =IF(E16,E16/E$9,"") -> 0.0086021358 | F30: =IF(COUNT(C30:E30)>2,CORREL(C$9:E$9,C16:E16),"") -> 0.96075935 | G30: =AVERAGE(C30:E30) -> 0.011053443 | H30: 0.0111
B31: =B17 -> 商检/报关费 | C31: =IF(C17,C17/C$9,"") -> 0.0097750683 | D31: =IF(D17,D17/D$9,"") -> 0.003565849 | E31: =IF(E17,E17/E$9,"") -> 0.0021253253 | F31: =IF(COUNT(C31:E31)>2,CORREL(C$9:E$9,C17:E17),"") -> -0.89268551 | G31: =AVERAGE(C31:E31) -> 0.0051554142 | H31: 0.0021
B32: =B18 -> 检定费/检测费 | C32: =IF(C18,C18/C$9,"") -> 0.0051155884 | D32: =IF(D18,D18/D$9,"") -> 0.0063772197 | E32: =IF(E18,E18/E$9,"") -> 0.010109498 | F32: =IF(COUNT(C32:E32)>2,CORREL(C$9:E$9,C18:E18),"") -> 0.98444391 | G32: =AVERAGE(C32:E32) -> 0.0072007688 | H32: 0.01
B33: =B19 -> 工资 | C33: =IF(C19,C19/C$9,"") -> 0.015394518 | D33: =IF(D19,D19/D$9,"") -> 0.021894862 | E33: =IF(E19,E19/E$9,"") -> 0.019963915 | F33: =IF(COUNT(C33:E33)>2,CORREL(C$9:E$9,C19:E19),"") -> 0.95038258 | G33: =AVERAGE(C33:E33) -> 0.019084432 | H33: 0.02
B34: =B20 -> 社保费 | C34: =IF(C20,C20/C$9,"") -> 0.0030012808 | D34: =IF(D20,D20/D$9,"") -> 0.0018381434 | E34: =IF(E20,E20/E$9,"") -> 0.0014955361 | F34: =IF(COUNT(C34:E34)>2,CORREL(C$9:E$9,C20:E20),"") -> -0.63478805 | G34: =AVERAGE(C34:E34) -> 0.0021116534 | H34: 0.0021
B35: =B21 -> 其他 | C35: =IF(C21,C21/C$9,"") -> 0.0010336393 | D35: =IF(D21,D21/D$9,"") -> 0.0011295516 | E35: =IF(E21,E21/E$9,"") -> 0.001334528 | F35: =IF(COUNT(C35:E35)>2,CORREL(C$9:E$9,C21:E21),"") -> 0.99662131 | G35: =AVERAGE(C35:E35) -> 0.0011659063 | H35: 0.0012
B37: 销售费用分析
B38: 项目 | C38: =C4 -> 2015年 | D38: =D4 -> 2016年 | E38: =E4 -> 2017年 | F38: =F4 -> 2018年 | G38: =G4 -> 2019年 | H38: =H4 -> 2020年 | I38: =I4 -> 2021年 | J38: =J4 -> 2022年
B39: 销售费用 | C39: =C23 -> 481.4591 | D39: =D23 -> 588.55087 | E39: =E23 -> 750.19684 | F39: =F23 -> 950.06399 | G39: =G23 -> 1125.6541 | H39: =H23 -> 1265.3359 | I39: =I23 -> 1342.3046 | J39: =J23 -> 1371.0663
B40: 占收入比 | C40: =IF(C9,C39/C9,"na") -> 0.085250803 | D40: =IF(D9,D39/D9,"na") -> 0.080570709 | E40: =IF(E9,E39/E9,"na") -> 0.078018916
B41: 销售费用 | F41: =IF(F39,F39,F40*F9) -> 950.06399 | G41: =IF(G39,G39,G40*G9) -> 1125.6541 | H41: =IF(H39,H39,H40*H9) -> 1265.3359 | I41: =IF(I39,I39,I40*I9) -> 1342.3046 | J41: =IF(J39,J39,J40*J9) -> 1371.0663
B42: 占收入比 | F42: =IF(F9,F41/F9,"na") -> 0.0796 | G42: =IF(G9,G41/G9,"na") -> 0.0796 | H42: =IF(H9,H41/H9,"na") -> 0.0796 | I42: =IF(I9,I41/I9,"na") -> 0.0796 | J42: =IF(J9,J41/J9,"na") -> 0.0796
B44: 管理费用分析（点行 "+" 号展开） | E44: 科目内容只是示例，根据具体项目改动！ | I44: 金额大、变动大的科目要分析
B45: 管理费用 | C45: =C4 -> 2015年 | D45: =D4 -> 2016年 | E45: =E4 -> 2017年 | F45: =F4 -> 2018年 | G45: =G4 -> 2019年 | H45: =H4 -> 2020年 | I45: =I4 -> 2021年 | J45: =J4 -> 2022年
B46: 办公费 | C46: 41.822011 | D46: 8.263602 | E46: 45.229921 | F46: 25 | G46: =F46*(1+$H$95) -> 26.25 | H46: =G46*(1+$H$95) -> 27.5625 | I46: =H46*(1+$H$95) -> 28.940625 | J46: =I46*(1+$H$95) -> 30.387656 | K46: 17年：有21万为电脑、家具、软件、监控等应计入固定资产，但企业做了当期费用化处理
B47: 通讯费 | D47: 6.109275 | E47: 4.988055 | F47: 6 | G47: =F47*(1+$H$96) -> 6.3 | H47: =G47*(1+$H$96) -> 6.615 | I47: =H47*(1+$H$96) -> 6.94575 | J47: =I47*(1+$H$96) -> 7.2930375
B48: 汽车费 | C48: 28.550807 | D48: 24.986498 | E48: 29.397226 | F48: =E48*(1+$H$96) -> 30.867087 | G48: =F48*(1+$H$96) -> 32.410442 | H48: =G48*(1+$H$96) -> 34.030964 | I48: =H48*(1+$H$96) -> 35.732512 | J48: =I48*(1+$H$96) -> 37.519138
B49: 社会保险费 | C49: 47.52855 | D49: 57.051292 | E49: 75.583544 | F49: =F9*$H$75 -> 95.483819 | G49: =G9*$H$75 -> 113.13107 | H49: =H9*$H$75 -> 127.16944 | I49: =I9*$H$75 -> 134.90498 | J49: =J9*$H$75 -> 137.79561
B50: 工资 | C50: 177.67083 | D50: 197.30127 | E50: 195.13102 | F50: =F9*$H$76 -> 313.90305 | G50: =G9*$H$76 -> 371.91839 | H50: =H9*$H$76 -> 418.06953 | I50: =I9*$H$76 -> 443.50013 | J50: =J9*$H$76 -> 453.00307
B51: 福利费 | C51: 81.736865 | D51: 86.809175 | E51: 96.303904 | F51: =F9*$H$77 -> 144.41928 | G51: =G9*$H$77 -> 171.11074 | H51: =H9*$H$77 -> 192.34378 | I51: =I9*$H$77 -> 204.04378 | J51: =J9*$H$77 -> 208.41586
B52: 折旧 | C52: 101.35448 | D52: 77.249111 | E52: 74.446046 | F52: ='7折旧'!F7 -> 73.4688 | G52: ='7折旧'!G7 -> 78.0408 | H52: ='7折旧'!H7 -> 40.810513 | I52: ='7折旧'!I7 -> 20.0711 | J52: ='7折旧'!J7 -> 21.3911 | K52: 管理费用中的折旧
B53: 无形资产摊销 | C53: 14.546207 | D53: 11.930153 | E53: 14.700808 | F53: ='8摊销'!F6 -> 71.838051 | G53: ='8摊销'!G6 -> 71.838051 | H53: ='8摊销'!H6 -> 51.201763 | I53: ='8摊销'!I6 -> 37.678504 | J53: ='8摊销'!J6 -> 57.678504
B54: 长摊资产摊销 | F54: ='8摊销'!F5 -> 0 | G54: ='8摊销'!G5 -> 0 | H54: ='8摊销'!H5 -> 0 | I54: ='8摊销'!I5 -> 0 | J54: ='8摊销'!J5 -> 0
B55: 培训费 | C55: 22.64804 | D55: 13.569061 | E55: 27.83403 | F55: =E55*(1+$H$104) -> 29.225731 | G55: =F55*(1+$H$104) -> 30.687018 | H55: =G55*(1+$H$104) -> 32.221369 | I55: =H55*(1+$H$104) -> 33.832437 | J55: =I55*(1+$H$104) -> 35.524059
B56: 诉讼律师费 | C56: 30.432 | D56: 3.670093 | E56: 47.18888 | F56: 25 | G56: =F56 -> 25 | H56: =G56 -> 25 | I56: =H56 -> 25 | J56: =I56 -> 25
B57: 工会经费 | C57: 3.913601 | D57: 13.850793 | E57: 18.1894 | F57: =F9*$H$83 -> 23.870955 | G57: =G9*$H$83 -> 28.282768 | H57: =H9*$H$83 -> 31.79236 | I57: =I9*$H$83 -> 33.726245 | J57: =J9*$H$83 -> 34.448902
B58: 住房公积金 | E58: 11.0471 | F58: =F9*$H$84 -> 13.129025 | G58: =G9*$H$84 -> 15.555522 | H58: =H9*$H$84 -> 17.485798 | I58: =I9*$H$84 -> 18.549435 | J58: =J9*$H$84 -> 18.946896
B59: 电费 | D59: 5.55046 | E59: 6.085231 | F59: =F9*$H$85 -> 8.3548341 | G59: =G9*$H$85 -> 9.8989686 | H59: =H9*$H$85 -> 11.127326 | I59: =I9*$H$85 -> 11.804186 | J59: =J9*$H$85 -> 12.057116
B60: 服务费 | C60: 14.686545 | E60: 85.490876 | F60: 50 | G60: =F60*(1+$H$109) -> 52.5 | H60: =G60*(1+$H$109) -> 55.125 | I60: =H60*(1+$H$109) -> 57.88125 | J60: =I60*(1+$H$109) -> 60.775313
B61: 劳务费 | C61: 6.09 | D61: 7.800475 | E61: 22.264155 | F61: =E61*(1+$H$110) -> 23.377363 | G61: =F61*(1+$H$110) -> 24.546231 | H61: =G61*(1+$H$110) -> 25.773542 | I61: =H61*(1+$H$110) -> 27.06222 | J61: =I61*(1+$H$110) -> 28.415331
B62: 咨询顾问费 | D62: 11.824258 | E62: 138.25889 | F62: 11 | G62: =F62*(1+$H$111) -> 11.55 | H62: =G62*(1+$H$111) -> 12.1275 | I62: =H62*(1+$H$111) -> 12.733875 | J62: =I62*(1+$H$111) -> 13.370569 | K62: 17年：其中127万为17年新三板的券商费用
B63: 差旅费 | C63: 23.790021 | D63: 74.207794 | E63: 62.853446 | F63: =F9*$H$89 -> 83.548341 | G63: =G9*$H$89 -> 98.989686 | H63: =H9*$H$89 -> 111.27326 | I63: =I9*$H$89 -> 118.04186 | J63: =J9*$H$89 -> 120.57116
B64: 招待费 | C64: 60.28409 | D64: 77.368081 | E64: 56.901213 | F64: =E64*(1+$H$113) -> 59.746274 | G64: =F64*(1+$H$113) -> 62.733587 | H64: =G64*(1+$H$113) -> 65.870267 | I64: =H64*(1+$H$113) -> 69.16378 | J64: =I64*(1+$H$113) -> 72.621969
B65: 水费、污水费 | C65: 6.227687 | D65: 6.83465 | E65: 8.131775 | F65: =F9*$H$91 -> 11.935477 | G65: =G9*$H$91 -> 14.141384 | H65: =H9*$H$91 -> 15.89618 | I65: =I9*$H$91 -> 16.863123 | J65: =J9*$H$91 -> 17.224451
B66: 其他 | C66: 33.025233 | D66: 26.060497 | E66: 32.421207 | F66: 40 | G66: =F66 -> 40 | H66: =G66 -> 40 | I66: =H66 -> 40 | J66: =I66 -> 40
B68: 合计 | C68: =SUM(C46:C67) -> 694.30697 | D68: =SUM(D46:D67) -> 710.43654 | E68: =SUM(E46:E67) -> 1052.4467 | F68: =SUM(F46:F67) -> 1140.1681 | G68: =SUM(G46:G67) -> 1284.8847 | H68: =SUM(H46:H67) -> 1341.4961 | I68: =SUM(I46:I67) -> 1376.4758 | J68: =SUM(J46:J67) -> 1432.4397
B69: 检查核对 | C69: =C68-C6 -> 0 | D69: =D68-D6 -> 0 | E69: =E68-E6 -> 0
B70: 与报表一致? | C70: =IF(ROUND(C69,0)=0,"OK","需要检查") -> OK | D70: =IF(ROUND(D69,0)=0,"OK","需要检查") -> OK | E70: =IF(ROUND(E69,0)=0,"OK","需要检查") -> OK
B71: 占收入比例 | E71: =C45&"-"&E45 -> 2015年-2017年 | F71: 相关系数 | G71: 平均值 | H71: 评估取值
B72: =B46 -> 办公费 | C72: =IF(C46,C46/C$9,"") -> 0.0074053228 | D72: =IF(D46,D46/D$9,"") -> 0.0011312604 | E72: =IF(E46,E46/E$9,"") -> 0.004703818 | F72: =IF(COUNT(C72:E72)>2,CORREL(C$9:E$9,C46:E46),"") -> 0.17737105 | G72: =AVERAGE(C72:E72) -> 0.004413467
B73: =B47 -> 通讯费 | C73: =IF(C47,C47/C$9,"") | D73: =IF(D47,D47/D$9,"") -> 0.00083633998 | E73: =IF(E47,E47/E$9,"") -> 0.00051874738 | F73: =IF(COUNT(C73:E73)>2,CORREL(C$9:E$9,C47:E47),"") | G73: =AVERAGE(C73:E73) -> 0.00067754368 | I73: 少于3个数据，无意义
B74: =B48 -> 汽车费 | C74: =IF(C48,C48/C$9,"") -> 0.0050554226 | D74: =IF(D48,D48/D$9,"") -> 0.0034205707 | E74: =IF(E48,E48/E$9,"") -> 0.0030572505 | F74: =IF(COUNT(C74:E74)>2,CORREL(C$9:E$9,C48:E48),"") -> 0.27309763 | G74: =AVERAGE(C74:E74) -> 0.0038444146
B75: =B49 -> 社会保险费 | C75: =IF(C49,C49/C$9,"") -> 0.0084157659 | D75: =IF(D49,D49/D$9,"") -> 0.0078101373 | E75: =IF(E49,E49/E$9,"") -> 0.0078605318 | F75: =IF(COUNT(C75:E75)>2,CORREL(C$9:E$9,C49:E49),"") -> 0.99608516 | G75: =AVERAGE(C75:E75) -> 0.0080288117 | H75: 0.008
B76: =B50 -> 工资 | C76: =IF(C50,C50/C$9,"") -> 0.031459747 | D76: =IF(D50,D50/D$9,"") -> 0.027009906 | E76: =IF(E50,E50/E$9,"") -> 0.020293222 | F76: =IF(COUNT(C76:E76)>2,CORREL(C$9:E$9,C50:E50),"") -> 0.75219309 | G76: =AVERAGE(C76:E76) -> 0.026254291 | H76: 0.0263
B77: =B51 -> 福利费 | C77: =IF(C51,C51/C$9,"") -> 0.01447295 | D77: =IF(D51,D51/D$9,"") -> 0.011883895 | E77: =IF(E51,E51/E$9,"") -> 0.010015406 | F77: =IF(COUNT(C77:E77)>2,CORREL(C$9:E$9,C51:E51),"") -> 0.99690452 | G77: =AVERAGE(C77:E77) -> 0.012124084 | H77: 0.0121
B78: =B52 -> 折旧 | C78: =IF(C52,C52/C$9,"") -> 0.017946594 | D78: =IF(D52,D52/D$9,"") -> 0.010575153 | E78: =IF(E52,E52/E$9,"") -> 0.0077422344 | F78: =IF(COUNT(C78:E78)>2,CORREL(C$9:E$9,C52:E52),"") -> -0.86606186 | G78: =AVERAGE(C78:E78) -> 0.012087994
B79: =B53 -> 无形资产摊销 | C79: =IF(C53,C53/C$9,"") -> 0.0025756618 | D79: =IF(D53,D53/D$9,"") -> 0.0016331993 | E79: =IF(E53,E53/E$9,"") -> 0.0015288535 | F79: =IF(COUNT(C79:E79)>2,CORREL(C$9:E$9,C53:E53),"") -> 0.14398021 | G79: =AVERAGE(C79:E79) -> 0.0019125716
B80: =B54 -> 长摊资产摊销
B81: =B55 -> 培训费 | C81: =IF(C55,C55/C$9,"") -> 0.0040102339 | D81: =IF(D55,D55/D$9,"") -> 0.0018575606 | E81: =IF(E55,E55/E$9,"") -> 0.0028946814 | F81: =IF(COUNT(C81:E81)>2,CORREL(C$9:E$9,C55:E55),"") -> 0.44585934 | G81: =AVERAGE(C81:E81) -> 0.0029208253
B82: =B56 -> 诉讼律师费 | C82: =IF(C56,C56/C$9,"") -> 0.005388521 | D82: =IF(D56,D56/D$9,"") -> 0.00050242386 | E82: =IF(E56,E56/E$9,"") -> 0.0049075457 | F82: =IF(COUNT(C82:E82)>2,CORREL(C$9:E$9,C56:E56),"") -> 0.4674899 | G82: =AVERAGE(C82:E82) -> 0.0035994968
B83: =B57 -> 工会经费 | C83: =IF(C57,C57/C$9,"") -> 0.0006929719 | D83: =IF(D57,D57/D$9,"") -> 0.0018961288 | E83: =IF(E57,E57/E$9,"") -> 0.0018916599 | F83: =IF(COUNT(C83:E83)>2,CORREL(C$9:E$9,C57:E57),"") -> 0.95002529 | G83: =AVERAGE(C83:E83) -> 0.0014935868 | H83: 0.002
B84: =B58 -> 住房公积金 | C84: =IF(C58,C58/C$9,"") | D84: =IF(D58,D58/D$9,"") | E84: =IF(E58,E58/E$9,"") -> 0.0011488755 | F84: =IF(COUNT(C84:E84)>2,CORREL(C$9:E$9,C58:E58),"") | G84: =AVERAGE(C84:E84) -> 0.0011488755 | H84: 0.0011
B85: =B59 -> 电费 | C85: =IF(C59,C59/C$9,"") | D85: =IF(D59,D59/D$9,"") -> 0.00075984002 | E85: =IF(E59,E59/E$9,"") -> 0.00063285141 | F85: =IF(COUNT(C85:E85)>2,CORREL(C$9:E$9,C59:E59),"") | G85: =AVERAGE(C85:E85) -> 0.00069634571 | H85: 0.0007 | I85: 少于3个数据，无意义
B86: =B60 -> 服务费 | C86: =IF(C60,C60/C$9,"") -> 0.0026005112 | D86: =IF(D60,D60/D$9,"") | E86: =IF(E60,E60/E$9,"") -> 0.0088908738 | F86: =IF(COUNT(C86:E86)>2,CORREL(C$9:E$9,C60:E60),"") | G86: =AVERAGE(C86:E86) -> 0.0057456925 | I86: 少于3个数据，无意义 | K86: 工业设计服务费、专利代理费、软件服务费等
B87: =B61 -> 劳务费 | C87: =IF(C61,C61/C$9,"") -> 0.0010783416 | D87: =IF(D61,D61/D$9,"") -> 0.0010678598 | E87: =IF(E61,E61/E$9,"") -> 0.002315426 | F87: =IF(COUNT(C87:E87)>2,CORREL(C$9:E$9,C61:E61),"") -> 0.945266 | G87: =AVERAGE(C87:E87) -> 0.0014872091
B88: =B62 -> 咨询顾问费 | C88: =IF(C62,C62/C$9,"") | D88: =IF(D62,D62/D$9,"") -> 0.0016187027 | E88: =IF(E62,E62/E$9,"") -> 0.014378637 | F88: =IF(COUNT(C88:E88)>2,CORREL(C$9:E$9,C62:E62),"") | G88: =AVERAGE(C88:E88) -> 0.00799867 | I88: 少于3个数据，无意义
B89: =B63 -> 差旅费 | C89: =IF(C63,C63/C$9,"") -> 0.0042124417 | D89: =IF(D63,D63/D$9,"") -> 0.010158807 | E89: =IF(E63,E63/E$9,"") -> 0.0065366281 | F89: =IF(COUNT(C89:E89)>2,CORREL(C$9:E$9,C63:E63),"") -> 0.6713606 | G89: =AVERAGE(C89:E89) -> 0.0069692922 | H89: 0.007
B90: =B64 -> 招待费 | C90: =IF(C64,C64/C$9,"") -> 0.010674359 | D90: =IF(D64,D64/D$9,"") -> 0.01059144 | E90: =IF(E64,E64/E$9,"") -> 0.0059176082 | F90: =IF(COUNT(C90:E90)>2,CORREL(C$9:E$9,C64:E64),"") -> -0.24701753 | G90: =AVERAGE(C90:E90) -> 0.0090611356
B91: =B65 -> 水费、污水费 | C91: =IF(C65,C65/C$9,"") -> 0.0011027215 | D91: =IF(D65,D65/D$9,"") -> 0.00093564147 | E91: =IF(E65,E65/E$9,"") -> 0.00084568774 | F91: =IF(COUNT(C91:E91)>2,CORREL(C$9:E$9,C65:E65),"") -> 0.99379269 | G91: =AVERAGE(C91:E91) -> 0.00096135025 | H91: 0.001
B92: =B66 -> 其他 | C92: =IF(C66,C66/C$9,"") -> 0.0058476985 | D92: =IF(D66,D66/D$9,"") -> 0.0035675977 | E92: =IF(E66,E66/E$9,"") -> 0.0033717383 | F92: =IF(COUNT(C92:E92)>2,CORREL(C$9:E$9,C66:E66),"") -> 0.016460863 | G92: =AVERAGE(C92:E92) -> 0.0042623448
B94: 增长比例 | G94: 平均值 | H94: 评估取值
B95: =B46 -> 办公费 | D95: =IF(C46,D46/C46-1,"") -> -0.80241022 | E95: =IF(D46,E46/D46-1,"") -> 4.4733905 | G95: =AVERAGE(C95:E95) -> 1.8354902 | H95: 0.05
B96: =B47 -> 通讯费 | D96: =IF(C47,D47/C47-1,"") | E96: =IF(D47,E47/D47-1,"") -> -0.18352751 | G96: =AVERAGE(C96:E96) -> -0.18352751 | H96: 0.05
B97: =B48 -> 汽车费 | D97: =IF(C48,D48/C48-1,"") -> -0.12484092 | E97: =IF(D48,E48/D48-1,"") -> 0.17652446 | G97: =AVERAGE(C97:E97) -> 0.025841769 | H97: 0.05
B98: =B49 -> 社会保险费 | D98: =IF(C49,D49/C49-1,"") -> 0.20035835 | E98: =IF(D49,E49/D49-1,"") -> 0.32483492 | G98: =AVERAGE(C98:E98) -> 0.26259664
B99: =B50 -> 工资 | D99: =IF(C50,D50/C50-1,"") -> 0.11048767 | E99: =IF(D50,E50/D50-1,"") -> -0.010999666 | G99: =AVERAGE(C99:E99) -> 0.049744004
B100: =B51 -> 福利费 | D100: =IF(C51,D51/C51-1,"") -> 0.062056576 | E100: =IF(D51,E51/D51-1,"") -> 0.10937472 | G100: =AVERAGE(C100:E100) -> 0.085715647
B101: =B52 -> 折旧 | D101: =IF(C52,D52/C52-1,"") -> -0.23783233 | E101: =IF(D52,E52/D52-1,"") -> -0.036286049 | G101: =AVERAGE(C101:E101) -> -0.13705919
B102: =B53 -> 无形资产摊销 | D102: =IF(C53,D53/C53-1,"") -> -0.17984441 | E102: =IF(D53,E53/D53-1,"") -> 0.23223969 | G102: =AVERAGE(C102:E102) -> 0.026197639
B103: =B54 -> 长摊资产摊销 | G103: =AVERAGE(C103:E103) -> #DIV/0!
B104: =B55 -> 培训费 | D104: =IF(C55,D55/C55-1,"") -> -0.40087261 | E104: =IF(D55,E55/D55-1,"") -> 1.0512864 | G104: =AVERAGE(C104:E104) -> 0.32520688 | H104: 0.05
B105: =B56 -> 诉讼律师费 | D105: =IF(C56,D56/C56-1,"") -> -0.8794002 | E105: =IF(D56,E56/D56-1,"") -> 11.85768 | G105: =AVERAGE(C105:E105) -> 5.4891397 | I105: 固定费用
...

Sheet 7折旧
B1: 固定资产支出与折旧预测表
B2: ='1报表'!B11 -> 评估基准日：2017/12/31 | K2: 该工作表已保护！
B3: ='1报表'!B12 -> 被评估单位：JSBD公司 | J3: 单位：万元
B4: 项目 | C4: 评估取值 | D4: =E4&"占比" -> 2017年占比 | E4: ='3收入'!E4 -> 2017年 | F4: ='3收入'!F4 -> 2018年 | G4: ='3收入'!G4 -> 2019年 | H4: ='3收入'!H4 -> 2020年 | I4: ='3收入'!I4 -> 2021年 | J4: ='3收入'!J4 -> 2022年
B5: 生产成本中的折旧 | C5: 0.88 | D5: =IF(E5,E5/E$9,"") -> 0.87156503 | E5: 505.19395 | F5: =$C5*F$9 -> 538.7712 | G5: =$C5*G$9 -> 572.2992 | H5: =$C5*H$9 -> 299.2771 | I5: =$C5*I$9 -> 147.18807 | J5: =$C5*J$9 -> 156.86807
B6: 销售费用中的折旧 | D6: =IF(E6,E6/E$9,"") | F6: =$C6*F$9 -> 0 | G6: =$C6*G$9 -> 0 | H6: =$C6*H$9 -> 0 | I6: =$C6*I$9 -> 0 | J6: =$C6*J$9 -> 0
B7: 管理费用中的折旧 | C7: 0.12 | D7: =IF(E7,E7/E$9,"") -> 0.12843497 | E7: 74.446046 | F7: =$C7*F$9 -> 73.4688 | G7: =$C7*G$9 -> 78.0408 | H7: =$C7*H$9 -> 40.810513 | I7: =$C7*I$9 -> 20.0711 | J7: =$C7*J$9 -> 21.3911
B8: 研发费用中的折旧 | D8: =IF(E8,E8/E$9,"") | F8: =$C8*F$9 -> 0 | G8: =$C8*G$9 -> 0 | H8: =$C8*H$9 -> 0 | I8: =$C8*I$9 -> 0 | J8: =$C8*J$9 -> 0
B9: 固定资产折旧额 | C9: =SUM(C5:C8) -> 1 | D9: =SUM(D5:D8) -> 1 | E9: =SUM(E5:E8) -> 579.64 | F9: =F28+F43 -> 612.24 | G9: =G28+G43 -> 650.34 | H9: =H28+H43 -> 340.08761 | I9: =I28+I43 -> 167.25917 | J9: =J28+J43 -> 178.25917
B10: 固定资产支出 | F10: =F26+SUM(F37:F39) -> 232 | G10: =G26+SUM(G37:G39) -> 50 | H10: =H26+SUM(H37:H39) -> 50 | I10: =I26+SUM(I37:I39) -> 50 | J10: =J26+SUM(J37:J39) -> 50
B11: 未转固资产的处理
B12: 科目 | C12: 折旧率 | D12: 折旧年限 | E12: =E4 -> 2017年 | F12: =F4 -> 2018年 | G12: =G4 -> 2019年 | H12: =H4 -> 2020年 | I12: =I4 -> 2021年 | J12: =J4 -> 2022年
B13: 未转固建筑物的账面值
B14: 年度转固金额
B15: 未转固设备的账面值 | E15: =201.28+153.52 -> 354.8
B16: 年度转固金额-机器 | F16: =E15 -> 354.8
B17: 年度转固金额-车辆
B18: 年度转固金额-电子设备
B20: 房屋建筑物
B21: 项目 | C21: 折旧率 | D21: 折旧年限 | E21: ='3收入'!E4 -> 2017年 | F21: ='3收入'!F4 -> 2018年 | G21: ='3收入'!G4 -> 2019年 | H21: ='3收入'!H4 -> 2020年 | I21: ='3收入'!I4 -> 2021年 | J21: ='3收入'!J4 -> 2022年
B22: 基准日已提足折旧建筑类账面原值 | E22: 0
B23: 基准日未提足折旧建筑类账面原值 | E23: 1569.6667
B24: 基准日建筑类账面净值 | E24: 1134.7382
B25: 存量建筑类折旧额 | C25: 0.0475 | F25: =IF(E24>E23*C25,E23*C25,E24) -> 74.559169 | G25: =IF(($E24-SUM($F25:F25))>$F25,$F25,$E24-SUM($F25:F25)) -> 74.559169 | H25: =IF(($E24-SUM($F25:G25))>$F25,$F25,$E24-SUM($F25:G25)) -> 74.559169 | I25: =IF(($E24-SUM($F25:H25))>$F25,$F25,$E24-SUM($F25:H25)) -> 74.559169 | J25: =IF(($E24-SUM($F25:I25))>$F25,$F25,$E24-SUM($F25:I25)) -> 74.559169
B26: 新增建筑物投入原值
B27: 新增建筑类折旧额 | F27: =IF($D13,SUM($F14:F14)/$D13,0)+IF($D27,SUM($F26:F26)/$D27,0) -> 0 | G27: =IF($D13,SUM($F14:G14)/$D13,0)+IF($D27,SUM($F26:G26)/$D27,0) -> 0 | H27: =IF($D13,SUM($F14:H14)/$D13,0)+IF($D27,SUM($F26:H26)/$D27,0) -> 0 | I27: =IF($D13,SUM($F14:I14)/$D13,0)+IF($D27,SUM($F26:I26)/$D27,0) -> 0 | J27: =IF($D13,SUM($F14:J14)/$D13,0)+IF($D27,SUM($F26:J26)/$D27,0) -> 0
B28: 建筑类折旧额小计 | F28: =F25+F27 -> 74.559169 | G28: =G25+G27 -> 74.559169 | H28: =H25+H27 -> 74.559169 | I28: =I25+I27 -> 74.559169 | J28: =J25+J27 -> 74.559169
B29: 期末建筑物类账面净值 | F29: =E24+F14+F26-F28 -> 1060.1791 | G29: =F29+G14+G26-G28 -> 985.61989 | H29: =G29+H14+H26-H28 -> 911.06072 | I29: =H29+I14+I26-I28 -> 836.50156 | J29: =I29+J14+J26-J28 -> 761.94239
B31: 设备
B32: 项目 | C32: 折旧率 | D32: 折旧年限 | E32: =E21 -> 2017年 | F32: =F21 -> 2018年 | G32: =G21 -> 2019年 | H32: =H21 -> 2020年 | I32: =I21 -> 2021年 | J32: =J21 -> 2022年
B33: 基准日已提足折旧设备类账面原值 | E33: 0
B34: 基准日未提足折旧设备类账面原值 | E34: 3572.8487
B35: 基准日设备类账面净值 | E35: 1193.9901
B36: 存量设备类折旧额 | C36: 0.14136642 | F36: =IF(E35>E34*C36,E34*C36,E35) -> 505.08083 | G36: =IF(($E35-SUM($F36:F36))>$F36,$F36,$E35-SUM($F36:F36)) -> 505.08083 | H36: =IF(($E35-SUM($F36:G36))>$F36,$F36,$E35-SUM($F36:G36)) -> 183.82844 | I36: =IF(($E35-SUM($F36:H36))>$F36,$F36,$E35-SUM($F36:H36)) -> 0 | J36: =IF(($E35-SUM($F36:I36))>$F36,$F36,$E35-SUM($F36:I36)) -> 0
B37: 新增机器投入原值 | D37: 9 | F37: =232 -> 232
B38: 新增车辆投入原值 | D38: 4 | G38: 20 | H38: 20 | I38: 20 | J38: 20
B39: 新增电子设备投入原值 | D39: 5 | G39: 30 | H39: 30 | I39: 30 | J39: 30
B40: 新增机器折旧额 | F40: =F55 -> 32.6 | G40: =G55 -> 65.2 | H40: =H55 -> 65.2 | I40: =I55 -> 65.2 | J40: =J55 -> 65.2
B41: 新增车辆折旧额 | F41: =F63 -> 0 | G41: =G63 -> 2.5 | H41: =H63 -> 7.5 | I41: =I63 -> 12.5 | J41: =J63 -> 17.5
B42: 新增电子设备折旧额 | F42: =F71 -> 0 | G42: =G71 -> 3 | H42: =H71 -> 9 | I42: =I71 -> 15 | J42: =J71 -> 21
B43: 设备类折旧额小计 | F43: =F36+SUM(F40:F42) -> 537.68083 | G43: =G36+SUM(G40:G42) -> 575.78083 | H43: =H36+SUM(H40:H42) -> 265.52844 | I43: =I36+SUM(I40:I42) -> 92.7 | J43: =J36+SUM(J40:J42) -> 103.7
B44: 期末设备类账面净值 | F44: =E35+SUM(F16:F18)+SUM(F37:F39)-F43 -> 1243.1093 | G44: =F44+SUM(G16:G18)+SUM(G37:G39)-G43 -> 717.32844 | H44: =G44+SUM(H16:H18)+SUM(H37:H39)-H43 -> 501.8 | I44: =H44+SUM(I16:I18)+SUM(I37:I39)-I43 -> 459.1 | J44: =I44+SUM(J16:J18)+SUM(J37:J39)-J43 -> 405.4
B45: 基准日数据与资产负债表检查核对
B46: 固定资产 | E46: =IF(ROUND(E24+E35-'2报表调整'!G32,-1),"数据不一致","OK") -> OK
B47: 在建工程 | E47: =IF(ROUND(E13+E15+'8摊销'!E13-'2报表调整'!G33,-1),"数据不一致","OK") -> OK
B49: 年度 | C49: 机器折旧额自动计算过程 | F49: =F32 -> 2018年 | G49: =G32 -> 2019年 | H49: =H32 -> 2020年 | I49: =I32 -> 2021年 | J49: =J32 -> 2022年
B50: =F49 -> 2018年 | F50: =IF(D37,(F16+F37)/D37/2,0) -> 32.6 | G50: =IF(D37,(F16+F37)/D37,0) -> 65.2 | H50: =IF(($F16+$F37-SUM($F50:G50))>$G50,$G50,$F16+$F37-SUM($F50:G50)) -> 65.2 | I50: =IF(($F16+$F37-SUM($F50:H50))>$G50,$G50,$F16+$F37-SUM($F50:H50)) -> 65.2 | J50: =IF(($F16+$F37-SUM($F50:I50))>$G50,$G50,$F16+$F37-SUM($F50:I50)) -> 65.2
B51: =G49 -> 2019年 | G51: =IF(D37,(G16+G37)/D37/2,0) -> 0 | H51: =IF(D37,(G16+G37)/D37,0) -> 0 | I51: =IF(($G16+$G37-SUM($G51:H51))>$H51,$H51,$G16+$G37-SUM($G51:H51)) -> 0 | J51: =IF(($G16+$G37-SUM($G51:I51))>$H51,$H51,$G16+$G37-SUM($G51:I51)) -> 0
B52: =H49 -> 2020年 | H52: =IF(D37,(H16+H37)/D37/2,0) -> 0 | I52: =IF(D37,(H16+H37)/D37,0) -> 0 | J52: =IF(($H16+$H37-SUM($H52:I52))>$I52,$I52,$H16+$H37-SUM($H52:I52)) -> 0
B53: =I49 -> 2021年 | I53: =IF(D37,(I16+I37)/D37/2,0) -> 0 | J53: =IF(D37,(I16+I37)/D37,0) -> 0
B54: =J49 -> 2022年 | J54: =IF(D37,(J16+J37)/D37/2,0) -> 0
B55: 合计 | F55: =SUM(F50:F54) -> 32.6 | G55: =SUM(G50:G54) -> 65.2 | H55: =SUM(H50:H54) -> 65.2 | I55: =SUM(I50:I54) -> 65.2 | J55: =SUM(J50:J54) -> 65.2
B57: 年度 | C57: 车辆折旧额自动计算过程 | F57: =F32 -> 2018年 | G57: =G32 -> 2019年 | H57: =H32 -> 2020年 | I57: =I32 -> 2021年 | J57: =J32 -> 2022年
B58: =F57 -> 2018年 | F58: =IF(D38,(F17+F38)/D38/2,0) -> 0 | G58: =IF(D38,(F17+F38)/D38,0) -> 0 | H58: =IF(($F17+$F38-SUM($F58:G58))>$G58,$G58,$F17+$F38-SUM($F58:G58)) -> 0 | I58: =IF(($F17+$F38-SUM($F58:H58))>$G58,$G58,$F17+$F38-SUM($F58:H58)) -> 0 | J58: =IF(($F17+$F38-SUM($F58:I58))>$G58,$G58,$F17+$F38-SUM($F58:I58)) -> 0
B59: =G57 -> 2019年 | G59: =IF(D38,(G17+G38)/D38/2,0) -> 2.5 | H59: =IF(D38,(G17+G38)/D38,0) -> 5 | I59: =IF(($G17+$G38-SUM($G59:H59))>$H59,$H59,$G17+$G38-SUM($G59:H59)) -> 5 | J59: =IF(($G17+$G38-SUM($G59:I59))>$H59,$H59,$G17+$G38-SUM($G59:I59)) -> 5
B60: =H57 -> 2020年 | H60: =IF(D38,(H17+H38)/D38/2,0) -> 2.5 | I60: =IF(D38,(H17+H38)/D38,0) -> 5 | J60: =IF(($H17+$H38-SUM($H60:I60))>$I60,$I60,$H17+$H38-SUM($H60:I60)) -> 5
B61: =I57 -> 2021年 | I61: =IF(D38,(I17+I38)/D38/2,0) -> 2.5 | J61: =IF(D38,(I17+I38)/D38,0) -> 5
B62: =J57 -> 2022年 | J62: =IF(D38,(J17+J38)/D38/2,0) -> 2.5
B63: 合计 | F63: =SUM(F58:F62) -> 0 | G63: =SUM(G58:G62) -> 2.5 | H63: =SUM(H58:H62) -> 7.5 | I63: =SUM(I58:I62) -> 12.5 | J63: =SUM(J58:J62) -> 17.5
B65: 年度 | C65: 电子设备折旧额自动计算过程 | F65: =F32 -> 2018年 | G65: =G32 -> 2019年 | H65: =H32 -> 2020年 | I65: =I32 -> 2021年 | J65: =J32 -> 2022年
B66: =F65 -> 2018年 | F66: =IF(D39,(F18+F39)/D39/2,0) -> 0 | G66: =IF(D39,(F18+F39)/D39,0) -> 0 | H66: =IF(($F18+$F39-SUM($F66:G66))>$G66,$G66,$F18+$F39-SUM($F66:G66)) -> 0 | I66: =IF(($F18+$F39-SUM($F66:H66))>$G66,$G66,$F18+$F39-SUM($F66:H66)) -> 0 | J66: =IF(($F18+$F39-SUM($F66:I66))>$G66,$G66,$F18+$F39-SUM($F66:I66)) -> 0
B67: =G65 -> 2019年 | G67: =IF(D39,(G18+G39)/D39/2,0) -> 3 | H67: =IF(D39,(G18+G39)/D39,0) -> 6 | I67: =IF(($G18+$G39-SUM($G67:H67))>$H67,$H67,$G18+$G39-SUM($G67:H67)) -> 6 | J67: =IF(($G18+$G39-SUM($G67:I67))>$H67,$H67,$G18+$G39-SUM($G67:I67)) -> 6
B68: =H65 -> 2020年 | H68: =IF(D39,(H18+H39)/D39/2,0) -> 3 | I68: =IF(D39,(H18+H39)/D39,0) -> 6 | J68: =IF(($H18+$H39-SUM($H68:I68))>$I68,$I68,$H18+$H39-SUM($H68:I68)) -> 6
B69: =I65 -> 2021年 | I69: =IF(D39,(I18+I39)/D39/2,0) -> 3 | J69: =IF(D39,(I18+I39)/D39,0) -> 6
B70: =J65 -> 2022年 | J70: =IF(D39,(J18+J39)/D39/2,0) -> 3
B71: 合计 | F71: =SUM(F66:F70) -> 0 | G71: =SUM(G66:G70) -> 3 | H71: =SUM(H66:H70) -> 9 | I71: =SUM(I66:I70) -> 15 | J71: =SUM(J66:J70) -> 21
B72: 固定资产投入分析
C73: 建筑类 | D73: 设备类
B74: =E4&"账面净值" -> 2017年账面净值 | C74: =E24 -> 1134.7382 | D74: =E35 -> 1193.9901
B75: =E4&"资产负债表中已计入" -> 2017年资产负债表中已计入 | C75: =E13 -> 0 | D75: =E15 -> 354.8
B76: =F4&"尚需要再投入" -> 2018年尚需要再投入 | C76: =F26 -> 0 | D76: =SUM(F37:F39) -> 232
B77: 小计 | C77: =SUM(C74:C76) -> 1134.7382 | D77: =SUM(D74:D76) -> 1780.7901

Sheet 8摊销
B1: 长摊和无形资产支出与摊销预测表
B2: ='1报表'!B11 -> 评估基准日：2017/12/31 | L2: 该工作表已保护！
B3: ='1报表'!B12 -> 被评估单位：JSBD公司 | J3: 单位：万元
B4: 数据汇总 | E4: ='3收入'!E4 -> 2017年 | F4: ='3收入'!F4 -> 2018年 | G4: ='3收入'!G4 -> 2019年 | H4: ='3收入'!H4 -> 2020年 | I4: ='3收入'!I4 -> 2021年 | J4: ='3收入'!J4 -> 2022年
B5: 长期待摊费用摊销 | F5: =F51 -> 0 | G5: =G51 -> 0 | H5: =H51 -> 0 | I5: =I51 -> 0 | J5: =J51 -> 0
B6: 无形资产摊销 | F6: =F25+F34 -> 71.838051 | G6: =G25+G34 -> 71.838051 | H6: =H25+H34 -> 51.201763 | I6: =I25+I34 -> 37.678504 | J6: =J25+J34 -> 57.678504
B7: 摊销合计 | F7: =F5+F6 -> 71.838051 | G7: =G5+G6 -> 71.838051 | H7: =H5+H6 -> 51.201763 | I7: =I5+I6 -> 37.678504 | J7: =J5+J6 -> 57.678504
B8: 长摊资产支出 | F8: =F49 -> 0 | G8: =G49 -> 0 | H8: =H49 -> 0 | I8: =I49 -> 0 | J8: =J49 -> 0
B9: 无形资产支出 | F9: =F23+F32 -> 0 | G9: =G23+G32 -> 0 | H9: =H23+H32 -> 60 | I9: =I23+I32 -> 60 | J9: =J23+J32 -> 60
B10: 长摊和无形资产支出 | F10: =F8+F9 -> 0 | G10: =G8+G9 -> 0 | H10: =H8+H9 -> 60 | I10: =I8+I9 -> 60 | J10: =J8+J9 -> 60
B11: 未资本化无形资产的处理
B12: 科目 | D12: 摊销年限 | E12: =E4 -> 2017年 | F12: =F4 -> 2018年 | G12: =G4 -> 2019年 | H12: =H4 -> 2020年 | I12: =I4 -> 2021年 | J12: =J4 -> 2022年
B13: 未资本化的土地
B14: 年度资本化金额
B15: 未资本化的无形资产 | E15: ='2报表调整'!G37 -> 0
B16: 年度资本化金额
B18: 土地使用权
B19: 项目 | D19: 摊销年限 | E19: =E4 -> 2017年 | F19: =F4 -> 2018年 | G19: =G4 -> 2019年 | H19: =H4 -> 2020年 | I19: =I4 -> 2021年 | J19: =J4 -> 2022年
B20: 基准日土地账面原值 | E20: 383.9252
B21: 基准日土地账面净值 | E21: 297.7661
B22: 存量土地摊销额 | D22: 50 | F22: =IF(D22,IF(E21>E20/D22,E20/D22,E21),0) -> 7.678504 | G22: =IF(($E21-SUM($F22:F22))>$F22,$F22,$E21-SUM($F22:F22)) -> 7.678504 | H22: =IF(($E21-SUM($F22:G22))>$F22,$F22,$E21-SUM($F22:G22)) -> 7.678504 | I22: =IF(($E21-SUM($F22:H22))>$F22,$F22,$E21-SUM($F22:H22)) -> 7.678504 | J22: =IF(($E21-SUM($F22:I22))>$F22,$F22,$E21-SUM($F22:I22)) -> 7.678504
B23: 新增土地投入原值
B24: 新增土地摊销额 | F24: =IF($D13,SUM($F14:F14)/$D13,0)+IF($D24,SUM($F23:F23)/$D24,0) -> 0 | G24: =IF($D13,SUM($F14:G14)/$D13,0)+IF($D24,SUM($F23:G23)/$D24,0) -> 0 | H24: =IF($D13,SUM($F14:H14)/$D13,0)+IF($D24,SUM($F23:H23)/$D24,0) -> 0 | I24: =IF($D13,SUM($F14:I14)/$D13,0)+IF($D24,SUM($F23:I23)/$D24,0) -> 0 | J24: =IF($D13,SUM($F14:J14)/$D13,0)+IF($D24,SUM($F23:J23)/$D24,0) -> 0
B25: 土地摊销额小计 | F25: =F22+F24 -> 7.678504 | G25: =G22+G24 -> 7.678504 | H25: =H22+H24 -> 7.678504 | I25: =I22+I24 -> 7.678504 | J25: =J22+J24 -> 7.678504
B26: 土地使用权账面净值 | F26: =E21+F14+F23-F25 -> 290.0876 | G26: =F26+G14+G23-G25 -> 282.40909 | H26: =G26+H14+H23-H25 -> 274.73059 | I26: =H26+I14+I23-I25 -> 267.05208 | J26: =I26+J14+J23-J25 -> 259.37358
B27: 其他无形资产
B28: 项目 | D28: 摊销年限 | E28: =E19 -> 2017年 | F28: =F19 -> 2018年 | G28: =G19 -> 2019年 | H28: =H19 -> 2020年 | I28: =I19 -> 2021年 | J28: =J19 -> 2022年
B29: 基准日其他无形资产账面原值 | E29: 192.47864
B30: 基准日其他无形资产账面净值 | E30: 161.84235
B31: 存量其他无形资产摊销额 | D31: 3 | F31: =IF(D31,IF(E30>E29/D31,E29/D31,E30),0) -> 64.159547 | G31: =IF(($E30-SUM($F31:F31))>$F31,$F31,$E30-SUM($F31:F31)) -> 64.159547 | H31: =IF(($E30-SUM($F31:G31))>$F31,$F31,$E30-SUM($F31:G31)) -> 33.523259 | I31: =IF(($E30-SUM($F31:H31))>$F31,$F31,$E30-SUM($F31:H31)) -> 0 | J31: =IF(($E30-SUM($F31:I31))>$F31,$F31,$E30-SUM($F31:I31)) -> 0
B32: 新增技术类无形资产投入原值 | D32: 3 | H32: 60 | I32: 60 | J32: 60
B33: 新增无形资产摊销额 | F33: =F43 -> 0 | G33: =G43 -> 0 | H33: =H43 -> 10 | I33: =I43 -> 30 | J33: =J43 -> 50
B34: 无形资产摊销额小计 | F34: =F31+F33 -> 64.159547 | G34: =G31+G33 -> 64.159547 | H34: =H31+H33 -> 43.523259 | I34: =I31+I33 -> 30 | J34: =J31+J33 -> 50
B35: 其他无形资产账面净值 | F35: =E30+F16+F32-F34 -> 97.682807 | G35: =F35+G16+G32-G34 -> 33.523259 | H35: =G35+H16+H32-H34 -> 50 | I35: =H35+I16+I32-I34 -> 80 | J35: =I35+J16+J32-J34 -> 90
B37: 年度 | C37: 技术无形资产摊销额自动计算过程 | F37: =F19 -> 2018年 | G37: =G19 -> 2019年 | H37: =H19 -> 2020年 | I37: =I19 -> 2021年 | J37: =J19 -> 2022年
B38: =F37 -> 2018年 | F38: =IF(D32,(F16+F32)/D32/2,0) -> 0 | G38: =IF(D32,(F16+F32)/D32,0) -> 0 | H38: =IF(($F16+$F32-SUM($F38:G38))>$G38,$G38,$F16+$F32-SUM($F38:G38)) -> 0 | I38: =IF(($F16+$F32-SUM($F38:H38))>$G38,$G38,$F16+$F32-SUM($F38:H38)) -> 0 | J38: =IF(($F16+$F32-SUM($F38:I38))>$G38,$G38,$F16+$F32-SUM($F38:I38)) -> 0
B39: =G37 -> 2019年 | G39: =IF(D32,(G16+G32)/D32/2,0) -> 0 | H39: =IF(D32,(G16+G32)/D32,0) -> 0 | I39: =IF(($G16+$G32-SUM($G39:H39))>$H39,$H39,$G16+$G32-SUM($G39:H39)) -> 0 | J39: =IF(($G16+$G32-SUM($G39:I39))>$H39,$H39,$G16+$G32-SUM($G39:I39)) -> 0
B40: =H37 -> 2020年 | H40: =IF(D32,(H16+H32)/D32/2,0) -> 10 | I40: =IF(D32,(H16+H32)/D32,0) -> 20 | J40: =IF(($H16+$H32-SUM($H40:I40))>$I40,$I40,$H16+$H32-SUM($H40:I40)) -> 20
B41: =I37 -> 2021年 | I41: =IF(D32,(I16+I32)/D32/2,0) -> 10 | J41: =IF(D32,(I16+I32)/D32,0) -> 20
B42: =J37 -> 2022年 | J42: =IF(D32,(J16+J32)/D32/2,0) -> 10
B43: 合计 | F43: =SUM(F38:F42) -> 0 | G43: =SUM(G38:G42) -> 0 | H43: =SUM(H38:H42) -> 10 | I43: =SUM(I38:I42) -> 30 | J43: =SUM(J38:J42) -> 50
B44: 长期待摊费用
B45: 项目 | D45: 摊销年限 | E45: =E19 -> 2017年 | F45: =F19 -> 2018年 | G45: =G19 -> 2019年 | H45: =H19 -> 2020年 | I45: =I19 -> 2021年 | J45: =J19 -> 2022年
B46: 基准日长摊费用原值
B47: 基准日长摊费用净值 | E47: ='2报表调整'!G39 -> 0
B48: 存量长摊费用摊销额 | F48: =IF(D48,IF(E47>E46/D48,E46/D48,E47),0) -> 0 | G48: =IF(($E47-SUM($F48:F48))>$F48,$F48,$E47-SUM($F48:F48)) -> 0 | H48: =IF(($E47-SUM($F48:G48))>$F48,$F48,$E47-SUM($F48:G48)) -> 0 | I48: =IF(($E47-SUM($F48:H48))>$F48,$F48,$E47-SUM($F48:H48)) -> 0 | J48: =IF(($E47-SUM($F48:I48))>$F48,$F48,$E47-SUM($F48:I48)) -> 0
B49: 新增长摊资产投入原值
B50: 新增长摊费用摊销额 | F50: =F60 -> 0 | G50: =G60 -> 0 | H50: =H60 -> 0 | I50: =I60 -> 0 | J50: =J60 -> 0
B51: 长期费用摊销额小计 | F51: =F48+F50 -> 0 | G51: =G48+G50 -> 0 | H51: =H48+H50 -> 0 | I51: =I48+I50 -> 0 | J51: =J48+J50 -> 0
B52: 长期待摊费用账面净值 | F52: =E47+F49-F51 -> 0 | G52: =F52+G49-G51 -> 0 | H52: =G52+H49-H51 -> 0 | I52: =H52+I49-I51 -> 0 | J52: =I52+J49-J51 -> 0
B54: 年度 | C54: 长摊资产摊销额自动计算过程 | F54: =F19 -> 2018年 | G54: =G19 -> 2019年 | H54: =H19 -> 2020年 | I54: =I19 -> 2021年 | J54: =J19 -> 2022年
B55: =F54 -> 2018年 | F55: =IF(D49,F49/D49,0) -> 0 | G55: =IF(($F49-SUM($F55:F55))>$F55,$F55,$F49-SUM($F55:F55)) -> 0 | H55: =IF(($F49-SUM($F55:G55))>$F55,$F55,$F49-SUM($F55:G55)) -> 0 | I55: =IF(($F49-SUM($F55:H55))>$F55,$F55,$F49-SUM($F55:H55)) -> 0 | J55: =IF(($F49-SUM($F55:I55))>$F55,$F55,$F49-SUM($F55:I55)) -> 0
B56: =G54 -> 2019年 | G56: =IF(D49,G49/D49,0) -> 0 | H56: =IF(($G49-SUM($G56:G56))>$G56,$G56,$G49-SUM($G56:G56)) -> 0 | I56: =IF(($G49-SUM($G56:H56))>$G56,$G56,$G49-SUM($G56:H56)) -> 0 | J56: =IF(($G49-SUM($G56:I56))>$G56,$G56,$G49-SUM($G56:I56)) -> 0
B57: =H54 -> 2020年 | H57: =IF(D49,H49/D49,0) -> 0 | I57: =IF(($H49-SUM($H57:H57))>$H57,$H57,$H49-SUM($H57:H57)) -> 0 | J57: =IF(($H49-SUM($H57:I57))>$H57,$H57,$H49-SUM($H57:I57)) -> 0
B58: =I54 -> 2021年 | I58: =IF(D49,I49/D49,0) -> 0 | J58: =IF(($I49-SUM($I58:I58))>$I58,$I58,$I49-SUM($I58:I58)) -> 0
B59: =J54 -> 2022年 | J59: =IF(D49,J49/D49,0) -> 0
B60: 合计 | F60: =SUM(F55:F59) -> 0 | G60: =SUM(G55:G59) -> 0 | H60: =SUM(H55:H59) -> 0 | I60: =SUM(I55:I59) -> 0 | J60: =SUM(J55:J59) -> 0
B61: 基准日数据与资产负债表检查核对
B62: 在建工程 | E62: =IF(ROUND(E13+'7折旧'!E13+'7折旧'!E15-'2报表调整'!G33,-1),"数据不一致","OK") -> OK
B63: 无形资产 | E63: =IF(ROUND(E21+E30-'2报表调整'!G36,-1),"数据不一致","OK") -> OK
B64: 开发支出 | E64: =IF(E15-'2报表调整'!G37,"数据不一致","OK") -> OK
B65: 长期待摊费用 | E65: =IF(E47-'2报表调整'!G39,"数据不一致","OK") -> OK

Sheet 9溢余现金
B1: 经营最低保有现金分析表
B2: ='1报表'!B11 -> 评估基准日：2017/12/31
B3: ='1报表'!B12 -> 被评估单位：JSBD公司 | J3: 单位：万元
B4: 项目 | C4: ='3收入'!C4 -> 2015年 | D4: ='3收入'!D4 -> 2016年 | E4: ='3收入'!E4 -> 2017年 | F4: ='3收入'!F4 -> 2018年 | G4: ='3收入'!G4 -> 2019年 | H4: ='3收入'!H4 -> 2020年 | I4: ='3收入'!I4 -> 2021年 | J4: ='3收入'!J4 -> 2022年
B5: 生产成本的人工费用 | C5: 310.03546 | D5: 415.56892 | E5: 517.74326 | F5: 614.54 | G5: 676.29 | H5: 710.1 | I5: 745.61 | J5: 782.89
B6: 营业税金及附加 | C6: ='5税金'!C5 -> 53.873421 | D6: ='5税金'!D5 -> 81.416231 | E6: ='5税金'!E5 -> 113.39456 | F6: ='5税金'!F5 -> 107.26836 | G6: ='5税金'!G5 -> 127.21454 | H6: ='5税金'!H5 -> 142.79594 | I6: ='5税金'!I5 -> 152.48181 | J6: ='5税金'!J5 -> 155.38377
B7: 销售费用 | C7: ='6销管'!C5 -> 481.4591 | D7: ='6销管'!D5 -> 588.55087 | E7: ='6销管'!E5 -> 750.19684 | F7: ='6销管'!F5 -> 950.06399 | G7: ='6销管'!G5 -> 1125.6541 | H7: ='6销管'!H5 -> 1265.3359 | I7: ='6销管'!I5 -> 1342.3046 | J7: ='6销管'!J5 -> 1371.0663
B8: 管理费用 | C8: ='6销管'!C6 -> 694.30698 | D8: ='6销管'!D6 -> 710.43654 | E8: ='6销管'!E6 -> 1052.4467 | F8: ='6销管'!F6 -> 1140.1681 | G8: ='6销管'!G6 -> 1284.8847 | H8: ='6销管'!H6 -> 1341.4961 | I8: ='6销管'!I6 -> 1376.4758 | J8: ='6销管'!J6 -> 1432.4397
B9: 研发费用 | C9: ='6销管'!C7 -> 384.83578 | D9: ='6销管'!D7 -> 369.90657 | E9: ='6销管'!E7 -> 435.369 | F9: ='6销管'!F7 -> 596.77387 | G9: ='6销管'!G7 -> 707.06919 | H9: ='6销管'!H7 -> 794.809 | I9: ='6销管'!I7 -> 843.15614 | J9: ='6销管'!J7 -> 861.22256
B10: 财务费用中的利息支出 | C10: ='11财务费用'!C18 -> 144.02572 | D10: ='11财务费用'!D18 -> 132.21571 | E10: ='11财务费用'!E18 -> 92.333057 | F10: ='11财务费用'!F18 -> 54.1 | G10: ='11财务费用'!G18 -> 71.178944 | H10: ='11财务费用'!H18 -> 54.1 | I10: ='11财务费用'!I18 -> 54.1 | J10: ='11财务费用'!J18 -> 54.1
B11: 减：销售费用中折旧与摊销
B12: 减：管理费用中折旧与摊销 | C12: ='6销管'!C52+'6销管'!C53 -> 115.90069 | D12: ='6销管'!D52+'6销管'!D53 -> 89.179264 | E12: ='6销管'!E52+'6销管'!E53 -> 89.146854 | F12: ='6销管'!F52+'6销管'!F53 -> 145.30685 | G12: ='6销管'!G52+'6销管'!G53 -> 149.87885 | H12: ='6销管'!H52+'6销管'!H53 -> 92.012276 | I12: ='6销管'!I52+'6销管'!I53 -> 57.749604 | J12: ='6销管'!J52+'6销管'!J53 -> 79.069604
B13: 减：研发费用中折旧与摊销
B14: 估计的付现成本合计 | C14: =SUM(C5:C10)-SUM(C11:C13) -> 1952.6358 | D14: =SUM(D5:D10)-SUM(D11:D13) -> 2208.9156 | E14: =SUM(E5:E10)-SUM(E11:E13) -> 2872.3366 | F14: =SUM(F5:F10)-SUM(F11:F13) -> 3317.6075 | G14: =SUM(G5:G10)-SUM(G11:G13) -> 3842.4126 | H14: =SUM(H5:H10)-SUM(H11:H13) -> 4216.6247 | I14: =SUM(I5:I10)-SUM(I11:I13) -> 4456.3787 | J14: =SUM(J5:J10)-SUM(J11:J13) -> 4578.0328
B15: 月数 | C15: 12 | D15: 12 | E15: 12 | F15: 12 | G15: 12 | H15: 12 | I15: 12 | J15: 12
B16: 月均付现成本 | C16: =C14/C15 -> 162.71965 | D16: =D14/D15 -> 184.0763 | E16: =E14/E15 -> 239.36138 | F16: =F14/F15 -> 276.46729 | G16: =G14/G15 -> 320.20105 | H16: =H14/H15 -> 351.38539 | I16: =I14/I15 -> 371.36489 | J16: =J14/J15 -> 381.50273
B17: 保有现金系数(月） | C17: =D17 -> 1 | D17: =E17 -> 1 | E17: 1 | F17: =E17 -> 1 | G17: =F17 -> 1 | H17: =G17 -> 1 | I17: =H17 -> 1 | J17: =I17 -> 1 | K17: 一般取1，取其他数据应结合行业特点说明
B18: 限制用途现金
B19: 经营最低保有现金测算 | C19: =MIN(C16*C17,C23)+C18 -> 162.71965 | D19: =MIN(D16*D17,D23)+D18 -> 184.0763 | E19: =MIN(E16*E17,E23)+E18 -> 239.36138 | F19: =F16*F17+F18 -> 276.46729 | G19: =G16*G17+G18 -> 320.20105 | H19: =H16*H17+H18 -> 351.38539 | I19: =I16*I17+I18 -> 371.36489 | J19: =J16*J17+J18 -> 381.50273
B20: 经营必备现金/收入（检查） | C20: =C19/'3收入'!C5 -> 0.028812376 | D20: =D19/'3收入'!D5 -> 0.02519945 | E20: =E19/'3收入'!E5 -> 0.024893087 | F20: =F19/'3收入'!F5 -> 0.023163488 | G20: =G19/'3收入'!G5 -> 0.022642837 | H20: =H19/'3收入'!H5 -> 0.022105021 | I20: =I19/'3收入'!I5 -> 0.022022309 | J20: =J19/'3收入'!J5 -> 0.022148905
B21: 评估基准日溢余现金分析表
B22: 项目 | E22: =E4 -> 2017年
B23: 资产负债表中的货币资金 | E23: ='2报表调整'!D8 -> 276.81451
B24: 其中：经营最低保有现金 | E24: =E19 -> 239.36138
B25: 溢余现金 | E25: =MAX(E23-E24,0) -> 37.453128

Sheet 10营运
B1: 营运资金预测表
B2: ='1报表'!B11 -> 评估基准日：2017/12/31
B3: ='1报表'!B12 -> 被评估单位：JSBD公司 | J3: 单位：万元
B4: 项目 | C4: ='3收入'!C4 -> 2015年 | D4: ='3收入'!D4 -> 2016年 | E4: ='3收入'!E4 -> 2017年 | F4: ='3收入'!F4 -> 2018年 | G4: ='3收入'!G4 -> 2019年 | H4: ='3收入'!H4 -> 2020年 | I4: ='3收入'!I4 -> 2021年 | J4: ='3收入'!J4 -> 2022年 | K4: 全部为经营性资产负债；不含非经营！
B5: 经营最低保有现金 | C5: ='9溢余现金'!C19 -> 162.71965 | D5: ='9溢余现金'!D19 -> 184.0763 | E5: ='9溢余现金'!E19 -> 239.36138 | F5: ='9溢余现金'!F19 -> 276.46729 | G5: ='9溢余现金'!G19 -> 320.20105 | H5: ='9溢余现金'!H19 -> 351.38539 | I5: ='9溢余现金'!I19 -> 371.36489 | J5: ='9溢余现金'!J19 -> 381.50273 | K5: 当企业不稳定时，不能用周转天数预测！采用绝对额进行预测！
B6: 应收票据及应收账款计算行 | C6: ='1报表'!C18-'2报表调整'!K11 -> 2177.8959 | D6: ='1报表'!D18-'2报表调整'!L11 -> 2618.1402 | E6: ='2报表调整'!G11 -> 3436.3947
B7: 周转天数 | C7: =IF(C41,360*C6/C41,0) -> 138.82852 | D7: =IF(D41,360*D6/D41,0) -> 129.02937 | E7: =IF(E41,360*E6/E41,0) -> 128.65605 | F7: 130 | G7: =F7 -> 130 | H7: =G7 -> 130 | I7: =H7 -> 130 | J7: =I7 -> 130
B8: 应收票据及应收账款 | C8: =C6 -> 2177.8959 | D8: =D6 -> 2618.1402 | E8: =E6 -> 3436.3947 | F8: =IF(F6,F6,F41*F7/360) -> 4310.0335 | G8: =IF(G6,G6,G41*G7/360) -> 5106.6108 | H8: =IF(H6,H6,H41*H7/360) -> 5740.2872 | I8: =IF(I6,I6,I41*I7/360) -> 6089.461 | J8: =IF(J6,J6,J41*J7/360) -> 6219.9407
B9: 预付款项计算行 | C9: ='1报表'!C19-'2报表调整'!K12 -> 163.1034 | D9: ='1报表'!D19-'2报表调整'!L12 -> 99.846675 | E9: ='2报表调整'!G12 -> 43.550822
B10: 周转天数 | C10: =IF(C42,360*C9/C42,0) -> 17.014572 | D10: =IF(D42,360*D9/D42,0) -> 7.7706963 | E10: =IF(E42,360*E9/E42,0) -> 2.7205161 | F10: 10 | G10: =F10 -> 10 | H10: =G10 -> 10 | I10: =H10 -> 10 | J10: =I10 -> 10
B11: 预付款项 | C11: =C9 -> 163.1034 | D11: =D9 -> 99.846675 | E11: =E9 -> 43.550822 | F11: =IF(F9,F9,F42*F10/360) -> 198.92462 | G11: =IF(G9,G9,G42*G10/360) -> 235.68973 | H11: =IF(H9,H9,H42*H10/360) -> 264.93633 | I11: =IF(I9,I9,I42*I10/360) -> 281.05205 | J11: =IF(J9,J9,J42*J10/360) -> 287.07419
B12: 其他应收款计算行 | C12: ='1报表'!C22-'2报表调整'!K15 -> 113.81446 | D12: ='1报表'!D22-'2报表调整'!L15 -> 191.70885 | E12: ='2报表调整'!G15 -> 22.319492
B13: 周转天数 | C13: =IF(C41,360*C12/C41,0) -> 7.2550267 | D13: =IF(D41,360*D12/D41,0) -> 9.4479558 | E13: =IF(E41,360*E12/E41,0) -> 0.83562512 | F13: 7 | G13: =F13 -> 7 | H13: =G13 -> 7 | I13: =H13 -> 7 | J13: =I13 -> 7
B14: 其他应收款 | C14: =C12 -> 113.81446 | D14: =D12 -> 191.70885 | E14: =E12 -> 22.319492 | F14: =IF(F12,F12,F41*F13/360) -> 232.07873 | G14: =IF(G12,G12,G41*G13/360) -> 274.97135 | H14: =IF(H12,H12,H41*H13/360) -> 309.09239 | I14: =IF(I12,I12,I41*I13/360) -> 327.89405 | J14: =IF(J12,J12,J41*J13/360) -> 334.91988
B15: 存货计算行 | C15: ='1报表'!C23-'2报表调整'!K16 -> 879.74901 | D15: ='1报表'!D23-'2报表调整'!L16 -> 1054.9352 | E15: ='2报表调整'!G16 -> 1331.2815
B16: 周转天数 | C16: =IF(C42,360*C15/C42,0) -> 91.773398 | D16: =IF(D42,360*D15/D42,0) -> 82.101695 | E16: =IF(E42,360*E15/E42,0) -> 83.161985 | F16: 85 | G16: =F16 -> 85 | H16: =G16 -> 85 | I16: =H16 -> 85 | J16: =I16 -> 85
B17: 存货 | C17: =C15 -> 879.74901 | D17: =D15 -> 1054.9352 | E17: =E15 -> 1331.2815 | F17: =IF(F15,F15,F42*F16/360) -> 1690.8593 | G17: =IF(G15,G15,G42*G16/360) -> 2003.3627 | H17: =IF(H15,H15,H42*H16/360) -> 2251.9588 | I17: =IF(I15,I15,I42*I16/360) -> 2388.9424 | J17: =IF(J15,J15,J42*J16/360) -> 2440.1306
B18: 合同资产 | C18: ='1报表'!C24-'2报表调整'!K17 -> 0 | D18: ='1报表'!D24-'2报表调整'!L17 -> 0 | E18: ='2报表调整'!G17 -> 0
B19: 一年内到期的非流动资产 | C19: ='1报表'!C26-'2报表调整'!K19 -> 0 | D19: ='1报表'!D26-'2报表调整'!L19 -> 0 | E19: ='2报表调整'!G19 -> 0
B20: 其他流动资产 | C20: ='1报表'!C27-'2报表调整'!K20 -> 34.793744 | D20: ='1报表'!D27-'2报表调整'!L20 -> 21.197218 | E20: ='2报表调整'!G20 -> 85.05866 | F20: =E20 -> 85.05866 | G20: =F20 -> 85.05866 | H20: =G20 -> 85.05866 | I20: =H20 -> 85.05866 | J20: =I20 -> 85.05866
B21: 流动资产合计 | C21: =C5+C8+C11+C14+C17+C18+C19+C20 -> 3532.0762 | D21: =D5+D8+D11+D14+D17+D18+D19+D20 -> 4169.9044 | E21: =E5+E8+E11+E14+E17+E18+E19+E20 -> 5157.9666 | F21: =F5+F8+F11+F14+F17+F18+F19+F20 -> 6793.4221 | G21: =G5+G8+G11+G14+G17+G18+G19+G20 -> 8025.8943 | H21: =H5+H8+H11+H14+H17+H18+H19+H20 -> 9002.7188 | I21: =I5+I8+I11+I14+I17+I18+I19+I20 -> 9543.773 | J21: =J5+J8+J11+J14+J17+J18+J19+J20 -> 9748.6267
B23: 应付票据及应付款项计算行 | C23: ='1报表'!C55-'2报表调整'!K48 -> 417.61032 | D23: ='1报表'!D55-'2报表调整'!L48 -> 1037.928 | E23: ='2报表调整'!G48 -> 1257.6974
B24: 周转天数 | C24: =IF(C42,360*C23/C42,0) -> 43.56415 | D24: =IF(D42,360*D23/D42,0) -> 80.778087 | E24: =IF(E42,360*E23/E42,0) -> 78.565357 | F24: 70 | G24: =F24 -> 70 | H24: =G24 -> 70 | I24: =H24 -> 70 | J24: =I24 -> 70
B25: 应付票据及应付账款 | C25: =C23 -> 417.61032 | D25: =D23 -> 1037.928 | E25: =E23 -> 1257.6974 | F25: =IF(F23,F23,F42*F24/360) -> 1392.4724 | G25: =IF(G23,G23,G42*G24/360) -> 1649.8281 | H25: =IF(H23,H23,H42*H24/360) -> 1854.5543 | I25: =IF(I23,I23,I42*I24/360) -> 1967.3643 | J25: =IF(J23,J23,J42*J24/360) -> 2009.5193
B26: 预收款项计算行 | C26: ='1报表'!C56-'2报表调整'!K49 -> 131.76532 | D26: ='1报表'!D56-'2报表调整'!L49 -> 195.99939 | E26: ='2报表调整'!G49 -> 351.09636
B27: 周转天数 | C27: =IF(C41,360*C26/C41,0) -> 8.3992923 | D27: =IF(D41,360*D26/D41,0) -> 9.6594056 | E27: =IF(E41,360*E26/E41,0) -> 13.144786 | F27: 9 | G27: =F27 -> 9 | H27: =G27 -> 9 | I27: =H27 -> 9 | J27: =I27 -> 9
B28: 预收款项 | C28: =C26 -> 131.76532 | D28: =D26 -> 195.99939 | E28: =E26 -> 351.09636 | F28: =IF(F26,F26,F41*F27/360) -> 298.38693 | G28: =IF(G26,G26,G41*G27/360) -> 353.53459 | H28: =IF(H26,H26,H41*H27/360) -> 397.4045 | I28: =IF(I26,I26,I41*I27/360) -> 421.57807 | J28: =IF(J26,J26,J41*J27/360) -> 430.61128
B29: 合同负债 | C29: ='1报表'!C57-'2报表调整'!K50 -> 0 | D29: ='1报表'!D57-'2报表调整'!L50 -> 0 | E29: ='2报表调整'!G50 -> 0
B30: 应付职工薪酬 | C30: ='1报表'!C58-'2报表调整'!K51 -> 132.57767 | D30: ='1报表'!D58-'2报表调整'!L51 -> 163.35175 | E30: ='2报表调整'!G51 -> 345.76284 | F30: =E30 -> 345.76284 | G30: =F30 -> 345.76284 | H30: =G30 -> 345.76284 | I30: =H30 -> 345.76284 | J30: =I30 -> 345.76284
B31: 应交税费 | C31: ='1报表'!C59-'2报表调整'!K52 -> 104.3759 | D31: ='1报表'!D59-'2报表调整'!L52 -> 117.08402 | E31: ='2报表调整'!G52 -> 225.302 | F31: =E31 -> 225.302 | G31: =F31 -> 225.302 | H31: =G31 -> 225.302 | I31: =H31 -> 225.302 | J31: =I31 -> 225.302
B32: 其他应付款计算行 | C32: ='1报表'!C62-'2报表调整'!K55 -> 1493.8281 | D32: ='1报表'!D62-'2报表调整'!L55 -> 1824.9313 | E32: ='2报表调整'!G55 -> 161.15448 | K32: 扣除17年应付设备款88.34万元后，占成本为1.3%
B33: 占成本比例 | C33: =IF(C42,C32/C42,0) -> 0.43286866 | D33: =IF(D42,D32/D42,0) -> 0.3945212 | E33: =IF(E42,E32/E42,0) -> 0.027963712 | F33: 0.15 | G33: =F33 -> 0.15 | H33: =G33 -> 0.15 | I33: =H33 -> 0.15 | J33: =I33 -> 0.15 | K33: 需要延伸剔除2015、2016年中的非经营
B34: 其他应付款 | C34: =C32 -> 1493.8281 | D34: =D32 -> 1824.9313 | E34: =E32 -> 161.15448 | F34: =IF(F32,F32,F42*F33) -> 1074.193 | G34: =IF(G32,G32,G42*G33) -> 1272.7245 | H34: =IF(H32,H32,H42*H33) -> 1430.6562 | I34: =IF(I32,I32,I42*I33) -> 1517.681 | J34: =IF(J32,J32,J42*J33) -> 1550.2006
B35: 其他流动负债计算行 | C35: ='1报表'!C65-'2报表调整'!K58 -> 0 | D35: ='1报表'!D65-'2报表调整'!L58 -> 0 | E35: ='2报表调整'!G58 -> 0
B36: 占成本比例 | C36: =IF(C42,C35/C42,0) -> 0 | D36: =IF(D42,D35/D42,0) -> 0 | E36: =IF(E42,E35/E42,0) -> 0
B37: 其他流动负债 | C37: =C35 -> 0 | D37: =D35 -> 0 | E37: =E35 -> 0 | F37: =IF(F35,F35,F42*F36) -> 0 | G37: =IF(G35,G35,G42*G36) -> 0 | H37: =IF(H35,H35,H42*H36) -> 0 | I37: =IF(I35,I35,I42*I36) -> 0 | J37: =IF(J35,J35,J42*J36) -> 0
B38: 流动负债合计 | C38: =C25+C28+C29+C30+C31+C34+C37 -> 2280.1573 | D38: =D25+D28+D29+D30+D31+D34+D37 -> 3339.2944 | E38: =E25+E28+E29+E30+E31+E34+E37 -> 2341.0131 | F38: =F25+F28+F29+F30+F31+F34+F37 -> 3336.1171 | G38: =G25+G28+G29+G30+G31+G34+G37 -> 3847.1521 | H38: =H25+H28+H29+H30+H31+H34+H37 -> 4253.6799 | I38: =I25+I28+I29+I30+I31+I34+I37 -> 4477.6883 | J38: =J25+J28+J29+J30+J31+J34+J37 -> 4561.396
B39: 营运资金 | C39: =C21-C38 -> 1251.9189 | D39: =D21-D38 -> 830.61 | E39: =E21-E38 -> 2816.9536 | F39: =F21-F38 -> 3457.305 | G39: =G21-G38 -> 4178.7422 | H39: =H21-H38 -> 4749.0389 | I39: =I21-I38 -> 5066.0847 | J39: =J21-J38 -> 5187.2307
B40: 营运资金增加额 | F40: =F39-E39 -> 640.3514 | G40: =G39-F39 -> 721.43725 | H40: =H39-G39 -> 570.29671 | I40: =I39-H39 -> 317.04582 | J40: =J39-I39 -> 121.14597
B41: 营业收入 | C41: ='3收入'!C5 -> 5647.5609 | D41: ='3收入'!D5 -> 7304.7745 | E41: ='3收入'!E5 -> 9615.5763 | F41: ='3收入'!F5 -> 11935.477 | G41: ='3收入'!G5 -> 14141.384 | H41: ='3收入'!H5 -> 15896.18 | I41: ='3收入'!I5 -> 16863.123 | J41: ='3收入'!J5 -> 17224.451
B42: 营业成本 | C42: ='4成本'!C5 -> 3450.9962 | D42: ='4成本'!D5 -> 4625.6862 | E42: ='4成本'!E5 -> 5762.986 | F42: ='4成本'!F5 -> 7161.2864 | G42: ='4成本'!G5 -> 8484.8303 | H42: ='4成本'!H5 -> 9537.7079 | I42: ='4成本'!I5 -> 10117.874 | J42: ='4成本'!J5 -> 10334.671
B43: 营运资金/收入（检查） | C43: =C39/C41 -> 0.22167426 | D43: =D39/D41 -> 0.11370782 | E43: =E39/E41 -> 0.29295733 | F43: =F39/F41 -> 0.28966625 | G43: =G39/G41 -> 0.29549741 | H43: =H39/H41 -> 0.29875347 | I43: =I39/I41 -> 0.30042388 | J43: =J39/J41 -> 0.30115506
D44: 如果将历史年度的非经营剔除后，营运资金占比就更清晰反映出趋势。

Sheet 11财务费用
B1: 财务费用预测表
B2: ='1报表'!B11 -> 评估基准日：2017/12/31
B3: ='1报表'!B12 -> 被评估单位：JSBD公司 | J3: 单位：万元
B4: 汇总数据 | C4: 利息率% | D4: 借款起讫日期 | E4: ='3收入'!E4 -> 2017年 | F4: ='3收入'!F4 -> 2018年 | G4: ='3收入'!G4 -> 2019年 | H4: ='3收入'!H4 -> 2020年 | I4: ='3收入'!I4 -> 2021年 | J4: ='3收入'!J4 -> 2022年
B5: 短期借款 | C5: 0.0541 | E5: 1000 | F5: 1000 | G5: 1000 | H5: 1000 | I5: 1000 | J5: 1000
B6: 一年内到期的非流动负债
B7: 长期借款
B8: 新增借款 | C8: 0.0541 | F8: 315.69213 | G8: 0 | H8: 0 | I8: 0 | J8: 0 | K8: 该行迭代计算得出
B9: 应付债券
B10: 付息负债合计 | E10: =SUM(E5:E9) -> 1000 | F10: =SUM(F5:F9) -> 1315.6921 | G10: =SUM(G5:G9) -> 1000 | H10: =SUM(H5:H9) -> 1000 | I10: =SUM(I5:I9) -> 1000 | J10: =SUM(J5:J9) -> 1000
B11: 财务费用测算
B12: 利息支出 | C12: ='3收入'!C4 -> 2015年 | D12: ='3收入'!D4 -> 2016年 | E12: ='3收入'!E4 -> 2017年 | F12: ='3收入'!F4 -> 2018年 | G12: ='3收入'!G4 -> 2019年 | H12: ='3收入'!H4 -> 2020年 | I12: ='3收入'!I4 -> 2021年 | J12: ='3收入'!K4 -> 0
B13: 短期借款 | F13: =$C5*E5 -> 54.1 | G13: =$C5*F5 -> 54.1 | H13: =$C5*G5 -> 54.1 | I13: =$C5*H5 -> 54.1 | J13: =$C5*I5 -> 54.1 | K13: 采用上年数计算，可根据具体发生情况填列
B14: 一年内到期的非流动负债 | F14: =$C6*E6 -> 0 | G14: =$C6*F6 -> 0 | H14: =$C6*G6 -> 0 | I14: =$C6*H6 -> 0 | J14: =$C6*I6 -> 0
B15: 长期借款 | F15: =$C7*E7 -> 0 | G15: =$C7*F7 -> 0 | H15: =$C7*G7 -> 0 | I15: =$C7*H7 -> 0 | J15: =$C7*I7 -> 0
B16: 新增借款 | F16: =$C8*E8 -> 0 | G16: =$C8*F8 -> 17.078944 | H16: =$C8*G8 -> 0 | I16: =$C8*H8 -> 0 | J16: =$C8*I8 -> 0
B17: 应付债券 | F17: =$C9*E9 -> 0 | G17: =$C9*F9 -> 0 | H17: =$C9*G9 -> 0 | I17: =$C9*H9 -> 0 | J17: =$C9*I9 -> 0
B18: 利息支出小计 | C18: ='1报表'!C104 -> 144.02572 | D18: ='1报表'!D104 -> 132.21571 | E18: ='1报表'!E104 -> 92.333057 | F18: =SUM(F13:F17) -> 54.1 | G18: =SUM(G13:G17) -> 71.178944 | H18: =SUM(H13:H17) -> 54.1 | I18: =SUM(I13:I17) -> 54.1 | J18: =SUM(J13:J17) -> 54.1
B19: 利息收入 | C19: ='1报表'!C105 -> 1.41285 | D19: ='1报表'!D105 -> 1.028431 | E19: ='1报表'!E105 -> 1.207926
B20: 汇兑损益及手续费等 | C20: =C21-C18+C19 -> -11.15778 | D20: =D21-D18+D19 -> -19.370293 | E20: =E21-E18+E19 -> 8.923127 | F20: 9 | G20: 9 | H20: 9 | I20: 9 | J20: 9 | K20: 预测期只考虑手续费，不考虑汇兑损益
B21: 财务费用合计 | C21: ='1报表'!C103 -> 131.45509 | D21: ='1报表'!D103 -> 111.81699 | E21: ='1报表'!E103 -> 100.04826 | F21: =SUM(F18:F20) -> 63.1 | G21: =SUM(G18:G20) -> 80.178944 | H21: =SUM(H18:H20) -> 63.1 | I21: =SUM(I18:I20) -> 63.1 | J21: =SUM(J18:J20) -> 63.1
B23: 新增借款(由预测资产负债表计算得出) | D23: 无“预测财报”表删除 | F23: =预测财报!F83 -> 0 | G23: =预测财报!G83 -> 0 | H23: =预测财报!H83 -> 0 | I23: =预测财报!I83 -> 0 | J23: =预测财报!J83 -> 0 | K23: 企业未来是否有资金缺口，需要融多少资金，
B24: 是否相等？ | F24: =F8-F23 -> 315.69213 | G24: =G8-G23 -> 0 | H24: =H8-H23 -> 0 | I24: =I8-I23 -> 0 | J24: =J8-J23 -> 0 | K24: 只有通过预测资产负债表计算才能得出。
B27: 借款明细核实如下

Sheet 12收益表
B1: 收益预测表
B2: ='1报表'!B11 -> 评估基准日：2017/12/31
B3: ='1报表'!B12 -> 被评估单位：JSBD公司 | J3: 单位：万元
B4: 利润表（经营性） | C4: ='3收入'!C4 -> 2015年 | D4: ='3收入'!D4 -> 2016年 | E4: ='3收入'!E4 -> 2017年 | F4: ='3收入'!F4 -> 2018年 | G4: ='3收入'!G4 -> 2019年 | H4: ='3收入'!H4 -> 2020年 | I4: ='3收入'!I4 -> 2021年 | J4: ='3收入'!J4 -> 2022年
B5: 一、营业收入 | C5: ='3收入'!C5 -> 5647.5609 | D5: ='3收入'!D5 -> 7304.7745 | E5: ='3收入'!E5 -> 9615.5763 | F5: ='3收入'!F5 -> 11935.477 | G5: ='3收入'!G5 -> 14141.384 | H5: ='3收入'!H5 -> 15896.18 | I5: ='3收入'!I5 -> 16863.123 | J5: ='3收入'!J5 -> 17224.451
B6: 减:营业成本 | C6: ='4成本'!C5 -> 3450.9962 | D6: ='4成本'!D5 -> 4625.6862 | E6: ='4成本'!E5 -> 5762.986 | F6: ='4成本'!F5 -> 7161.2864 | G6: ='4成本'!G5 -> 8484.8303 | H6: ='4成本'!H5 -> 9537.7079 | I6: ='4成本'!I5 -> 10117.874 | J6: ='4成本'!J5 -> 10334.671
B7: 减:税金及附加 | C7: ='5税金'!C5 -> 53.873421 | D7: ='5税金'!D5 -> 81.416231 | E7: ='5税金'!E5 -> 113.39456 | F7: ='5税金'!F5 -> 107.26836 | G7: ='5税金'!G5 -> 127.21454 | H7: ='5税金'!H5 -> 142.79594 | I7: ='5税金'!I5 -> 152.48181 | J7: ='5税金'!J5 -> 155.38377
B8: 减:销售费用 | C8: ='6销管'!C5 -> 481.4591 | D8: ='6销管'!D5 -> 588.55087 | E8: ='6销管'!E5 -> 750.19684 | F8: ='6销管'!F5 -> 950.06399 | G8: ='6销管'!G5 -> 1125.6541 | H8: ='6销管'!H5 -> 1265.3359 | I8: ='6销管'!I5 -> 1342.3046 | J8: ='6销管'!J5 -> 1371.0663
B9: 减:管理费用 | C9: ='6销管'!C6 -> 694.30698 | D9: ='6销管'!D6 -> 710.43654 | E9: ='6销管'!E6 -> 1052.4467 | F9: ='6销管'!F6 -> 1140.1681 | G9: ='6销管'!G6 -> 1284.8847 | H9: ='6销管'!H6 -> 1341.4961 | I9: ='6销管'!I6 -> 1376.4758 | J9: ='6销管'!J6 -> 1432.4397
B10: 减:研发费用 | C10: ='6销管'!C7 -> 384.83578 | D10: ='6销管'!D7 -> 369.90657 | E10: ='6销管'!E7 -> 435.369 | F10: ='6销管'!F7 -> 596.77387 | G10: ='6销管'!G7 -> 707.06919 | H10: ='6销管'!H7 -> 794.809 | I10: ='6销管'!I7 -> 843.15614 | J10: ='6销管'!J7 -> 861.22256
B11: 减:财务费用 | C11: ='11财务费用'!C21 -> 131.45509 | D11: ='11财务费用'!D21 -> 111.81699 | E11: ='11财务费用'!E21 -> 100.04826 | F11: ='11财务费用'!F21 -> 63.1 | G11: ='11财务费用'!G21 -> 80.178944 | H11: ='11财务费用'!H21 -> 63.1 | I11: ='11财务费用'!I21 -> 63.1 | J11: ='11财务费用'!J21 -> 63.1
B12: 二、营业利润 | C12: =C5-SUM(C6:C11) -> 450.63432 | D12: =D5-SUM(D6:D11) -> 816.9611 | E12: =E5-SUM(E6:E11) -> 1401.135 | F12: =F5-SUM(F6:F11) -> 1916.8166 | G12: =G5-SUM(G6:G11) -> 2331.552 | H12: =H5-SUM(H6:H11) -> 2750.935 | I12: =I5-SUM(I6:I11) -> 2967.7308 | J12: =J5-SUM(J6:J11) -> 3006.5681
B13: 三、利润总额 | C13: =C12 -> 450.63432 | D13: =D12 -> 816.9611 | E13: =E12 -> 1401.135 | F13: =F12 -> 1916.8166 | G13: =G12 -> 2331.552 | H13: =H12 -> 2750.935 | I13: =I12 -> 2967.7308 | J13: =J12 -> 3006.5681
B14: 减：弥补以前年度亏损
B15: 减：研发费用加计扣除 | F15: ='6销管'!F7*0.75 -> 447.5804 | G15: ='6销管'!G7*0.75 -> 530.30189 | H15: ='6销管'!H7*0.5 -> 397.4045 | I15: ='6销管'!I7*0.5 -> 421.57807 | J15: ='6销管'!J7*0.5 -> 430.61128
B16: 减：其他纳税调减额
B17: 加：其他纳税调增额
B18: 应纳税所得额 | F18: =F13-F14-F15-F16+F17 -> 1469.2362 | G18: =G13-G14-G15-G16+G17 -> 1801.2501 | H18: =H13-H14-H15-H16+H17 -> 2353.5305 | I18: =I13-I14-I15-I16+I17 -> 2546.1527 | J18: =J13-J14-J15-J16+J17 -> 2575.9568
B19: 所得税税率 | F19: 0.25 | G19: 0.15 | H19: 0.15 | I19: 0.15 | J19: 0.25
B20: 减:所得税费用 | F20: =IF(F18<0,0,F18*F19) -> 367.30906 | G20: =IF(G18<0,0,G18*G19) -> 270.18752 | H20: =IF(H18<0,0,H18*H19) -> 353.02958 | I20: =IF(I18<0,0,I18*I19) -> 381.92291 | J20: =IF(J18<0,0,J18*J19) -> 643.9892
B21: 四、净利润 | F21: =F13-F20 -> 1549.5076 | G21: =G13-G20 -> 2061.3645 | H21: =H13-H20 -> 2397.9054 | I21: =I13-I20 -> 2585.8079 | J21: =J13-J20 -> 2362.5789
B22: 减:少数股东损益
B23: 五、归母净利润 | F23: =F21-F22 -> 1549.5076 | G23: =G21-G22 -> 2061.3645 | H23: =H21-H22 -> 2397.9054 | I23: =I21-I22 -> 2585.8079 | J23: =J21-J22 -> 2362.5789
B26: 补充预测利润表用数据，无“预测财报”表删除下列数据！
B27: 三、利润总额 | C27: =C13 -> 450.63432 | D27: =D13 -> 816.9611 | E27: =E13 -> 1401.135
B28: 减：弥补以前年度亏损
B29: 减：研发费用加计扣除 | C29: ='6销管'!C7*0.75 -> 288.62683 | D29: ='6销管'!D7*0.75 -> 277.42993 | E29: ='6销管'!E7*0.75 -> 326.52675
B30: 减：其他纳税调减额
B31: 加：其他纳税调增额
B32: 应纳税所得额 | C32: =C27-C28-C29-C30+C31 -> 162.00749 | D32: =D27-D28-D29-D30+D31 -> 539.53118 | E32: =E27-E28-E29-E30+E31 -> 1074.6082
B33: 所得税税率 | C33: 0.15 | D33: 0.15 | E33: 0.15
B34: 减:所得税费用 | C34: =IF(C32<0,0,C32*C33) -> 24.301124 | D34: =IF(D32<0,0,D32*D33) -> 80.929676 | E34: =IF(E32<0,0,E32*E33) -> 161.19123

Sheet 13FCFF
B1: 企业自由现金流量测算表
B2: ='1报表'!B11 -> 评估基准日：2017/12/31
B3: ='1报表'!B12 -> 被评估单位：JSBD公司 | K3: 单位：万元
B4: 项目 | F4: ='3收入'!F4 -> 2018年 | G4: ='3收入'!G4 -> 2019年 | H4: ='3收入'!H4 -> 2020年 | I4: ='3收入'!I4 -> 2021年 | J4: ='3收入'!J4 -> 2022年 | K4: 永续期
B5: 一、营业收入 | F5: ='12收益表'!F5 -> 11935.477 | G5: ='12收益表'!G5 -> 14141.384 | H5: ='12收益表'!H5 -> 15896.18 | I5: ='12收益表'!I5 -> 16863.123 | J5: ='12收益表'!J5 -> 17224.451 | K5: =J5 -> 17224.451
B6: 减：营业成本 | F6: ='12收益表'!F6 -> 7161.2864 | G6: ='12收益表'!G6 -> 8484.8303 | H6: ='12收益表'!H6 -> 9537.7079 | I6: ='12收益表'!I6 -> 10117.874 | J6: ='12收益表'!J6 -> 10334.671 | K6: =J6 -> 10334.671
B7: 减：税金及附加 | F7: ='12收益表'!F7 -> 107.26836 | G7: ='12收益表'!G7 -> 127.21454 | H7: ='12收益表'!H7 -> 142.79594 | I7: ='12收益表'!I7 -> 152.48181 | J7: ='12收益表'!J7 -> 155.38377 | K7: =J7 -> 155.38377
B8: 减：销售费用 | F8: ='12收益表'!F8 -> 950.06399 | G8: ='12收益表'!G8 -> 1125.6541 | H8: ='12收益表'!H8 -> 1265.3359 | I8: ='12收益表'!I8 -> 1342.3046 | J8: ='12收益表'!J8 -> 1371.0663 | K8: =J8 -> 1371.0663
B9: 减：管理费用 | F9: ='12收益表'!F9 -> 1140.1681 | G9: ='12收益表'!G9 -> 1284.8847 | H9: ='12收益表'!H9 -> 1341.4961 | I9: ='12收益表'!I9 -> 1376.4758 | J9: ='12收益表'!J9 -> 1432.4397 | K9: =J9 -> 1432.4397
B10: 减：研发费用 | F10: ='12收益表'!F10 -> 596.77387 | G10: ='12收益表'!G10 -> 707.06919 | H10: ='12收益表'!H10 -> 794.809 | I10: ='12收益表'!I10 -> 843.15614 | J10: ='12收益表'!J10 -> 861.22256 | K10: =J10 -> 861.22256
B11: 减：财务费用 | F11: ='12收益表'!F11 -> 63.1 | G11: ='12收益表'!G11 -> 80.178944 | H11: ='12收益表'!H11 -> 63.1 | I11: ='12收益表'!I11 -> 63.1 | J11: ='12收益表'!J11 -> 63.1 | K11: =IF('11财务费用'!J10,SUMPRODUCT('11财务费用'!C5:C9,'11财务费用'!J5:J9)+'11财务费用'!J20,0) -> 63.1
B12: 二、营业利润 | F12: =F5-SUM(F6:F11) -> 1916.8166 | G12: =G5-SUM(G6:G11) -> 2331.552 | H12: =H5-SUM(H6:H11) -> 2750.935 | I12: =I5-SUM(I6:I11) -> 2967.7308 | J12: =J5-SUM(J6:J11) -> 3006.5681 | K12: =K5-SUM(K6:K11) -> 3006.5681
B13: 三、利润总额 | F13: =F12 -> 1916.8166 | G13: =G12 -> 2331.552 | H13: =H12 -> 2750.935 | I13: =I12 -> 2967.7308 | J13: =J12 -> 3006.5681 | K13: =K12 -> 3006.5681
B14: 减：所得税费用 | F14: ='12收益表'!F20 -> 367.30906 | G14: ='12收益表'!G20 -> 270.18752 | H14: ='12收益表'!H20 -> 353.02958 | I14: ='12收益表'!I20 -> 381.92291 | J14: ='12收益表'!J20 -> 643.9892 | K14: =K13*K32 -> 751.64202 | L14: 永续期未考虑研发费用加计扣除，因为这是一个短期政策。
B15: 四、净利润 | F15: =F13-F14 -> 1549.5076 | G15: =G13-G14 -> 2061.3645 | H15: =H13-H14 -> 2397.9054 | I15: =I13-I14 -> 2585.8079 | J15: =J13-J14 -> 2362.5789 | K15: =K13-K14 -> 2254.9261
B16: 加：扣税后利息费用 | F16: =(1-F32)*'11财务费用'!F18 -> 40.575 | G16: =(1-G32)*'11财务费用'!G18 -> 60.502102 | H16: =(1-H32)*'11财务费用'!H18 -> 45.985 | I16: =(1-I32)*'11财务费用'!I18 -> 45.985 | J16: =(1-J32)*'11财务费用'!J18 -> 40.575 | K16: =(1-K32)*SUMPRODUCT('11财务费用'!C5:C9,'11财务费用'!J5:J9) -> 40.575
B17: 加：折旧与摊销 | F17: ='7折旧'!F9+'8摊销'!F7 -> 684.07805 | G17: ='7折旧'!G9+'8摊销'!G7 -> 722.17805 | H17: ='7折旧'!H9+'8摊销'!H7 -> 391.28937 | I17: ='7折旧'!I9+'8摊销'!I7 -> 204.93767 | J17: ='7折旧'!J9+'8摊销'!J7 -> 235.93767 | K17: =J17 -> 235.93767
B18: 减：资本性支出 | F18: ='7折旧'!F10+'8摊销'!F10 -> 232 | G18: ='7折旧'!G10+'8摊销'!G10 -> 50 | H18: ='7折旧'!H10+'8摊销'!H10 -> 110 | I18: ='7折旧'!I10+'8摊销'!I10 -> 110 | J18: ='7折旧'!J10+'8摊销'!J10 -> 110 | K18: =K17 -> 235.93767
B19: 减：净营运资金变动 | F19: ='10营运'!F40 -> 640.3514 | G19: ='10营运'!G40 -> 721.43725 | H19: ='10营运'!H40 -> 570.29671 | I19: ='10营运'!I40 -> 317.04582 | J19: ='10营运'!J40 -> 121.14597 | K19: 0
B20: 五、企业自由现金流量 | F20: =F15+F16+F17-F18-F19 -> 1401.8092 | G20: =G15+G16+G17-G18-G19 -> 2072.6074 | H20: =H15+H16+H17-H18-H19 -> 2154.8831 | I20: =I15+I16+I17-I18-I19 -> 2409.6847 | J20: =J15+J16+J17-J18-J19 -> 2407.9456 | K20: =K15+K16+K17-K18-K19 -> 2295.5011
B21: 折现期 | F21: 1 | G21: =1+F21 -> 2 | H21: =1+G21 -> 3 | I21: =1+H21 -> 4 | J21: =1+I21 -> 5
B22: 折现率 | F22: =F48 -> 0.1331479 | G22: =F22 -> 0.1331479 | H22: =G22 -> 0.1331479 | I22: =H22 -> 0.1331479 | J22: =I22 -> 0.1331479 | K22: =J22 -> 0.1331479
B23: 折现系数 | F23: =1/(1+F22) -> 0.88249733 | G23: =F23/(1+G22) -> 0.77880154 | H23: =G23/(1+H22) -> 0.68729028 | I23: =H23/(1+I22) -> 0.60653184 | J23: =I23/(1+J22) -> 0.53526273 | K23: =J23/K22 -> 4.0200613
B24: (计算WACC1)折现值 | F24: =F20*F23 -> 1237.0929 | G24: =G20*G23 -> 1614.1498 | H24: =H20*H23 -> 1481.0302 | I24: =I20*I23 -> 1461.5505 | J24: =J20*J23 -> 1288.8835 | K24: =K20*K23 -> 9228.0551
B25: 迭代后折现率 | F25: =F48 -> 0.1331479 | G25: =I48 -> 0.13385421 | H25: =I48 -> 0.13385421 | I25: =I48 -> 0.13385421 | J25: =L48 -> 0.1331491 | K25: =L48 -> 0.1331491 | L25: 无付息负债，无需迭代计算！
B26: 迭代后折现系数 | F26: =1/(1+F25) -> 0.88249733 | G26: =F26/(1+G25) -> 0.7783164 | H26: =G26/(1+H25) -> 0.68643428 | I26: =H26/(1+I25) -> 0.60539907 | J26: =I26/(1+J25) -> 0.5342625 | K26: =J26/K25 -> 4.0125129
B27: 最终评估折现值 | F27: =F20*F26 -> 1237.0929 | G27: =G20*G26 -> 1613.1443 | H27: =H20*H26 -> 1479.1856 | I27: =I20*I26 -> 1458.8209 | J27: =J20*J26 -> 1286.475 | K27: =K20*K26 -> 9210.7276
B28: 六、企业自由现金流现值合计 | F28: =SUM(F27:K27) -> 16285.446
B29: 经营性资产价值 | F29: =F28*J29 -> 16285.446 | H29: 是否选择年中折现？ | J29: =IF(K29="年末",1,(1+F25)^0.5) -> 1 | K29: 年末 | L29: 调整系数 | M29: 本公式为单一折现率使用的年中折现调整系数，多折现率的公式尚未导出。
B31: 项目 | F31: =F4 -> 2018年 | G31: =G4 -> 2019年 | H31: =H4 -> 2020年 | I31: =I4 -> 2021年 | J31: =J4 -> 2022年 | K31: =K4 -> 永续期
B32: 企业所得税率T | F32: ='12收益表'!F19 -> 0.25 | G32: ='12收益表'!G19 -> 0.15 | H32: ='12收益表'!H19 -> 0.15 | I32: ='12收益表'!I19 -> 0.15 | J32: ='12收益表'!J19 -> 0.25 | K32: =J32 -> 0.25
B33: WACC1测算（2018年） | I33: WACC2测算（2019-2021年） | L33: WACC3测算（2022年及以后）
B34: 付息债务D | F34: ='11财务费用'!E10 -> 1000
B35: 企业所得税率T | F35: =F32 -> 0.25 | I35: =G32 -> 0.15 | L35: =J32 -> 0.25
B36: 无风险报酬率Rf | F36: 0.0455 | I36: =F36 -> 0.0455 | L36: =I36 -> 0.0455
B37: 市场风险溢价MRP | F37: 0.0656 | I37: =F37 -> 0.0656 | L37: =I37 -> 0.0656
B38: 个别风险调整系数Q | F38: 0.03 | I38: =F38 -> 0.03 | L38: =I38 -> 0.03
B39: 行业βU | F39: 0.9257 | I39: =F39 -> 0.9257 | L39: =I39 -> 0.9257
B40: 债务成本Kd | F40: 0.0541 | I40: =F40 -> 0.0541 | L40: =I40 -> 0.0541
B41: βL=βu[1+(1-T)D/E] | F41: =F39*(1+(1-F35)*F44) -> 0.97114039 | I41: =I39*(1+(1-I35)*I44) -> 0.97717738 | L41: =L39*(1+(1-L35)*L44) -> 0.97112146
B42: 权益成本Ke＝Rf＋βL×MRP＋Q | F42: =F36+F41*F37+F38 -> 0.13920681 | I42: =I36+I41*I37+I38 -> 0.13960284 | L42: =L36+L41*L37+L38 -> 0.13920557
B44: D/E | F44: 0.065450124 | G44: =F34/(SUM(F27:K27)-F34) -> 0.065421707 | H44: =F44-G44 -> 2.8417027e-05 | I44: 0.065422511 | J44: =F34/(SUM(F27:K27)-F34) -> 0.065421707 | K44: =I44-J44 -> 8.0330966e-07 | L44: 0.065422866 | M44: =F34/(SUM(F27:K27)-F34) -> 0.065421707 | N44: =L44-M44 -> 1.1583206e-06
B45: We=E/(D+E) | F45: =G45 -> 0.93857045 | G45: =1/(F44+1) -> 0.93857045 | H45: =F45-G45 -> 0 | I45: =J45 -> 0.93859477 | J45: =1/(I44+1) -> 0.93859477 | K45: =I45-J45 -> 0 | L45: =M45 -> 0.93859446 | M45: =1/(L44+1) -> 0.93859446 | N45: =L45-M45 -> 0
B46: Wd=D/(D+E) | F46: =G46 -> 0.061429553 | G46: =1-F45 -> 0.061429553 | H46: =F46-G46 -> 0 | I46: =J46 -> 0.061405227 | J46: =1-I45 -> 0.061405227 | K46: =I46-J46 -> 0 | L46: =M46 -> 0.061405539 | M46: =1-L45 -> 0.061405539 | N46: =L46-M46 -> 0
B48: WACC=Ke×We+(1-T)Kd×Wd | F48: =F42*F45+(1-F35)*F40*F46 -> 0.1331479 | I48: =I42*I45+(1-I35)*I40*I46 -> 0.13385421 | L48: =L42*L45+(1-L35)*L40*L46 -> 0.1331491
B51: 股东权益价值测算表
B52: 项目 | F52: 评估值 | G52: 备注
B53: 经营性资产价值 | F53: =F29 -> 16285.446
B54: 加：溢余资产评估值 | F54: ='2报表调整'!F80 -> 37.453128
B55: 加：非经营性资产评估值 | F55: ='2报表调整'!N43 -> 83.680218
B56: 减：非经营性负债评估值 | F56: ='2报表调整'!N70 -> 1415.2446
B57: 企业整体资产价值 | F57: =F53+F54+F55-F56 -> 14991.335
B58: 减：付息负债价值 | F58: ='11财务费用'!E10 -> 1000
B59: 减：股票期权
B60: 减：可转换债券
B61: 减：少数股东权益
B62: 股东全部权益价值 | F62: =F57-SUM(F58:F61) -> 13991.335
B63: 股东全部权益价值（取整） | F63: =ROUND(F62,-1) -> 13990
B64: 控制权对评估对象价值的影响 | G64: 未考虑
B65: 流动性对评估对象价值的影响 | G65: 未考虑
B66: 本次评估股权比例
B67: 部分股权评估值 | F67: =F63*F66 -> 0

Sheet 14FCFE
B1: 股权自由现金流量测算表
B2: ='1报表'!B11 -> 评估基准日：2017/12/31
B3: ='1报表'!B12 -> 被评估单位：JSBD公司 | K3: 单位：万元
B4: 项目 | F4: ='3收入'!F4 -> 2018年 | G4: ='3收入'!G4 -> 2019年 | H4: ='3收入'!H4 -> 2020年 | I4: ='3收入'!I4 -> 2021年 | J4: ='3收入'!J4 -> 2022年 | K4: 永续期
B5: 一、营业收入 | F5: ='12收益表'!F5 -> 11935.477 | G5: ='12收益表'!G5 -> 14141.384 | H5: ='12收益表'!H5 -> 15896.18 | I5: ='12收益表'!I5 -> 16863.123 | J5: ='12收益表'!J5 -> 17224.451 | K5: =J5 -> 17224.451
B6: 减：营业成本 | F6: ='12收益表'!F6 -> 7161.2864 | G6: ='12收益表'!G6 -> 8484.8303 | H6: ='12收益表'!H6 -> 9537.7079 | I6: ='12收益表'!I6 -> 10117.874 | J6: ='12收益表'!J6 -> 10334.671 | K6: =J6 -> 10334.671
B7: 减：税金及附加 | F7: ='12收益表'!F7 -> 107.26836 | G7: ='12收益表'!G7 -> 127.21454 | H7: ='12收益表'!H7 -> 142.79594 | I7: ='12收益表'!I7 -> 152.48181 | J7: ='12收益表'!J7 -> 155.38377 | K7: =J7 -> 155.38377
B8: 减：销售费用 | F8: ='12收益表'!F8 -> 950.06399 | G8: ='12收益表'!G8 -> 1125.6541 | H8: ='12收益表'!H8 -> 1265.3359 | I8: ='12收益表'!I8 -> 1342.3046 | J8: ='12收益表'!J8 -> 1371.0663 | K8: =J8 -> 1371.0663
B9: 减：管理费用 | F9: ='12收益表'!F9 -> 1140.1681 | G9: ='12收益表'!G9 -> 1284.8847 | H9: ='12收益表'!H9 -> 1341.4961 | I9: ='12收益表'!I9 -> 1376.4758 | J9: ='12收益表'!J9 -> 1432.4397 | K9: =J9 -> 1432.4397
B10: 减：研发费用 | F10: ='12收益表'!F10 -> 596.77387 | G10: ='12收益表'!G10 -> 707.06919 | H10: ='12收益表'!H10 -> 794.809 | I10: ='12收益表'!I10 -> 843.15614 | J10: ='12收益表'!J10 -> 861.22256 | K10: =J10 -> 861.22256
B11: 减：财务费用 | F11: =IF('11财务费用'!E10,"模型不适用",'11财务费用'!F21) -> 模型不适用 | G11: =IF('11财务费用'!F10,"模型不适用",'11财务费用'!G21) -> 模型不适用 | H11: =IF('11财务费用'!G10,"模型不适用",'11财务费用'!H21) -> 模型不适用 | I11: =IF('11财务费用'!H10,"模型不适用",'11财务费用'!I21) -> 模型不适用 | J11: =IF('11财务费用'!I10,"模型不适用",'11财务费用'!J21) -> 模型不适用 | K11: =IF('11财务费用'!J10,"模型不适用",'11财务费用'!K21) -> 模型不适用
B12: 二、营业利润 | F12: =F5-SUM(F6:F11) -> 1979.9166 | G12: =G5-SUM(G6:G11) -> 2411.731 | H12: =H5-SUM(H6:H11) -> 2814.035 | I12: =I5-SUM(I6:I11) -> 3030.8308 | J12: =J5-SUM(J6:J11) -> 3069.6681 | K12: =K5-SUM(K6:K11) -> 3069.6681
B13: 三、利润总额 | F13: =F12 -> 1979.9166 | G13: =G12 -> 2411.731 | H13: =H12 -> 2814.035 | I13: =I12 -> 3030.8308 | J13: =J12 -> 3069.6681 | K13: =K12 -> 3069.6681
B14: 减:所得税费用 | F14: ='12收益表'!F20 -> 367.30906 | G14: ='12收益表'!G20 -> 270.18752 | H14: ='12收益表'!H20 -> 353.02958 | I14: ='12收益表'!I20 -> 381.92291 | J14: ='12收益表'!J20 -> 643.9892 | K14: =K13*'12收益表'!J19 -> 767.41702
B15: 四、净利润 | F15: =F13-F14 -> 1612.6076 | G15: =G13-G14 -> 2141.5434 | H15: =H13-H14 -> 2461.0054 | I15: =I13-I14 -> 2648.9079 | J15: =J13-J14 -> 2425.6789 | K15: =K13-K14 -> 2302.2511
B16: 加：折旧与摊销 | F16: ='7折旧'!F9+'8摊销'!F7 -> 684.07805 | G16: ='7折旧'!G9+'8摊销'!G7 -> 722.17805 | H16: ='7折旧'!H9+'8摊销'!H7 -> 391.28937 | I16: ='7折旧'!I9+'8摊销'!I7 -> 204.93767 | J16: ='7折旧'!J9+'8摊销'!J7 -> 235.93767 | K16: =J16 -> 235.93767
B17: 减：资本性支出 | F17: ='7折旧'!F10+'8摊销'!F10 -> 232 | G17: ='7折旧'!G10+'8摊销'!G10 -> 50 | H17: ='7折旧'!H10+'8摊销'!H10 -> 110 | I17: ='7折旧'!I10+'8摊销'!I10 -> 110 | J17: ='7折旧'!J10+'8摊销'!J10 -> 110 | K17: =K16 -> 235.93767
B18: 减：净营运资金变动 | F18: ='10营运'!F40 -> 640.3514 | G18: ='10营运'!G40 -> 721.43725 | H18: ='10营运'!H40 -> 570.29671 | I18: ='10营运'!I40 -> 317.04582 | J18: ='10营运'!J40 -> 121.14597 | K18: 0
B19: 加：付息债务的增加 | F19: =IF('11财务费用'!E10,"模型不适用",0) -> 模型不适用 | G19: =IF('11财务费用'!F10,"模型不适用",0) -> 模型不适用 | H19: =IF('11财务费用'!G10,"模型不适用",0) -> 模型不适用 | I19: =IF('11财务费用'!H10,"模型不适用",0) -> 模型不适用 | J19: =IF('11财务费用'!I10,"模型不适用",0) -> 模型不适用 | K19: 0
B20: 五、股权自由现金流 (FCFE) | F20: =F15+F16-F17-F18+F19 -> #VALUE! | G20: =G15+G16-G17-G18+G19 -> #VALUE! | H20: =H15+H16-H17-H18+H19 -> #VALUE! | I20: =I15+I16-I17-I18+I19 -> #VALUE! | J20: =J15+J16-J17-J18+J19 -> #VALUE! | K20: =K15+K16-K17-K18+K19 -> 2302.2511
B21: 折现期 | F21: 1 | G21: =1+F21 -> 2 | H21: =1+G21 -> 3 | I21: =1+H21 -> 4 | J21: =1+I21 -> 5
B22: 折现率 | F22: =ROUND(F33,4) -> 0.1348 | G22: =F22 -> 0.1348 | H22: =G22 -> 0.1348 | I22: =H22 -> 0.1348 | J22: =I22 -> 0.1348 | K22: =J22 -> 0.1348
B23: 折现系数 | F23: =1/(1+F22) -> 0.88121255 | G23: =F23/(1+G22) -> 0.77653556 | H23: =G23/(1+H22) -> 0.68429288 | I23: =H23/(1+I22) -> 0.60300747 | J23: =I23/(1+J22) -> 0.53137775 | K23: =J23/K22 -> 3.9419714
B24: 股权自由现金流现值 | F24: =F20*F23 -> #VALUE! | G24: =G20*G23 -> #VALUE! | H24: =H20*H23 -> #VALUE! | I24: =I20*I23 -> #VALUE! | J24: =J20*J23 -> #VALUE! | K24: =K20*K23 -> 9075.4079
B25: 六、股权自由现金流现值合计 | F25: =SUM(F24:K24) -> #VALUE!
B27: 折现率计算表
B28: 项目 | F28: 取值
B29: 无风险报酬率（Rf） | F29: 0.0441
B30: MRP（市场风险溢价）=Rm-Rf | F30: 0.0656
B31: βL（=βU） | F31: 0.9257
B32: Q | F32: 0.03
B33: 权益成本Ke | F33: =F29+F31*F30+F32 -> 0.13482592
B34: 永续期不考虑增长
B36: 股东权益价值测算表
B37: 项目 | F37: 评估值 | G37: 备注
B38: 股权自由现金流现值 | F38: =F25 -> #VALUE!
B39: 加：溢余资产评估值 | F39: ='2报表调整'!F80 -> 37.453128
B40: 加：非经营性资产评估值 | F40: ='2报表调整'!N43 -> 83.680218
B41: 减：非经营性负债评估值 | F41: ='2报表调整'!N70 -> 1415.2446
B42: 股东全部权益价值E1 | F42: =F38+F39+F40-F41 -> #VALUE!
B43: 减：股票期权
B44: 减：可转换债券
B45: 减：少数股东权益
B46: 股东全部权益价值E2 | F46: =F42-SUM(F43:F45) -> #VALUE!
B47: 股东全部权益价值（取整） | F47: =ROUND(F46,-1) -> #VALUE!
B48: 控制权对评估对象价值的影响 | G48: 未考虑
B49: 流动性对评估对象价值的影响 | G49: 未考虑
B50: 本次评估股权比例
B51: 部分股权评估值 | F51: =F47*F50 -> #VALUE!
B53: 应用前提
B54: 该FCFE模型只适用评估基准日及未来预测期间无付息负债的情形。

Sheet 预测财报
B1: 经营性资产财务报表预测表（检查用）
B2: ='1报表'!B11 -> 评估基准日：2017/12/31
B3: ='1报表'!B12 -> 被评估单位：JSBD公司 | J3: 单位：万元
B4: 完成资产负债表剩余项目 | C4: ='1报表'!C13 -> 42369 | D4: ='1报表'!D13 -> 42735 | E4: ='1报表'!E13 -> 43100 | F4: =EDATE(E4,12) -> 43465 | G4: =EDATE(F4,12) -> 43830 | H4: =EDATE(G4,12) -> 44196 | I4: =EDATE(H4,12) -> 44561 | J4: =EDATE(I4,12) -> 44926
B5: 长期应收款 | C5: ='1报表'!C34-'2报表调整'!K27 -> 0 | D5: ='1报表'!D34-'2报表调整'!L27 -> 0 | E5: ='2报表调整'!G27 -> 0
B6: 其他非流动资产 | C6: ='1报表'!C48-'2报表调整'!K41 -> 28.32889 | D6: ='1报表'!D48-'2报表调整'!L41 -> 294.362 | E6: ='2报表调整'!G41 -> 38.18068 | F6: =E6 -> 38.18068 | G6: =F6 -> 38.18068 | H6: =G6 -> 38.18068 | I6: =H6 -> 38.18068 | J6: =I6 -> 38.18068
B7: 长期应付款 | C7: ='1报表'!C70-'2报表调整'!K63 -> 0 | D7: ='1报表'!D70-'2报表调整'!L63 -> 0 | E7: ='2报表调整'!G63 -> 0
B8: 长期应付职工薪酬 | C8: ='1报表'!C71-'2报表调整'!K64 -> 0 | D8: ='1报表'!D71-'2报表调整'!L64 -> 0 | E8: ='2报表调整'!G64 -> 0
B9: 预计负债 | C9: ='1报表'!C72-'2报表调整'!K65 -> 0 | D9: ='1报表'!D72-'2报表调整'!L65 -> 0 | E9: ='2报表调整'!G65 -> 0
B10: 递延收益 | C10: ='1报表'!C73-'2报表调整'!K66 -> 0 | D10: ='1报表'!D73-'2报表调整'!L66 -> 0 | E10: ='2报表调整'!G66 -> 0
B11: 其他非流动负债 | C11: ='1报表'!C75-'2报表调整'!K68 -> 0 | D11: ='1报表'!D75-'2报表调整'!L68 -> 0 | E11: ='2报表调整'!G68 -> 0
B12: 少数股东所在公司派发股利的比例 | F12: 0.5 | G12: =F12 -> 0.5 | H12: =G12 -> 0.5 | I12: =H12 -> 0.5 | J12: =I12 -> 0.5
B13: 补充投入资本计算表剩余历史数据
B14: 加：收购无形资产的累计摊销额
B15: 加：累计减值的商誉
B16: 完成利润表剩余项目
B17: 新增借款利率 | F17: ='11财务费用'!C8 -> 0.0541
B19: 利润表（经营性） | C19: ='3收入'!C4 -> 2015年 | D19: ='3收入'!D4 -> 2016年 | E19: ='3收入'!E4 -> 2017年 | F19: ='3收入'!F4 -> 2018年 | G19: ='3收入'!G4 -> 2019年 | H19: ='3收入'!H4 -> 2020年 | I19: ='3收入'!I4 -> 2021年 | J19: ='3收入'!J4 -> 2022年
B20: 一、营业收入 | C20: ='3收入'!C5 -> 5647.5609 | D20: ='3收入'!D5 -> 7304.7745 | E20: ='3收入'!E5 -> 9615.5763 | F20: ='3收入'!F5 -> 11935.477 | G20: ='3收入'!G5 -> 14141.384 | H20: ='3收入'!H5 -> 15896.18 | I20: ='3收入'!I5 -> 16863.123 | J20: ='3收入'!J5 -> 17224.451
B21: 减:营业成本 | C21: ='4成本'!C5 -> 3450.9962 | D21: ='4成本'!D5 -> 4625.6862 | E21: ='4成本'!E5 -> 5762.986 | F21: ='4成本'!F5 -> 7161.2864 | G21: ='4成本'!G5 -> 8484.8303 | H21: ='4成本'!H5 -> 9537.7079 | I21: ='4成本'!I5 -> 10117.874 | J21: ='4成本'!J5 -> 10334.671
B22: 减:税金及附加 | C22: ='5税金'!C5 -> 53.873421 | D22: ='5税金'!D5 -> 81.416231 | E22: ='5税金'!E5 -> 113.39456 | F22: ='5税金'!F5 -> 107.26836 | G22: ='5税金'!G5 -> 127.21454 | H22: ='5税金'!H5 -> 142.79594 | I22: ='5税金'!I5 -> 152.48181 | J22: ='5税金'!J5 -> 155.38377
B23: 减:销售费用 | C23: ='6销管'!C5 -> 481.4591 | D23: ='6销管'!D5 -> 588.55087 | E23: ='6销管'!E5 -> 750.19684 | F23: ='6销管'!F5 -> 950.06399 | G23: ='6销管'!G5 -> 1125.6541 | H23: ='6销管'!H5 -> 1265.3359 | I23: ='6销管'!I5 -> 1342.3046 | J23: ='6销管'!J5 -> 1371.0663
B24: 减:管理费用 | C24: ='6销管'!C6 -> 694.30698 | D24: ='6销管'!D6 -> 710.43654 | E24: ='6销管'!E6 -> 1052.4467 | F24: ='6销管'!F6 -> 1140.1681 | G24: ='6销管'!G6 -> 1284.8847 | H24: ='6销管'!H6 -> 1341.4961 | I24: ='6销管'!I6 -> 1376.4758 | J24: ='6销管'!J6 -> 1432.4397
B25: 减:研发费用 | C25: ='6销管'!C7 -> 384.83578 | D25: ='6销管'!D7 -> 369.90657 | E25: ='6销管'!E7 -> 435.369 | F25: ='6销管'!F7 -> 596.77387 | G25: ='6销管'!G7 -> 707.06919 | H25: ='6销管'!H7 -> 794.809 | I25: ='6销管'!I7 -> 843.15614 | J25: ='6销管'!J7 -> 861.22256
B26: 减:手续费和汇兑损益等 | C26: ='11财务费用'!C20 -> -11.15778 | D26: ='11财务费用'!D20 -> -19.370293 | E26: ='11财务费用'!E20 -> 8.923127 | F26: ='11财务费用'!F20 -> 9 | G26: ='11财务费用'!G20 -> 9 | H26: ='11财务费用'!H20 -> 9 | I26: ='11财务费用'!I20 -> 9 | J26: ='11财务费用'!J20 -> 9
B27: 减:利息支出(新增借款) | G27: =$F$17*F83 -> 0 | H27: =$F$17*G83 -> 0 | I27: =$F$17*H83 -> 0 | J27: =$F$17*I83 -> 0
B28: 减:利息支出(原有债务) | C28: ='11财务费用'!C18 -> 144.02572 | D28: ='11财务费用'!D18 -> 132.21571 | E28: ='11财务费用'!E18 -> 92.333057 | F28: ='11财务费用'!F18 -> 54.1 | G28: ='11财务费用'!G18 -> 71.178944 | H28: ='11财务费用'!H18 -> 54.1 | I28: ='11财务费用'!I18 -> 54.1 | J28: ='11财务费用'!J18 -> 54.1
B29: 加:利息收入(保有、溢余现金) | C29: ='11财务费用'!C19 -> 1.41285 | D29: ='11财务费用'!D19 -> 1.028431 | E29: ='11财务费用'!E19 -> 1.207926
B30: 二、营业利润 | C30: =C20-SUM(C21:C28)+C29 -> 450.63432 | D30: =D20-SUM(D21:D28)+D29 -> 816.9611 | E30: =E20-SUM(E21:E28)+E29 -> 1401.135 | F30: =F20-SUM(F21:F28)+F29 -> 1916.8166 | G30: =G20-SUM(G21:G28)+G29 -> 2331.552 | H30: =H20-SUM(H21:H28)+H29 -> 2750.935 | I30: =I20-SUM(I21:I28)+I29 -> 2967.7308 | J30: =J20-SUM(J21:J28)+J29 -> 3006.5681
B31: 三、利润总额 | C31: =C30 -> 450.63432 | D31: =D30 -> 816.9611 | E31: =E30 -> 1401.135 | F31: =F30 -> 1916.8166 | G31: =G30 -> 2331.552 | H31: =H30 -> 2750.935 | I31: =I30 -> 2967.7308 | J31: =J30 -> 3006.5681
B32: 减:所得税费用 | C32: ='12收益表'!C34 -> 24.301124 | D32: ='12收益表'!D34 -> 80.929676 | E32: ='12收益表'!E34 -> 161.19123 | F32: ='12收益表'!F20 -> 367.30906 | G32: ='12收益表'!G20 -> 270.18752 | H32: ='12收益表'!H20 -> 353.02958 | I32: ='12收益表'!I20 -> 381.92291 | J32: ='12收益表'!J20 -> 643.9892
B33: 四、净利润 | C33: =C31-C32 -> 426.3332 | D33: =D31-D32 -> 736.03143 | E33: =E31-E32 -> 1239.9437 | F33: =F31-F32 -> 1549.5076 | G33: =G31-G32 -> 2061.3645 | H33: =H31-H32 -> 2397.9054 | I33: =I31-I32 -> 2585.8079 | J33: =J31-J32 -> 2362.5789
B34: 减:少数股东损益 | C34: ='1报表'!C88 -> 0 | D34: ='1报表'!D88 -> 0 | E34: ='1报表'!E88 -> 0 | F34: ='12收益表'!F22 -> 0 | G34: ='12收益表'!G22 -> 0 | H34: ='12收益表'!H22 -> 0 | I34: ='12收益表'!I22 -> 0 | J34: ='12收益表'!J22 -> 0
B35: 五、归母净利润 | C35: =C33-C34 -> 426.3332 | D35: =D33-D34 -> 736.03143 | E35: =E33-E34 -> 1239.9437 | F35: =F33-F34 -> 1549.5076 | G35: =G33-G34 -> 2061.3645 | H35: =H33-H34 -> 2397.9054 | I35: =I33-I34 -> 2585.8079 | J35: =J33-J34 -> 2362.5789
B36: 股利支付 | G36: =F41 -> 1398.6861 | H36: =G41 -> 2012.1053 | I36: =H41 -> 2108.8981 | J36: =I41 -> 2363.6997
B37: 扣除股利支付后净利润 | F37: =F35-F36 -> 1549.5076 | G37: =G35-G36 -> 662.67839 | H37: =H35-H36 -> 385.80013 | I37: =I35-I36 -> 476.90977 | J37: =J35-J36 -> -1.1208373
B39: 资产负债表（经营性） | C39: =C4 -> 42369 | D39: =D4 -> 42735 | E39: =E4 -> 43100 | F39: =F4 -> 43465 | G39: =G4 -> 43830 | H39: =H4 -> 44196 | I39: =I4 -> 44561 | J39: =J4 -> 44926
B40: 流动资产
B41: 盈余现金 | C41: =MAX('1报表'!C15-'10营运'!C5,0) -> 0 | D41: =MAX('1报表'!D15-'10营运'!D5,0) -> 48.190582 | E41: =MAX('1报表'!E15-'10营运'!E5,0) -> 37.453128 | F41: =MAX(F100,0) -> 1398.6861 | G41: =MAX(G100,0) -> 2012.1053 | H41: =MAX(H100,0) -> 2108.8981 | I41: =MAX(I100,0) -> 2363.6997 | J41: =MAX(J100,0) -> 2367.3706
B42: 经营最低保有现金 | C42: =MIN('1报表'!C15,'10营运'!C5) -> 107.23511 | D42: =MIN('1报表'!D15,'10营运'!D5) -> 184.0763 | E42: =MIN('1报表'!E15,'10营运'!E5) -> 239.36138 | F42: ='9溢余现金'!F19 -> 276.46729 | G42: ='9溢余现金'!G19 -> 320.20105 | H42: ='9溢余现金'!H19 -> 351.38539 | I42: ='9溢余现金'!I19 -> 371.36489 | J42: ='9溢余现金'!J19 -> 381.50273
B43: 应收票据及应收账款 | C43: ='10营运'!C8 -> 2177.8959 | D43: ='10营运'!D8 -> 2618.1402 | E43: ='10营运'!E8 -> 3436.3947 | F43: ='10营运'!F8 -> 4310.0335 | G43: ='10营运'!G8 -> 5106.6108 | H43: ='10营运'!H8 -> 5740.2872 | I43: ='10营运'!I8 -> 6089.461 | J43: ='10营运'!J8 -> 6219.9407
B44: 预付款项 | C44: ='10营运'!C11 -> 163.1034 | D44: ='10营运'!D11 -> 99.846675 | E44: ='10营运'!E11 -> 43.550822 | F44: ='10营运'!F11 -> 198.92462 | G44: ='10营运'!G11 -> 235.68973 | H44: ='10营运'!H11 -> 264.93633 | I44: ='10营运'!I11 -> 281.05205 | J44: ='10营运'!J11 -> 287.07419
B45: 其他应收款 | C45: ='10营运'!C14 -> 113.81446 | D45: ='10营运'!D14 -> 191.70885 | E45: ='10营运'!E14 -> 22.319492 | F45: ='10营运'!F14 -> 232.07873 | G45: ='10营运'!G14 -> 274.97135 | H45: ='10营运'!H14 -> 309.09239 | I45: ='10营运'!I14 -> 327.89405 | J45: ='10营运'!J14 -> 334.91988
B46: 存货 | C46: ='10营运'!C17 -> 879.74901 | D46: ='10营运'!D17 -> 1054.9352 | E46: ='10营运'!E17 -> 1331.2815 | F46: ='10营运'!F17 -> 1690.8593 | G46: ='10营运'!G17 -> 2003.3627 | H46: ='10营运'!H17 -> 2251.9588 | I46: ='10营运'!I17 -> 2388.9424 | J46: ='10营运'!J17 -> 2440.1306
B47: 合同资产 | C47: ='10营运'!C18 -> 0 | D47: ='10营运'!D18 -> 0 | E47: ='10营运'!E18 -> 0 | F47: ='10营运'!F18 -> 0 | G47: ='10营运'!G18 -> 0 | H47: ='10营运'!H18 -> 0 | I47: ='10营运'!I18 -> 0 | J47: ='10营运'!J18 -> 0
B48: 一年内到期的非流动资产 | C48: ='10营运'!C19 -> 0 | D48: ='10营运'!D19 -> 0 | E48: ='10营运'!E19 -> 0 | F48: ='10营运'!F19 -> 0 | G48: ='10营运'!G19 -> 0 | H48: ='10营运'!H19 -> 0 | I48: ='10营运'!I19 -> 0 | J48: ='10营运'!J19 -> 0
B49: 其他流动资产 | C49: ='10营运'!C20 -> 34.793744 | D49: ='10营运'!D20 -> 21.197218 | E49: ='10营运'!E20 -> 85.05866 | F49: ='10营运'!F20 -> 85.05866 | G49: ='10营运'!G20 -> 85.05866 | H49: ='10营运'!H20 -> 85.05866 | I49: ='10营运'!I20 -> 85.05866 | J49: ='10营运'!J20 -> 85.05866
B50: 流动资产合计 | C50: =SUM(C41:C49) -> 3476.5917 | D50: =SUM(D41:D49) -> 4218.095 | E50: =SUM(E41:E49) -> 5195.4198 | F50: =SUM(F41:F49) -> 8192.1082 | G50: =SUM(G41:G49) -> 10038 | H50: =SUM(H41:H49) -> 11111.617 | I50: =SUM(I41:I49) -> 11907.473 | J50: =SUM(J41:J49) -> 12115.997
B51: 非流动资产
B52: 长期应收款 | C52: =C5 -> 0 | D52: =D5 -> 0 | E52: =E5 -> 0 | F52: =F5 -> 0 | G52: =G5 -> 0 | H52: =H5 -> 0 | I52: =I5 -> 0 | J52: =J5 -> 0
B53: 固定资产 | C53: ='1报表'!C39-'2报表调整'!K32 -> 2374.1047 | D53: ='1报表'!D39-'2报表调整'!L32 -> 2109.0141 | E53: ='2报表调整'!G32 -> 2328.7283 | F53: ='7折旧'!F29+'7折旧'!F44 -> 2303.2883 | G53: ='7折旧'!G29+'7折旧'!G44 -> 1702.9483 | H53: ='7折旧'!H29+'7折旧'!H44 -> 1412.8607 | I53: ='7折旧'!I29+'7折旧'!I44 -> 1295.6016 | J53: ='7折旧'!J29+'7折旧'!J44 -> 1167.3424
B54: 在建工程 | C54: ='1报表'!C40-'2报表调整'!K33 -> 0 | D54: ='1报表'!D40-'2报表调整'!L33 -> 0 | E54: ='2报表调整'!G33 -> 354.7988
B55: 生产性生物资产 | C55: ='1报表'!C41-'2报表调整'!K34 -> 0 | D55: ='1报表'!D41-'2报表调整'!L34 -> 0 | E55: ='2报表调整'!G34 -> 0
B56: 油气资产 | C56: ='1报表'!C42-'2报表调整'!K35 -> 0 | D56: ='1报表'!D42-'2报表调整'!L35 -> 0 | E56: ='2报表调整'!G35 -> 0
B57: 无形资产 | C57: ='1报表'!C43-'2报表调整'!K36 -> 317.96748 | D57: ='1报表'!D43-'2报表调整'!L36 -> 306.03733 | E57: ='2报表调整'!G36 -> 459.60841 | F57: ='8摊销'!F26+'8摊销'!F35 -> 387.7704 | G57: ='8摊销'!G26+'8摊销'!G35 -> 315.93235 | H57: ='8摊销'!H26+'8摊销'!H35 -> 324.73059 | I57: ='8摊销'!I26+'8摊销'!I35 -> 347.05208 | J57: ='8摊销'!J26+'8摊销'!J35 -> 349.37358
B58: 开发支出 | C58: ='1报表'!C44-'2报表调整'!K37 -> 0 | D58: ='1报表'!D44-'2报表调整'!L37 -> 0 | E58: ='2报表调整'!G37 -> 0
B59: 商誉 | C59: ='1报表'!C45 -> 0 | D59: ='1报表'!D45 -> 0 | E59: ='2报表调整'!G38 -> 0 | F59: =E59 -> 0 | G59: =F59 -> 0 | H59: =G59 -> 0 | I59: =H59 -> 0 | J59: =I59 -> 0
B60: 长期待摊费用 | C60: ='1报表'!C46-'2报表调整'!K39 -> 0 | D60: ='1报表'!D46-'2报表调整'!L39 -> 0 | E60: ='2报表调整'!G39 -> 0 | F60: ='8摊销'!F52 -> 0 | G60: ='8摊销'!G52 -> 0 | H60: ='8摊销'!H52 -> 0 | I60: ='8摊销'!I52 -> 0 | J60: ='8摊销'!J52 -> 0
B61: 递延所得税资产 | C61: ='1报表'!C47-'2报表调整'!K40 -> 77.510453 | D61: ='1报表'!D47-'2报表调整'!L40 -> 88.215967 | E61: ='2报表调整'!G40 -> 101.06477 | F61: =E61 -> 101.06477 | G61: =F61 -> 101.06477 | H61: =G61 -> 101.06477 | I61: =H61 -> 101.06477 | J61: =I61 -> 101.06477
B62: 其他非流动资产 | C62: =C6 -> 28.32889 | D62: =D6 -> 294.362 | E62: =E6 -> 38.18068 | F62: =F6 -> 38.18068 | G62: =G6 -> 38.18068 | H62: =H6 -> 38.18068 | I62: =I6 -> 38.18068 | J62: =J6 -> 38.18068
B63: 非流动资产合计 | C63: =SUM(C52:C62) -> 2797.9116 | D63: =SUM(D52:D62) -> 2797.6294 | E63: =SUM(E52:E62) -> 3282.381 | F63: =SUM(F52:F62) -> 2830.3042 | G63: =SUM(G52:G62) -> 2158.1261 | H63: =SUM(H52:H62) -> 1876.8368 | I63: =SUM(I52:I62) -> 1781.8991 | J63: =SUM(J52:J62) -> 1655.9614
B64: 资产总计 | C64: =C50+C63 -> 6274.5032 | D64: =D50+D63 -> 7015.7244 | E64: =E50+E63 -> 8477.8007 | F64: =F50+F63 -> 11022.412 | G64: =G50+G63 -> 12196.126 | H64: =H50+H63 -> 12988.454 | I64: =I50+I63 -> 13689.372 | J64: =J50+J63 -> 13771.959
B65: 非付息流动负债
B66: 应付票据及应付款项 | C66: ='10营运'!C25 -> 417.61032 | D66: ='10营运'!D25 -> 1037.928 | E66: ='10营运'!E25 -> 1257.6974 | F66: ='10营运'!F25 -> 1392.4724 | G66: ='10营运'!G25 -> 1649.8281 | H66: ='10营运'!H25 -> 1854.5543 | I66: ='10营运'!I25 -> 1967.3643 | J66: ='10营运'!J25 -> 2009.5193
B67: 预收款项 | C67: ='10营运'!C28 -> 131.76532 | D67: ='10营运'!D28 -> 195.99939 | E67: ='10营运'!E28 -> 351.09636 | F67: ='10营运'!F28 -> 298.38693 | G67: ='10营运'!G28 -> 353.53459 | H67: ='10营运'!H28 -> 397.4045 | I67: ='10营运'!I28 -> 421.57807 | J67: ='10营运'!J28 -> 430.61128
B68: 合同负债 | C68: ='10营运'!C29 -> 0 | D68: ='10营运'!D29 -> 0 | E68: ='10营运'!E29 -> 0 | F68: ='10营运'!F29 -> 0 | G68: ='10营运'!G29 -> 0 | H68: ='10营运'!H29 -> 0 | I68: ='10营运'!I29 -> 0 | J68: ='10营运'!J29 -> 0
B69: 应付职工薪酬 | C69: ='10营运'!C30 -> 132.57767 | D69: ='10营运'!D30 -> 163.35175 | E69: ='10营运'!E30 -> 345.76284 | F69: ='10营运'!F30 -> 345.76284 | G69: ='10营运'!G30 -> 345.76284 | H69: ='10营运'!H30 -> 345.76284 | I69: ='10营运'!I30 -> 345.76284 | J69: ='10营运'!J30 -> 345.76284
B70: 应交税费 | C70: ='10营运'!C31 -> 104.3759 | D70: ='10营运'!D31 -> 117.08402 | E70: ='10营运'!E31 -> 225.302 | F70: ='10营运'!F31 -> 225.302 | G70: ='10营运'!G31 -> 225.302 | H70: ='10营运'!H31 -> 225.302 | I70: ='10营运'!I31 -> 225.302 | J70: ='10营运'!J31 -> 225.302
B71: 其他应付款 | C71: ='10营运'!C34 -> 1493.8281 | D71: ='10营运'!D34 -> 1824.9313 | E71: ='10营运'!E34 -> 161.15448 | F71: ='10营运'!F34 -> 1074.193 | G71: ='10营运'!G34 -> 1272.7245 | H71: ='10营运'!H34 -> 1430.6562 | I71: ='10营运'!I34 -> 1517.681 | J71: ='10营运'!J34 -> 1550.2006
B72: 其他流动负债 | C72: ='10营运'!C37 -> 0 | D72: ='10营运'!D37 -> 0 | E72: ='10营运'!E37 -> 0 | F72: ='10营运'!F37 -> 0 | G72: ='10营运'!G37 -> 0 | H72: ='10营运'!H37 -> 0 | I72: ='10营运'!I37 -> 0 | J72: ='10营运'!J37 -> 0
B73: 非付息流动负债合计 | C73: =SUM(C66:C72) -> 2280.1573 | D73: =SUM(D66:D72) -> 3339.2944 | E73: =SUM(E66:E72) -> 2341.0131 | F73: =SUM(F66:F72) -> 3336.1171 | G73: =SUM(G66:G72) -> 3847.1521 | H73: =SUM(H66:H72) -> 4253.6799 | I73: =SUM(I66:I72) -> 4477.6883 | J73: =SUM(J66:J72) -> 4561.396
B74: 非付息非流动负债
B75: 长期应付款 | C75: =C7 -> 0 | D75: =D7 -> 0 | E75: =E7 -> 0 | F75: =F7 -> 0 | G75: =G7 -> 0 | H75: =H7 -> 0 | I75: =I7 -> 0 | J75: =J7 -> 0
B76: 长期应付职工薪酬 | C76: =C8 -> 0 | D76: =D8 -> 0 | E76: =E8 -> 0 | F76: =F8 -> 0 | G76: =G8 -> 0 | H76: =H8 -> 0 | I76: =I8 -> 0 | J76: =J8 -> 0
B77: 预计负债 | C77: =C9 -> 0 | D77: =D9 -> 0 | E77: =E9 -> 0 | F77: =F9 -> 0 | G77: =G9 -> 0 | H77: =H9 -> 0 | I77: =I9 -> 0 | J77: =J9 -> 0
B78: 递延收益 | C78: =C10 -> 0 | D78: =D10 -> 0 | E78: =E10 -> 0 | F78: =F10 -> 0 | G78: =G10 -> 0 | H78: =H10 -> 0 | I78: =I10 -> 0 | J78: =J10 -> 0
B79: 递延所得税负债 | C79: ='1报表'!C74-'2报表调整'!K67 -> 0 | D79: ='1报表'!D74-'2报表调整'!L67 -> 0 | E79: ='2报表调整'!G67 -> 0 | F79: =E79 -> 0 | G79: =F79 -> 0 | H79: =G79 -> 0 | I79: =H79 -> 0 | J79: =I79 -> 0
B80: 其他非流动负债 | C80: =C11 -> 0 | D80: =D11 -> 0 | E80: =E11 -> 0 | F80: =F11 -> 0 | G80: =G11 -> 0 | H80: =H11 -> 0 | I80: =I11 -> 0 | J80: =J11 -> 0
B81: 非付息非流动负债合计 | C81: =SUM(C75:C80) -> 0 | D81: =SUM(D75:D80) -> 0 | E81: =SUM(E75:E80) -> 0 | F81: =SUM(F75:F80) -> 0 | G81: =SUM(G75:G80) -> 0 | H81: =SUM(H75:H80) -> 0 | I81: =SUM(I75:I80) -> 0 | J81: =SUM(J75:J80) -> 0
B82: 付息负债
B83: 新增借款 | F83: =-MIN(F100,0) -> 0 | G83: =-MIN(G100,0) -> 0 | H83: =-MIN(H100,0) -> 0 | I83: =-MIN(I100,0) -> 0 | J83: =-MIN(J100,0) -> 0
B84: 短期借款 | C84: ='1报表'!C52 -> 900 | D84: ='1报表'!D52 -> 1100 | E84: ='1报表'!E52 -> 1000 | F84: ='11财务费用'!F5 -> 1000 | G84: ='11财务费用'!G5 -> 1000 | H84: ='11财务费用'!H5 -> 1000 | I84: ='11财务费用'!I5 -> 1000 | J84: ='11财务费用'!J5 -> 1000
B85: 一年内到期的非流动负债 | C85: ='1报表'!C64 -> 1150 | D85: ='1报表'!D64 -> 0 | E85: ='1报表'!E64 -> 0 | F85: ='11财务费用'!F6 -> 0 | G85: ='11财务费用'!G6 -> 0 | H85: ='11财务费用'!H6 -> 0 | I85: ='11财务费用'!I6 -> 0 | J85: ='11财务费用'!J6 -> 0
B86: 长期借款 | C86: ='1报表'!C68 -> 0 | D86: ='1报表'!D68 -> 0 | E86: ='1报表'!E68 -> 0 | F86: ='11财务费用'!F7 -> 0 | G86: ='11财务费用'!G7 -> 0 | H86: ='11财务费用'!H7 -> 0 | I86: ='11财务费用'!I7 -> 0 | J86: ='11财务费用'!J7 -> 0
B87: 应付债券 | C87: ='1报表'!C69 -> 0 | D87: ='1报表'!D69 -> 0 | E87: ='1报表'!E69 -> 0 | F87: ='11财务费用'!F9 -> 0 | G87: ='11财务费用'!G9 -> 0 | H87: ='11财务费用'!H9 -> 0 | I87: ='11财务费用'!I9 -> 0 | J87: ='11财务费用'!J9 -> 0
B88: 付息负债合计 | C88: =SUM(C83:C87) -> 2050 | D88: =SUM(D83:D87) -> 1100 | E88: =SUM(E83:E87) -> 1000 | F88: =SUM(F83:F87) -> 1000 | G88: =SUM(G83:G87) -> 1000 | H88: =SUM(H83:H87) -> 1000 | I88: =SUM(I83:I87) -> 1000 | J88: =SUM(J83:J87) -> 1000
B89: 负债合计 | C89: =C73+C81+C88 -> 4330.1573 | D89: =D73+D81+D88 -> 4439.2944 | E89: =E73+E81+E88 -> 3341.0131 | F89: =F73+F81+F88 -> 4336.1171 | G89: =G73+G81+G88 -> 4847.1521 | H89: =H73+H81+H88 -> 5253.6799 | I89: =I73+I81+I88 -> 5477.6883 | J89: =J73+J81+J88 -> 5561.396
B90: 所有者权益
B91: 归母权益 | C91: ='1报表'!C87-'2报表调整'!K43+'2报表调整'!K70 -> 1944.3459 | D91: ='1报表'!D87-'2报表调整'!L43+'2报表调整'!L70 -> 2576.4299 | E91: ='1报表'!E87-'2报表调整'!M43+'2报表调整'!M70 -> 5136.7877 | F91: =E91+F37+F34*F12 -> 6686.2953 | G91: =F91+G37+G34*G12 -> 7348.9737 | H91: =G91+H37+H34*H12 -> 7734.7738 | I91: =H91+I37+I34*I12 -> 8211.6836 | J91: =I91+J37+J34*J12 -> 8210.5627
B92: 少数股东权益 | C92: ='1报表'!C88 -> 0 | D92: ='1报表'!D88 -> 0 | E92: ='1报表'!E88 -> 0 | F92: =E92+(1-F12)*F34 -> 0 | G92: =F92+(1-G12)*G34 -> 0 | H92: =G92+(1-H12)*H34 -> 0 | I92: =H92+(1-I12)*I34 -> 0 | J92: =I92+(1-J12)*J34 -> 0
B93: 所有者权益合计 | C93: =C91+C92 -> 1944.3459 | D93: =D91+D92 -> 2576.4299 | E93: =E91+E92 -> 5136.7877 | F93: =F91+F92 -> 6686.2953 | G93: =G91+G92 -> 7348.9737 | H93: =H91+H92 -> 7734.7738 | I93: =I91+I92 -> 8211.6836 | J93: =J91+J92 -> 8210.5627
B94: 负债和所有者权益总计 | C94: =C89+C93 -> 6274.5032 | D94: =D89+D93 -> 7015.7244 | E94: =E89+E93 -> 8477.8007 | F94: =F89+F93 -> 11022.412 | G94: =G89+G93 -> 12196.126 | H94: =H89+H93 -> 12988.454 | I94: =I89+I93 -> 13689.372 | J94: =J89+J93 -> 13771.959
B95: 检查核对 | C95: =C64-C94 -> 0 | D95: =D64-D94 -> 0 | E95: =E64-E94 -> 0 | F95: =F64-F94 -> 0 | G95: =G64-G94 -> 0 | H95: =H64-H94 -> 0 | I95: =I64-I94 -> 0 | J95: =J64-J94 -> 0
B96: 报表是否平衡？ | C96: =IF(ROUND(C95,0),"需要检查","OK") -> OK | D96: =IF(ROUND(D95,0),"需要检查","OK") -> OK | E96: =IF(ROUND(E95,0),"需要检查","OK") -> OK | F96: =IF(ROUND(F95,0),"需要检查","OK") -> OK | G96: =IF(ROUND(G95,0),"需要检查","OK") -> OK | H96: =IF(ROUND(H95,0),"需要检查","OK") -> OK | I96: =IF(ROUND(I95,0),"需要检查","OK") -> OK | J96: =IF(ROUND(J95,0),"需要检查","OK") -> OK
B97: 报表调平自动计算公式
B98: 扣除溢余现金的资产 | F98: =SUM(F42:F49)+F63 -> 9623.7262 | G98: =SUM(G42:G49)+G63 -> 10184.02 | H98: =SUM(H42:H49)+H63 -> 10879.556 | I98: =SUM(I42:I49)+I63 -> 11325.672 | J98: =SUM(J42:J49)+J63 -> 11404.588
B99: 扣除新增借款的负债与权益 | F99: =F73+F81+SUM(F84:F87)+F93 -> 11022.412 | G99: =G73+G81+SUM(G84:G87)+G93 -> 12196.126 | H99: =H73+H81+SUM(H84:H87)+H93 -> 12988.454 | I99: =I73+I81+SUM(I84:I87)+I93 -> 13689.372 | J99: =J73+J81+SUM(J84:J87)+J93 -> 13771.959
B100: 溢余现金（新增借款） | F100: =IF(ISERROR(F99-F98),0,F99-F98) -> 1398.6861 | G100: =IF(ISERROR(G99-G98),0,G99-G98) -> 2012.1053 | H100: =IF(ISERROR(H99-H98),0,H99-H98) -> 2108.8981 | I100: =IF(ISERROR(I99-I98),0,I99-I98) -> 2363.6997 | J100: =IF(ISERROR(J99-J98),0,J99-J98) -> 2367.3706
B102: 经营性投入资本的计算 | J102: 单位：万元
B103: 科目 | C103: =C19 -> 2015年 | D103: =D19 -> 2016年 | E103: =E19 -> 2017年 | F103: =F19 -> 2018年 | G103: =G19 -> 2019年 | H103: =H19 -> 2020年 | I103: =I19 -> 2021年 | J103: =J19 -> 2022年
...
